Workbook
Name _____________________MHA1: {"rtn",#N/A,FALSE,"RTN";"tables",#N/A,FALSE,"RTN";"cf",#N/A,FALSE,"CF";"stats",#N/A,FALSE,"Stats";"prop",#N/A,FALSE,"Prop"}
Name _____________________T123456: {"COUNT",#N/A,FALSE,"AB"}
Name _____________________T12347: {"COUNT",#N/A,FALSE,"AB"}
Name __________________T123456: {"COUNT",#N/A,FALSE,"AB"}
Name __________________T12347: {"COUNT",#N/A,FALSE,"AB"}
Name ________________MHA1: {"rtn",#N/A,FALSE,"RTN";"tables",#N/A,FALSE,"RTN";"cf",#N/A,FALSE,"CF";"stats",#N/A,FALSE,"Stats";"prop",#N/A,FALSE,"Prop"}
Name ______________T123456: {"COUNT",#N/A,FALSE,"AB"}
Name ______________T12347: {"COUNT",#N/A,FALSE,"AB"}
Name _____________MHA1: {"rtn",#N/A,FALSE,"RTN";"tables",#N/A,FALSE,"RTN";"cf",#N/A,FALSE,"CF";"stats",#N/A,FALSE,"Stats";"prop",#N/A,FALSE,"Prop"}
Name ___________MHA1: {"rtn",#N/A,FALSE,"RTN";"tables",#N/A,FALSE,"RTN";"cf",#N/A,FALSE,"CF";"stats",#N/A,FALSE,"Stats";"prop",#N/A,FALSE,"Prop"}
Name __________MHA1: {"rtn",#N/A,FALSE,"RTN";"tables",#N/A,FALSE,"RTN";"cf",#N/A,FALSE,"CF";"stats",#N/A,FALSE,"Stats";"prop",#N/A,FALSE,"Prop"}
Name _________MHA1: {"rtn",#N/A,FALSE,"RTN";"tables",#N/A,FALSE,"RTN";"cf",#N/A,FALSE,"CF";"stats",#N/A,FALSE,"Stats";"prop",#N/A,FALSE,"Prop"}
Name _________MHA1_1: {"rtn",#N/A,FALSE,"RTN";"tables",#N/A,FALSE,"RTN";"cf",#N/A,FALSE,"CF";"stats",#N/A,FALSE,"Stats";"prop",#N/A,FALSE,"Prop"}
Name ________MHA1: {"rtn",#N/A,FALSE,"RTN";"tables",#N/A,FALSE,"RTN";"cf",#N/A,FALSE,"CF";"stats",#N/A,FALSE,"Stats";"prop",#N/A,FALSE,"Prop"}
Name ________MHA1_1: {"rtn",#N/A,FALSE,"RTN";"tables",#N/A,FALSE,"RTN";"cf",#N/A,FALSE,"CF";"stats",#N/A,FALSE,"Stats";"prop",#N/A,FALSE,"Prop"}
Name _______MHA1: {"rtn",#N/A,FALSE,"RTN";"tables",#N/A,FALSE,"RTN";"cf",#N/A,FALSE,"CF";"stats",#N/A,FALSE,"Stats";"prop",#N/A,FALSE,"Prop"}
Name _______MHA1_1: {"rtn",#N/A,FALSE,"RTN";"tables",#N/A,FALSE,"RTN";"cf",#N/A,FALSE,"CF";"stats",#N/A,FALSE,"Stats";"prop",#N/A,FALSE,"Prop"}
Name _______T123456: {"COUNT",#N/A,FALSE,"AB"}
Name _______T12347: {"COUNT",#N/A,FALSE,"AB"}
Name ______MHA1: {"rtn",#N/A,FALSE,"RTN";"tables",#N/A,FALSE,"RTN";"cf",#N/A,FALSE,"CF";"stats",#N/A,FALSE,"Stats";"prop",#N/A,FALSE,"Prop"}
Name ______MHA1_1: {"rtn",#N/A,FALSE,"RTN";"tables",#N/A,FALSE,"RTN";"cf",#N/A,FALSE,"CF";"stats",#N/A,FALSE,"Stats";"prop",#N/A,FALSE,"Prop"}
Name _____DF4: #REF!
Name _____MHA1: {"rtn",#N/A,FALSE,"RTN";"tables",#N/A,FALSE,"RTN";"cf",#N/A,FALSE,"CF";"stats",#N/A,FALSE,"Stats";"prop",#N/A,FALSE,"Prop"}
Name _____MHA1_1: {"rtn",#N/A,FALSE,"RTN";"tables",#N/A,FALSE,"RTN";"cf",#N/A,FALSE,"CF";"stats",#N/A,FALSE,"Stats";"prop",#N/A,FALSE,"Prop"}
Name _____New2: {"TOTAL",#N/A,FALSE,"A";"FISCAL94",#N/A,FALSE,"A";"FISCAL95",#N/A,FALSE,"A";"FISCAL96",#N/A,FALSE,"A";"misc page",#N/A,FALSE,"A"}
Name _____R: {#N/A,#N/A,FALSE,"Minors";#N/A,#N/A,FALSE,"96CAPREV"}
Name _____T123456: {"COUNT",#N/A,FALSE,"AB"}
Name _____T12347: {"COUNT",#N/A,FALSE,"AB"}
Name ____DCF2: {#N/A,#N/A,TRUE,"DCF Summary (2)";#N/A,#N/A,TRUE,"DCF Summary";#N/A,"Middle Case Drivers",TRUE,"DCF"}
Name ____DF4: #REF!
Name ____JLC1: {#N/A,#N/A,TRUE,"97plnfpg"}
Name ____JLC3: {#N/A,#N/A,FALSE,"J97plnfp"}
Name ____MHA1: {"rtn",#N/A,FALSE,"RTN";"tables",#N/A,FALSE,"RTN";"cf",#N/A,FALSE,"CF";"stats",#N/A,FALSE,"Stats";"prop",#N/A,FALSE,"Prop"}
Name ____MHA1_1: {"rtn",#N/A,FALSE,"RTN";"tables",#N/A,FALSE,"RTN";"cf",#N/A,FALSE,"CF";"stats",#N/A,FALSE,"Stats";"prop",#N/A,FALSE,"Prop"}
Name ____New2: {"TOTAL",#N/A,FALSE,"A";"FISCAL94",#N/A,FALSE,"A";"FISCAL95",#N/A,FALSE,"A";"FISCAL96",#N/A,FALSE,"A";"misc page",#N/A,FALSE,"A"}
Name ____R: {#N/A,#N/A,FALSE,"Minors";#N/A,#N/A,FALSE,"96CAPREV"}
Name ____T123456: {"COUNT",#N/A,FALSE,"AB"}
Name ____T12347: {"COUNT",#N/A,FALSE,"AB"}
Name ____wrn2: {#N/A,#N/A,FALSE,"ASSUMPTIONS";#N/A,#N/A,FALSE,"Valuation Summary";"page1",#N/A,FALSE,"PRESENTATION";"page2",#N/A,FALSE,"PRESENTATION";#N/A,#N/A,FALSE,"ORIGINAL_ROLLBACK"}
Name ____wrn3: {#N/A,#N/A,FALSE,"ASSUMPTIONS";#N/A,#N/A,FALSE,"Valuation Summary";"page1",#N/A,FALSE,"PRESENTATION";"page2",#N/A,FALSE,"PRESENTATION";#N/A,#N/A,FALSE,"ORIGINAL_ROLLBACK"}
Name ___aaa1: {#N/A,#N/A,FALSE,"Model";#N/A,#N/A,FALSE,"Division"}
Name ___c: {#N/A,#N/A,FALSE,"Layout Cash Flow"}
Name ___DCF2: {#N/A,#N/A,TRUE,"DCF Summary (2)";#N/A,#N/A,TRUE,"DCF Summary";#N/A,"Middle Case Drivers",TRUE,"DCF"}
Name ___DF4: #REF!
Name ___fy97: {#N/A,#N/A,FALSE,"FY97";#N/A,#N/A,FALSE,"FY98";#N/A,#N/A,FALSE,"FY99";#N/A,#N/A,FALSE,"FY00";#N/A,#N/A,FALSE,"FY01"}
Name ___key2: #REF!
Name ___MHA1: {"rtn",#N/A,FALSE,"RTN";"tables",#N/A,FALSE,"RTN";"cf",#N/A,FALSE,"CF";"stats",#N/A,FALSE,"Stats";"prop",#N/A,FALSE,"Prop"}
Name ___MHA1_1: {"rtn",#N/A,FALSE,"RTN";"tables",#N/A,FALSE,"RTN";"cf",#N/A,FALSE,"CF";"stats",#N/A,FALSE,"Stats";"prop",#N/A,FALSE,"Prop"}
Name ___New2: {"TOTAL",#N/A,FALSE,"A";"FISCAL94",#N/A,FALSE,"A";"FISCAL95",#N/A,FALSE,"A";"FISCAL96",#N/A,FALSE,"A";"misc page",#N/A,FALSE,"A"}
Name ___r: {"consolidated",#N/A,FALSE,"Sheet1";"cms",#N/A,FALSE,"Sheet1";"fse",#N/A,FALSE,"Sheet1"}
Name ___T12347: {"COUNT",#N/A,FALSE,"AB"}
Name ___wrn1: {#N/A,#N/A,FALSE,"DCF";#N/A,#N/A,FALSE,"WACC";#N/A,#N/A,FALSE,"Sales_EBIT";#N/A,#N/A,FALSE,"Capex_Depreciation";#N/A,#N/A,FALSE,"WC";#N/A,#N/A,FALSE,"Interest";#N/A,#N/A,FALSE,"Assumptions"}
Name __1__123Graph_ACHART_1: #REF!
Name __10__123Graph_CCHART_3: #REF!
Name __11__123Graph_CCHART_8: #REF!
Name __12__123Graph_DCHART_1: #REF!
Name __123Graph_A: #REF!
Name __123Graph_AANIDRO: #REF!
Name __123Graph_AAPPIP: #REF!
Name __123Graph_AB06: #REF!

Sheet Cover
B5: Financial Databook
B7: Table of Contents:
B8: Summary
B9: Income Statement
B10: Calculations
B11: Revenue_Calcs
B12: COGS_Calcs
B13: Opex_Calcs
B14: Bookings to Revenue_Calcs
B15: Assumptions
B16: Revenue_Assumptions
B17: COGS_Assumptions
B18: Opex_Assumptions
B20: As of: | C20: 44286

Sheet Summary
B2: Summary Income Statement | H2: 2022 Run-Rate
B3: ($ in millions) | D3: 2019 | E3: =+D3+1 | F3: =+E3+1 | G3: =+F3+1 | H3: Run-Rate | I3: =+G3+1 | J3: =+I3+1 | K3: =+J3+1 | L3: =+K3+1
B5: =+'Income Statement'!B12 | D5: =+'Income Statement'!F12/10^3 | E5: =+'Income Statement'!G12/10^3 | F5: =+'Income Statement'!H12/10^3 | G5: =+'Income Statement'!I12/10^3 | H5: =+'Income Statement'!O12/10^3 | I5: =+'Income Statement'!J12/10^3 | J5: =+'Income Statement'!K12/10^3 | K5: =+'Income Statement'!L12/10^3 | L5: =+'Income Statement'!M12/10^3
B6: =+'Income Statement'!B13 | D6: =+'Income Statement'!F13/10^3 | E6: =+'Income Statement'!G13/10^3 | F6: =+'Income Statement'!H13/10^3 | G6: =+'Income Statement'!I13/10^3 | H6: =+'Income Statement'!O13/10^3 | I6: =+'Income Statement'!J13/10^3 | J6: =+'Income Statement'!K13/10^3 | K6: =+'Income Statement'!L13/10^3 | L6: =+'Income Statement'!M13/10^3
B7: =+'Income Statement'!B14 | D7: =+'Income Statement'!F14/10^3 | E7: =+'Income Statement'!G14/10^3 | F7: =+'Income Statement'!H14/10^3 | G7: =+'Income Statement'!I14/10^3 | H7: =+'Income Statement'!O14/10^3 | I7: =+'Income Statement'!J14/10^3 | J7: =+'Income Statement'!K14/10^3 | K7: =+'Income Statement'!L14/10^3 | L7: =+'Income Statement'!M14/10^3
B8: =+'Income Statement'!B15 | D8: =+'Income Statement'!F15/10^3 | E8: =+'Income Statement'!G15/10^3 | F8: =+'Income Statement'!H15/10^3 | G8: =+'Income Statement'!I15/10^3 | H8: =+'Income Statement'!O15/10^3 | I8: =+'Income Statement'!J15/10^3 | J8: =+'Income Statement'!K15/10^3 | K8: =+'Income Statement'!L15/10^3 | L8: =+'Income Statement'!M15/10^3
B9: =+'Income Statement'!B16 | D9: =+'Income Statement'!F16/10^3 | E9: =+'Income Statement'!G16/10^3 | F9: =+'Income Statement'!H16/10^3 | G9: =+'Income Statement'!I16/10^3 | H9: =+'Income Statement'!O16/10^3 | I9: =+'Income Statement'!J16/10^3 | J9: =+'Income Statement'!K16/10^3 | K9: =+'Income Statement'!L16/10^3 | L9: =+'Income Statement'!M16/10^3
B10: % Growth | E10: =+E9/D9-1 | F10: =+F9/E9-1 | G10: =+G9/F9-1 | I10: =+I9/G9-1 | J10: =+J9/I9-1 | K10: =+K9/J9-1 | L10: =+L9/K9-1
B12: Cost of Sales | D12: =+'Income Statement'!F22/10^3 | E12: =+'Income Statement'!G22/10^3 | F12: =+'Income Statement'!H22/10^3 | G12: =+'Income Statement'!I22/10^3 | H12: =+'Income Statement'!O22/10^3 | I12: =+'Income Statement'!J22/10^3 | J12: =+'Income Statement'!K22/10^3 | K12: =+'Income Statement'!L22/10^3 | L12: =+'Income Statement'!M22/10^3
B13: Gross Profit | D13: =+D9-D12 | E13: =+E9-E12 | F13: =+F9-F12 | G13: =+G9-G12 | H13: =+H9-H12 | I13: =+I9-I12 | J13: =+J9-J12 | K13: =+K9-K12 | L13: =+L9-L12
B14: % Gross Margin | D14: =+D13/D$9 | E14: =+E13/E$9 | F14: =+F13/F$9 | G14: =+G13/G$9 | H14: =+H13/H$9 | I14: =+I13/I$9 | J14: =+J13/J$9 | K14: =+K13/K$9 | L14: =+L13/L$9
B16: =+'Income Statement'!B27 | D16: =+'Income Statement'!F27/10^3 | E16: =+'Income Statement'!G27/10^3 | F16: =+'Income Statement'!H27/10^3 | G16: =+'Income Statement'!I27/10^3 | H16: =+'Income Statement'!O27/10^3 | I16: =+'Income Statement'!J27/10^3 | J16: =+'Income Statement'!K27/10^3 | K16: =+'Income Statement'!L27/10^3 | L16: =+'Income Statement'!M27/10^3
B17: Rent | D17: =+'Income Statement'!F28/10^3 | E17: =+'Income Statement'!G28/10^3 | F17: =+'Income Statement'!H28/10^3 | G17: =+'Income Statement'!I28/10^3 | H17: =+'Income Statement'!O28/10^3 | I17: =+'Income Statement'!J28/10^3 | J17: =+'Income Statement'!K28/10^3 | K17: =+'Income Statement'!L28/10^3 | L17: =+'Income Statement'!M28/10^3
B18: Sales & Marketing | D18: =+'Income Statement'!F30/10^3 | E18: =+'Income Statement'!G30/10^3 | F18: =+'Income Statement'!H30/10^3 | G18: =+'Income Statement'!I30/10^3 | H18: =+'Income Statement'!O30/10^3 | I18: =+'Income Statement'!J30/10^3 | J18: =+'Income Statement'!K30/10^3 | K18: =+'Income Statement'!L30/10^3 | L18: =+'Income Statement'!M30/10^3
B19: Other Opex | D19: =+SUM('Income Statement'!F29,'Income Statement'!F31:F33)/10^3 | E19: =+SUM('Income Statement'!G29,'Income Statement'!G31:G33)/10^3 | F19: =+SUM('Income Statement'!H29,'Income Statement'!H31:H33)/10^3 | G19: =+SUM('Income Statement'!I29,'Income Statement'!I31:I33)/10^3 | H19: =+SUM('Income Statement'!O29,'Income Statement'!O31:O33)/10^3 | I19: =+SUM('Income Statement'!J29,'Income Statement'!J31:J33)/10^3 | J19: =+SUM('Income Statement'!K29,'Income Statement'!K31:K33)/10^3 | K19: =+SUM('Income Statement'!L29,'Income Statement'!L31:L33)/10^3 | L19: =+SUM('Income Statement'!M29,'Income Statement'!M31:M33)/10^3
B20: Other I/E | D20: =+'Income Statement'!F35/10^3 | E20: =+'Income Statement'!G35/10^3 | F20: =+'Income Statement'!H35/10^3 | G20: =+'Income Statement'!I35/10^3 | H20: =+'Income Statement'!O35/10^3 | I20: =+'Income Statement'!J35/10^3 | J20: =+'Income Statement'!K35/10^3 | K20: =+'Income Statement'!L35/10^3 | L20: =+'Income Statement'!M35/10^3
B21: Reported EBITDA | D21: =+D13-SUM(D16:D20) | E21: =+E13-SUM(E16:E20) | F21: =+F13-SUM(F16:F20) | G21: =+G13-SUM(G16:G20) | H21: =+H13-SUM(H16:H20) | I21: =+I13-SUM(I16:I20) | J21: =+J13-SUM(J16:J20) | K21: =+K13-SUM(K16:K20) | L21: =+L13-SUM(L16:L20)
B22: % Margin | D22: =+D21/D$9 | E22: =+E21/E$9 | F22: =+F21/F$9 | G22: =+G21/G$9 | H22: =+H21/H$9 | I22: =+I21/I$9 | J22: =+J21/J$9 | K22: =+K21/K$9 | L22: =+L21/L$9
B24: Adjustments | D24: =+'Income Statement'!F48/10^3 | E24: =+'Income Statement'!G48/10^3 | F24: =+'Income Statement'!H48/10^3 | G24: =+'Income Statement'!I48/10^3 | H24: =+'Income Statement'!O48/10^3 | I24: =+'Income Statement'!J48/10^3 | J24: =+'Income Statement'!K48/10^3 | K24: =+'Income Statement'!L48/10^3 | L24: =+'Income Statement'!M48/10^3
B25: Adjusted EBITDA | D25: =+D21+D24 | E25: =+E21+E24 | F25: =+F21+F24 | G25: =+G21+G24 | H25: =+H21+H24 | I25: =+I21+I24 | J25: =+J21+J24 | K25: =+K21+K24 | L25: =+L21+L24
B26: % Margin | D26: =+D25/D$9 | E26: =+E25/E$9 | F26: =+F25/F$9 | G26: =+G25/G$9 | H26: =+H25/H$9 | I26: =+I25/I$9 | J26: =+J25/J$9 | K26: =+K25/K$9 | L26: =+L25/L$9
B27: Check | D27: =+D25-'Income Statement'!F50/10^3 | E27: =+E25-'Income Statement'!G50/10^3 | F27: =+F25-'Income Statement'!H50/10^3 | G27: =+G25-'Income Statement'!I50/10^3 | H27: =+H25-'Income Statement'!O50/10^3 | I27: =+I25-'Income Statement'!J50/10^3 | J27: =+J25-'Income Statement'!K50/10^3 | K27: =+K25-'Income Statement'!L50/10^3 | L27: =+L25-'Income Statement'!M50/10^3 | M27: =+M25-'Income Statement'!N50/10^3

Sheet Model ->

Sheet Income Statement
B2: Project Shasta
B3: {=MID(CELL("filename",A1),FIND("]",CELL("filename",A1))+1,255)}
B4: Spring 2022
B5: CONFIDENTIAL
F7: 2019 | G7: =+F7+1 | H7: =+G7+1 | I7: =+H7+1 | J7: =+I7+1 | K7: =+J7+1 | L7: =+K7+1 | M7: =+L7+1 | O7: =+I7 | Q7: =+YEAR(Q8) | R7: =+YEAR(R8) | S7: =+YEAR(S8) | T7: =+YEAR(T8) | U7: =+YEAR(U8) | V7: =+YEAR(V8) | W7: =+YEAR(W8) | X7: =+YEAR(X8) | ... DH7: =+YEAR(DH8) | DJ7: Growth / Margin Analysis
F8: =+DATE(F7,12,31) | G8: =+DATE(G7,12,31) | H8: =+DATE(H7,12,31) | I8: =+DATE(I7,12,31) | J8: =+DATE(J7,12,31) | K8: =+DATE(K7,12,31) | L8: =+DATE(L7,12,31) | M8: =+DATE(M7,12,31) | O8: =+I8 | Q8: 43496 | R8: =+EOMONTH(Q8,1) | S8: =+EOMONTH(R8,1) | T8: =+EOMONTH(S8,1) | U8: =+EOMONTH(T8,1) | V8: =+EOMONTH(U8,1) | W8: =+EOMONTH(V8,1) | X8: =+EOMONTH(W8,1) | Y8: =+EOMONTH(X8,1) | ... DH8: =+EOMONTH(DG8,1) | DJ8: 2019 | DK8: =+DJ8+1 | DL8: =+DK8+1 | DM8: =+DL8+1 | DN8: =+DM8+1 | DO8: =+DN8+1 | DP8: =+DO8+1 | DQ8: =+DP8+1
B9: $ in thousands | F9: Actual | G9: Actual | H9: Actual | I9: Budget | J9: Projection | K9: Projection | L9: Projection | M9: Projection | O9: Run Rate | Q9: Actual | R9: Actual | S9: Actual | T9: Actual | U9: Actual | V9: Actual | W9: Actual | X9: Actual | Y9: Actual | Z9: Actual | AA9: Actual | AB9: Actual | AC9: Actual | AD9: Actual | AE9: Actual | AF9: Actual | AG9: Actual | AH9: Actual | AI9: Actual | AJ9: Actual | AK9: Actual | AL9: Actual | AM9: Actual | AN9: Actual | AO9: Actual | AP9: Actual | AQ9: Actual | AR9: Actual | AS9: Actual | AT9: Actual | AU9: Actual | AV9: Actual | AW9: Actual | AX9: Actual | AY9: Actual | AZ9: Actual | BA9: Actual | BB9: Actual | BC9: Actual | BD9: Budget | BE9: Budget | BF9: Budget | BG9: Budget | BH9: Budget | BI9: Budget | BJ9: Budget | BK9: Budget | BL9: Budget | BM9: Projection | BN9: Projection | BO9: Projection | BP9: Projection | BQ9: Projection | BR9: Projection | BS9: Projection | BT9: Projection | BU9: Projection | BV9: Projection | BW9: Projection | BX9: Projection | BY9: Projection | BZ9: Projection | CA9: Projection | CB9: Projection | CC9: Projection | CD9: Projection | CE9: Projection | CF9: Projection | CG9: Projection | CH9: Projection | CI9: Projection | CJ9: Projection | CK9: Projection | CL9: Projection | CM9: Projection | CN9: Projection | CO9: Projection | CP9: Projection | CQ9: Projection | CR9: Projection | CS9: Projection | CT9: Projection | CU9: Projection | CV9: Projection | CW9: Projection | CX9: Projection | CY9: Projection | CZ9: Projection | DA9: Projection | DB9: Projection | DC9: Projection | DD9: Projection | DE9: Projection | DF9: Projection | DG9: Projection | DH9: Projection | DJ9: Actual | DK9: Actual | DL9: Actual | DM9: Budget | DN9: Projection | DO9: Projection | DP9: Projection | DQ9: Projection
B11: Revenue | DJ11: Growth Analysis
B12: Licensing | F12: =+'Revenue_Calcs'!F122 | G12: =+'Revenue_Calcs'!G122 | H12: =+'Revenue_Calcs'!H122 | I12: =+'Revenue_Calcs'!I122 | J12: =+'Revenue_Calcs'!J122 | K12: =+'Revenue_Calcs'!K122 | L12: =+'Revenue_Calcs'!L122 | M12: =+'Revenue_Calcs'!M122 | O12: =I12+992.899 | DK12: =+IFERROR(G12/F12-1,0) | DL12: =+IFERROR(H12/G12-1,0) | DM12: =+IFERROR(I12/H12-1,0) | DN12: =+IFERROR(J12/I12-1,0) | DP12: =+IFERROR(L12/K12-1,0) | DQ12: =+IFERROR(M12/L12-1,0)
B13: Managed Services | F13: =+'Revenue_Calcs'!F209 | G13: =+'Revenue_Calcs'!G209 | H13: =+'Revenue_Calcs'!H209 | I13: =+'Revenue_Calcs'!I209 | J13: =+'Revenue_Calcs'!J209 | K13: =+'Revenue_Calcs'!K209 | L13: =+'Revenue_Calcs'!L209 | M13: =+'Revenue_Calcs'!M209 | O13: =+I13 | DK13: =+IFERROR(G13/F13-1,0) | DL13: =+IFERROR(H13/G13-1,0) | DM13: =+IFERROR(I13/H13-1,0) | DN13: =+IFERROR(J13/I13-1,0) | DP13: =+IFERROR(L13/K13-1,0) | DQ13: =+IFERROR(M13/L13-1,0)
B14: Implementation | F14: =+'Revenue_Calcs'!F283 | G14: =+'Revenue_Calcs'!G283 | H14: =+'Revenue_Calcs'!H283 | I14: =+'Revenue_Calcs'!I283 | J14: =+'Revenue_Calcs'!J283 | K14: =+'Revenue_Calcs'!K283 | L14: =+'Revenue_Calcs'!L283 | M14: =+'Revenue_Calcs'!M283 | O14: =+I14 | DK14: =+IFERROR(G14/F14-1,0) | DL14: =+IFERROR(H14/G14-1,0) | DM14: =+IFERROR(I14/H14-1,0) | DN14: =+IFERROR(J14/I14-1,0) | DP14: =+IFERROR(L14/K14-1,0) | DQ14: =+IFERROR(M14/L14-1,0)
B15: Other Revenue | F15: =+'Revenue_Calcs'!F287 | G15: =+'Revenue_Calcs'!G287 | H15: =+'Revenue_Calcs'!H287 | I15: =+'Revenue_Calcs'!I287 | J15: =+'Revenue_Calcs'!J287 | K15: =+'Revenue_Calcs'!K287 | L15: =+'Revenue_Calcs'!L287 | M15: =+'Revenue_Calcs'!M287 | O15: =+I15 | DK15: =+IFERROR(G15/F15-1,0) | DL15: =+IFERROR(H15/G15-1,0) | DM15: =+IFERROR(I15/H15-1,0) | DN15: =+IFERROR(J15/I15-1,0) | DP15: =+IFERROR(L15/K15-1,0) | DQ15: =+IFERROR(M15/L15-1,0)
B16: Total Revenue | F16: =SUM(F12:F15) | G16: =SUM(G12:G15) | H16: =SUM(H12:H15) | I16: =SUM(I12:I15) | J16: =SUM(J12:J15) | K16: =SUM(K12:K15) | L16: =SUM(L12:L15) | M16: =SUM(M12:M15) | O16: =SUM(O12:O15) | DK16: =+G16/F16-1 | DL16: =+H16/G16-1 | DM16: =+I16/H16-1 | DN16: =+J16/I16-1 | DP16: =+L16/K16-1 | DQ16: =+M16/L16-1
B18: Cost of Sales | DJ18: Margin Analysis
B19: Licensing | F19: =+'COGS_Calcs'!F107 | G19: =+'COGS_Calcs'!G107 | H19: =+'COGS_Calcs'!H107 | I19: =+'COGS_Calcs'!I107 | J19: =+'COGS_Calcs'!J107 | K19: =+'COGS_Calcs'!K107 | L19: =+'COGS_Calcs'!L107 | M19: =+'COGS_Calcs'!M107 | O19: =+I19+((O12-I12)*0.11) | DJ19: =+F19/F$16 | DK19: =+G19/G$16 | DL19: =+H19/H$16 | DM19: =+I19/I$16 | DN19: =+J19/J$16 | DP19: =+L19/L$16 | DQ19: =+M19/M$16
B20: Managed Services | F20: =+'COGS_Calcs'!F159 | G20: =+'COGS_Calcs'!G159 | H20: =+'COGS_Calcs'!H159 | I20: =+'COGS_Calcs'!I159 | J20: =+'COGS_Calcs'!J159 | K20: =+'COGS_Calcs'!K159 | L20: =+'COGS_Calcs'!L159 | M20: =+'COGS_Calcs'!M159 | O20: =+I20 | DJ20: =+F20/F$16 | DK20: =+G20/G$16 | DL20: =+H20/H$16 | DM20: =+I20/I$16 | DN20: =+J20/J$16 | DP20: =+L20/L$16 | DQ20: =+M20/M$16
B21: Implementation | F21: =+'COGS_Calcs'!F173 | G21: =+'COGS_Calcs'!G173 | H21: =+'COGS_Calcs'!H173 | I21: =+'COGS_Calcs'!I173 | J21: =+'COGS_Calcs'!J173 | K21: =+'COGS_Calcs'!K173 | L21: =+'COGS_Calcs'!L173 | M21: =+'COGS_Calcs'!M173 | O21: =+I21 | DJ21: =+F21/F$16 | DK21: =+G21/G$16 | DL21: =+H21/H$16 | DM21: =+I21/I$16 | DN21: =+J21/J$16 | DP21: =+L21/L$16 | DQ21: =+M21/M$16
B22: Total Cost of Sales | F22: =SUM(F19:F21) | G22: =SUM(G19:G21) | H22: =SUM(H19:H21) | I22: =SUM(I19:I21) | J22: =SUM(J19:J21) | K22: =SUM(K19:K21) | L22: =SUM(L19:L21) | M22: =SUM(M19:M21) | O22: =SUM(O19:O21) | DJ22: =+F22/F$16 | DK22: =+G22/G$16 | DL22: =+H22/H$16 | DM22: =+I22/I$16 | DN22: =+J22/J$16 | DP22: =+L22/L$16 | DQ22: =+M22/M$16
B24: Gross Profit | F24: =+SUM(F16,-F22) | G24: =+SUM(G16,-G22) | H24: =+SUM(H16,-H22) | I24: =+SUM(I16,-I22) | J24: =+SUM(J16,-J22) | K24: =+SUM(K16,-K22) | L24: =+SUM(L16,-L22) | M24: =+SUM(M16,-M22) | O24: =+SUM(O16,-O22) | DJ24: =+F24/F$16 | DK24: =+G24/G$16 | DL24: =+H24/H$16 | DM24: =+I24/I$16 | DN24: =+J24/J$16 | DP24: =+L24/L$16 | DQ24: =+M24/M$16
B26: Operating Expenses
B27: Payroll & Benefits | F27: =+'Opex_Calcs'!F44 | G27: =+'Opex_Calcs'!G44 | H27: =+'Opex_Calcs'!H44 | I27: =+'Opex_Calcs'!I44 | J27: =+'Opex_Calcs'!J44 | K27: =+'Opex_Calcs'!K44 | L27: =+'Opex_Calcs'!L44 | M27: =+'Opex_Calcs'!M44 | O27: =+I27 | DJ27: =+F27/F$16 | DK27: =+G27/G$16 | DL27: =+H27/H$16 | DM27: =+I27/I$16 | DN27: =+J27/J$16 | DP27: =+L27/L$16 | DQ27: =+M27/M$16
B28: Office and Occupancy | F28: =+'Opex_Calcs'!F46 | G28: =+'Opex_Calcs'!G46 | H28: =+'Opex_Calcs'!H46 | I28: =+'Opex_Calcs'!I46 | J28: =+'Opex_Calcs'!J46 | K28: =+'Opex_Calcs'!K46 | L28: =+'Opex_Calcs'!L46 | M28: =+'Opex_Calcs'!M46 | O28: =+I28 | DJ28: =+F28/F$16 | DK28: =+G28/G$16 | DL28: =+H28/H$16 | DM28: =+I28/I$16 | DN28: =+J28/J$16 | DP28: =+L28/L$16 | DQ28: =+M28/M$16
B29: HR Other | F29: =+'Opex_Calcs'!F47 | G29: =+'Opex_Calcs'!G47 | H29: =+'Opex_Calcs'!H47 | I29: =+'Opex_Calcs'!I47 | J29: =+'Opex_Calcs'!J47 | K29: =+'Opex_Calcs'!K47 | L29: =+'Opex_Calcs'!L47 | M29: =+'Opex_Calcs'!M47 | O29: =+I29 | DJ29: =+F29/F$16 | DK29: =+G29/G$16 | DL29: =+H29/H$16 | DM29: =+I29/I$16 | DN29: =+J29/J$16 | DP29: =+L29/L$16 | DQ29: =+M29/M$16
B30: Sales and Marketing | F30: =+'Opex_Calcs'!F48 | G30: =+'Opex_Calcs'!G48 | H30: =+'Opex_Calcs'!H48 | I30: =+'Opex_Calcs'!I48 | J30: =+'Opex_Calcs'!J48 | K30: =+'Opex_Calcs'!K48 | L30: =+'Opex_Calcs'!L48 | M30: =+'Opex_Calcs'!M48 | O30: =+I30 | DJ30: =+F30/F$16 | DK30: =+G30/G$16 | DL30: =+H30/H$16 | DM30: =+I30/I$16 | DN30: =+J30/J$16 | DP30: =+L30/L$16 | DQ30: =+M30/M$16
B31: Other G&A | F31: =+'Opex_Calcs'!F49 | G31: =+'Opex_Calcs'!G49 | H31: =+'Opex_Calcs'!H49 | I31: =+'Opex_Calcs'!I49 | J31: =+'Opex_Calcs'!J49 | K31: =+'Opex_Calcs'!K49 | L31: =+'Opex_Calcs'!L49 | M31: =+'Opex_Calcs'!M49 | O31: =+I31 | DJ31: =+F31/F$16 | DK31: =+G31/G$16 | DL31: =+H31/H$16 | DM31: =+I31/I$16 | DN31: =+J31/J$16 | DP31: =+L31/L$16 | DQ31: =+M31/M$16
B32: Professional Fees | F32: =+'Opex_Calcs'!F50 | G32: =+'Opex_Calcs'!G50 | H32: =+'Opex_Calcs'!H50 | I32: =+'Opex_Calcs'!I50 | J32: =+'Opex_Calcs'!J50 | K32: =+'Opex_Calcs'!K50 | L32: =+'Opex_Calcs'!L50 | M32: =+'Opex_Calcs'!M50 | O32: =+I32 | DJ32: =+F32/F$16 | DK32: =+G32/G$16 | DL32: =+H32/H$16 | DM32: =+I32/I$16 | DN32: =+J32/J$16 | DP32: =+L32/L$16 | DQ32: =+M32/M$16
B33: Service Costs | F33: =+'Opex_Calcs'!F51 | G33: =+'Opex_Calcs'!G51 | H33: =+'Opex_Calcs'!H51 | I33: =+'Opex_Calcs'!I51 | J33: =+'Opex_Calcs'!J51 | K33: =+'Opex_Calcs'!K51 | L33: =+'Opex_Calcs'!L51 | M33: =+'Opex_Calcs'!M51 | O33: =+I33 | DJ33: =+F33/F$16 | DK33: =+G33/G$16 | DL33: =+H33/H$16 | DM33: =+I33/I$16 | DN33: =+J33/J$16 | DP33: =+L33/L$16 | DQ33: =+M33/M$16
B34: Total Operating Expenses | F34: =+'Opex_Calcs'!F52 | G34: =+'Opex_Calcs'!G52 | H34: =+'Opex_Calcs'!H52 | I34: =+'Opex_Calcs'!I52 | J34: =+'Opex_Calcs'!J52 | K34: =+'Opex_Calcs'!K52 | L34: =+'Opex_Calcs'!L52 | M34: =+'Opex_Calcs'!M52 | O34: =+I34 | DJ34: =+F34/F$16 | DK34: =+G34/G$16 | DL34: =+H34/H$16 | DM34: =+I34/I$16 | DN34: =+J34/J$16 | DP34: =+L34/L$16 | DQ34: =+M34/M$16
B35: Other Income / Expenses | F35: =+'Opex_Calcs'!F55 | G35: =+'Opex_Calcs'!G55 | H35: =+'Opex_Calcs'!H55 | I35: =+'Opex_Calcs'!I55 | J35: =+'Opex_Calcs'!J55 | K35: =+'Opex_Calcs'!K55 | L35: =+'Opex_Calcs'!L55 | M35: =+'Opex_Calcs'!M55 | O35: =+I35 | DJ35: =+F35/F$16 | DK35: =+G35/G$16 | DL35: =+H35/H$16 | DM35: =+I35/I$16 | DN35: =+J35/J$16 | DP35: =+L35/L$16 | DQ35: =+M35/M$16
B37: Reported EBITDA | F37: =+SUM(F24,-F34,-F35) | G37: =+SUM(G24,-G34,-G35) | H37: =+SUM(H24,-H34,-H35) | I37: =+SUM(I24,-I34,-I35) | J37: =+SUM(J24,-J34,-J35) | K37: =+SUM(K24,-K34,-K35) | L37: =+SUM(L24,-L34,-L35) | M37: =+SUM(M24,-M34,-M35) | O37: =+SUM(O24,-O34,-O35) | DJ37: =+F37/F$16 | DK37: =+G37/G$16 | DL37: =+H37/H$16 | DM37: =+I37/I$16 | DN37: =+J37/J$16 | DP37: =+L37/L$16 | DQ37: =+M37/M$16
B39: Adjustments
B40: Non-cash Stock-based Compensation | F40: =SUMIFS($Q40:$DI40,$Q$7:$DI$7,F$7) | G40: =SUMIFS($Q40:$DI40,$Q$7:$DI$7,G$7) | H40: =SUMIFS($Q40:$DI40,$Q$7:$DI$7,H$7) | I40: =SUMIFS($Q40:$DI40,$Q$7:$DI$7,I$7) | J40: =SUMIFS($Q40:$DI40,$Q$7:$DI$7,J$7) | K40: =SUMIFS($Q40:$DI40,$Q$7:$DI$7,K$7) | L40: =SUMIFS($Q40:$DI40,$Q$7:$DI$7,L$7) | M40: =SUMIFS($Q40:$DI40,$Q$7:$DI$7,M$7) | O40: =+I40 | Q40: 20.833 | R40: 20.833 | S40: 20.833 | T40: 20.833 | U40: 20.833 | V40: 20.833 | W40: 20.833 | X40: 20.833 | Y40: 20.833 | Z40: 20.833 | AA40: 20.833 | AB40: -204.124 | AC40: 8.33333 | AD40: 8.33333 | AE40: 8.33333 | AF40: 8.33333 | AG40: 8.33333 | AH40: 8.33333 | AI40: 8.33333 | AJ40: 8.33333 | AK40: 8.33333 | AL40: 8.33333 | AM40: 8.33333 | AN40: -27.88063 | AO40: 2.08333 | AP40: 2.08333 | AQ40: 2.08333 | AR40: 2.08333 | AS40: 2.08333 | AT40: 2.08333 | AU40: 2.08333 | AV40: 2.08333 | AW40: 2.08333 | AX40: 2.08333 | AY40: 2.08333 | AZ40: 237.01437 | BA40: 0 | BB40: 0 | BC40: 0 | BD40: 0 | BE40: 0 | BF40: 0 | BG40: 0 | BH40: 0 | BI40: 0 | BJ40: 0 | BK40: 0 | BL40: 0 | BM40: 0 | BN40: 0 | BO40: 0 | BP40: 0 | BQ40: 0 | BR40: 0 | BS40: 0 | BT40: 0 | BU40: 0 | BV40: 0 | BW40: 0 | BX40: 0 | BY40: 0 | BZ40: 0 | CA40: 0 | CB40: 0 | CC40: 0 | CD40: 0 | CE40: 0 | CF40: 0 | CG40: 0 | CH40: 0 | CI40: 0 | CJ40: 0 | CK40: 0 | CL40: 0 | CM40: 0 | CN40: 0 | CO40: 0 | CP40: 0 | CQ40: 0 | CR40: 0 | CS40: 0 | CT40: 0 | CU40: 0 | CV40: 0 | CW40: 0 | CX40: 0 | CY40: 0 | CZ40: 0 | DA40: 0 | DB40: 0 | DC40: 0 | DD40: 0 | DE40: 0 | DF40: 0 | DG40: 0 | DH40: 0 | DJ40: =+F40/F$16 | DK40: =+G40/G$16 | DL40: =+H40/H$16 | DM40: =+I40/I$16 | DN40: =+J40/J$16 | DP40: =+L40/L$16 | DQ40: =+M40/M$16
B41: Other Miscellaneous Items | F41: =SUMIFS($Q41:$DI41,$Q$7:$DI$7,F$7) | G41: =SUMIFS($Q41:$DI41,$Q$7:$DI$7,G$7) | H41: =SUMIFS($Q41:$DI41,$Q$7:$DI$7,H$7) | I41: =SUMIFS($Q41:$DI41,$Q$7:$DI$7,I$7) | J41: =SUMIFS($Q41:$DI41,$Q$7:$DI$7,J$7) | K41: =SUMIFS($Q41:$DI41,$Q$7:$DI$7,K$7) | L41: =SUMIFS($Q41:$DI41,$Q$7:$DI$7,L$7) | M41: =SUMIFS($Q41:$DI41,$Q$7:$DI$7,M$7) | O41: =+I41 | Q41: 9.25165 | R41: 3.01295 | S41: 16.41295 | T41: -4.58705 | U41: 4.78698 | V41: 3.01295 | W41: 13.01295 | X41: 20.44512 | Y41: 17.51013 | Z41: 1.88017 | AA41: 11.52846 | AB41: 14.82482 | AC41: 12.5 | AD41: 13.65994 | AE41: 22.392 | AF41: 19.868 | AG41: 4.9663 | AH41: 18.383 | AI41: -69.84 | AJ41: 2.502 | AK41: 2.549 | AL41: 3.96917 | AM41: 3.8983 | AN41: 11.64995 | AO41: 0.76966667 | AP41: 0.76966667 | AQ41: 1.5246667 | AR41: 0.75466667 | AS41: 2.2554467 | AT41: -5.2453333 | AU41: -0.29328333 | AV41: 3.3546667 | AW41: 15.004667 | AX41: 14.5 | AY41: 1.38931 | AZ41: 0 | BA41: 0 | BB41: 0 | BC41: 0 | BD41: 0 | BE41: 0 | BF41: 0 | BG41: 0 | BH41: 0 | BI41: 0 | BJ41: 0 | BK41: 0 | BL41: 0 | BM41: 0 | BN41: 0 | BO41: 0 | BP41: 0 | BQ41: 0 | BR41: 0 | BS41: 0 | BT41: 0 | BU41: 0 | BV41: 0 | BW41: 0 | BX41: 0 | BY41: 0 | BZ41: 0 | CA41: 0 | CB41: 0 | CC41: 0 | CD41: 0 | CE41: 0 | CF41: 0 | CG41: 0 | CH41: 0 | CI41: 0 | CJ41: 0 | CK41: 0 | CL41: 0 | CM41: 0 | CN41: 0 | CO41: 0 | CP41: 0 | CQ41: 0 | CR41: 0 | CS41: 0 | CT41: 0 | CU41: 0 | CV41: 0 | CW41: 0 | CX41: 0 | CY41: 0 | CZ41: 0 | DA41: 0 | DB41: 0 | DC41: 0 | DD41: 0 | DE41: 0 | DF41: 0 | DG41: 0 | DH41: 0 | DJ41: =+F41/F$16 | DK41: =+G41/G$16 | DL41: =+H41/H$16 | DM41: =+I41/I$16 | DN41: =+J41/J$16 | DP41: =+L41/L$16 | DQ41: =+M41/M$16
B42: Employee Related Expenses | F42: =SUMIFS($Q42:$DI42,$Q$7:$DI$7,F$7) | G42: =SUMIFS($Q42:$DI42,$Q$7:$DI$7,G$7) | H42: =SUMIFS($Q42:$DI42,$Q$7:$DI$7,H$7) | I42: =SUMIFS($Q42:$DI42,$Q$7:$DI$7,I$7) | J42: =SUMIFS($Q42:$DI42,$Q$7:$DI$7,J$7) | K42: =SUMIFS($Q42:$DI42,$Q$7:$DI$7,K$7) | L42: =SUMIFS($Q42:$DI42,$Q$7:$DI$7,L$7) | M42: =SUMIFS($Q42:$DI42,$Q$7:$DI$7,M$7) | O42: =+I42 | Q42: 8.4869783 | R42: 38.358638 | S42: 8.3586383 | T42: 10.358638 | U42: 8.3586383 | V42: 8.3586383 | W42: 11.358638 | X42: 18.858638 | Y42: 17.358638 | Z42: 13.983638 | AA42: 19.014638 | AB42: -79.323362 | AC42: 13.517087 | AD42: 13.095877 | AE42: 18.054667 | AF42: 16.147717 | AG42: 3.7620867 | AH42: -1.2379133 | AI42: -1.2379133 | AJ42: -1.2379133 | AK42: -1.2379233 | AL42: -1.2379233 | AM42: 55.257077 | AN42: -9.0089233 | AO42: 8.04 | AP42: 0.52568 | AQ42: 0 | AR42: 0 | AS42: 0 | AT42: 0.28933 | AU42: 0 | AV42: 5 | AW42: 17.11879 | AX42: 0 | AY42: 0 | AZ42: 0 | BA42: 0 | BB42: 0 | BC42: 0 | BD42: 0 | BE42: 0 | BF42: 0 | BG42: 0 | BH42: 0 | BI42: 0 | BJ42: 0 | BK42: 0 | BL42: 0 | BM42: 0 | BN42: 0 | BO42: 0 | BP42: 0 | BQ42: 0 | BR42: 0 | BS42: 0 | BT42: 0 | BU42: 0 | BV42: 0 | BW42: 0 | BX42: 0 | BY42: 0 | BZ42: 0 | CA42: 0 | CB42: 0 | CC42: 0 | CD42: 0 | CE42: 0 | CF42: 0 | CG42: 0 | CH42: 0 | CI42: 0 | CJ42: 0 | CK42: 0 | CL42: 0 | CM42: 0 | CN42: 0 | CO42: 0 | CP42: 0 | CQ42: 0 | CR42: 0 | CS42: 0 | CT42: 0 | CU42: 0 | CV42: 0 | CW42: 0 | CX42: 0 | CY42: 0 | CZ42: 0 | DA42: 0 | DB42: 0 | DC42: 0 | DD42: 0 | DE42: 0 | DF42: 0 | DG42: 0 | DH42: 0 | DJ42: =+F42/F$16 | DK42: =+G42/G$16 | DL42: =+H42/H$16 | DM42: =+I42/I$16 | DN42: =+J42/J$16 | DP42: =+L42/L$16 | DQ42: =+M42/M$16
B43: Non-recurring Build Subsidies | F43: =SUMIFS($Q43:$DI43,$Q$7:$DI$7,F$7) | G43: =SUMIFS($Q43:$DI43,$Q$7:$DI$7,G$7) | H43: =SUMIFS($Q43:$DI43,$Q$7:$DI$7,H$7) | I43: =SUMIFS($Q43:$DI43,$Q$7:$DI$7,I$7) | J43: =SUMIFS($Q43:$DI43,$Q$7:$DI$7,J$7) | K43: =SUMIFS($Q43:$DI43,$Q$7:$DI$7,K$7) | L43: =SUMIFS($Q43:$DI43,$Q$7:$DI$7,L$7) | M43: =SUMIFS($Q43:$DI43,$Q$7:$DI$7,M$7) | O43: =+I43 | Q43: 135.84913 | R43: 219.74271 | S43: 294.61578 | T43: 237.61969 | U43: 282.9635 | V43: 333.30398 | W43: 341.19059 | X43: 405.02271 | Y43: 323.66688 | Z43: 428.12455 | AA43: 312.23943 | AB43: 277.35696 | AC43: 290.11101 | AD43: 288.41538 | AE43: 370.12266 | AF43: 315.70853 | AG43: 291.44613 | AH43: 213.13591 | AI43: 169.27227 | AJ43: 137.43883 | AK43: 120.37583 | AL43: 83.636543 | AM43: -6.8386667 | AN43: -3.91747 | AO43: 61.8405 | AP43: 37.405 | AQ43: 51.271 | AR43: 47.215 | AS43: 48.908 | AT43: -15.65 | AU43: -14.851 | AV43: 61.208 | AW43: -0.169 | AX43: 30.794 | AY43: 26.507 | AZ43: 23.922 | BA43: 12.1 | BB43: 13.695 | BC43: 52.25 | BD43: 34.241182 | BE43: 13.521848 | BF43: 24.521848 | BG43: 27.271848 | BH43: 39.741182 | BI43: 36.991182 | BJ43: 23.241182 | BK43: 19.721182 | BL43: 12.241182 | BM43: 13.441182 | BN43: 7.6411818 | BO43: 8.7 | BP43: 5.8 | BQ43: 2.9 | BR43: 0 | BS43: 0 | BT43: 0 | BU43: 0 | BV43: 0 | BW43: 0 | BX43: 0 | BY43: 0 | BZ43: 0 | CA43: 0 | CB43: 0 | CC43: 0 | CD43: 0 | CE43: 0 | CF43: 0 | CG43: 0 | CH43: 0 | CI43: 0 | CJ43: 0 | CK43: 0 | CL43: 0 | CM43: 0 | CN43: 0 | CO43: 0 | CP43: 0 | CQ43: 0 | CR43: 0 | CS43: 0 | CT43: 0 | CU43: 0 | CV43: 0 | CW43: 0 | CX43: 0 | CY43: 0 | CZ43: 0 | DA43: 0 | DB43: 0 | DC43: 0 | DD43: 0 | DE43: 0 | DF43: 0 | DG43: 0 | DH43: 0 | DJ43: =+F43/F$16 | DK43: =+G43/G$16 | DL43: =+H43/H$16 | DM43: =+I43/I$16 | DN43: =+J43/J$16 | DP43: =+L43/L$16 | DQ43: =+M43/M$16
B44: Duplicative Hosting Costs | F44: =SUMIFS($Q44:$DI44,$Q$7:$DI$7,F$7) | G44: =SUMIFS($Q44:$DI44,$Q$7:$DI$7,G$7) | H44: =SUMIFS($Q44:$DI44,$Q$7:$DI$7,H$7) | I44: =SUMIFS($Q44:$DI44,$Q$7:$DI$7,I$7) | J44: =SUMIFS($Q44:$DI44,$Q$7:$DI$7,J$7) | K44: =SUMIFS($Q44:$DI44,$Q$7:$DI$7,K$7) | L44: =SUMIFS($Q44:$DI44,$Q$7:$DI$7,L$7) | M44: =SUMIFS($Q44:$DI44,$Q$7:$DI$7,M$7) | O44: =+I44 | Q44: 0 | R44: 0 | S44: 0 | T44: 0 | U44: 0 | V44: 0 | W44: 0 | X44: 0 | Y44: 0 | Z44: 0 | AA44: 0 | AB44: 0 | AC44: 0 | AD44: 0 | AE44: 3.51225 | AF44: 3.51225 | AG44: 3.51225 | AH44: 29.2315 | AI44: 1.6034413 | AJ44: 1.6034413 | AK44: 3.9133879 | AL44: 5.2761676 | AM44: 5.1352645 | AN44: 7.4517559 | AO44: 14.374712 | AP44: 11.373587 | AQ44: 23.293 | AR44: 22.4 | AS44: 9.028 | AT44: 6.87705 | AU44: 6.44708 | AV44: 6.44708 | AW44: 6.44708 | AX44: 6.44708 | AY44: 6.44708 | AZ44: 6.44708 | BA44: 0 | BB44: 0 | BC44: 0 | BD44: 0 | BE44: 0 | BF44: 0 | BG44: 0 | BH44: 0 | BI44: 0 | BJ44: 0 | BK44: 0 | BL44: 0 | BM44: 0 | BN44: 0 | BO44: 0 | BP44: 0 | BQ44: 0 | BR44: 0 | BS44: 0 | BT44: 0 | BU44: 0 | BV44: 0 | BW44: 0 | BX44: 0 | BY44: 0 | BZ44: 0 | CA44: 0 | CB44: 0 | CC44: 0 | CD44: 0 | CE44: 0 | CF44: 0 | CG44: 0 | CH44: 0 | CI44: 0 | CJ44: 0 | CK44: 0 | CL44: 0 | CM44: 0 | CN44: 0 | CO44: 0 | CP44: 0 | CQ44: 0 | CR44: 0 | CS44: 0 | CT44: 0 | CU44: 0 | CV44: 0 | CW44: 0 | CX44: 0 | CY44: 0 | CZ44: 0 | DA44: 0 | DB44: 0 | DC44: 0 | DD44: 0 | DE44: 0 | DF44: 0 | DG44: 0 | DH44: 0 | DJ44: =+F44/F$16 | DK44: =+G44/G$16 | DL44: =+H44/H$16 | DM44: =+I44/I$16 | DN44: =+J44/J$16 | DP44: =+L44/L$16 | DQ44: =+M44/M$16
B45: COVID-19 Marketing Cost Savings | F45: =SUMIFS($Q45:$DI45,$Q$7:$DI$7,F$7) | G45: =SUMIFS($Q45:$DI45,$Q$7:$DI$7,G$7) | H45: =SUMIFS($Q45:$DI45,$Q$7:$DI$7,H$7) | I45: =SUMIFS($Q45:$DI45,$Q$7:$DI$7,I$7) | J45: =SUMIFS($Q45:$DI45,$Q$7:$DI$7,J$7) | K45: =SUMIFS($Q45:$DI45,$Q$7:$DI$7,K$7) | L45: =SUMIFS($Q45:$DI45,$Q$7:$DI$7,L$7) | M45: =SUMIFS($Q45:$DI45,$Q$7:$DI$7,M$7) | O45: =+I45 | Q45: 0 | R45: 0 | S45: 0 | T45: 0 | U45: 0 | V45: 0 | W45: 0 | X45: 0 | Y45: 147.40685 | Z45: 63.98637 | AA45: 0 | AB45: 0 | AC45: 0 | AD45: 0 | AE45: 0 | AF45: 0 | AG45: 0 | AH45: 0 | AI45: 0 | AJ45: 0 | AK45: 0 | AL45: 0 | AM45: 0 | AN45: 0 | AO45: 0 | AP45: 0 | AQ45: 11.452 | AR45: 0 | AS45: 0 | AT45: 0 | AU45: 0 | AV45: 0 | AW45: 0 | AX45: 0 | AY45: 0 | AZ45: 0 | BA45: 0 | BB45: 0 | BC45: 0 | BD45: 0 | BE45: 0 | BF45: 0 | BG45: 0 | BH45: 0 | BI45: 0 | BJ45: 0 | BK45: 0 | BL45: 0 | BM45: 0 | BN45: 0 | BO45: 0 | BP45: 0 | BQ45: 0 | BR45: 0 | BS45: 0 | BT45: 0 | BU45: 0 | BV45: 0 | BW45: 0 | BX45: 0 | BY45: 0 | BZ45: 0 | CA45: 0 | CB45: 0 | CC45: 0 | CD45: 0 | CE45: 0 | CF45: 0 | CG45: 0 | CH45: 0 | CI45: 0 | CJ45: 0 | CK45: 0 | CL45: 0 | CM45: 0 | CN45: 0 | CO45: 0 | CP45: 0 | CQ45: 0 | CR45: 0 | CS45: 0 | CT45: 0 | CU45: 0 | CV45: 0 | CW45: 0 | CX45: 0 | CY45: 0 | CZ45: 0 | DA45: 0 | DB45: 0 | DC45: 0 | DD45: 0 | DE45: 0 | DF45: 0 | DG45: 0 | DH45: 0 | DJ45: =+F45/F$16 | DK45: =+G45/G$16 | DL45: =+H45/H$16 | DM45: =+I45/I$16 | DN45: =+J45/J$16 | DP45: =+L45/L$16 | DQ45: =+M45/M$16
B46: Normalized Legal Fees | F46: =SUMIFS($Q46:$DI46,$Q$7:$DI$7,F$7) | G46: =SUMIFS($Q46:$DI46,$Q$7:$DI$7,G$7) | H46: =SUMIFS($Q46:$DI46,$Q$7:$DI$7,H$7) | I46: =SUMIFS($Q46:$DI46,$Q$7:$DI$7,I$7) | J46: =SUMIFS($Q46:$DI46,$Q$7:$DI$7,J$7) | K46: =SUMIFS($Q46:$DI46,$Q$7:$DI$7,K$7) | L46: =SUMIFS($Q46:$DI46,$Q$7:$DI$7,L$7) | M46: =SUMIFS($Q46:$DI46,$Q$7:$DI$7,M$7) | O46: =+I46 | Q46: 14.423127 | R46: 14.423127 | S46: 39.423127 | T46: 17.423127 | U46: 17.423127 | V46: -2.5768733 | W46: -2.5768733 | X46: -40.012373 | Y46: 4.0137367 | Z46: -2.7363733 | AA46: -1.4603733 | AB46: -7.2245233 | AC46: 18.256457 | AD46: 18.256457 | AE46: 16.441457 | AF46: 8.2929467 | AG46: 16.230577 | AH46: 13.560577 | AI46: 16.230577 | AJ46: 15.223577 | AK46: 11.818587 | AL46: -128.77147 | AM46: -2.2628733 | AN46: -2.5768733 | AO46: 0 | AP46: 0 | AQ46: 0 | AR46: 0 | AS46: 0 | AT46: 0 | AU46: 0 | AV46: 0 | AW46: 0 | AX46: 0 | AY46: 0 | AZ46: 0 | BA46: 0 | BB46: 0 | BC46: 0 | BD46: 0 | BE46: 0 | BF46: 0 | BG46: 0 | BH46: 0 | BI46: 0 | BJ46: 0 | BK46: 0 | BL46: 0 | BM46: 0 | BN46: 0 | BO46: 0 | BP46: 0 | BQ46: 0 | BR46: 0 | BS46: 0 | BT46: 0 | BU46: 0 | BV46: 0 | BW46: 0 | BX46: 0 | BY46: 0 | BZ46: 0 | CA46: 0 | CB46: 0 | CC46: 0 | CD46: 0 | CE46: 0 | CF46: 0 | CG46: 0 | CH46: 0 | CI46: 0 | CJ46: 0 | CK46: 0 | CL46: 0 | CM46: 0 | CN46: 0 | CO46: 0 | CP46: 0 | CQ46: 0 | CR46: 0 | CS46: 0 | CT46: 0 | CU46: 0 | CV46: 0 | CW46: 0 | CX46: 0 | CY46: 0 | CZ46: 0 | DA46: 0 | DB46: 0 | DC46: 0 | DD46: 0 | DE46: 0 | DF46: 0 | DG46: 0 | DH46: 0 | DJ46: =+F46/F$16 | DK46: =+G46/G$16 | DL46: =+H46/H$16 | DM46: =+I46/I$16 | DN46: =+J46/J$16 | DP46: =+L46/L$16 | DQ46: =+M46/M$16
B47: Eligible Costs for Capitalization | F47: =SUMIFS($Q47:$DI47,$Q$7:$DI$7,F$7) | G47: =SUMIFS($Q47:$DI47,$Q$7:$DI$7,G$7) | H47: =SUMIFS($Q47:$DI47,$Q$7:$DI$7,H$7) | I47: =SUMIFS($Q47:$DI47,$Q$7:$DI$7,I$7) | J47: =SUMIFS($Q47:$DI47,$Q$7:$DI$7,J$7) | K47: =SUMIFS($Q47:$DI47,$Q$7:$DI$7,K$7) | L47: =SUMIFS($Q47:$DI47,$Q$7:$DI$7,L$7) | M47: =SUMIFS($Q47:$DI47,$Q$7:$DI$7,M$7) | O47: =+I47 | DJ47: =+F47/F$16 | DK47: =+G47/G$16 | DL47: =+H47/H$16 | DM47: =+I47/I$16 | DN47: =+J47/J$16 | DP47: =+L47/L$16 | DQ47: =+M47/M$16
B48: Total Adjustments | F48: =SUM(F40:F47) | G48: =SUM(G40:G47) | H48: =SUM(H40:H47) | I48: =SUM(I40:I47) | J48: =SUM(J40:J47) | K48: =SUM(K40:K47) | L48: =SUM(L40:L47) | M48: =SUM(M40:M47) | O48: =+I48 | Q48: =SUM(Q40:Q46) | DJ48: =+F48/F$16 | DK48: =+G48/G$16 | DL48: =+H48/H$16 | DM48: =+I48/I$16 | DN48: =+J48/J$16 | DP48: =+L48/L$16 | DQ48: =+M48/M$16
B50: Adjusted EBITDA | F50: =+SUM(F37,F48) | G50: =+SUM(G37,G48) | H50: =+SUM(H37,H48) | I50: =+SUM(I37,I48) | J50: =+SUM(J37,J48) | K50: =+SUM(K37,K48) | L50: =+SUM(L37,L48) | M50: =+SUM(M37,M48) | O50: =+SUM(O37,O48) | Q50: =+SUM(Q37,Q48) | R50: =+SUM(R37,R48) | S50: =+SUM(S37,S48) | T50: =+SUM(T37,T48) | U50: =+SUM(U37,U48) | V50: =+SUM(V37,V48) | W50: =+SUM(W37,W48) | X50: =+SUM(X37,X48) | ... DH50: =+SUM(DH37,DH48) | DJ50: =+F50/F$16 | DK50: =+G50/G$16 | DL50: =+H50/H$16 | DM50: =+I50/I$16 | DN50: =+J50/J$16 | DP50: =+L50/L$16 | DQ50: =+M50/M$16

Sheet Calculations ->

Sheet Revenue_Calcs
B2: Project Shasta
B3: {=MID(CELL("filename",A1),FIND("]",CELL("filename",A1))+1,255)}
B4: Spring 2022
B5: CONFIDENTIAL
E7: 2018 | F7: =+E7+1 | G7: =+F7+1 | H7: =+G7+1 | I7: =+H7+1 | J7: =+I7+1 | K7: =+J7+1 | L7: =+K7+1 | M7: =+L7+1 | O7: =+YEAR(O8) | P7: =+YEAR(P8) | Q7: =+YEAR(Q8) | R7: =+YEAR(R8) | S7: =+YEAR(S8) | T7: =+YEAR(T8) | U7: =+YEAR(U8) | V7: =+YEAR(V8) | ... DR7: =+YEAR(DR8)
E8: =+DATE(E7,12,31) | F8: =+DATE(F7,12,31) | G8: =+DATE(G7,12,31) | H8: =+DATE(H7,12,31) | I8: =+DATE(I7,12,31) | J8: =+DATE(J7,12,31) | K8: =+DATE(K7,12,31) | L8: =+DATE(L7,12,31) | M8: =+DATE(M7,12,31) | O8: 43131 | P8: =+EOMONTH(O8,1) | Q8: =+EOMONTH(P8,1) | R8: =+EOMONTH(Q8,1) | S8: =+EOMONTH(R8,1) | T8: =+EOMONTH(S8,1) | U8: =+EOMONTH(T8,1) | V8: =+EOMONTH(U8,1) | W8: =+EOMONTH(V8,1) | ... DR8: =+EOMONTH(DQ8,1) | DT8: Upsell / Downsell
B9: $ in thousands | E9: Actual | F9: Actual | G9: Actual | H9: Actual | I9: Budget | J9: Projection | K9: Projection | L9: Projection | M9: Projection | O9: Actual | P9: Actual | Q9: Actual | R9: Actual | S9: Actual | T9: Actual | U9: Actual | V9: Actual | W9: Actual | X9: Actual | Y9: Actual | Z9: Actual | AA9: Actual | AB9: Actual | AC9: Actual | AD9: Actual | AE9: Actual | AF9: Actual | AG9: Actual | AH9: Actual | AI9: Actual | AJ9: Actual | AK9: Actual | AL9: Actual | AM9: Actual | AN9: Actual | AO9: Actual | AP9: Actual | AQ9: Actual | AR9: Actual | AS9: Actual | AT9: Actual | AU9: Actual | AV9: Actual | AW9: Actual | AX9: Actual | AY9: Actual | AZ9: Actual | BA9: Actual | BB9: Actual | BC9: Actual | BD9: Actual | BE9: Actual | BF9: Actual | BG9: Actual | BH9: Actual | BI9: Actual | BJ9: Actual | BK9: Actual | BL9: Actual | BM9: Actual | BN9: Projection | BO9: Projection | BP9: Projection | BQ9: Projection | BR9: Projection | BS9: Projection | BT9: Projection | BU9: Projection | BV9: Projection | BW9: Projection | BX9: Projection | BY9: Projection | BZ9: Projection | CA9: Projection | CB9: Projection | CC9: Projection | CD9: Projection | CE9: Projection | CF9: Projection | CG9: Projection | CH9: Projection | CI9: Projection | CJ9: Projection | CK9: Projection | CL9: Projection | CM9: Projection | CN9: Projection | CO9: Projection | CP9: Projection | CQ9: Projection | CR9: Projection | CS9: Projection | CT9: Projection | CU9: Projection | CV9: Projection | CW9: Projection | CX9: Projection | CY9: Projection | CZ9: Projection | DA9: Projection | DB9: Projection | DC9: Projection | DD9: Projection | DE9: Projection | DF9: Projection | DG9: Projection | DH9: Projection | DI9: Projection | DJ9: Projection | DK9: Projection | DL9: Projection | DM9: Projection | DN9: Projection | DO9: Projection | DP9: Projection | DQ9: Projection | DR9: Projection | DT9: 2019 | DU9: 2020 | DV9: 2021 | DW9: 2022
B11: Licensing
B13: AACN | C13: Lower Middle Market | E13: =+SUMIFS($O13:$DR13,$O$7:$DR$7,E$7) | F13: =+SUMIFS($O13:$DR13,$O$7:$DR$7,F$7) | G13: =+SUMIFS($O13:$DR13,$O$7:$DR$7,G$7) | H13: =+SUMIFS($O13:$DR13,$O$7:$DR$7,H$7) | I13: =+SUMIFS($O13:$DR13,$O$7:$DR$7,I$7) | J13: =+SUMIFS($O13:$DR13,$O$7:$DR$7,J$7) | K13: =+SUMIFS($O13:$DR13,$O$7:$DR$7,K$7) | L13: =+SUMIFS($O13:$DR13,$O$7:$DR$7,L$7) | M13: =+SUMIFS($O13:$DR13,$O$7:$DR$7,M$7) | O13: 0 | P13: 0 | Q13: 0 | R13: 0 | S13: 0 | T13: 0 | U13: 0 | V13: 0 | W13: 0 | X13: 0 | Y13: 0 | Z13: 0 | AA13: 0 | AB13: 0 | AC13: 0 | AD13: 0 | AE13: 0 | AF13: 0 | AG13: 0 | AH13: 0 | AI13: 0 | AJ13: 0 | AK13: 0 | AL13: 13.416 | AM13: 9.584 | AN13: 9.583 | AO13: 9.583 | AP13: 9.583 | AQ13: 9.583 | AR13: 9.584 | AS13: 9.584 | AT13: 9.584 | AU13: 8.23 | AV13: 9.583 | AW13: 9.584 | AX13: 9.871 | AY13: 9.8708333 | AZ13: 9.8708333 | BA13: 9.8708333 | BB13: 9.8708333 | BC13: 9.8708333 | BD13: 9.8708333 | BE13: 9.8708333 | BF13: 9.8708333 | BG13: 9.8708333 | BH13: 9.8708333 | BI13: 9.8708333 | BJ13: 10.166958 | BK13: 10.166958 | BL13: 10.166958 | BM13: 10.166958 | BN13: 10.166958 | BO13: 10.166958 | BP13: 10.166958 | BQ13: 10.166958 | BR13: 10.166958 | BS13: 10.166958 | BT13: 10.166958 | BU13: 10.166958 | BV13: 10.471967 | BW13: 10.471967 | BX13: 10.471967 | BY13: 10.471967 | BZ13: 10.471967 | CA13: 10.471967 | CB13: 10.471967 | CC13: 10.471967 | CD13: 10.471967 | CE13: 10.471967 | CF13: 10.471967 | CG13: 10.471967 | CH13: 10.786126 | CI13: 10.786126 | CJ13: 10.786126 | CK13: 10.786126 | CL13: 10.786126 | CM13: 10.786126 | CN13: 10.786126 | CO13: 10.786126 | CP13: 10.786126 | CQ13: 10.786126 | CR13: 10.786126 | CS13: 10.786126 | CT13: 0 | CU13: 0 | CV13: 0 | CW13: 0 | CX13: 0 | CY13: 0 | CZ13: 0 | DA13: 0 | DB13: 0 | DC13: 0 | DD13: 0 | DE13: 0 | DF13: 0 | DG13: 0 | DH13: 0 | DI13: 0 | DJ13: 0 | DK13: 0 | DL13: 0 | DM13: 0 | DN13: 0 | DO13: 0 | DP13: 0 | DQ13: 0 | DR13: 0 | DT13: =+F13-E13 | DU13: =+G13-F13 | DV13: =+H13-G13 | DW13: =+I13-H13
B14: AACR | C14: Lower Middle Market | E14: =+SUMIFS($O14:$DR14,$O$7:$DR$7,E$7) | F14: =+SUMIFS($O14:$DR14,$O$7:$DR$7,F$7) | G14: =+SUMIFS($O14:$DR14,$O$7:$DR$7,G$7) | H14: =+SUMIFS($O14:$DR14,$O$7:$DR$7,H$7) | I14: =+SUMIFS($O14:$DR14,$O$7:$DR$7,I$7) | J14: =+SUMIFS($O14:$DR14,$O$7:$DR$7,J$7) | K14: =+SUMIFS($O14:$DR14,$O$7:$DR$7,K$7) | L14: =+SUMIFS($O14:$DR14,$O$7:$DR$7,L$7) | M14: =+SUMIFS($O14:$DR14,$O$7:$DR$7,M$7) | O14: 0 | P14: 0 | Q14: 0 | R14: 0 | S14: 0 | T14: 0 | U14: 0 | V14: 0 | W14: 0 | X14: 0 | Y14: 0 | Z14: 0 | AA14: 0 | AB14: 0 | AC14: 0 | AD14: 0 | AE14: 0 | AF14: 0 | AG14: 0 | AH14: 0 | AI14: 0 | AJ14: 0 | AK14: 0 | AL14: 0 | AM14: 0 | AN14: 0 | AO14: 0 | AP14: 0 | AQ14: 0 | AR14: 0 | AS14: 0 | AT14: 0 | AU14: 0 | AV14: 0 | AW14: 0 | AX14: 0 | AY14: 0 | AZ14: 0 | BA14: 0 | BB14: 0 | BC14: 0 | BD14: 0 | BE14: 0 | BF14: 0 | BG14: 0 | BH14: 2.916 | BI14: 2.916 | BJ14: 14.583 | BK14: 14.583333 | BL14: 14.583333 | BM14: 14.583333 | BN14: 14.583333 | BO14: 14.583333 | BP14: 14.583333 | BQ14: 14.583333 | BR14: 14.583333 | BS14: 14.583333 | BT14: 14.583333 | BU14: 14.583333 | BV14: 15.3125 | BW14: 15.3125 | BX14: 15.3125 | BY14: 15.3125 | BZ14: 15.3125 | CA14: 15.3125 | CB14: 15.3125 | CC14: 15.3125 | CD14: 15.3125 | CE14: 15.3125 | CF14: 15.3125 | CG14: 15.3125 | CH14: 16.078 | CI14: 16.078 | CJ14: 16.078 | CK14: 16.078 | CL14: 16.078 | CM14: 16.078 | CN14: 16.078 | CO14: 16.078 | CP14: 16.078 | CQ14: 16.078 | CR14: 16.078 | CS14: 16.078 | CT14: 16.882 | CU14: 16.882 | CV14: 16.882 | CW14: 16.882 | CX14: 16.882 | CY14: 16.882 | CZ14: 16.882 | DA14: 16.882 | DB14: 16.882 | DC14: 16.882 | DD14: 16.882 | DE14: 16.882 | DF14: 17.7261 | DG14: 17.7261 | DH14: 17.7261 | DI14: 17.7261 | DJ14: 17.7261 | DK14: 17.7261 | DL14: 17.7261 | DM14: 17.7261 | DN14: 17.7261 | DO14: 17.7261 | DP14: 17.7261 | DQ14: 17.7261 | DR14: 0 | DT14: =+F14-E14 | DU14: =+G14-F14 | DV14: =+H14-G14 | DW14: =+I14-H14
B15: AAI | C15: Lower Middle Market | E15: =+SUMIFS($O15:$DR15,$O$7:$DR$7,E$7) | F15: =+SUMIFS($O15:$DR15,$O$7:$DR$7,F$7) | G15: =+SUMIFS($O15:$DR15,$O$7:$DR$7,G$7) | H15: =+SUMIFS($O15:$DR15,$O$7:$DR$7,H$7) | I15: =+SUMIFS($O15:$DR15,$O$7:$DR$7,I$7) | J15: =+SUMIFS($O15:$DR15,$O$7:$DR$7,J$7) | K15: =+SUMIFS($O15:$DR15,$O$7:$DR$7,K$7) | L15: =+SUMIFS($O15:$DR15,$O$7:$DR$7,L$7) | M15: =+SUMIFS($O15:$DR15,$O$7:$DR$7,M$7) | O15: 0 | P15: 0 | Q15: 0 | R15: 0 | S15: 0 | T15: 0 | U15: 0 | V15: 0 | W15: 0 | X15: 0 | Y15: 0 | Z15: 0 | AA15: 0 | AB15: 0 | AC15: 0 | AD15: 0 | AE15: 0 | AF15: 0 | AG15: 0 | AH15: 0 | AI15: 0 | AJ15: 0 | AK15: 0 | AL15: 0 | AM15: 0 | AN15: 0 | AO15: 0 | AP15: 0 | AQ15: 0 | AR15: 0 | AS15: 0 | AT15: 0 | AU15: 0 | AV15: 0 | AW15: 0 | AX15: 0 | AY15: 0 | AZ15: 0 | BA15: 0 | BB15: 0 | BC15: 0 | BD15: 0 | BE15: 0 | BF15: 0 | BG15: 0 | BH15: 0 | BI15: 0 | BJ15: 0 | BK15: 0 | BL15: 0 | BM15: 2 | BN15: 2 | BO15: 2 | BP15: 2 | BQ15: 2 | BR15: 2 | BS15: 2 | BT15: 2 | BU15: 12.458333 | BV15: 12.458333 | BW15: 12.458333 | BX15: 12.458333 | BY15: 12.458333 | BZ15: 12.458333 | CA15: 12.458333 | CB15: 12.458333 | CC15: 12.458333 | CD15: 12.458333 | CE15: 12.458333 | CF15: 12.458333 | CG15: 12.832083 | CH15: 12.832083 | CI15: 12.832083 | CJ15: 12.832083 | CK15: 12.832083 | CL15: 12.832083 | CM15: 12.832083 | CN15: 12.832083 | CO15: 12.832083 | CP15: 12.832083 | CQ15: 12.832083 | CR15: 12.832083 | CS15: 13.217046 | CT15: 13.217046 | CU15: 13.217046 | CV15: 13.217046 | CW15: 13.217046 | CX15: 13.217046 | CY15: 13.217046 | CZ15: 13.217046 | DA15: 13.217046 | DB15: 13.217046 | DC15: 13.217046 | DD15: 13.217046 | DE15: 13.613557 | DF15: 13.613557 | DG15: 13.613557 | DH15: 13.613557 | DI15: 13.613557 | DJ15: 13.613557 | DK15: 13.613557 | DL15: 13.613557 | DM15: 13.613557 | DN15: 13.613557 | DO15: 13.613557 | DP15: 13.613557 | DQ15: 14.021964 | DR15: 14.021964 | DT15: =+F15-E15 | DU15: =+G15-F15 | DV15: =+H15-G15 | DW15: =+I15-H15
B16: AAOS | C16: Upper Middle Market | E16: =+SUMIFS($O16:$DR16,$O$7:$DR$7,E$7) | F16: =+SUMIFS($O16:$DR16,$O$7:$DR$7,F$7) | G16: =+SUMIFS($O16:$DR16,$O$7:$DR$7,G$7) | H16: =+SUMIFS($O16:$DR16,$O$7:$DR$7,H$7) | I16: =+SUMIFS($O16:$DR16,$O$7:$DR$7,I$7) | J16: =+SUMIFS($O16:$DR16,$O$7:$DR$7,J$7) | K16: =+SUMIFS($O16:$DR16,$O$7:$DR$7,K$7) | L16: =+SUMIFS($O16:$DR16,$O$7:$DR$7,L$7) | M16: =+SUMIFS($O16:$DR16,$O$7:$DR$7,M$7) | O16: 0 | P16: 0 | Q16: 0 | R16: 0 | S16: 0 | T16: 0 | U16: 0 | V16: 0 | W16: 0 | X16: 0 | Y16: 0 | Z16: 0 | AA16: 0 | AB16: 0 | AC16: 0 | AD16: 0 | AE16: 0 | AF16: 0 | AG16: 0 | AH16: 0 | AI16: 0 | AJ16: 0 | AK16: 0 | AL16: 0 | AM16: 0 | AN16: 0 | AO16: 0 | AP16: 0 | AQ16: 0 | AR16: 2.5 | AS16: 2.5 | AT16: 2.5 | AU16: 2.5 | AV16: 2.5 | AW16: 2.5 | AX16: 2.5 | AY16: 2.5 | AZ16: 2.5 | BA16: 5.9 | BB16: 10.542 | BC16: 10.542 | BD16: 10.542 | BE16: 10.542 | BF16: 10.542 | BG16: 10.542 | BH16: 10.542 | BI16: 10.542 | BJ16: 11.0691 | BK16: 11.0691 | BL16: 11.0691 | BM16: 11.0691 | BN16: 11.0691 | BO16: 11.0691 | BP16: 11.0691 | BQ16: 11.0691 | BR16: 11.0691 | BS16: 11.0691 | BT16: 11.0691 | BU16: 11.0691 | BV16: 11.622555 | BW16: 11.622555 | BX16: 11.622555 | BY16: 11.622555 | BZ16: 11.622555 | CA16: 11.622555 | CB16: 11.622555 | CC16: 11.622555 | CD16: 11.622555 | CE16: 11.622555 | CF16: 11.622555 | CG16: 11.622555 | CH16: 12.203683 | CI16: 12.203683 | CJ16: 12.203683 | CK16: 12.203683 | CL16: 12.203683 | CM16: 12.203683 | CN16: 12.203683 | CO16: 12.203683 | CP16: 12.203683 | CQ16: 12.203683 | CR16: 12.203683 | CS16: 12.203683 | CT16: 12.813867 | CU16: 12.813867 | CV16: 12.813867 | CW16: 12.813867 | CX16: 12.813867 | CY16: 12.813867 | CZ16: 12.813867 | DA16: 12.813867 | DB16: 12.813867 | DC16: 12.813867 | DD16: 12.813867 | DE16: 12.813867 | DF16: 0 | DG16: 0 | DH16: 0 | DI16: 0 | DJ16: 0 | DK16: 0 | DL16: 0 | DM16: 0 | DN16: 0 | DO16: 0 | DP16: 0 | DQ16: 0 | DR16: 0 | DT16: =+F16-E16 | DU16: =+G16-F16 | DV16: =+H16-G16 | DW16: =+I16-H16
B17: AAP | C17: Major | E17: =+SUMIFS($O17:$DR17,$O$7:$DR$7,E$7) | F17: =+SUMIFS($O17:$DR17,$O$7:$DR$7,F$7) | G17: =+SUMIFS($O17:$DR17,$O$7:$DR$7,G$7) | H17: =+SUMIFS($O17:$DR17,$O$7:$DR$7,H$7) | I17: =+SUMIFS($O17:$DR17,$O$7:$DR$7,I$7) | J17: =+SUMIFS($O17:$DR17,$O$7:$DR$7,J$7) | K17: =+SUMIFS($O17:$DR17,$O$7:$DR$7,K$7) | L17: =+SUMIFS($O17:$DR17,$O$7:$DR$7,L$7) | M17: =+SUMIFS($O17:$DR17,$O$7:$DR$7,M$7) | O17: 18.212 | P17: 18.212 | Q17: 18.212 | R17: 18.212 | S17: 18.212 | T17: 18.212 | U17: 18.212 | V17: 18.212 | W17: 18.212 | X17: 18.917 | Y17: 21.337 | Z17: 21.337 | AA17: 21.883 | AB17: 21.883 | AC17: 21.883 | AD17: 21.883 | AE17: 21.883 | AF17: 21.883 | AG17: 21.883 | AH17: 21.883 | AI17: 21.883 | AJ17: 21.883 | AK17: 23.072 | AL17: 22.508 | AM17: 23.071 | AN17: 23.071 | AO17: 23.071 | AP17: 23.071 | AQ17: 23.071 | AR17: 23.071 | AS17: 23.071 | AT17: 22.629 | AU17: 23.071 | AV17: 23.071 | AW17: 23.071 | AX17: 23.071 | AY17: 23.763 | AZ17: 23.763 | BA17: 23.763 | BB17: 23.763 | BC17: 23.763 | BD17: 23.763 | BE17: 23.763 | BF17: 23.763 | BG17: 23.763 | BH17: 23.763 | BI17: 23.763 | BJ17: 23.763 | BK17: 33.25 | BL17: 33.25 | BM17: 33.25 | BN17: 33.25 | BO17: 33.25 | BP17: 33.25 | BQ17: 33.25 | BR17: 33.25 | BS17: 33.25 | BT17: 33.25 | BU17: 33.25 | BV17: 33.25 | BW17: 34.2475 | BX17: 34.2475 | BY17: 34.2475 | BZ17: 34.2475 | CA17: 34.2475 | CB17: 34.2475 | CC17: 34.2475 | CD17: 34.2475 | CE17: 34.2475 | CF17: 34.2475 | CG17: 34.2475 | CH17: 34.2475 | CI17: 35.274925 | CJ17: 35.274925 | CK17: 35.274925 | CL17: 35.274925 | CM17: 35.274925 | CN17: 35.274925 | CO17: 35.274925 | CP17: 35.274925 | CQ17: 35.274925 | CR17: 35.274925 | CS17: 35.274925 | CT17: 35.274925 | CU17: 36.333173 | CV17: 36.333173 | CW17: 36.333173 | CX17: 36.333173 | CY17: 36.333173 | CZ17: 36.333173 | DA17: 36.333173 | DB17: 36.333173 | DC17: 36.333173 | DD17: 36.333173 | DE17: 36.333173 | DF17: 36.333173 | DG17: 37.423168 | DH17: 37.423168 | DI17: 37.423168 | DJ17: 37.423168 | DK17: 37.423168 | DL17: 37.423168 | DM17: 37.423168 | DN17: 37.423168 | DO17: 37.423168 | DP17: 37.423168 | DQ17: 37.423168 | DR17: 37.423168 | DT17: =+F17-E17 | DU17: =+G17-F17 | DV17: =+H17-G17 | DW17: =+I17-H17
B18: ADA | C18: Lower Middle Market | E18: =+SUMIFS($O18:$DR18,$O$7:$DR$7,E$7) | F18: =+SUMIFS($O18:$DR18,$O$7:$DR$7,F$7) | G18: =+SUMIFS($O18:$DR18,$O$7:$DR$7,G$7) | H18: =+SUMIFS($O18:$DR18,$O$7:$DR$7,H$7) | I18: =+SUMIFS($O18:$DR18,$O$7:$DR$7,I$7) | J18: =+SUMIFS($O18:$DR18,$O$7:$DR$7,J$7) | K18: =+SUMIFS($O18:$DR18,$O$7:$DR$7,K$7) | L18: =+SUMIFS($O18:$DR18,$O$7:$DR$7,L$7) | M18: =+SUMIFS($O18:$DR18,$O$7:$DR$7,M$7) | O18: 0 | P18: 0 | Q18: 0 | R18: 0 | S18: 0 | T18: 0 | U18: 0 | V18: 0 | W18: 0 | X18: 0 | Y18: 0 | Z18: 0 | AA18: 0 | AB18: 0 | AC18: 0 | AD18: 0 | AE18: 0 | AF18: 0 | AG18: 0 | AH18: 0 | AI18: 0 | AJ18: 0 | AK18: 0 | AL18: 0 | AM18: 0 | AN18: 0 | AO18: 0 | AP18: 0 | AQ18: 0 | AR18: 0 | AS18: 0 | AT18: 0 | AU18: 0 | AV18: 0 | AW18: 0 | AX18: 0 | AY18: 0 | AZ18: 0 | BA18: 0 | BB18: 0 | BC18: 4.805 | BD18: 4.805 | BE18: 4.805 | BF18: 4.805 | BG18: 4.805 | BH18: 4.805 | BI18: 4.805 | BJ18: 4.805 | BK18: 14.875 | BL18: 14.875 | BM18: 14.875 | BN18: 14.875 | BO18: 14.875 | BP18: 14.875 | BQ18: 14.875 | BR18: 14.875 | BS18: 14.875 | BT18: 14.875 | BU18: 14.875 | BV18: 14.875 | BW18: 15.32125 | BX18: 15.32125 | BY18: 15.32125 | BZ18: 15.32125 | CA18: 15.32125 | CB18: 15.32125 | CC18: 15.32125 | CD18: 15.32125 | CE18: 15.32125 | CF18: 15.32125 | CG18: 15.32125 | CH18: 15.32125 | CI18: 15.780888 | CJ18: 15.780888 | CK18: 15.780888 | CL18: 15.780888 | CM18: 15.780888 | CN18: 15.780888 | CO18: 15.780888 | CP18: 15.780888 | CQ18: 15.780888 | CR18: 15.780888 | CS18: 15.780888 | CT18: 15.780888 | CU18: 16.254314 | CV18: 16.254314 | CW18: 16.254314 | CX18: 16.254314 | CY18: 16.254314 | CZ18: 16.254314 | DA18: 16.254314 | DB18: 16.254314 | DC18: 16.254314 | DD18: 16.254314 | DE18: 16.254314 | DF18: 16.254314 | DG18: 16.741944 | DH18: 16.741944 | DI18: 16.741944 | DJ18: 16.741944 | DK18: 16.741944 | DL18: 16.741944 | DM18: 16.741944 | DN18: 16.741944 | DO18: 16.741944 | DP18: 16.741944 | DQ18: 16.741944 | DR18: 16.741944 | DT18: =+F18-E18 | DU18: =+G18-F18 | DV18: =+H18-G18 | DW18: =+I18-H18
B19: AHRQ | C19: Lower Middle Market | E19: =+SUMIFS($O19:$DR19,$O$7:$DR$7,E$7) | F19: =+SUMIFS($O19:$DR19,$O$7:$DR$7,F$7) | G19: =+SUMIFS($O19:$DR19,$O$7:$DR$7,G$7) | H19: =+SUMIFS($O19:$DR19,$O$7:$DR$7,H$7) | I19: =+SUMIFS($O19:$DR19,$O$7:$DR$7,I$7) | J19: =+SUMIFS($O19:$DR19,$O$7:$DR$7,J$7) | K19: =+SUMIFS($O19:$DR19,$O$7:$DR$7,K$7) | L19: =+SUMIFS($O19:$DR19,$O$7:$DR$7,L$7) | M19: =+SUMIFS($O19:$DR19,$O$7:$DR$7,M$7) | O19: 0 | P19: 0 | Q19: 0 | R19: 0 | S19: 0 | T19: 0 | U19: 0 | V19: 0 | W19: 0 | X19: 0 | Y19: 0 | Z19: 0 | AA19: 0 | AB19: 0 | AC19: 0 | AD19: 0 | AE19: 0 | AF19: 0 | AG19: 0 | AH19: 0 | AI19: 0 | AJ19: 0 | AK19: 0 | AL19: 0 | AM19: 0 | AN19: 0 | AO19: 0 | AP19: 0 | AQ19: 0 | AR19: 0 | AS19: 0 | AT19: 0 | AU19: 0 | AV19: 0 | AW19: 0 | AX19: 0 | AY19: 0 | AZ19: 0 | BA19: 0 | BB19: 0 | BC19: 0 | BD19: 0 | BE19: 0 | BF19: 0 | BG19: 0 | BH19: 0 | BI19: 0 | BJ19: 0 | BK19: 0 | BL19: 0 | BM19: 0 | BN19: 4.1666667 | BO19: 4.1666667 | BP19: 4.1666667 | BQ19: 4.1666667 | BR19: 4.1666667 | BS19: 4.1666667 | BT19: 4.1666667 | BU19: 4.1666667 | BV19: 4.1666667 | BW19: 4.1666667 | BX19: 4.1666667 | BY19: 4.1666667 | BZ19: 4.1666667 | CA19: 4.1666667 | CB19: 4.1666667 | CC19: 4.1666667 | CD19: 4.1666667 | CE19: 4.1666667 | CF19: 4.1666667 | CG19: 4.1666667 | CH19: 4.1666667 | CI19: 4.1666667 | CJ19: 4.1666667 | CK19: 4.1666667 | CL19: 0 | CM19: 0 | CN19: 0 | CO19: 0 | CP19: 0 | CQ19: 0 | CR19: 0 | CS19: 0 | CT19: 0 | CU19: 0 | CV19: 0 | CW19: 0 | CX19: 0 | CY19: 0 | CZ19: 0 | DA19: 0 | DB19: 0 | DC19: 0 | DD19: 0 | DE19: 0 | DF19: 0 | DG19: 0 | DH19: 0 | DI19: 0 | DJ19: 0 | DK19: 0 | DL19: 0 | DM19: 0 | DN19: 0 | DO19: 0 | DP19: 0 | DQ19: 0 | DR19: 0 | DT19: =+F19-E19 | DU19: =+G19-F19 | DV19: =+H19-G19 | DW19: =+I19-H19
B20: AIPP | C20: Major | E20: =+SUMIFS($O20:$DR20,$O$7:$DR$7,E$7) | F20: =+SUMIFS($O20:$DR20,$O$7:$DR$7,F$7) | G20: =+SUMIFS($O20:$DR20,$O$7:$DR$7,G$7) | H20: =+SUMIFS($O20:$DR20,$O$7:$DR$7,H$7) | I20: =+SUMIFS($O20:$DR20,$O$7:$DR$7,I$7) | J20: =+SUMIFS($O20:$DR20,$O$7:$DR$7,J$7) | K20: =+SUMIFS($O20:$DR20,$O$7:$DR$7,K$7) | L20: =+SUMIFS($O20:$DR20,$O$7:$DR$7,L$7) | M20: =+SUMIFS($O20:$DR20,$O$7:$DR$7,M$7) | O20: 0 | P20: 0 | Q20: 0 | R20: 0 | S20: 0 | T20: 0 | U20: 0 | V20: 0 | W20: 0 | X20: 0 | Y20: 0 | Z20: 0 | AA20: 0 | AB20: 0 | AC20: 0 | AD20: 0 | AE20: 0 | AF20: 0 | AG20: 0 | AH20: 0 | AI20: 0 | AJ20: 0 | AK20: 0 | AL20: 0 | AM20: 0 | AN20: 0 | AO20: 0 | AP20: 0 | AQ20: 0 | AR20: 0 | AS20: 0 | AT20: 0 | AU20: 0 | AV20: 0 | AW20: 0 | AX20: 0 | AY20: 0 | AZ20: 0 | BA20: 0 | BB20: 0 | BC20: 0 | BD20: 0 | BE20: 0 | BF20: 0 | BG20: 0 | BH20: 0 | BI20: 0 | BJ20: 0 | BK20: 0 | BL20: 0 | BM20: 5.805 | BN20: 5.805 | BO20: 5.805 | BP20: 5.805 | BQ20: 5.805 | BR20: 5.805 | BS20: 5.805 | BT20: 5.805 | BU20: 5.805 | BV20: 5.805 | BW20: 5.805 | BX20: 5.805 | BY20: 47.975 | BZ20: 47.975 | CA20: 47.975 | CB20: 47.975 | CC20: 47.975 | CD20: 47.975 | CE20: 47.975 | CF20: 47.975 | CG20: 47.975 | CH20: 47.975 | CI20: 47.975 | CJ20: 47.975 | CK20: 49.41425 | CL20: 49.41425 | CM20: 49.41425 | CN20: 49.41425 | CO20: 49.41425 | CP20: 49.41425 | CQ20: 49.41425 | CR20: 49.41425 | CS20: 49.41425 | CT20: 49.41425 | CU20: 49.41425 | CV20: 49.41425 | CW20: 50.896678 | CX20: 50.896678 | CY20: 50.896678 | CZ20: 50.896678 | DA20: 50.896678 | DB20: 50.896678 | DC20: 50.896678 | DD20: 50.896678 | DE20: 50.896678 | DF20: 50.896678 | DG20: 50.896678 | DH20: 50.896678 | DI20: 52.423578 | DJ20: 52.423578 | DK20: 52.423578 | DL20: 52.423578 | DM20: 52.423578 | DN20: 52.423578 | DO20: 52.423578 | DP20: 52.423578 | DQ20: 52.423578 | DR20: 52.423578 | DT20: =+F20-E20 | DU20: =+G20-F20 | DV20: =+H20-G20 | DW20: =+I20-H20
B21: ALLEN | C21: Upper Middle Market | E21: =+SUMIFS($O21:$DR21,$O$7:$DR$7,E$7) | F21: =+SUMIFS($O21:$DR21,$O$7:$DR$7,F$7) | G21: =+SUMIFS($O21:$DR21,$O$7:$DR$7,G$7) | H21: =+SUMIFS($O21:$DR21,$O$7:$DR$7,H$7) | I21: =+SUMIFS($O21:$DR21,$O$7:$DR$7,I$7) | J21: =+SUMIFS($O21:$DR21,$O$7:$DR$7,J$7) | K21: =+SUMIFS($O21:$DR21,$O$7:$DR$7,K$7) | L21: =+SUMIFS($O21:$DR21,$O$7:$DR$7,L$7) | M21: =+SUMIFS($O21:$DR21,$O$7:$DR$7,M$7) | O21: 0 | P21: 0 | Q21: 0 | R21: 0 | S21: 0 | T21: 0 | U21: 0 | V21: 0 | W21: 0 | X21: 0 | Y21: 0 | Z21: 0 | AA21: 0 | AB21: 0 | AC21: 0 | AD21: 0 | AE21: 0 | AF21: 0 | AG21: 0 | AH21: 0 | AI21: 0 | AJ21: 0 | AK21: 0 | AL21: 0 | AM21: 0 | AN21: 8.334 | AO21: 10.417 | AP21: 12.5 | AQ21: 14.584 | AR21: 16.666 | AS21: 16.666 | AT21: 16.666 | AU21: 13.963 | AV21: 16.667 | AW21: 16.666 | AX21: 113.912 | AY21: 16.66667 | AZ21: 16.66667 | BA21: 25.95967 | BB21: 16.66667 | BC21: 16.66667 | BD21: 33.82867 | BE21: 16.66667 | BF21: 16.66667 | BG21: 23.81767 | BH21: 16.66667 | BI21: 16.66667 | BJ21: 40.36067 | BK21: 16.66667 | BL21: 16.66667 | BM21: 30.69167 | BN21: 16.66667 | BO21: 16.66667 | BP21: 31.66667 | BQ21: 16.66667 | BR21: 16.66667 | BS21: 31.66667 | BT21: 16.66667 | BU21: 16.66667 | BV21: 31.66667 | BW21: 16.66667 | BX21: 16.66667 | BY21: 31.11242 | BZ21: 16.66667 | CA21: 16.66667 | CB21: 32.11667 | CC21: 16.66667 | CD21: 16.66667 | CE21: 32.11667 | CF21: 16.66667 | CG21: 16.66667 | CH21: 32.11667 | CI21: 16.66667 | CJ21: 16.66667 | CK21: 31.545793 | CL21: 16.66667 | CM21: 16.66667 | CN21: 32.58017 | CO21: 16.66667 | CP21: 16.66667 | CQ21: 32.58017 | CR21: 16.66667 | CS21: 16.66667 | CT21: 32.58017 | CU21: 16.66667 | CV21: 16.66667 | CW21: 31.992166 | CX21: 16.66667 | CY21: 16.66667 | CZ21: 33.057575 | DA21: 16.66667 | DB21: 16.66667 | DC21: 33.057575 | DD21: 16.66667 | DE21: 16.66667 | DF21: 33.057575 | DG21: 16.66667 | DH21: 16.66667 | DI21: 32.451931 | DJ21: 16.66667 | DK21: 16.66667 | DL21: 33.549302 | DM21: 16.66667 | DN21: 16.66667 | DO21: 33.549302 | DP21: 16.66667 | DQ21: 16.66667 | DR21: 33.549302 | DT21: =+F21-E21 | DU21: =+G21-F21 | DV21: =+H21-G21 | DW21: =+I21-H21
B22: AMA | C22: Mega | E22: =+SUMIFS($O22:$DR22,$O$7:$DR$7,E$7) | F22: =+SUMIFS($O22:$DR22,$O$7:$DR$7,F$7) | G22: =+SUMIFS($O22:$DR22,$O$7:$DR$7,G$7) | H22: =+SUMIFS($O22:$DR22,$O$7:$DR$7,H$7) | I22: =+SUMIFS($O22:$DR22,$O$7:$DR$7,I$7) | J22: =+SUMIFS($O22:$DR22,$O$7:$DR$7,J$7) | K22: =+SUMIFS($O22:$DR22,$O$7:$DR$7,K$7) | L22: =+SUMIFS($O22:$DR22,$O$7:$DR$7,L$7) | M22: =+SUMIFS($O22:$DR22,$O$7:$DR$7,M$7) | O22: 104.247 | P22: 104.247 | Q22: 104.247 | R22: 104.247 | S22: 107.22 | T22: 110.647 | U22: 110.647 | V22: 100.647 | W22: 110.647 | X22: 110.646 | Y22: 110.647 | Z22: 156.48 | AA22: 137.27 | AB22: 137.27 | AC22: 133.104 | AD22: 133.103 | AE22: 133.104 | AF22: 133.103 | AG22: 133.103 | AH22: 133.103 | AI22: 133.104 | AJ22: 134.104 | AK22: 133.104 | AL22: 133.104 | AM22: 137.208 | AN22: 137.208 | AO22: 137.208 | AP22: 137.208 | AQ22: 137.208 | AR22: 137.208 | AS22: 138.208 | AT22: 131.394 | AU22: 138.208 | AV22: 138.208 | AW22: 143.575 | AX22: 149.708 | AY22: 154.25563 | AZ22: 154.25563 | BA22: 154.25563 | BB22: 154.25563 | BC22: 154.25563 | BD22: 154.25563 | BE22: 154.25563 | BF22: 154.25563 | BG22: 154.25563 | BH22: 150.92229 | BI22: 151.29729 | BJ22: 151.29729 | BK22: 156.83067 | BL22: 156.83067 | BM22: 156.83067 | BN22: 156.83067 | BO22: 156.83067 | BP22: 156.83067 | BQ22: 156.83067 | BR22: 156.83067 | BS22: 156.83067 | BT22: 156.83067 | BU22: 157.21692 | BV22: 157.21692 | BW22: 161.19313 | BX22: 161.19313 | BY22: 161.19313 | BZ22: 161.19313 | CA22: 161.19313 | CB22: 161.19313 | CC22: 161.19313 | CD22: 161.19313 | CE22: 161.19313 | CF22: 161.19313 | CG22: 161.59097 | CH22: 161.59097 | CI22: 13.659088 | CJ22: 13.659088 | CK22: 13.659088 | CL22: 13.659088 | CM22: 13.659088 | CN22: 13.659088 | CO22: 13.659088 | CP22: 13.659088 | CQ22: 13.659088 | CR22: 13.659088 | CS22: 14.06886 | CT22: 14.06886 | CU22: 14.06886 | CV22: 14.06886 | CW22: 14.06886 | CX22: 14.06886 | CY22: 14.06886 | CZ22: 14.06886 | DA22: 14.06886 | DB22: 14.06886 | DC22: 14.06886 | DD22: 14.06886 | DE22: 14.490926 | DF22: 14.490926 | DG22: 0 | DH22: 0 | DI22: 0 | DJ22: 0 | DK22: 0 | DL22: 0 | DM22: 0 | DN22: 0 | DO22: 0 | DP22: 0 | DQ22: 0 | DR22: 0 | DT22: =+F22-E22 | DU22: =+G22-F22 | DV22: =+H22-G22 | DW22: =+I22-H22
B23: AORN | C23: Lower Middle Market | E23: =+SUMIFS($O23:$DR23,$O$7:$DR$7,E$7) | F23: =+SUMIFS($O23:$DR23,$O$7:$DR$7,F$7) | G23: =+SUMIFS($O23:$DR23,$O$7:$DR$7,G$7) | H23: =+SUMIFS($O23:$DR23,$O$7:$DR$7,H$7) | I23: =+SUMIFS($O23:$DR23,$O$7:$DR$7,I$7) | J23: =+SUMIFS($O23:$DR23,$O$7:$DR$7,J$7) | K23: =+SUMIFS($O23:$DR23,$O$7:$DR$7,K$7) | L23: =+SUMIFS($O23:$DR23,$O$7:$DR$7,L$7) | M23: =+SUMIFS($O23:$DR23,$O$7:$DR$7,M$7) | O23: 0 | P23: 0 | Q23: 0 | R23: 10.417 | S23: 10.417 | T23: 10.417 | U23: 10.417 | V23: 10.417 | W23: 10.417 | X23: 10.417 | Y23: 10.417 | Z23: 10.416 | AA23: 10.417 | AB23: 10.417 | AC23: 10.417 | AD23: 10.782 | AE23: 10.781 | AF23: 10.782 | AG23: 10.782 | AH23: 10.782 | AI23: 10.782 | AJ23: 10.782 | AK23: 10.782 | AL23: 10.781 | AM23: 10.782 | AN23: 10.782 | AO23: 10.782 | AP23: 11.159 | AQ23: 11.158 | AR23: 11.159 | AS23: 11.159 | AT23: 10.874 | AU23: 11.159 | AV23: 11.158 | AW23: 11.159 | AX23: 11.158 | AY23: 11.158594 | AZ23: 11.158594 | BA23: 11.158594 | BB23: 11.549145 | BC23: 11.549145 | BD23: 11.549145 | BE23: 11.549145 | BF23: 11.549145 | BG23: 11.549145 | BH23: 11.549145 | BI23: 11.549145 | BJ23: 11.549145 | BK23: 11.549145 | BL23: 11.549145 | BM23: 11.549145 | BN23: 11.953365 | BO23: 11.953365 | BP23: 11.953365 | BQ23: 11.953365 | BR23: 11.953365 | BS23: 11.953365 | BT23: 11.953365 | BU23: 11.953365 | BV23: 11.953365 | BW23: 11.953365 | BX23: 11.953365 | BY23: 11.953365 | BZ23: 0 | CA23: 0 | CB23: 0 | CC23: 0 | CD23: 0 | CE23: 0 | CF23: 0 | CG23: 0 | CH23: 0 | CI23: 0 | CJ23: 0 | CK23: 0 | CL23: 0 | CM23: 0 | CN23: 0 | CO23: 0 | CP23: 0 | CQ23: 0 | CR23: 0 | CS23: 0 | CT23: 0 | CU23: 0 | CV23: 0 | CW23: 0 | CX23: 0 | CY23: 0 | CZ23: 0 | DA23: 0 | DB23: 0 | DC23: 0 | DD23: 0 | DE23: 0 | DF23: 0 | DG23: 0 | DH23: 0 | DI23: 0 | DJ23: 0 | DK23: 0 | DL23: 0 | DM23: 0 | DN23: 0 | DO23: 0 | DP23: 0 | DQ23: 0 | DR23: 0 | DT23: =+F23-E23 | DU23: =+G23-F23 | DV23: =+H23-G23 | DW23: =+I23-H23
B24: AOTA | C24: Lower Middle Market | E24: =+SUMIFS($O24:$DR24,$O$7:$DR$7,E$7) | F24: =+SUMIFS($O24:$DR24,$O$7:$DR$7,F$7) | G24: =+SUMIFS($O24:$DR24,$O$7:$DR$7,G$7) | H24: =+SUMIFS($O24:$DR24,$O$7:$DR$7,H$7) | I24: =+SUMIFS($O24:$DR24,$O$7:$DR$7,I$7) | J24: =+SUMIFS($O24:$DR24,$O$7:$DR$7,J$7) | K24: =+SUMIFS($O24:$DR24,$O$7:$DR$7,K$7) | L24: =+SUMIFS($O24:$DR24,$O$7:$DR$7,L$7) | M24: =+SUMIFS($O24:$DR24,$O$7:$DR$7,M$7) | O24: 7.5 | P24: 7.5 | Q24: 7.5 | R24: 7.5 | S24: 7.5 | T24: 7.5 | U24: 7.875 | V24: 7.875 | W24: 7.875 | X24: 7.875 | Y24: 7.875 | Z24: 7.875 | AA24: 7.875 | AB24: 7.875 | AC24: 7.875 | AD24: 7.875 | AE24: 7.875 | AF24: 7.875 | AG24: 7.98 | AH24: 7.98 | AI24: 7.98 | AJ24: 7.98 | AK24: 7.98 | AL24: 7.98 | AM24: 8.111 | AN24: 8.111 | AO24: 8.111 | AP24: 8.111 | AQ24: 8.111 | AR24: 8.22 | AS24: 8.22 | AT24: 7.549 | AU24: 8.22 | AV24: 8.22 | AW24: 3.713 | AX24: 3.713 | AY24: 3.713 | AZ24: 3.713 | BA24: 3.713 | BB24: 3.713 | BC24: 3.713 | BD24: 3.713 | BE24: 3.713 | BF24: 4.5833333 | BG24: 4.5833333 | BH24: 4.5833333 | BI24: 4.5833333 | BJ24: 4.5833333 | BK24: 4.5833333 | BL24: 4.5833333 | BM24: 4.5833333 | BN24: 4.5833333 | BO24: 4.5833333 | BP24: 4.5833333 | BQ24: 3.82439 | BR24: 4.7208333 | BS24: 4.7208333 | BT24: 4.7208333 | BU24: 4.7208333 | BV24: 4.7208333 | BW24: 4.7208333 | BX24: 4.7208333 | BY24: 4.7208333 | BZ24: 4.7208333 | CA24: 4.7208333 | CB24: 4.7208333 | CC24: 3.9391217 | CD24: 4.8624583 | CE24: 4.8624583 | CF24: 4.8624583 | CG24: 4.8624583 | CH24: 4.8624583 | CI24: 4.8624583 | CJ24: 4.8624583 | CK24: 4.8624583 | CL24: 4.8624583 | CM24: 4.8624583 | CN24: 4.8624583 | CO24: 4.0572954 | CP24: 5.0083321 | CQ24: 5.0083321 | CR24: 5.0083321 | CS24: 5.0083321 | CT24: 5.0083321 | CU24: 5.0083321 | CV24: 5.0083321 | CW24: 5.0083321 | CX24: 5.0083321 | CY24: 5.0083321 | CZ24: 5.0083321 | DA24: 4.1790142 | DB24: 5.158582 | DC24: 5.158582 | DD24: 5.158582 | DE24: 5.158582 | DF24: 5.158582 | DG24: 5.158582 | DH24: 5.158582 | DI24: 5.158582 | DJ24: 5.158582 | DK24: 5.158582 | DL24: 5.158582 | DM24: 0 | DN24: 0 | DO24: 0 | DP24: 0 | DQ24: 0 | DR24: 0 | DT24: =+F24-E24 | DU24: =+G24-F24 | DV24: =+H24-G24 | DW24: =+I24-H24
... B58: EL | C58: Lower Middle Market | E58: =+SUMIFS($O58:$DR58,$O$7:$DR$7,E$7) | F58: =+SUMIFS($O58:$DR58,$O$7:$DR$7,F$7) | G58: =+SUMIFS($O58:$DR58,$O$7:$DR$7,G$7) | H58: =+SUMIFS($O58:$DR58,$O$7:$DR$7,H$7) | I58: =+SUMIFS($O58:$DR58,$O$7:$DR$7,I$7) | J58: =+SUMIFS($O58:$DR58,$O$7:$DR$7,J$7) | K58: =+SUMIFS($O58:$DR58,$O$7:$DR$7,K$7) | L58: =+SUMIFS($O58:$DR58,$O$7:$DR$7,L$7) | M58: =+SUMIFS($O58:$DR58,$O$7:$DR$7,M$7) | O58: 0 | P58: 0 | Q58: 0 | R58: 0 | S58: 0 | T58: 0 | U58: 0 | V58: 0 | W58: 0 | X58: 0 | Y58: 0 | Z58: 0 | AA58: 0 | AB58: 0 | AC58: 0 | AD58: 0 | AE58: 0 | AF58: 0 | AG58: 0 | AH58: 0 | AI58: 0 | AJ58: 0 | AK58: 0 | AL58: 0 | AM58: 0 | AN58: 0 | AO58: 0 | AP58: 0 | AQ58: 0 | AR58: 0 | AS58: 0 | AT58: 0 | AU58: 0 | AV58: 0 | AW58: 0 | AX58: 0 | AY58: 0 | AZ58: 0 | BA58: 0 | BB58: 0 | BC58: 0 | BD58: 0 | BE58: 0 | BF58: 0 | BG58: 0 | BH58: 0 | BI58: 0 | BJ58: 0 | BK58: 0 | BL58: 0 | BM58: 0 | BN58: 0 | BO58: 0 | BP58: 0 | BQ58: 0 | BR58: 0 | BS58: 0 | BT58: 0 | BU58: 0 | BV58: 0 | BW58: 0 | BX58: 0 | BY58: 0 | BZ58: 0 | CA58: 0 | CB58: 0 | CC58: 0 | CD58: 0 | CE58: 0 | CF58: 0 | CG58: 0 | CH58: 0 | CI58: 0 | CJ58: 0 | CK58: 0 | CL58: 0 | CM58: 0 | CN58: 0 | CO58: 0 | CP58: 0 | CQ58: 0 | CR58: 0 | CS58: 0 | CT58: 0 | CU58: 0 | CV58: 0 | CW58: 0 | CX58: 0 | CY58: 0 | CZ58: 0 | DA58: 0 | DB58: 0 | DC58: 0 | DD58: 0 | DE58: 0 | DF58: 0 | DG58: 0 | DH58: 0 | DI58: 0 | DJ58: 0 | DK58: 0 | DL58: 0 | DM58: 0 | DN58: 0 | DO58: 0 | DP58: 0 | DQ58: 0 | DR58: 0 | DT58: =+F58-E58 | DU58: =+G58-F58 | DV58: =+H58-G58 | DW58: =+I58-H58
B60: Total Revenue1 | E60: =+SUMIFS($O60:$DR60,$O$7:$DR$7,E$7) | F60: =+SUMIFS($O60:$DR60,$O$7:$DR$7,F$7) | G60: =+SUMIFS($O60:$DR60,$O$7:$DR$7,G$7) | H60: =+SUMIFS($O60:$DR60,$O$7:$DR$7,H$7) | I60: =+SUMIFS($O60:$DR60,$O$7:$DR$7,I$7) | J60: =+SUMIFS($O60:$DR60,$O$7:$DR$7,J$7) | K60: =+SUMIFS($O60:$DR60,$O$7:$DR$7,K$7) | L60: =+SUMIFS($O60:$DR60,$O$7:$DR$7,L$7) | M60: =+SUMIFS($O60:$DR60,$O$7:$DR$7,M$7) | O60: =SUM(O13:O59) | P60: =SUM(P13:P59) | Q60: =SUM(Q13:Q59) | R60: =SUM(R13:R59) | S60: =SUM(S13:S59) | T60: =SUM(T13:T59) | U60: =SUM(U13:U59) | V60: =SUM(V13:V59) | ... DR60: =SUM(DR13:DR59)
B61: Check | BK61: 0 | BL61: 0 | BM61: 0 | BN61: 0 | BO61: 0 | BP61: 0 | BQ61: 0 | BR61: 0 | BS61: 0 | BT61: 0 | BU61: 0 | BV61: 0
B63: Revenue, Beginning | F63: =+E69 | G63: =+F69 | H63: =+G69
B64: Churn | F64: =+SUMIF(DT$13:DT$58,"<0") | G64: =+SUMIF(DU$13:DU$58,"<0") | H64: =+SUMIF(DV$13:DV$58,"<0")
B65: Gross Retention | F65: =SUM(F63:F64) | G65: =SUM(G63:G64) | H65: =SUM(H63:H64)
B66: Upsell | F66: =+SUMIF(DT$13:DT$58,">0")-F68 | G66: =+SUMIF(DU$13:DU$58,">0")-G68 | H66: =+SUMIF(DV$13:DV$58,">0")-H68
B67: Net Retention | F67: =+SUM(F65:F66) | G67: =+SUM(G65:G66) | H67: =+SUM(H65:H66)
B68: New | F68: =+SUMIFS(F$13:F$58,E$13:E$58,0) | G68: =+SUMIFS(G$13:G$58,F$13:F$58,0) | H68: =+SUMIFS(H$13:H$58,G$13:G$58,0)
B69: Revenue, Ending | E69: =+E60 | F69: =+SUM(F67:F68) | G69: =+SUM(G67:G68) | H69: =+SUM(H67:H68)
B71: Gross Retention | F71: =+F65/F63 | G71: =+G65/G63 | H71: =+H65/H63
B72: Net Retention | F72: =+F67/F63 | G72: =+G67/G63 | H72: =+H67/H63
B74: Mega
B75: Revenue, Beginning | F75: =+E84 | G75: =+F84 | H75: =+G84 | I75: =+H84 | J75: =+I84 | K75: =+J84 | L75: =+K84 | M75: =+L84
B76: Churn | F76: =+SUMIFS(DT$13:DT$58,DT$13:DT$58,"<0",$C$13:$C$58,$B$74) | G76: =+SUMIFS(DU$13:DU$58,DU$13:DU$58,"<0",$C$13:$C$58,$B$74) | H76: =+SUMIFS(DV$13:DV$58,DV$13:DV$58,"<0",$C$13:$C$58,$B$74) | I76: =+SUMIFS(DW$13:DW$58,DW$13:DW$58,"<0",$C$13:$C$58,$B$74) | J76: =+Revenue_Assumptions!J14*J$75 | K76: =+Revenue_Assumptions!K14*K$75 | L76: =+Revenue_Assumptions!L14*L$75 | M76: =+Revenue_Assumptions!M14*M$75
B77: Expansion | F77: =+SUMIFS(DT$13:DT$58,DT$13:DT$58,">0",$C$13:$C$58,$B$74)-F82 | G77: =+SUMIFS(DU$13:DU$58,DU$13:DU$58,">0",$C$13:$C$58,$B$74)-G82 | H77: =+SUMIFS(DV$13:DV$58,DV$13:DV$58,">0",$C$13:$C$58,$B$74)-H82 | I77: =+SUMIFS(DW$13:DW$58,DW$13:DW$58,">0",$C$13:$C$58,$B$74)-I82 | J77: =+Revenue_Assumptions!J15*J$75 | K77: =+Revenue_Assumptions!K15*K$75 | L77: =+Revenue_Assumptions!L15*L$75 | M77: =+Revenue_Assumptions!M15*M$75
B78: Net Retention | F78: =SUM(F75:F77) | G78: =SUM(G75:G77) | H78: =SUM(H75:H77) | I78: =SUM(I75:I77) | J78: =SUM(J75:J77) | K78: =SUM(K75:K77) | L78: =SUM(L75:L77) | M78: =SUM(M75:M77)
B80: YTD New Clients | AA80: =+'Bookings to Revenue_Calcs'!AA26 | AB80: =+'Bookings to Revenue_Calcs'!AB26 | AC80: =+'Bookings to Revenue_Calcs'!AC26 | AD80: =+'Bookings to Revenue_Calcs'!AD26 | AE80: =+'Bookings to Revenue_Calcs'!AE26 | AF80: =+'Bookings to Revenue_Calcs'!AF26 | AG80: =+'Bookings to Revenue_Calcs'!AG26 | AH80: =+'Bookings to Revenue_Calcs'!AH26 | ... DR80: =+'Bookings to Revenue_Calcs'!DR26
B81: Avg Revenue per New Client | AA81: =+SUMIFS(Revenue_Assumptions!$E18:$M18,Revenue_Assumptions!$E$7:$M$7,AA$7)/12 | AB81: =+SUMIFS(Revenue_Assumptions!$E18:$M18,Revenue_Assumptions!$E$7:$M$7,AB$7)/12 | AC81: =+SUMIFS(Revenue_Assumptions!$E18:$M18,Revenue_Assumptions!$E$7:$M$7,AC$7)/12 | AD81: =+SUMIFS(Revenue_Assumptions!$E18:$M18,Revenue_Assumptions!$E$7:$M$7,AD$7)/12 | AE81: =+SUMIFS(Revenue_Assumptions!$E18:$M18,Revenue_Assumptions!$E$7:$M$7,AE$7)/12 | AF81: =+SUMIFS(Revenue_Assumptions!$E18:$M18,Revenue_Assumptions!$E$7:$M$7,AF$7)/12 | AG81: =+SUMIFS(Revenue_Assumptions!$E18:$M18,Revenue_Assumptions!$E$7:$M$7,AG$7)/12 | AH81: =+SUMIFS(Revenue_Assumptions!$E18:$M18,Revenue_Assumptions!$E$7:$M$7,AH$7)/12 | ... DR81: =+SUMIFS(Revenue_Assumptions!$E18:$M18,Revenue_Assumptions!$E$7:$M$7,DR$7)/12
B82: New Revenue | E82: =+SUMIFS($AA82:$DR82,$AA$7:$DR$7,E$7) | F82: =+SUMIFS($AA82:$DR82,$AA$7:$DR$7,F$7) | G82: =+SUMIFS($AA82:$DR82,$AA$7:$DR$7,G$7) | H82: =+SUMIFS($AA82:$DR82,$AA$7:$DR$7,H$7) | I82: =+SUMIFS($AA82:$DR82,$AA$7:$DR$7,I$7) | J82: =+SUMIFS($AA82:$DR82,$AA$7:$DR$7,J$7) | K82: =+SUMIFS($AA82:$DR82,$AA$7:$DR$7,K$7) | L82: =+SUMIFS($AA82:$DR82,$AA$7:$DR$7,L$7) | M82: =+SUMIFS($AA82:$DR82,$AA$7:$DR$7,M$7) | AA82: =+AA80*AA81 | AB82: =+AB80*AB81 | AC82: =+AC80*AC81 | AD82: =+AD80*AD81 | AE82: =+AE80*AE81 | AF82: =+AF80*AF81 | AG82: =+AG80*AG81 | AH82: =+AH80*AH81 | ... DR82: =+DR80*DR81
B84: Total Revenue | E84: =+SUMIFS(E$13:E$58,$C$13:$C$58,$B$74) | F84: =+SUM(F78,F82) | G84: =+SUM(G78,G82) | H84: =+SUM(H78,H82) | I84: =+SUM(I78,I82) | J84: =+SUM(J78,J82) | K84: =+SUM(K78,K82) | L84: =+SUM(L78,L82) | M84: =+SUM(M78,M82)
B86: Major
B87: Revenue, Beginning | F87: =+E96 | G87: =+F96 | H87: =+G96 | I87: =+H96 | J87: =+I96 | K87: =+J96 | L87: =+K96 | M87: =+L96
B88: Churn | F88: =+SUMIFS(DT$13:DT$58,DT$13:DT$58,"<0",$C$13:$C$58,$B$86) | G88: =+SUMIFS(DU$13:DU$58,DU$13:DU$58,"<0",$C$13:$C$58,$B$86) | H88: =+SUMIFS(DV$13:DV$58,DV$13:DV$58,"<0",$C$13:$C$58,$B$86) | I88: =+SUMIFS(DW$13:DW$58,DW$13:DW$58,"<0",$C$13:$C$58,$B$86) | J88: =+Revenue_Assumptions!J21*J$87 | K88: =+Revenue_Assumptions!K21*K$87 | L88: =+Revenue_Assumptions!L21*L$87 | M88: =+Revenue_Assumptions!M21*M$87
B89: Expansion | F89: =+SUMIFS(DT$13:DT$58,DT$13:DT$58,">0",$C$13:$C$58,$B$86)-F94 | G89: =+SUMIFS(DU$13:DU$58,DU$13:DU$58,">0",$C$13:$C$58,$B$86)-G94 | H89: =+SUMIFS(DV$13:DV$58,DV$13:DV$58,">0",$C$13:$C$58,$B$86)-H94 | I89: =+SUMIFS(DW$13:DW$58,DW$13:DW$58,">0",$C$13:$C$58,$B$86)-I94 | J89: =+Revenue_Assumptions!J22*J$87 | K89: =+Revenue_Assumptions!K22*K$87 | L89: =+Revenue_Assumptions!L22*L$87 | M89: =+Revenue_Assumptions!M22*M$87
B90: Net Retention | F90: =SUM(F87:F89) | G90: =SUM(G87:G89) | H90: =SUM(H87:H89) | I90: =SUM(I87:I89) | J90: =SUM(J87:J89) | K90: =SUM(K87:K89) | L90: =SUM(L87:L89) | M90: =SUM(M87:M89)
B92: YTD New Clients | AA92: =+'Bookings to Revenue_Calcs'!AA33 | AB92: =+'Bookings to Revenue_Calcs'!AB33 | AC92: =+'Bookings to Revenue_Calcs'!AC33 | AD92: =+'Bookings to Revenue_Calcs'!AD33 | AE92: =+'Bookings to Revenue_Calcs'!AE33 | AF92: =+'Bookings to Revenue_Calcs'!AF33 | AG92: =+'Bookings to Revenue_Calcs'!AG33 | AH92: =+'Bookings to Revenue_Calcs'!AH33 | ... DR92: =+'Bookings to Revenue_Calcs'!DR33
B93: Avg Revenue per New Client | AA93: =+SUMIFS(Revenue_Assumptions!$E25:$M25,Revenue_Assumptions!$E$7:$M$7,AA$7)/12 | AB93: =+SUMIFS(Revenue_Assumptions!$E25:$M25,Revenue_Assumptions!$E$7:$M$7,AB$7)/12 | AC93: =+SUMIFS(Revenue_Assumptions!$E25:$M25,Revenue_Assumptions!$E$7:$M$7,AC$7)/12 | AD93: =+SUMIFS(Revenue_Assumptions!$E25:$M25,Revenue_Assumptions!$E$7:$M$7,AD$7)/12 | AE93: =+SUMIFS(Revenue_Assumptions!$E25:$M25,Revenue_Assumptions!$E$7:$M$7,AE$7)/12 | AF93: =+SUMIFS(Revenue_Assumptions!$E25:$M25,Revenue_Assumptions!$E$7:$M$7,AF$7)/12 | AG93: =+SUMIFS(Revenue_Assumptions!$E25:$M25,Revenue_Assumptions!$E$7:$M$7,AG$7)/12 | AH93: =+SUMIFS(Revenue_Assumptions!$E25:$M25,Revenue_Assumptions!$E$7:$M$7,AH$7)/12 | ... DR93: =+SUMIFS(Revenue_Assumptions!$E25:$M25,Revenue_Assumptions!$E$7:$M$7,DR$7)/12
B94: New Revenue | E94: =+SUMIFS($AA94:$DR94,$AA$7:$DR$7,E$7) | F94: =+SUMIFS($AA94:$DR94,$AA$7:$DR$7,F$7) | G94: =+SUMIFS($AA94:$DR94,$AA$7:$DR$7,G$7) | H94: =+SUMIFS($AA94:$DR94,$AA$7:$DR$7,H$7) | I94: =+SUMIFS($AA94:$DR94,$AA$7:$DR$7,I$7) | J94: =+SUMIFS($AA94:$DR94,$AA$7:$DR$7,J$7) | K94: =+SUMIFS($AA94:$DR94,$AA$7:$DR$7,K$7) | L94: =+SUMIFS($AA94:$DR94,$AA$7:$DR$7,L$7) | M94: =+SUMIFS($AA94:$DR94,$AA$7:$DR$7,M$7) | AA94: =+AA92*AA93 | AB94: =+AB92*AB93 | AC94: =+AC92*AC93 | AD94: =+AD92*AD93 | AE94: =+AE92*AE93 | AF94: =+AF92*AF93 | AG94: =+AG92*AG93 | AH94: =+AH92*AH93 | ... DR94: =+DR92*DR93
B96: Total Revenue | E96: =+SUMIFS(E$13:E$58,$C$13:$C$58,$B$86) | F96: =+SUM(F90,F94) | G96: =+SUM(G90,G94) | H96: =+SUM(H90,H94) | I96: =+SUM(I90,I94) | J96: =+SUM(J90,J94) | K96: =+SUM(K90,K94) | L96: =+SUM(L90,L94) | M96: =+SUM(M90,M94)
B98: Upper Middle Market
B99: Revenue, Beginning | F99: =+E108 | G99: =+F108 | H99: =+G108 | I99: =+H108 | J99: =+I108 | K99: =+J108 | L99: =+K108 | M99: =+L108
B100: Churn | F100: =+SUMIFS(DT$13:DT$58,DT$13:DT$58,"<0",$C$13:$C$58,$B$98) | G100: =+SUMIFS(DU$13:DU$58,DU$13:DU$58,"<0",$C$13:$C$58,$B$98) | H100: =+SUMIFS(DV$13:DV$58,DV$13:DV$58,"<0",$C$13:$C$58,$B$98) | I100: =+SUMIFS(DW$13:DW$58,DW$13:DW$58,"<0",$C$13:$C$58,$B$98) | J100: =+Revenue_Assumptions!J28*J$99 | K100: =+Revenue_Assumptions!K28*K$99 | L100: =+Revenue_Assumptions!L28*L$99 | M100: =+Revenue_Assumptions!M28*M$99
B101: Expansion | F101: =+SUMIFS(DT$13:DT$58,DT$13:DT$58,">0",$C$13:$C$58,$B$98)-F106 | G101: =+SUMIFS(DU$13:DU$58,DU$13:DU$58,">0",$C$13:$C$58,$B$98)-G106 | H101: =+SUMIFS(DV$13:DV$58,DV$13:DV$58,">0",$C$13:$C$58,$B$98)-H106 | I101: =+SUMIFS(DW$13:DW$58,DW$13:DW$58,">0",$C$13:$C$58,$B$98)-I106 | J101: =+Revenue_Assumptions!J29*J$99 | K101: =+Revenue_Assumptions!K29*K$99 | L101: =+Revenue_Assumptions!L29*L$99 | M101: =+Revenue_Assumptions!M29*M$99
B102: Net Retention | F102: =SUM(F99:F101) | G102: =SUM(G99:G101) | H102: =SUM(H99:H101) | I102: =SUM(I99:I101) | J102: =SUM(J99:J101) | K102: =SUM(K99:K101) | L102: =SUM(L99:L101) | M102: =SUM(M99:M101)
B104: YTD New Clients | AA104: =+'Bookings to Revenue_Calcs'!AA47 | AB104: =+'Bookings to Revenue_Calcs'!AB47 | AC104: =+'Bookings to Revenue_Calcs'!AC47 | AD104: =+'Bookings to Revenue_Calcs'!AD47 | AE104: =+'Bookings to Revenue_Calcs'!AE47 | AF104: =+'Bookings to Revenue_Calcs'!AF47 | AG104: =+'Bookings to Revenue_Calcs'!AG47 | AH104: =+'Bookings to Revenue_Calcs'!AH47 | ... DR104: =+'Bookings to Revenue_Calcs'!DR47
B105: Avg Revenue per New Client | AA105: =+SUMIFS(Revenue_Assumptions!$E32:$M32,Revenue_Assumptions!$E$7:$M$7,AA$7)/12 | AB105: =+SUMIFS(Revenue_Assumptions!$E32:$M32,Revenue_Assumptions!$E$7:$M$7,AB$7)/12 | AC105: =+SUMIFS(Revenue_Assumptions!$E32:$M32,Revenue_Assumptions!$E$7:$M$7,AC$7)/12 | AD105: =+SUMIFS(Revenue_Assumptions!$E32:$M32,Revenue_Assumptions!$E$7:$M$7,AD$7)/12 | AE105: =+SUMIFS(Revenue_Assumptions!$E32:$M32,Revenue_Assumptions!$E$7:$M$7,AE$7)/12 | AF105: =+SUMIFS(Revenue_Assumptions!$E32:$M32,Revenue_Assumptions!$E$7:$M$7,AF$7)/12 | AG105: =+SUMIFS(Revenue_Assumptions!$E32:$M32,Revenue_Assumptions!$E$7:$M$7,AG$7)/12 | AH105: =+SUMIFS(Revenue_Assumptions!$E32:$M32,Revenue_Assumptions!$E$7:$M$7,AH$7)/12 | ... DR105: =+SUMIFS(Revenue_Assumptions!$E32:$M32,Revenue_Assumptions!$E$7:$M$7,DR$7)/12
B106: New Revenue | E106: =+SUMIFS($AA106:$DR106,$AA$7:$DR$7,E$7) | F106: =+SUMIFS($AA106:$DR106,$AA$7:$DR$7,F$7) | G106: =+SUMIFS($AA106:$DR106,$AA$7:$DR$7,G$7) | H106: =+SUMIFS($AA106:$DR106,$AA$7:$DR$7,H$7) | I106: =+SUMIFS($AA106:$DR106,$AA$7:$DR$7,I$7) | J106: =+SUMIFS($AA106:$DR106,$AA$7:$DR$7,J$7) | K106: =+SUMIFS($AA106:$DR106,$AA$7:$DR$7,K$7) | L106: =+SUMIFS($AA106:$DR106,$AA$7:$DR$7,L$7) | M106: =+SUMIFS($AA106:$DR106,$AA$7:$DR$7,M$7) | AA106: =+AA104*AA105 | AB106: =+AB104*AB105 | AC106: =+AC104*AC105 | AD106: =+AD104*AD105 | AE106: =+AE104*AE105 | AF106: =+AF104*AF105 | AG106: =+AG104*AG105 | AH106: =+AH104*AH105 | ... DR106: =+DR104*DR105
B108: Total Revenue | E108: =+SUMIFS(E$13:E$58,$C$13:$C$58,$B$98) | F108: =+SUM(F102,F106) | G108: =+SUM(G102,G106) | H108: =+SUM(H102,H106) | I108: =+SUM(I102,I106) | J108: =+SUM(J102,J106) | K108: =+SUM(K102,K106) | L108: =+SUM(L102,L106) | M108: =+SUM(M102,M106)
B110: Lower Middle Market
B111: Revenue, Beginning | F111: =+E120 | G111: =+F120 | H111: =+G120 | I111: =+H120 | J111: =+I120 | K111: =+J120 | L111: =+K120 | M111: =+L120
B112: Churn | F112: =+SUMIFS(DT$13:DT$58,DT$13:DT$58,"<0",$C$13:$C$58,$B$110) | G112: =+SUMIFS(DU$13:DU$58,DU$13:DU$58,"<0",$C$13:$C$58,$B$110) | H112: =+SUMIFS(DV$13:DV$58,DV$13:DV$58,"<0",$C$13:$C$58,$B$110) | I112: =+SUMIFS(DW$13:DW$58,DW$13:DW$58,"<0",$C$13:$C$58,$B$110) | J112: =Revenue_Assumptions!J35*J$111 | K112: =Revenue_Assumptions!K35*K$111 | L112: =Revenue_Assumptions!L35*L$111 | M112: =Revenue_Assumptions!M35*M$111
B113: Expansion | F113: =+SUMIFS(DT$13:DT$58,DT$13:DT$58,">0",$C$13:$C$58,$B$110)-F118 | G113: =+SUMIFS(DU$13:DU$58,DU$13:DU$58,">0",$C$13:$C$58,$B$110)-G118 | H113: =+SUMIFS(DV$13:DV$58,DV$13:DV$58,">0",$C$13:$C$58,$B$110)-H118 | I113: =+SUMIFS(DW$13:DW$58,DW$13:DW$58,">0",$C$13:$C$58,$B$110)-I118 | J113: =Revenue_Assumptions!J36*J$111 | K113: =Revenue_Assumptions!K36*K$111 | L113: =Revenue_Assumptions!L36*L$111 | M113: =Revenue_Assumptions!M36*M$111
B114: Net Retention | F114: =SUM(F111:F113) | G114: =SUM(G111:G113) | H114: =SUM(H111:H113) | I114: =SUM(I111:I113) | J114: =SUM(J111:J113) | K114: =SUM(K111:K113) | L114: =SUM(L111:L113) | M114: =SUM(M111:M113)
B116: YTD New Clients | AA116: =+'Bookings to Revenue_Calcs'!AA47 | AB116: =+'Bookings to Revenue_Calcs'!AB47 | AC116: =+'Bookings to Revenue_Calcs'!AC47 | AD116: =+'Bookings to Revenue_Calcs'!AD47 | AE116: =+'Bookings to Revenue_Calcs'!AE47 | AF116: =+'Bookings to Revenue_Calcs'!AF47 | AG116: =+'Bookings to Revenue_Calcs'!AG47 | AH116: =+'Bookings to Revenue_Calcs'!AH47 | ... DR116: =+'Bookings to Revenue_Calcs'!DR47
B117: Avg Revenue per New Client | AA117: =+SUMIFS(Revenue_Assumptions!$E39:$M39,Revenue_Assumptions!$E$7:$M$7,AA$7)/12 | AB117: =+SUMIFS(Revenue_Assumptions!$E39:$M39,Revenue_Assumptions!$E$7:$M$7,AB$7)/12 | AC117: =+SUMIFS(Revenue_Assumptions!$E39:$M39,Revenue_Assumptions!$E$7:$M$7,AC$7)/12 | AD117: =+SUMIFS(Revenue_Assumptions!$E39:$M39,Revenue_Assumptions!$E$7:$M$7,AD$7)/12 | AE117: =+SUMIFS(Revenue_Assumptions!$E39:$M39,Revenue_Assumptions!$E$7:$M$7,AE$7)/12 | AF117: =+SUMIFS(Revenue_Assumptions!$E39:$M39,Revenue_Assumptions!$E$7:$M$7,AF$7)/12 | AG117: =+SUMIFS(Revenue_Assumptions!$E39:$M39,Revenue_Assumptions!$E$7:$M$7,AG$7)/12 | AH117: =+SUMIFS(Revenue_Assumptions!$E39:$M39,Revenue_Assumptions!$E$7:$M$7,AH$7)/12 | ... DR117: =+SUMIFS(Revenue_Assumptions!$E39:$M39,Revenue_Assumptions!$E$7:$M$7,DR$7)/12
B118: New Revenue | E118: =+SUMIFS($AA118:$DR118,$AA$7:$DR$7,E$7) | F118: =+SUMIFS($AA118:$DR118,$AA$7:$DR$7,F$7) | G118: =+SUMIFS($AA118:$DR118,$AA$7:$DR$7,G$7) | H118: =+SUMIFS($AA118:$DR118,$AA$7:$DR$7,H$7) | I118: =+SUMIFS($AA118:$DR118,$AA$7:$DR$7,I$7) | J118: =+SUMIFS($AA118:$DR118,$AA$7:$DR$7,J$7) | K118: =+SUMIFS($AA118:$DR118,$AA$7:$DR$7,K$7) | L118: =+SUMIFS($AA118:$DR118,$AA$7:$DR$7,L$7) | M118: =+SUMIFS($AA118:$DR118,$AA$7:$DR$7,M$7) | AA118: =+AA116*AA117 | AB118: =+AB116*AB117 | AC118: =+AC116*AC117 | AD118: =+AD116*AD117 | AE118: =+AE116*AE117 | AF118: =+AF116*AF117 | AG118: =+AG116*AG117 | AH118: =+AH116*AH117 | ... DR118: =+DR116*DR117
B120: Total Revenue | E120: =+SUMIFS(E$13:E$58,$C$13:$C$58,$B$110) | F120: =+SUM(F114,F118) | G120: =+SUM(G114,G118) | H120: =+SUM(H114,H118) | I120: =+SUM(I114,I118) | J120: =+SUM(J114,J118) | K120: =+SUM(K114,K118) | L120: =+SUM(L114,L118) | M120: =+SUM(M114,M118)
B122: Total Licensing Revenue | E122: =+SUMIFS($O122:$DR122,$O$7:$DR$7,E$7) | F122: =+SUMIFS($O122:$DR122,$O$7:$DR$7,F$7) | G122: =+SUMIFS($O122:$DR122,$O$7:$DR$7,G$7) | H122: =+SUMIFS($O122:$DR122,$O$7:$DR$7,H$7) | I122: =+SUMIFS($O122:$DR122,$O$7:$DR$7,I$7) | J122: =+SUM(J84,J96,J108,J120) | K122: =+SUM(K84,K96,K108,K120) | L122: =+SUM(L84,L96,L108,L120) | M122: =+SUM(M84,M96,M108,M120) | O122: =+SUM(O60,O82,O94,O106,O118) | P122: =+SUM(P60,P82,P94,P106,P118) | Q122: =+SUM(Q60,Q82,Q94,Q106,Q118) | R122: =+SUM(R60,R82,R94,R106,R118) | S122: =+SUM(S60,S82,S94,S106,S118) | T122: =+SUM(T60,T82,T94,T106,T118) | U122: =+SUM(U60,U82,U94,U106,U118) | V122: =+SUM(V60,V82,V94,V106,V118) | ... BV122: =+SUM(BV60,BV82,BV94,BV106,BV118) | BW122: =+SUMIFS($E122:$M122,$E$7:$M$7,BW$7)*BW123 | BX122: =+SUMIFS($E122:$M122,$E$7:$M$7,BX$7)*BX123 | BY122: =+SUMIFS($E122:$M122,$E$7:$M$7,BY$7)*BY123 | BZ122: =+SUMIFS($E122:$M122,$E$7:$M$7,BZ$7)*BZ123 | CA122: =+SUMIFS($E122:$M122,$E$7:$M$7,CA$7)*CA123 | CB122: =+SUMIFS($E122:$M122,$E$7:$M$7,CB$7)*CB123 | CC122: =+SUMIFS($E122:$M122,$E$7:$M$7,CC$7)*CC123 | CD122: =+SUMIFS($E122:$M122,$E$7:$M$7,CD$7)*CD123 | ... DR122: =+SUMIFS($E122:$M122,$E$7:$M$7,DR$7)*DR123
B123: % Seasonality | E123: =+E122/SUMIFS($O122:$DR122,$O$7:$DR$7,E$7) | F123: =+F122/SUMIFS($O122:$DR122,$O$7:$DR$7,F$7) | G123: =+G122/SUMIFS($O122:$DR122,$O$7:$DR$7,G$7) | H123: =+H122/SUMIFS($O122:$DR122,$O$7:$DR$7,H$7) | I123: =+I122/SUMIFS($O122:$DR122,$O$7:$DR$7,I$7) | J123: =+J122/SUMIFS($O122:$DR122,$O$7:$DR$7,J$7) | K123: =+K122/SUMIFS($O122:$DR122,$O$7:$DR$7,K$7) | L123: =+L122/SUMIFS($O122:$DR122,$O$7:$DR$7,L$7) | M123: =+M122/SUMIFS($O122:$DR122,$O$7:$DR$7,M$7) | O123: =+O122/SUMIFS($O122:$DR122,$O$7:$DR$7,O$7) | P123: =+P122/SUMIFS($O122:$DR122,$O$7:$DR$7,P$7) | Q123: =+Q122/SUMIFS($O122:$DR122,$O$7:$DR$7,Q$7) | R123: =+R122/SUMIFS($O122:$DR122,$O$7:$DR$7,R$7) | S123: =+S122/SUMIFS($O122:$DR122,$O$7:$DR$7,S$7) | T123: =+T122/SUMIFS($O122:$DR122,$O$7:$DR$7,T$7) | U123: =+U122/SUMIFS($O122:$DR122,$O$7:$DR$7,U$7) | V123: =+V122/SUMIFS($O122:$DR122,$O$7:$DR$7,V$7) | ... BV123: =+BV122/SUMIFS($O122:$DR122,$O$7:$DR$7,BV$7) | BW123: =+AVERAGE(O123,AA123,AM123,BK123) | BX123: =+AVERAGE(P123,AB123,AN123,BL123) | BY123: =+AVERAGE(Q123,AC123,AO123,BM123) | BZ123: =+AVERAGE(R123,AD123,AP123,BN123) | CA123: =+AVERAGE(S123,AE123,AQ123,BO123) | CB123: =+AVERAGE(T123,AF123,AR123,BP123) | CC123: =+AVERAGE(U123,AG123,AS123,BQ123) | CD123: =+AVERAGE(V123,AH123,AT123,BR123) | ... DR123: =+AVERAGE(BJ123,BV123,CH123,DF123)
B124: % Contracted | E124: =+E60/E122 | F124: =+F60/F122 | G124: =+G60/G122 | H124: =+H60/H122 | I124: 0.99543394 | J124: =+J60/J122 | K124: =+K60/K122 | L124: =+L60/L122 | M124: =+M60/M122
B126: Managed Services
B128: AACN | C128: Lower Middle Market | E128: =+SUMIFS($O128:$DR128,$O$7:$DR$7,E$7) | F128: =+SUMIFS($O128:$DR128,$O$7:$DR$7,F$7) | G128: =+SUMIFS($O128:$DR128,$O$7:$DR$7,G$7) | H128: =+SUMIFS($O128:$DR128,$O$7:$DR$7,H$7) | I128: =+SUMIFS($O128:$DR128,$O$7:$DR$7,I$7) | J128: =+SUMIFS($O128:$DR128,$O$7:$DR$7,J$7) | K128: =+SUMIFS($O128:$DR128,$O$7:$DR$7,K$7) | L128: =+SUMIFS($O128:$DR128,$O$7:$DR$7,L$7) | M128: =+SUMIFS($O128:$DR128,$O$7:$DR$7,M$7) | O128: 0 | P128: 0 | Q128: 0 | R128: 0 | S128: 0 | T128: 0 | U128: 0 | V128: 0 | W128: 0 | X128: 0 | Y128: 0 | Z128: 0 | AA128: 0 | AB128: 0 | AC128: 0 | AD128: 0 | AE128: 0 | AF128: 0 | AG128: 0 | AH128: 0 | AI128: 0 | AJ128: 0 | AK128: 0 | AL128: 0 | AM128: 0 | AN128: 0 | AO128: 0 | AP128: 0 | AQ128: 0 | AR128: 0 | AS128: 0 | AT128: 0 | AU128: 0 | AV128: 4.4 | AW128: 1.1 | AX128: 0 | AY128: 0 | AZ128: 0 | BA128: 0 | BB128: 0 | BC128: 0 | BD128: 0 | BE128: 7.48 | BF128: 1.32 | BG128: 0 | BH128: 0 | BI128: 0 | BJ128: 0 | BK128: 0 | BL128: 0 | BM128: 0 | BN128: 0.55555556 | BO128: 0.55555556 | BP128: 0.55555556 | BQ128: 0.55555556 | BR128: 0.55555556 | BS128: 0.55555556 | BT128: 0.55555556 | BU128: 0.55555556 | BV128: 0.55555556 | DT128: =+F128-E128 | DU128: =+G128-F128 | DV128: =+H128-G128 | DW128: =+I128-H128
B129: AACR | C129: Lower Middle Market | E129: =+SUMIFS($O129:$DR129,$O$7:$DR$7,E$7) | F129: =+SUMIFS($O129:$DR129,$O$7:$DR$7,F$7) | G129: =+SUMIFS($O129:$DR129,$O$7:$DR$7,G$7) | H129: =+SUMIFS($O129:$DR129,$O$7:$DR$7,H$7) | I129: =+SUMIFS($O129:$DR129,$O$7:$DR$7,I$7) | J129: =+SUMIFS($O129:$DR129,$O$7:$DR$7,J$7) | K129: =+SUMIFS($O129:$DR129,$O$7:$DR$7,K$7) | L129: =+SUMIFS($O129:$DR129,$O$7:$DR$7,L$7) | M129: =+SUMIFS($O129:$DR129,$O$7:$DR$7,M$7) | O129: 0 | P129: 0 | Q129: 0 | R129: 0 | S129: 0 | T129: 0 | U129: 0 | V129: 0 | W129: 0 | X129: 0 | Y129: 0 | Z129: 0 | AA129: 0 | AB129: 0 | AC129: 0 | AD129: 0 | AE129: 0 | AF129: 0 | AG129: 0 | AH129: 0 | AI129: 0 | AJ129: 0 | AK129: 0 | AL129: 0 | AM129: 0 | AN129: 0 | AO129: 0 | AP129: 0 | AQ129: 0 | AR129: 0 | AS129: 0 | AT129: 0 | AU129: 0 | AV129: 0 | AW129: 0 | AX129: 0 | AY129: 0 | AZ129: 0 | BA129: 0 | BB129: 0 | BC129: 0 | BD129: 9.345 | BE129: 8.593 | BF129: 4.742 | BG129: 0 | BH129: 7.65 | BI129: 30.33 | BJ129: 15.19 | BK129: 19.09 | BL129: 0 | BM129: 7.11 | BN129: 1.5333333 | BO129: 1.5333333 | BP129: 1.5333333 | BQ129: 1.5333333 | BR129: 1.5333333 | BS129: 1.5333333 | BT129: 1.5333333 | BU129: 1.5333333 | BV129: 1.5333333 | DT129: =+F129-E129 | DU129: =+G129-F129 | DV129: =+H129-G129 | DW129: =+I129-H129
B130: AAI | C130: Lower Middle Market | E130: =+SUMIFS($O130:$DR130,$O$7:$DR$7,E$7) | F130: =+SUMIFS($O130:$DR130,$O$7:$DR$7,F$7) | G130: =+SUMIFS($O130:$DR130,$O$7:$DR$7,G$7) | H130: =+SUMIFS($O130:$DR130,$O$7:$DR$7,H$7) | I130: =+SUMIFS($O130:$DR130,$O$7:$DR$7,I$7) | J130: =+SUMIFS($O130:$DR130,$O$7:$DR$7,J$7) | K130: =+SUMIFS($O130:$DR130,$O$7:$DR$7,K$7) | L130: =+SUMIFS($O130:$DR130,$O$7:$DR$7,L$7) | M130: =+SUMIFS($O130:$DR130,$O$7:$DR$7,M$7) | O130: 0 | P130: 0 | Q130: 0 | R130: 0 | S130: 0 | T130: 0 | U130: 0 | V130: 0 | W130: 0 | X130: 0 | Y130: 0 | Z130: 0 | AA130: 0 | AB130: 0 | AC130: 0 | AD130: 0 | AE130: 0 | AF130: 0 | AG130: 0 | AH130: 0 | AI130: 0 | AJ130: 0 | AK130: 0 | AL130: 0 | AM130: 0 | AN130: 0 | AO130: 0 | AP130: 0 | AQ130: 0 | AR130: 0 | AS130: 0 | AT130: 0 | AU130: 0 | AV130: 0 | AW130: 0 | AX130: 0 | AY130: 0 | AZ130: 0 | BA130: 0 | BB130: 0 | BC130: 0 | BD130: 0 | BE130: 0 | BF130: 0 | BG130: 0 | BH130: 0 | BI130: 0 | BJ130: 0 | BK130: 0 | BL130: 0 | BM130: 0 | BN130: 0 | BO130: 0 | BP130: 5.7142857 | BQ130: 5.7142857 | BR130: 5.7142857 | BS130: 5.7142857 | BT130: 5.7142857 | BU130: 5.7142857 | BV130: 5.7142857 | DT130: =+F130-E130 | DU130: =+G130-F130 | DV130: =+H130-G130 | DW130: =+I130-H130
B131: AAOS | C131: Upper Middle Market | E131: =+SUMIFS($O131:$DR131,$O$7:$DR$7,E$7) | F131: =+SUMIFS($O131:$DR131,$O$7:$DR$7,F$7) | G131: =+SUMIFS($O131:$DR131,$O$7:$DR$7,G$7) | H131: =+SUMIFS($O131:$DR131,$O$7:$DR$7,H$7) | I131: =+SUMIFS($O131:$DR131,$O$7:$DR$7,I$7) | J131: =+SUMIFS($O131:$DR131,$O$7:$DR$7,J$7) | K131: =+SUMIFS($O131:$DR131,$O$7:$DR$7,K$7) | L131: =+SUMIFS($O131:$DR131,$O$7:$DR$7,L$7) | M131: =+SUMIFS($O131:$DR131,$O$7:$DR$7,M$7) | O131: 0 | P131: 0 | Q131: 0 | R131: 0 | S131: 0 | T131: 0 | U131: 0 | V131: 0 | W131: 0 | X131: 0 | Y131: 0 | Z131: 0 | AA131: 0 | AB131: 0 | AC131: 0 | AD131: 0 | AE131: 0 | AF131: 0 | AG131: 0 | AH131: 0 | AI131: 0 | AJ131: 0 | AK131: 0 | AL131: 0 | AM131: 0 | AN131: 0 | AO131: 0 | AP131: 0 | AQ131: 0 | AR131: 0 | AS131: 0 | AT131: 0 | AU131: 4.83 | AV131: 1.915 | AW131: 4.776 | AX131: 27.518 | AY131: 3.238 | AZ131: 11.533 | BA131: 102.165 | BB131: 94.728 | BC131: 47.135 | BD131: 43.222 | BE131: 20.09 | BF131: 6.495 | BG131: 6.515 | BH131: 26.261 | BI131: 7.082 | BJ131: 6.445 | BK131: 6.648 | BL131: 7.694 | BM131: 14.08 | BN131: 18.128388 | BO131: 21.150687 | BP131: 24.972218 | BQ131: 24.347913 | BR131: 23.617476 | BS131: 22.73182 | BT131: 21.595229 | BU131: 17.370076 | BV131: 17.370076 | DT131: =+F131-E131 | DU131: =+G131-F131 | DV131: =+H131-G131 | DW131: =+I131-H131
B132: AAP | C132: Major | E132: =+SUMIFS($O132:$DR132,$O$7:$DR$7,E$7) | F132: =+SUMIFS($O132:$DR132,$O$7:$DR$7,F$7) | G132: =+SUMIFS($O132:$DR132,$O$7:$DR$7,G$7) | H132: =+SUMIFS($O132:$DR132,$O$7:$DR$7,H$7) | I132: =+SUMIFS($O132:$DR132,$O$7:$DR$7,I$7) | J132: =+SUMIFS($O132:$DR132,$O$7:$DR$7,J$7) | K132: =+SUMIFS($O132:$DR132,$O$7:$DR$7,K$7) | L132: =+SUMIFS($O132:$DR132,$O$7:$DR$7,L$7) | M132: =+SUMIFS($O132:$DR132,$O$7:$DR$7,M$7) | O132: 0.338 | P132: 4.918 | Q132: 2.624 | R132: 6.823 | S132: 1.096 | T132: 2.762 | U132: 20.101 | V132: 62.041 | W132: 28.793 | X132: 25.682 | Y132: 17.133 | Z132: 4.191 | AA132: 0 | AB132: 0 | AC132: 0 | AD132: 13.6 | AE132: 1.702 | AF132: 18.801 | AG132: 109.431 | AH132: 27.09 | AI132: 31.572 | AJ132: 11.418 | AK132: 2.45 | AL132: 6.319 | AM132: 10.028 | AN132: 3.997 | AO132: 17.425 | AP132: 26.763 | AQ132: 49.497 | AR132: 4.315 | AS132: 7.3 | AT132: 2.04 | AU132: 1.125 | AV132: 1.272 | AW132: 0 | AX132: 0 | AY132: 0 | AZ132: 0 | BA132: 11.15 | BB132: 21.839 | BC132: 19.734 | BD132: 26.358 | BE132: 80.795 | BF132: 89.325 | BG132: 84.318 | BH132: 71.031 | BI132: 47.879 | BJ132: 8.621 | BK132: 0.787 | BL132: 27.032 | BM132: 14.856 | BN132: 17.643333 | BO132: 17.91901 | BP132: 16.587884 | BQ132: 16.034954 | BR132: 14.752158 | BS132: 14.198952 | BT132: 13.489005 | BU132: 11.934837 | BV132: 9.7648664 | DT132: =+F132-E132 | DU132: =+G132-F132 | DV132: =+H132-G132 | DW132: =+I132-H132
B133: ADA | C133: Lower Middle Market | E133: =+SUMIFS($O133:$DR133,$O$7:$DR$7,E$7) | F133: =+SUMIFS($O133:$DR133,$O$7:$DR$7,F$7) | G133: =+SUMIFS($O133:$DR133,$O$7:$DR$7,G$7) | H133: =+SUMIFS($O133:$DR133,$O$7:$DR$7,H$7) | I133: =+SUMIFS($O133:$DR133,$O$7:$DR$7,I$7) | J133: =+SUMIFS($O133:$DR133,$O$7:$DR$7,J$7) | K133: =+SUMIFS($O133:$DR133,$O$7:$DR$7,K$7) | L133: =+SUMIFS($O133:$DR133,$O$7:$DR$7,L$7) | M133: =+SUMIFS($O133:$DR133,$O$7:$DR$7,M$7) | O133: 0 | P133: 0 | Q133: 0 | R133: 0 | S133: 0 | T133: 0 | U133: 0 | V133: 0 | W133: 0 | X133: 0 | Y133: 0 | Z133: 0 | AA133: 0 | AB133: 0 | AC133: 0 | AD133: 0 | AE133: 0 | AF133: 0 | AG133: 0 | AH133: 0 | AI133: 0 | AJ133: 0 | AK133: 0 | AL133: 0 | AM133: 0 | AN133: 0 | AO133: 0 | AP133: 0 | AQ133: 0 | AR133: 0 | AS133: 0 | AT133: 0 | AU133: 0 | AV133: 0 | AW133: 0 | AX133: 0 | AY133: 0 | AZ133: 0 | BA133: 0 | BB133: 0 | BC133: 0 | BD133: 0 | BE133: 0 | BF133: 0.85 | BG133: 14.45 | BH133: 7.6 | BI133: 1.7 | BJ133: 0 | BK133: 8.46 | BL133: 1.23 | BM133: 20.81 | BN133: 3.8333333 | BO133: 3.8333333 | BP133: 3.8333333 | BQ133: 3.8333333 | BR133: 3.8333333 | BS133: 3.8333333 | BT133: 3.8333333 | BU133: 3.8333333 | BV133: 3.8333333 | DT133: =+F133-E133 | DU133: =+G133-F133 | DV133: =+H133-G133 | DW133: =+I133-H133
B134: AHRQ | C134: Lower Middle Market | E134: =+SUMIFS($O134:$DR134,$O$7:$DR$7,E$7) | F134: =+SUMIFS($O134:$DR134,$O$7:$DR$7,F$7) | G134: =+SUMIFS($O134:$DR134,$O$7:$DR$7,G$7) | H134: =+SUMIFS($O134:$DR134,$O$7:$DR$7,H$7) | I134: =+SUMIFS($O134:$DR134,$O$7:$DR$7,I$7) | J134: =+SUMIFS($O134:$DR134,$O$7:$DR$7,J$7) | K134: =+SUMIFS($O134:$DR134,$O$7:$DR$7,K$7) | L134: =+SUMIFS($O134:$DR134,$O$7:$DR$7,L$7) | M134: =+SUMIFS($O134:$DR134,$O$7:$DR$7,M$7) | O134: 0 | P134: 0 | Q134: 0 | R134: 0 | S134: 0 | T134: 0 | U134: 0 | V134: 0 | W134: 0 | X134: 0 | Y134: 0 | Z134: 0 | AA134: 0 | AB134: 0 | AC134: 0 | AD134: 0 | AE134: 0 | AF134: 0 | AG134: 0 | AH134: 0 | AI134: 0 | AJ134: 0 | AK134: 0 | AL134: 0 | AM134: 0 | AN134: 0 | AO134: 0 | AP134: 0 | AQ134: 0 | AR134: 0 | AS134: 0 | AT134: 0 | AU134: 0 | AV134: 0 | AW134: 0 | AX134: 0 | AY134: 0 | AZ134: 0 | BA134: 0 | BB134: 0 | BC134: 0 | BD134: 0 | BE134: 0 | BF134: 0 | BG134: 0 | BH134: 0 | BI134: 0 | BJ134: 0 | BK134: 0 | BL134: 0 | BM134: 0 | BN134: 0 | BO134: 0 | BP134: 0 | BQ134: 0 | BR134: 0 | BS134: 0 | BT134: 0 | BU134: 0 | BV134: 0 | DT134: =+F134-E134 | DU134: =+G134-F134 | DV134: =+H134-G134 | DW134: =+I134-H134
B135: AIPP | C135: Major | E135: =+SUMIFS($O135:$DR135,$O$7:$DR$7,E$7) | F135: =+SUMIFS($O135:$DR135,$O$7:$DR$7,F$7) | G135: =+SUMIFS($O135:$DR135,$O$7:$DR$7,G$7) | H135: =+SUMIFS($O135:$DR135,$O$7:$DR$7,H$7) | I135: =+SUMIFS($O135:$DR135,$O$7:$DR$7,I$7) | J135: =+SUMIFS($O135:$DR135,$O$7:$DR$7,J$7) | K135: =+SUMIFS($O135:$DR135,$O$7:$DR$7,K$7) | L135: =+SUMIFS($O135:$DR135,$O$7:$DR$7,L$7) | M135: =+SUMIFS($O135:$DR135,$O$7:$DR$7,M$7) | O135: 0 | P135: 0 | Q135: 0 | R135: 0 | S135: 0 | T135: 0 | U135: 0 | V135: 0 | W135: 0 | X135: 0 | Y135: 0 | Z135: 0 | AA135: 0 | AB135: 0 | AC135: 0 | AD135: 0 | AE135: 0 | AF135: 0 | AG135: 0 | AH135: 0 | AI135: 0 | AJ135: 0 | AK135: 0 | AL135: 0 | AM135: 0 | AN135: 0 | AO135: 0 | AP135: 0 | AQ135: 0 | AR135: 0 | AS135: 0 | AT135: 0 | AU135: 0 | AV135: 0 | AW135: 0 | AX135: 0 | AY135: 0 | AZ135: 0 | BA135: 0 | BB135: 0 | BC135: 0 | BD135: 0 | BE135: 0 | BF135: 0 | BG135: 0 | BH135: 0 | BI135: 0 | BJ135: 0 | BK135: 0 | BL135: 0 | BM135: 0 | BN135: 0 | BO135: 0 | BP135: 0 | BQ135: 8.3333333 | BR135: 18.333333 | BS135: 18.333333 | BT135: 20.166667 | BU135: 17.416667 | BV135: 17.416667 | DT135: =+F135-E135 | DU135: =+G135-F135 | DV135: =+H135-G135 | DW135: =+I135-H135
B136: ALLEN | C136: Upper Middle Market | E136: =+SUMIFS($O136:$DR136,$O$7:$DR$7,E$7) | F136: =+SUMIFS($O136:$DR136,$O$7:$DR$7,F$7) | G136: =+SUMIFS($O136:$DR136,$O$7:$DR$7,G$7) | H136: =+SUMIFS($O136:$DR136,$O$7:$DR$7,H$7) | I136: =+SUMIFS($O136:$DR136,$O$7:$DR$7,I$7) | J136: =+SUMIFS($O136:$DR136,$O$7:$DR$7,J$7) | K136: =+SUMIFS($O136:$DR136,$O$7:$DR$7,K$7) | L136: =+SUMIFS($O136:$DR136,$O$7:$DR$7,L$7) | M136: =+SUMIFS($O136:$DR136,$O$7:$DR$7,M$7) | O136: 0 | P136: 0 | Q136: 0 | R136: 0 | S136: 0 | T136: 0 | U136: 0 | V136: 0 | W136: 0 | X136: 0 | Y136: 0 | Z136: 0 | AA136: 0 | AB136: 0 | AC136: 0 | AD136: 0 | AE136: 0 | AF136: 0 | AG136: 0 | AH136: 0 | AI136: 0 | AJ136: 0 | AK136: 0 | AL136: 0 | AM136: 0 | AN136: 0 | AO136: 0 | AP136: 0 | AQ136: 0 | AR136: 0 | AS136: 0 | AT136: 0 | AU136: 0 | AV136: 1.9 | AW136: 0.95 | AX136: 2.85 | AY136: 0 | AZ136: 10.675 | BA136: 16.615 | BB136: 3.52 | BC136: 6.38 | BD136: 13.23 | BE136: 10.045 | BF136: 1.34 | BG136: 0 | BH136: 8.95 | BI136: 2.685 | BJ136: 0 | BK136: 0 | BL136: 3.3 | BM136: 0.4 | BN136: 7.9222222 | BO136: 7.9222222 | BP136: 7.9222222 | BQ136: 7.9222222 | BR136: 7.9222222 | BS136: 7.9222222 | BT136: 7.9222222 | BU136: 7.9222222 | BV136: 7.9222222 | DT136: =+F136-E136 | DU136: =+G136-F136 | DV136: =+H136-G136 | DW136: =+I136-H136
B137: AMA | C137: Mega | E137: =+SUMIFS($O137:$DR137,$O$7:$DR$7,E$7) | F137: =+SUMIFS($O137:$DR137,$O$7:$DR$7,F$7) | G137: =+SUMIFS($O137:$DR137,$O$7:$DR$7,G$7) | H137: =+SUMIFS($O137:$DR137,$O$7:$DR$7,H$7) | I137: =+SUMIFS($O137:$DR137,$O$7:$DR$7,I$7) | J137: =+SUMIFS($O137:$DR137,$O$7:$DR$7,J$7) | K137: =+SUMIFS($O137:$DR137,$O$7:$DR$7,K$7) | L137: =+SUMIFS($O137:$DR137,$O$7:$DR$7,L$7) | M137: =+SUMIFS($O137:$DR137,$O$7:$DR$7,M$7) | O137: 113.894 | P137: 133.412 | Q137: 121.507 | R137: 140.542 | S137: 185.268 | T137: 193.304 | U137: 197.47 | V137: 196.875 | W137: 181.672 | X137: 170.909 | Y137: 182.677 | Z137: 167.797 | AA137: 172.142 | AB137: 131.78 | AC137: 194.192 | AD137: 136.503 | AE137: 152.135 | AF137: 155.664 | AG137: 151.005 | AH137: 197.002 | AI137: 208.296 | AJ137: 215.74 | AK137: 154.136 | AL137: 128.981 | AM137: 174.44 | AN137: 96.04 | AO137: 144.48 | AP137: 107.94 | AQ137: 105.7 | AR137: 140.98 | AS137: 172.2 | AT137: 177.52 | AU137: 182.98 | AV137: 162.54 | AW137: 122.92 | AX137: 158.08 | AY137: 150.815 | AZ137: 141.205 | BA137: 184.76 | BB137: 195.415 | BC137: 153.995 | BD137: 188.041 | BE137: 151.255 | BF137: 150.76 | BG137: 148.179 | BH137: 141.795 | BI137: 92.845 | BJ137: 112.85 | BK137: 121.96 | BL137: 128.9 | BM137: 156.06 | BN137: 152.85289 | BO137: 160.72631 | BP137: 160.79275 | BQ137: 176.59158 | BR137: 173.03788 | BS137: 176.2601 | BT137: 167.44709 | BU137: 147.99822 | BV137: 121.37319 | DT137: =+F137-E137 | DU137: =+G137-F137 | DV137: =+H137-G137 | DW137: =+I137-H137
B138: AORN | C138: Lower Middle Market | E138: =+SUMIFS($O138:$DR138,$O$7:$DR$7,E$7) | F138: =+SUMIFS($O138:$DR138,$O$7:$DR$7,F$7) | G138: =+SUMIFS($O138:$DR138,$O$7:$DR$7,G$7) | H138: =+SUMIFS($O138:$DR138,$O$7:$DR$7,H$7) | I138: =+SUMIFS($O138:$DR138,$O$7:$DR$7,I$7) | J138: =+SUMIFS($O138:$DR138,$O$7:$DR$7,J$7) | K138: =+SUMIFS($O138:$DR138,$O$7:$DR$7,K$7) | L138: =+SUMIFS($O138:$DR138,$O$7:$DR$7,L$7) | M138: =+SUMIFS($O138:$DR138,$O$7:$DR$7,M$7) | O138: 0 | P138: 18.67 | Q138: 0.34 | R138: 1.221 | S138: 4.57 | T138: 1.819 | U138: 7.038 | V138: 0.969 | W138: 8.473 | X138: 2.425 | Y138: 1.455 | Z138: 0 | AA138: 23.513 | AB138: 4.437 | AC138: 0.8 | AD138: 0 | AE138: 0.738 | AF138: 2.042 | AG138: 0.695 | AH138: 0 | AI138: 0 | AJ138: 0 | AK138: 27.019 | AL138: 2.111 | AM138: 0 | AN138: 10.399 | AO138: 14.696 | AP138: 12.373 | AQ138: 11.823 | AR138: 9.647 | AS138: 0.342 | AT138: 0 | AU138: 0 | AV138: 0 | AW138: 4.38 | AX138: 6.165 | AY138: 5.415 | AZ138: 6.453 | BA138: 27.265 | BB138: 36.112 | BC138: 11.06 | BD138: 0 | BE138: 8.03 | BF138: 0 | BG138: 10.8 | BH138: 0.88 | BI138: 2.85 | BJ138: 10.59 | BK138: 20.82 | BL138: 19 | BM138: 0 | BN138: 10.575556 | BO138: 10.575556 | BP138: 10.575556 | BQ138: 10.575556 | BR138: 10.575556 | BS138: 10.575556 | BT138: 10.575556 | BU138: 10.575556 | BV138: 10.575556 | DT138: =+F138-E138 | DU138: =+G138-F138 | DV138: =+H138-G138 | DW138: =+I138-H138
B139: AOTA | C139: Lower Middle Market | E139: =+SUMIFS($O139:$DR139,$O$7:$DR$7,E$7) | F139: =+SUMIFS($O139:$DR139,$O$7:$DR$7,F$7) | G139: =+SUMIFS($O139:$DR139,$O$7:$DR$7,G$7) | H139: =+SUMIFS($O139:$DR139,$O$7:$DR$7,H$7) | I139: =+SUMIFS($O139:$DR139,$O$7:$DR$7,I$7) | J139: =+SUMIFS($O139:$DR139,$O$7:$DR$7,J$7) | K139: =+SUMIFS($O139:$DR139,$O$7:$DR$7,K$7) | L139: =+SUMIFS($O139:$DR139,$O$7:$DR$7,L$7) | M139: =+SUMIFS($O139:$DR139,$O$7:$DR$7,M$7) | O139: 0 | P139: 0 | Q139: 0 | R139: 0 | S139: 0 | T139: 0 | U139: 0 | V139: 0 | W139: 0 | X139: 0 | Y139: 0 | Z139: 0 | AA139: 0 | AB139: 0 | AC139: 0 | AD139: 0 | AE139: 0 | AF139: 0 | AG139: 0 | AH139: 0 | AI139: 3.85 | AJ139: 29.259 | AK139: 7.545 | AL139: 1.964 | AM139: 3.581 | AN139: 0 | AO139: 0 | AP139: 0 | AQ139: 0 | AR139: 0 | AS139: 0 | AT139: 0 | AU139: 0 | AV139: 0 | AW139: 0 | AX139: 0 | AY139: 0 | AZ139: 0 | BA139: 0 | BB139: 0 | BC139: 1.968 | BD139: 0.492 | BE139: 0 | BF139: 0 | BG139: 0 | BH139: 0 | BI139: 0 | BJ139: 0 | BK139: 0 | BL139: 0 | BM139: 0 | BN139: 0.27777778 | BO139: 0.27777778 | BP139: 0.27777778 | BQ139: 0.27777778 | BR139: 0.27777778 | BS139: 0.27777778 | BT139: 0.27777778 | BU139: 0.27777778 | BV139: 0.27777778 | DT139: =+F139-E139 | DU139: =+G139-F139 | DV139: =+H139-G139 | DW139: =+I139-H139
... B170: UCSF | C170: Upper Middle Market | E170: =+SUMIFS($O170:$DR170,$O$7:$DR$7,E$7) | F170: =+SUMIFS($O170:$DR170,$O$7:$DR$7,F$7) | G170: =+SUMIFS($O170:$DR170,$O$7:$DR$7,G$7) | H170: =+SUMIFS($O170:$DR170,$O$7:$DR$7,H$7) | I170: =+SUMIFS($O170:$DR170,$O$7:$DR$7,I$7) | J170: =+SUMIFS($O170:$DR170,$O$7:$DR$7,J$7) | K170: =+SUMIFS($O170:$DR170,$O$7:$DR$7,K$7) | L170: =+SUMIFS($O170:$DR170,$O$7:$DR$7,L$7) | M170: =+SUMIFS($O170:$DR170,$O$7:$DR$7,M$7) | O170: 7.323 | P170: 5.821 | Q170: 5.965 | R170: 8.682 | S170: 7.886 | T170: 5.609 | U170: 8.146 | V170: 6.149 | W170: 5.929 | X170: 7.436 | Y170: 6.46 | Z170: 6.83 | AA170: 4.09 | AB170: 3.959 | AC170: 6.298 | AD170: 6.553 | AE170: 4.683 | AF170: 4.528 | AG170: 6.343 | AH170: 6.348 | AI170: 6.06 | AJ170: 0 | AK170: 0 | AL170: 0 | AM170: 0 | AN170: 0 | AO170: 0 | AP170: 0 | AQ170: 0 | AR170: 0 | AS170: 0 | AT170: 0 | AU170: 0 | AV170: 0 | AW170: 0 | AX170: 0 | AY170: 0 | AZ170: 0 | BA170: 0 | BB170: 0 | BC170: 0 | BD170: 0 | BE170: 0 | BF170: 0 | BG170: 0 | BH170: 0 | BI170: 0 | BJ170: 0 | BK170: 0 | BL170: 0 | BM170: 0 | BN170: 0 | BO170: 0 | BP170: 0 | BQ170: 0 | BR170: 0 | BS170: 0 | BT170: 0 | BU170: 0 | BV170: 0 | DT170: =+F170-E170 | DU170: =+G170-F170 | DV170: =+H170-G170 | DW170: =+I170-H170
B171: OTHER | E171: =+SUMIFS($O171:$DR171,$O$7:$DR$7,E$7) | F171: =+SUMIFS($O171:$DR171,$O$7:$DR$7,F$7) | G171: =+SUMIFS($O171:$DR171,$O$7:$DR$7,G$7) | H171: =+SUMIFS($O171:$DR171,$O$7:$DR$7,H$7) | I171: =+SUMIFS($O171:$DR171,$O$7:$DR$7,I$7) | J171: =+SUMIFS($O171:$DR171,$O$7:$DR$7,J$7) | K171: =+SUMIFS($O171:$DR171,$O$7:$DR$7,K$7) | L171: =+SUMIFS($O171:$DR171,$O$7:$DR$7,L$7) | M171: =+SUMIFS($O171:$DR171,$O$7:$DR$7,M$7) | O171: 0 | P171: 0 | Q171: 0 | R171: 0 | S171: 0 | T171: 0 | U171: 0 | V171: 0 | W171: 0 | X171: 0 | Y171: 0 | Z171: 0 | AA171: 0 | AB171: 0 | AC171: 0 | AD171: 0 | AE171: 0 | AF171: 0 | AG171: 0 | AH171: 0 | AI171: 0 | AJ171: 0 | AK171: 0 | AL171: 0 | AM171: 0 | AN171: 0 | AO171: 0 | AP171: 0 | AQ171: 0 | AR171: 0 | AS171: 0 | AT171: 0 | AU171: 0 | AV171: 0 | AW171: 0 | AX171: 0 | AY171: 0 | AZ171: 0 | BA171: 0 | BB171: 0 | BC171: 0 | BD171: 0 | BE171: 0 | BF171: 0 | BG171: 0 | BH171: 0 | BI171: 0 | BJ171: 0 | BK171: 0 | BL171: 0 | BM171: 0 | BN171: 0 | BO171: 0 | BP171: 0 | BQ171: 33.333333 | BR171: 69 | BS171: 91.441667 | BT171: 91.69 | BU171: 76.69425 | BV171: 62.84075 | DT171: =+F171-E171 | DU171: =+G171-F171 | DV171: =+H171-G171 | DW171: =+I171-H171
B172: AAAS | C172: Lower Middle Market | E172: =+SUMIFS($O172:$DR172,$O$7:$DR$7,E$7) | F172: =+SUMIFS($O172:$DR172,$O$7:$DR$7,F$7) | G172: =+SUMIFS($O172:$DR172,$O$7:$DR$7,G$7) | H172: =+SUMIFS($O172:$DR172,$O$7:$DR$7,H$7) | I172: =+SUMIFS($O172:$DR172,$O$7:$DR$7,I$7) | J172: =+SUMIFS($O172:$DR172,$O$7:$DR$7,J$7) | K172: =+SUMIFS($O172:$DR172,$O$7:$DR$7,K$7) | L172: =+SUMIFS($O172:$DR172,$O$7:$DR$7,L$7) | M172: =+SUMIFS($O172:$DR172,$O$7:$DR$7,M$7) | O172: 0 | P172: 0 | Q172: 0 | R172: 0 | S172: 0 | T172: 0 | U172: 0 | V172: 0 | W172: 0 | X172: 0 | Y172: 0 | Z172: 0 | AA172: 0 | AB172: 0 | AC172: 0 | AD172: 0 | AE172: 0 | AF172: 0 | AG172: 0 | AH172: 0 | AI172: 0 | AJ172: 0 | AK172: 0 | AL172: 0 | AM172: 0 | AN172: 0 | AO172: 0 | AP172: 0 | AQ172: 0 | AR172: 0 | AS172: 0 | AT172: 0 | AU172: 0 | AV172: 0 | AW172: 0 | AX172: 0 | AY172: 0 | AZ172: 0 | BA172: 0 | BB172: 0 | BC172: 0 | BD172: 0 | BE172: 0 | BF172: 0 | BG172: 0 | BH172: 0 | BI172: 0 | BJ172: 0 | BK172: 0 | BL172: 0 | BM172: 0 | BN172: 0 | BO172: 0 | BP172: 0 | BQ172: 0 | BR172: 0 | BS172: 0 | BT172: 0 | BU172: 0 | BV172: 0 | DT172: =+F172-E172 | DU172: =+G172-F172 | DV172: =+H172-G172 | DW172: =+I172-H172
B173: EL | C173: Lower Middle Market | E173: =+SUMIFS($O173:$DR173,$O$7:$DR$7,E$7) | F173: =+SUMIFS($O173:$DR173,$O$7:$DR$7,F$7) | G173: =+SUMIFS($O173:$DR173,$O$7:$DR$7,G$7) | H173: =+SUMIFS($O173:$DR173,$O$7:$DR$7,H$7) | I173: =+SUMIFS($O173:$DR173,$O$7:$DR$7,I$7) | J173: =+SUMIFS($O173:$DR173,$O$7:$DR$7,J$7) | K173: =+SUMIFS($O173:$DR173,$O$7:$DR$7,K$7) | L173: =+SUMIFS($O173:$DR173,$O$7:$DR$7,L$7) | M173: =+SUMIFS($O173:$DR173,$O$7:$DR$7,M$7) | O173: 0 | P173: 0 | Q173: 0 | R173: 0 | S173: 0 | T173: 0 | U173: 0 | V173: 0 | W173: 0 | X173: 0 | Y173: 0 | Z173: 0 | AA173: 0 | AB173: 0 | AC173: 0 | AD173: 0 | AE173: 0 | AF173: 0 | AG173: 0 | AH173: 0 | AI173: 0 | AJ173: 0 | AK173: 0 | AL173: 0 | AM173: 0 | AN173: 0 | AO173: 0 | AP173: 0 | AQ173: 0 | AR173: 0 | AS173: 0 | AT173: 0 | AU173: 0 | AV173: 0 | AW173: 0 | AX173: 0 | AY173: 0 | AZ173: 0 | BA173: 0 | BB173: 0 | BC173: 0 | BD173: 0 | BE173: 0 | BF173: 0 | BG173: 0 | BH173: 0 | BI173: 0 | BJ173: 0 | BK173: 0 | BL173: 0 | BM173: 0 | BN173: 0 | BO173: 0 | BP173: 0 | BQ173: 0 | BR173: 0 | BS173: 0 | BT173: 0 | BU173: 0 | BV173: 0 | DT173: =+F173-E173 | DU173: =+G173-F173 | DV173: =+H173-G173 | DW173: =+I173-H173
B175: Forecast Revenue | E175: =+SUMIFS($O175:$DR175,$O$7:$DR$7,E$7) | F175: =+SUMIFS($O175:$DR175,$O$7:$DR$7,F$7) | G175: =+SUMIFS($O175:$DR175,$O$7:$DR$7,G$7) | H175: =+SUMIFS($O175:$DR175,$O$7:$DR$7,H$7) | I175: =+SUMIFS($O175:$DR175,$O$7:$DR$7,I$7) | J175: =+SUMIFS($O175:$DR175,$O$7:$DR$7,J$7) | K175: =+SUMIFS($O175:$DR175,$O$7:$DR$7,K$7) | L175: =+SUMIFS($O175:$DR175,$O$7:$DR$7,L$7) | M175: =+SUMIFS($O175:$DR175,$O$7:$DR$7,M$7) | O175: =SUM(O128:O174) | P175: =SUM(P128:P174) | Q175: =SUM(Q128:Q174) | R175: =SUM(R128:R174) | S175: =SUM(S128:S174) | T175: =SUM(T128:T174) | U175: =SUM(U128:U174) | V175: =SUM(V128:V174) | ... DR175: =SUM(DR128:DR174)
B176: Check | BK176: 0 | BL176: 0 | BM176: 0 | BN176: 0 | BO176: 0 | BP176: 0 | BQ176: 0 | BR176: 0 | BS176: 0 | BT176: 0 | BU176: 0 | BV176: 0
B178: Revenue, Beginning | F178: =+E184 | G178: =+F184 | H178: =+G184
B179: Churn | F179: =+SUMIF(DT$128:DT$173,"<0") | G179: =+SUMIF(DU$128:DU$173,"<0") | H179: =+SUMIF(DV$128:DV$173,"<0")
B180: Gross Retention | F180: =SUM(F178:F179) | G180: =SUM(G178:G179) | H180: =SUM(H178:H179)
B181: Upsell | F181: =+SUMIF(DT$128:DT$173,">0")-F183 | G181: =+SUMIF(DU$128:DU$173,">0")-G183 | H181: =+SUMIF(DV$128:DV$173,">0")-H183
B182: Net Retention | F182: =+SUM(F180:F181) | G182: =+SUM(G180:G181) | H182: =+SUM(H180:H181)
B183: New | F183: =+SUMIFS(F$128:F$173,E$128:E$173,0) | G183: =+SUMIFS(G$128:G$173,F$128:F$173,0) | H183: =+SUMIFS(H$128:H$173,G$128:G$173,0)
B184: Revenue, Ending | E184: =+E175 | F184: =+SUM(F182:F183) | G184: =+SUM(G182:G183) | H184: =+SUM(H182:H183)
B186: Gross Retention | F186: =+F180/F178 | G186: =+G180/G178 | H186: =+H180/H178
B187: Net Retention | F187: =+F182/F178 | G187: =+G182/G178 | H187: =+H182/H178
B189: Mega
...

Sheet COGS_Calcs
B2: Project Shasta
B3: {=MID(CELL("filename",A1),FIND("]",CELL("filename",A1))+1,255)}
B4: Spring 2022
B5: CONFIDENTIAL
F7: 2019 | G7: =+F7+1 | H7: =+G7+1 | I7: =+H7+1 | J7: =+I7+1 | K7: =+J7+1 | L7: =+K7+1 | M7: =+L7+1 | AA7: =+YEAR(AA8) | AB7: =+YEAR(AB8) | AC7: =+YEAR(AC8) | AD7: =+YEAR(AD8) | AE7: =+YEAR(AE8) | AF7: =+YEAR(AF8) | AG7: =+YEAR(AG8) | AH7: =+YEAR(AH8) | ... DR7: =+YEAR(DR8)
F8: =+DATE(F7,12,31) | G8: =+DATE(G7,12,31) | H8: =+DATE(H7,12,31) | I8: =+DATE(I7,12,31) | J8: =+DATE(J7,12,31) | K8: =+DATE(K7,12,31) | L8: =+DATE(L7,12,31) | M8: =+DATE(M7,12,31) | AA8: 43496 | AB8: =+EOMONTH(AA8,1) | AC8: =+EOMONTH(AB8,1) | AD8: =+EOMONTH(AC8,1) | AE8: =+EOMONTH(AD8,1) | AF8: =+EOMONTH(AE8,1) | AG8: =+EOMONTH(AF8,1) | AH8: =+EOMONTH(AG8,1) | AI8: =+EOMONTH(AH8,1) | ... DR8: =+EOMONTH(DQ8,1)
B9: $ in thousands | F9: Actual | G9: Actual | H9: Actual | I9: Budget | J9: Projection | K9: Projection | L9: Projection | M9: Projection | AA9: Actual | AB9: Actual | AC9: Actual | AD9: Actual | AE9: Actual | AF9: Actual | AG9: Actual | AH9: Actual | AI9: Actual | AJ9: Actual | AK9: Actual | AL9: Actual | AM9: Actual | AN9: Actual | AO9: Actual | AP9: Actual | AQ9: Actual | AR9: Actual | AS9: Actual | AT9: Actual | AU9: Actual | AV9: Actual | AW9: Actual | AX9: Actual | AY9: Actual | AZ9: Actual | BA9: Actual | BB9: Actual | BC9: Actual | BD9: Actual | BE9: Actual | BF9: Actual | BG9: Actual | BH9: Actual | BI9: Actual | BJ9: Actual | BK9: Actual | BL9: Actual | BM9: Actual | BN9: Budget | BO9: Budget | BP9: Budget | BQ9: Budget | BR9: Budget | BS9: Budget | BT9: Budget | BU9: Budget | BV9: Budget | BW9: Projection | BX9: Projection | BY9: Projection | BZ9: Projection | CA9: Projection | CB9: Projection | CC9: Projection | CD9: Projection | CE9: Projection | CF9: Projection | CG9: Projection | CH9: Projection | CI9: Projection | CJ9: Projection | CK9: Projection | CL9: Projection | CM9: Projection | CN9: Projection | CO9: Projection | CP9: Projection | CQ9: Projection | CR9: Projection | CS9: Projection | CT9: Projection | CU9: Projection | CV9: Projection | CW9: Projection | CX9: Projection | CY9: Projection | CZ9: Projection | DA9: Projection | DB9: Projection | DC9: Projection | DD9: Projection | DE9: Projection | DF9: Projection | DG9: Projection | DH9: Projection | DI9: Projection | DJ9: Projection | DK9: Projection | DL9: Projection | DM9: Projection | DN9: Projection | DO9: Projection | DP9: Projection | DQ9: Projection | DR9: Projection
B11: Licensing
B13: AACN | C13: Lower Middle Market | F13: =+SUMIFS($AA13:$DR13,$AA$7:$DR$7,F$7) | G13: =+SUMIFS($AA13:$DR13,$AA$7:$DR$7,G$7) | H13: =+SUMIFS($AA13:$DR13,$AA$7:$DR$7,H$7) | I13: =+SUMIFS($AA13:$DR13,$AA$7:$DR$7,I$7) | J13: =+SUMIFS($AA13:$DR13,$AA$7:$DR$7,J$7) | K13: =+SUMIFS($AA13:$DR13,$AA$7:$DR$7,K$7) | L13: =+SUMIFS($AA13:$DR13,$AA$7:$DR$7,L$7) | M13: =+SUMIFS($AA13:$DR13,$AA$7:$DR$7,M$7) | AA13: 0 | AB13: 0 | AC13: 0 | AD13: 0 | AE13: 0 | AF13: 0 | AG13: 0.013812677 | AH13: 0 | AI13: 0.0043150032 | AJ13: 0.1975421 | AK13: 1.0030476 | AL13: 1.2549436 | AM13: 0.9292265 | AN13: 3.478431 | AO13: 1.7152249 | AP13: 2.3633506 | AQ13: 0.74093747 | AR13: 0.41773475 | AS13: 1.4611706 | AT13: 0.60891347 | AU13: 0.61079065 | AV13: 0.4765874 | AW13: 0.19945129 | AX13: 0.60160824 | AY13: 1.7303651 | AZ13: 0.19463814 | BA13: 0.092654293 | BB13: 0.11529826 | BC13: 0.31412815 | BD13: 0.18835335 | BE13: 0.53349225 | BF13: 0.23165989 | BG13: 0.89204201 | BH13: 0.23044284 | BI13: 0.48405136 | BJ13: 0.24821816
B14: AACR | C14: Lower Middle Market | F14: =+SUMIFS($AA14:$DR14,$AA$7:$DR$7,F$7) | G14: =+SUMIFS($AA14:$DR14,$AA$7:$DR$7,G$7) | H14: =+SUMIFS($AA14:$DR14,$AA$7:$DR$7,H$7) | I14: =+SUMIFS($AA14:$DR14,$AA$7:$DR$7,I$7) | J14: =+SUMIFS($AA14:$DR14,$AA$7:$DR$7,J$7) | K14: =+SUMIFS($AA14:$DR14,$AA$7:$DR$7,K$7) | L14: =+SUMIFS($AA14:$DR14,$AA$7:$DR$7,L$7) | M14: =+SUMIFS($AA14:$DR14,$AA$7:$DR$7,M$7) | AA14: 0 | AB14: 0 | AC14: 0 | AD14: 0 | AE14: 0 | AF14: 0 | AG14: 0 | AH14: 0 | AI14: 0 | AJ14: 0 | AK14: 0 | AL14: 0 | AM14: 0 | AN14: 0 | AO14: 0 | AP14: 0 | AQ14: 0 | AR14: 0 | AS14: 0 | AT14: 0 | AU14: 0 | AV14: 0 | AW14: 0 | AX14: 0 | AY14: 0 | AZ14: 0 | BA14: 0 | BB14: 0.0037956411 | BC14: 0.0085845416 | BD14: 0.10543871 | BE14: 0.14893678 | BF14: 0.087297308 | BG14: 0.13812463 | BH14: 0.47229775 | BI14: 0.6011921 | BJ14: 0.49244301
B15: AAI | C15: Lower Middle Market | F15: =+SUMIFS($AA15:$DR15,$AA$7:$DR$7,F$7) | G15: =+SUMIFS($AA15:$DR15,$AA$7:$DR$7,G$7) | H15: =+SUMIFS($AA15:$DR15,$AA$7:$DR$7,H$7) | I15: =+SUMIFS($AA15:$DR15,$AA$7:$DR$7,I$7) | J15: =+SUMIFS($AA15:$DR15,$AA$7:$DR$7,J$7) | K15: =+SUMIFS($AA15:$DR15,$AA$7:$DR$7,K$7) | L15: =+SUMIFS($AA15:$DR15,$AA$7:$DR$7,L$7) | M15: =+SUMIFS($AA15:$DR15,$AA$7:$DR$7,M$7) | AA15: 0 | AB15: 0 | AC15: 0 | AD15: 0 | AE15: 0 | AF15: 0 | AG15: 0 | AH15: 0 | AI15: 0 | AJ15: 0 | AK15: 0 | AL15: 0 | AM15: 0 | AN15: 0 | AO15: 0 | AP15: 0 | AQ15: 0 | AR15: 0 | AS15: 0 | AT15: 0 | AU15: 0 | AV15: 0 | AW15: 0 | AX15: 0 | AY15: 0 | AZ15: 0 | BA15: 0 | BB15: 0 | BC15: 0 | BD15: 0 | BE15: 0 | BF15: 0 | BG15: 0 | BH15: 0 | BI15: 0 | BJ15: 0
B16: AAOS | C16: Upper Middle Market | F16: =+SUMIFS($AA16:$DR16,$AA$7:$DR$7,F$7) | G16: =+SUMIFS($AA16:$DR16,$AA$7:$DR$7,G$7) | H16: =+SUMIFS($AA16:$DR16,$AA$7:$DR$7,H$7) | I16: =+SUMIFS($AA16:$DR16,$AA$7:$DR$7,I$7) | J16: =+SUMIFS($AA16:$DR16,$AA$7:$DR$7,J$7) | K16: =+SUMIFS($AA16:$DR16,$AA$7:$DR$7,K$7) | L16: =+SUMIFS($AA16:$DR16,$AA$7:$DR$7,L$7) | M16: =+SUMIFS($AA16:$DR16,$AA$7:$DR$7,M$7) | AA16: 0 | AB16: 0 | AC16: 0 | AD16: 0 | AE16: 0 | AF16: 0 | AG16: 0 | AH16: 0 | AI16: 0 | AJ16: 0 | AK16: 0 | AL16: 0 | AM16: 0 | AN16: 0 | AO16: 0 | AP16: 0 | AQ16: 0 | AR16: 0 | AS16: 0 | AT16: 0 | AU16: 0 | AV16: 0 | AW16: 0 | AX16: 0 | AY16: 0 | AZ16: 0.01980245 | BA16: 0.0068485652 | BB16: 0 | BC16: 0.33832217 | BD16: 0.34834676 | BE16: 0.91670979 | BF16: 3.4851088 | BG16: 3.090564 | BH16: 6.2581993 | BI16: 4.8818074 | BJ16: 5.1281479
B17: AAP | C17: Major | F17: =+SUMIFS($AA17:$DR17,$AA$7:$DR$7,F$7) | G17: =+SUMIFS($AA17:$DR17,$AA$7:$DR$7,G$7) | H17: =+SUMIFS($AA17:$DR17,$AA$7:$DR$7,H$7) | I17: =+SUMIFS($AA17:$DR17,$AA$7:$DR$7,I$7) | J17: =+SUMIFS($AA17:$DR17,$AA$7:$DR$7,J$7) | K17: =+SUMIFS($AA17:$DR17,$AA$7:$DR$7,K$7) | L17: =+SUMIFS($AA17:$DR17,$AA$7:$DR$7,L$7) | M17: =+SUMIFS($AA17:$DR17,$AA$7:$DR$7,M$7) | AA17: 3.3629843 | AB17: 1.1368268 | AC17: 8.209188 | AD17: 3.223379 | AE17: 3.1298497 | AF17: 4.1842419 | AG17: 5.6674764 | AH17: 6.0234296 | AI17: 2.8700845 | AJ17: 5.0786975 | AK17: 2.0987348 | AL17: 2.0348698 | AM17: 1.4829749 | AN17: 0.93823992 | AO17: 2.4291153 | AP17: 1.7853337 | AQ17: 1.2271394 | AR17: 1.1766318 | AS17: 1.7744851 | AT17: 2.9930649 | AU17: 1.8871839 | AV17: 3.5760756 | AW17: 3.658232 | AX17: 1.7732493 | AY17: 2.3495539 | AZ17: 2.1539916 | BA17: 1.3322629 | BB17: 0.53347452 | BC17: 0.99883581 | BD17: 0.39215628 | BE17: 2.7289429 | BF17: 0.47376552 | BG17: 1.4062687 | BH17: 0.49121131 | BI17: 1.7457504 | BJ17: 2.3382948
B18: ADA | C18: Lower Middle Market | F18: =+SUMIFS($AA18:$DR18,$AA$7:$DR$7,F$7) | G18: =+SUMIFS($AA18:$DR18,$AA$7:$DR$7,G$7) | H18: =+SUMIFS($AA18:$DR18,$AA$7:$DR$7,H$7) | I18: =+SUMIFS($AA18:$DR18,$AA$7:$DR$7,I$7) | J18: =+SUMIFS($AA18:$DR18,$AA$7:$DR$7,J$7) | K18: =+SUMIFS($AA18:$DR18,$AA$7:$DR$7,K$7) | L18: =+SUMIFS($AA18:$DR18,$AA$7:$DR$7,L$7) | M18: =+SUMIFS($AA18:$DR18,$AA$7:$DR$7,M$7) | AA18: 0 | AB18: 0 | AC18: 0 | AD18: 0 | AE18: 0 | AF18: 0 | AG18: 0 | AH18: 0 | AI18: 0 | AJ18: 0 | AK18: 0 | AL18: 0 | AM18: 0 | AN18: 0 | AO18: 0 | AP18: 0 | AQ18: 0 | AR18: 0 | AS18: 0 | AT18: 0 | AU18: 0 | AV18: 0 | AW18: 0 | AX18: 0 | AY18: 0 | AZ18: 0 | BA18: 0 | BB18: 0 | BC18: 0 | BD18: 0.036517133 | BE18: 0.0039547863 | BF18: 0.0038595745 | BG18: 0 | BH18: 0.082851005 | BI18: 0.29803071 | BJ18: 0.51274873
B19: AHRQ | C19: Lower Middle Market | F19: =+SUMIFS($AA19:$DR19,$AA$7:$DR$7,F$7) | G19: =+SUMIFS($AA19:$DR19,$AA$7:$DR$7,G$7) | H19: =+SUMIFS($AA19:$DR19,$AA$7:$DR$7,H$7) | I19: =+SUMIFS($AA19:$DR19,$AA$7:$DR$7,I$7) | J19: =+SUMIFS($AA19:$DR19,$AA$7:$DR$7,J$7) | K19: =+SUMIFS($AA19:$DR19,$AA$7:$DR$7,K$7) | L19: =+SUMIFS($AA19:$DR19,$AA$7:$DR$7,L$7) | M19: =+SUMIFS($AA19:$DR19,$AA$7:$DR$7,M$7) | AA19: 0 | AB19: 0 | AC19: 0 | AD19: 0 | AE19: 0 | AF19: 0 | AG19: 0 | AH19: 0 | AI19: 0 | AJ19: 0 | AK19: 0 | AL19: 0 | AM19: 0 | AN19: 0 | AO19: 0 | AP19: 0 | AQ19: 0 | AR19: 0 | AS19: 0 | AT19: 0 | AU19: 0 | AV19: 0 | AW19: 0 | AX19: 0 | AY19: 0 | AZ19: 0 | BA19: 0 | BB19: 0 | BC19: 0 | BD19: 0 | BE19: 0 | BF19: 0 | BG19: 0 | BH19: 0 | BI19: 0 | BJ19: 0
B20: AIPP | C20: Major | F20: =+SUMIFS($AA20:$DR20,$AA$7:$DR$7,F$7) | G20: =+SUMIFS($AA20:$DR20,$AA$7:$DR$7,G$7) | H20: =+SUMIFS($AA20:$DR20,$AA$7:$DR$7,H$7) | I20: =+SUMIFS($AA20:$DR20,$AA$7:$DR$7,I$7) | J20: =+SUMIFS($AA20:$DR20,$AA$7:$DR$7,J$7) | K20: =+SUMIFS($AA20:$DR20,$AA$7:$DR$7,K$7) | L20: =+SUMIFS($AA20:$DR20,$AA$7:$DR$7,L$7) | M20: =+SUMIFS($AA20:$DR20,$AA$7:$DR$7,M$7) | AA20: 0 | AB20: 0 | AC20: 0 | AD20: 0 | AE20: 0 | AF20: 0 | AG20: 0 | AH20: 0 | AI20: 0 | AJ20: 0 | AK20: 0 | AL20: 0 | AM20: 0 | AN20: 0 | AO20: 0 | AP20: 0 | AQ20: 0 | AR20: 0 | AS20: 0 | AT20: 0 | AU20: 0 | AV20: 0 | AW20: 0 | AX20: 0 | AY20: 0 | AZ20: 0 | BA20: 0 | BB20: 0 | BC20: 0 | BD20: 0 | BE20: 0 | BF20: 0 | BG20: 0 | BH20: 0 | BI20: 0 | BJ20: 0
B21: ALLEN | C21: Upper Middle Market | F21: =+SUMIFS($AA21:$DR21,$AA$7:$DR$7,F$7) | G21: =+SUMIFS($AA21:$DR21,$AA$7:$DR$7,G$7) | H21: =+SUMIFS($AA21:$DR21,$AA$7:$DR$7,H$7) | I21: =+SUMIFS($AA21:$DR21,$AA$7:$DR$7,I$7) | J21: =+SUMIFS($AA21:$DR21,$AA$7:$DR$7,J$7) | K21: =+SUMIFS($AA21:$DR21,$AA$7:$DR$7,K$7) | L21: =+SUMIFS($AA21:$DR21,$AA$7:$DR$7,L$7) | M21: =+SUMIFS($AA21:$DR21,$AA$7:$DR$7,M$7) | AA21: 0 | AB21: 0 | AC21: 0.075913136 | AD21: 0 | AE21: 0 | AF21: 0.0081275186 | AG21: 0 | AH21: 0.018045105 | AI21: 0 | AJ21: 0.18331029 | AK21: 0.025261544 | AL21: 0.14490316 | AM21: 0.11215024 | AN21: 1.7140474 | AO21: 1.2186278 | AP21: 1.3591446 | AQ21: 1.4596021 | AR21: 4.7302452 | AS21: 4.1455135 | AT21: 4.6366293 | AU21: 2.964056 | AV21: 3.5676551 | AW21: 4.7714323 | AX21: 4.675927 | AY21: 3.8963324 | AZ21: 4.1499295 | BA21: 3.9963912 | BB21: 3.7621576 | BC21: 5.4598672 | BD21: 3.9648356 | BE21: 2.804399 | BF21: 4.3127886 | BG21: 3.3024298 | BH21: 2.0957186 | BI21: 4.6312241 | BJ21: 1.3321116
B22: AMA | C22: Mega | F22: =+SUMIFS($AA22:$DR22,$AA$7:$DR$7,F$7) | G22: =+SUMIFS($AA22:$DR22,$AA$7:$DR$7,G$7) | H22: =+SUMIFS($AA22:$DR22,$AA$7:$DR$7,H$7) | I22: =+SUMIFS($AA22:$DR22,$AA$7:$DR$7,I$7) | J22: =+SUMIFS($AA22:$DR22,$AA$7:$DR$7,J$7) | K22: =+SUMIFS($AA22:$DR22,$AA$7:$DR$7,K$7) | L22: =+SUMIFS($AA22:$DR22,$AA$7:$DR$7,L$7) | M22: =+SUMIFS($AA22:$DR22,$AA$7:$DR$7,M$7) | AA22: 19.603729 | AB22: 32.856753 | AC22: 33.267641 | AD22: 43.751815 | AE22: 44.320755 | AF22: 29.45154 | AG22: 24.16103 | AH22: 23.892125 | AI22: 19.874672 | AJ22: 23.855028 | AK22: 16.446241 | AL22: 14.771366 | AM22: 15.251374 | AN22: 23.223621 | AO22: 17.432501 | AP22: 15.500902 | AQ22: 12.103186 | AR22: 13.448291 | AS22: 16.485301 | AT22: 9.6413695 | AU22: 8.7718837 | AV22: 12.922258 | AW22: 7.6589432 | AX22: 6.1698606 | AY22: 14.708746 | AZ22: 14.754205 | BA22: 15.604159 | BB22: 7.8179854 | BC22: 13.554693 | BD22: 11.810563 | BE22: 14.513418 | BF22: 22.262411 | BG22: 13.983032 | BH22: 22.831333 | BI22: 22.935812 | BJ22: 17.805809
B23: AORN | C23: Lower Middle Market | F23: =+SUMIFS($AA23:$DR23,$AA$7:$DR$7,F$7) | G23: =+SUMIFS($AA23:$DR23,$AA$7:$DR$7,G$7) | H23: =+SUMIFS($AA23:$DR23,$AA$7:$DR$7,H$7) | I23: =+SUMIFS($AA23:$DR23,$AA$7:$DR$7,I$7) | J23: =+SUMIFS($AA23:$DR23,$AA$7:$DR$7,J$7) | K23: =+SUMIFS($AA23:$DR23,$AA$7:$DR$7,K$7) | L23: =+SUMIFS($AA23:$DR23,$AA$7:$DR$7,L$7) | M23: =+SUMIFS($AA23:$DR23,$AA$7:$DR$7,M$7) | AA23: 0.25410076 | AB23: 1.1676479 | AC23: 0.42854922 | AD23: 0.37604447 | AE23: 1.2968035 | AF23: 1.9979773 | AG23: 1.4795579 | AH23: 2.675975 | AI23: 2.6422212 | AJ23: 2.0457121 | AK23: 0.30386441 | AL23: 0.357535 | AM23: 1.7224298 | AN23: 0.25582884 | AO23: 2.1378906 | AP23: 0.12028488 | AQ23: 0.30666768 | AR23: 0.2414936 | AS23: 0.60353814 | AT23: 0.90471689 | AU23: 0.85373749 | AV23: 0.14434922 | AW23: 0.94047544 | AX23: 0.55680024 | AY23: 2.3530467 | AZ23: 1.4153498 | BA23: 0.63903564 | BB23: 0.30773774 | BC23: 0.65826906 | BD23: 2.4019413 | BE23: 2.9493892 | BF23: 0.53659957 | BG23: 0.93714791 | BH23: 2.1480429 | BI23: 0.14381543 | BJ23: 0.61106418
B24: AOTA | C24: Lower Middle Market | F24: =+SUMIFS($AA24:$DR24,$AA$7:$DR$7,F$7) | G24: =+SUMIFS($AA24:$DR24,$AA$7:$DR$7,G$7) | H24: =+SUMIFS($AA24:$DR24,$AA$7:$DR$7,H$7) | I24: =+SUMIFS($AA24:$DR24,$AA$7:$DR$7,I$7) | J24: =+SUMIFS($AA24:$DR24,$AA$7:$DR$7,J$7) | K24: =+SUMIFS($AA24:$DR24,$AA$7:$DR$7,K$7) | L24: =+SUMIFS($AA24:$DR24,$AA$7:$DR$7,L$7) | M24: =+SUMIFS($AA24:$DR24,$AA$7:$DR$7,M$7) | AA24: 1.3495978 | AB24: 0.4007777 | AC24: 0.76726246 | AD24: 0.69307634 | AE24: 3.2118626 | AF24: 1.7887281 | AG24: 0.27879355 | AH24: 1.1003811 | AI24: 0.087498458 | AJ24: 0.16298269 | AK24: 1.0167134 | AL24: 1.2351992 | AM24: 1.1653699 | AN24: 0.53680937 | AO24: 0.18981007 | AP24: 1.0490112 | AQ24: 0.23130573 | AR24: 0.0082188723 | AS24: 0.13259701 | AT24: 0.086405672 | AU24: 0.017171906 | AV24: 0.10092093 | AW24: 0.040628275 | AX24: 0.09567984 | AY24: 0.3913812 | AZ24: 0.47929634 | BA24: 0.28045939 | BB24: 0.84224942 | BC24: 0.18105606 | BD24: 0.22003255 | BE24: 0.44894256 | BF24: 0.35756853 | BG24: 0.84052494 | BH24: 0.42061198 | BI24: 0.86302832 | BJ24: 0.30873486
... B58: EL | C58: Lower Middle Market | F58: =+SUMIFS($AA58:$DR58,$AA$7:$DR$7,F$7) | G58: =+SUMIFS($AA58:$DR58,$AA$7:$DR$7,G$7) | H58: =+SUMIFS($AA58:$DR58,$AA$7:$DR$7,H$7) | I58: =+SUMIFS($AA58:$DR58,$AA$7:$DR$7,I$7) | J58: =+SUMIFS($AA58:$DR58,$AA$7:$DR$7,J$7) | K58: =+SUMIFS($AA58:$DR58,$AA$7:$DR$7,K$7) | L58: =+SUMIFS($AA58:$DR58,$AA$7:$DR$7,L$7) | M58: =+SUMIFS($AA58:$DR58,$AA$7:$DR$7,M$7) | AA58: 2.4831102 | AB58: 5.2025387 | AC58: 1.9420829 | AD58: 1.9803777 | AE58: 2.7168995 | AF58: 0.53145975 | AG58: 0 | AH58: 0 | AI58: 0 | AJ58: 0 | AK58: 0 | AL58: 0 | AM58: 0.5854165 | AN58: 0 | AO58: 0.31649546 | AP58: 1.1194254 | AQ58: 0.88241545 | AR58: 0 | AS58: 0.068453317 | AT58: 0.15589522 | AU58: 0.25377458 | AV58: 0 | AW58: 0 | AX58: 0.080155638 | AY58: 0.35832793 | AZ58: 0 | BA58: 0 | BB58: 0 | BC58: 0 | BD58: 0 | BE58: 0 | BF58: 0 | BG58: 0 | BH58: 0 | BI58: 0 | BJ58: 0
B60: Total | F60: =+SUMIFS($AA60:$DR60,$AA$7:$DR$7,F$7) | G60: =+SUMIFS($AA60:$DR60,$AA$7:$DR$7,G$7) | H60: =+SUMIFS($AA60:$DR60,$AA$7:$DR$7,H$7) | I60: =+SUMIFS($AA60:$DR60,$AA$7:$DR$7,I$7) | J60: =+SUMIFS($AA60:$DR60,$AA$7:$DR$7,J$7) | K60: =+SUMIFS($AA60:$DR60,$AA$7:$DR$7,K$7) | L60: =+SUMIFS($AA60:$DR60,$AA$7:$DR$7,L$7) | M60: =+SUMIFS($AA60:$DR60,$AA$7:$DR$7,M$7) | AA60: =SUM(AA13:AA59) | AB60: =SUM(AB13:AB59) | AC60: =SUM(AC13:AC59) | AD60: =SUM(AD13:AD59) | AE60: =SUM(AE13:AE59) | AF60: =SUM(AF13:AF59) | AG60: =SUM(AG13:AG59) | AH60: =SUM(AH13:AH59) | ... BJ60: =SUM(BJ13:BJ59)
B62: Revenue
B63: Mega | F63: =+Revenue_Calcs!F84 | G63: =+Revenue_Calcs!G84 | H63: =+Revenue_Calcs!H84 | I63: =+Revenue_Calcs!I84 | J63: =+Revenue_Calcs!J84 | K63: =+Revenue_Calcs!K84 | L63: =+Revenue_Calcs!L84 | M63: =+Revenue_Calcs!M84
B64: Major | F64: =+Revenue_Calcs!F96 | G64: =+Revenue_Calcs!G96 | H64: =+Revenue_Calcs!H96 | I64: =+Revenue_Calcs!I96 | J64: =+Revenue_Calcs!J96 | K64: =+Revenue_Calcs!K96 | L64: =+Revenue_Calcs!L96 | M64: =+Revenue_Calcs!M96
B65: Upper Middle Market | F65: =+Revenue_Calcs!F108 | G65: =+Revenue_Calcs!G108 | H65: =+Revenue_Calcs!H108 | I65: =+Revenue_Calcs!I108 | J65: =+Revenue_Calcs!J108 | K65: =+Revenue_Calcs!K108 | L65: =+Revenue_Calcs!L108 | M65: =+Revenue_Calcs!M108
B66: Lower Middle Market | F66: =+Revenue_Calcs!F120 | G66: =+Revenue_Calcs!G120 | H66: =+Revenue_Calcs!H120 | I66: =+Revenue_Calcs!I120 | J66: =+Revenue_Calcs!J120 | K66: =+Revenue_Calcs!K120 | L66: =+Revenue_Calcs!L120 | M66: =+Revenue_Calcs!M120
B67: Total | F67: =SUM(F63:F66) | G67: =SUM(G63:G66) | H67: =SUM(H63:H66) | I67: =SUM(I63:I66) | J67: =SUM(J63:J66) | K67: =SUM(K63:K66) | L67: =SUM(L63:L66) | M67: =SUM(M63:M66)
B69: Cost of Sales
B70: Mega | F70: =+SUMIFS($AA70:$DR70,$AA$7:$DR$7,F$7) | G70: =+SUMIFS($AA70:$DR70,$AA$7:$DR$7,G$7) | H70: =+SUMIFS($AA70:$DR70,$AA$7:$DR$7,H$7) | I70: =+I63*(1-COGS_Assumptions!I13) | J70: =+J63*(1-COGS_Assumptions!J13) | K70: =+K63*(1-COGS_Assumptions!K13) | L70: =+L63*(1-COGS_Assumptions!L13) | M70: =+M63*(1-COGS_Assumptions!M13) | AA70: =+SUMIFS(AA$13:AA$58,$C$13:$C$58,$B70) | AB70: =+SUMIFS(AB$13:AB$58,$C$13:$C$58,$B70) | AC70: =+SUMIFS(AC$13:AC$58,$C$13:$C$58,$B70) | AD70: =+SUMIFS(AD$13:AD$58,$C$13:$C$58,$B70) | AE70: =+SUMIFS(AE$13:AE$58,$C$13:$C$58,$B70) | AF70: =+SUMIFS(AF$13:AF$58,$C$13:$C$58,$B70) | AG70: =+SUMIFS(AG$13:AG$58,$C$13:$C$58,$B70) | AH70: =+SUMIFS(AH$13:AH$58,$C$13:$C$58,$B70) | ... BJ70: =+SUMIFS(BJ$13:BJ$58,$C$13:$C$58,$B70) | BK70: =+SUMIFS($F70:$M70,$F$7:$M$7,BK$7)*BK$75 | BL70: =+SUMIFS($F70:$M70,$F$7:$M$7,BL$7)*BL$75 | BM70: =+SUMIFS($F70:$M70,$F$7:$M$7,BM$7)*BM$75 | BN70: =+SUMIFS($F70:$M70,$F$7:$M$7,BN$7)*BN$75 | BO70: =+SUMIFS($F70:$M70,$F$7:$M$7,BO$7)*BO$75 | BP70: =+SUMIFS($F70:$M70,$F$7:$M$7,BP$7)*BP$75 | BQ70: =+SUMIFS($F70:$M70,$F$7:$M$7,BQ$7)*BQ$75 | BR70: =+SUMIFS($F70:$M70,$F$7:$M$7,BR$7)*BR$75 | ... DR70: =+SUMIFS($F70:$M70,$F$7:$M$7,DR$7)*DR$75
B71: Major | F71: =+SUMIFS($AA71:$DR71,$AA$7:$DR$7,F$7) | G71: =+SUMIFS($AA71:$DR71,$AA$7:$DR$7,G$7) | H71: =+SUMIFS($AA71:$DR71,$AA$7:$DR$7,H$7) | I71: =+I64*(1-COGS_Assumptions!I14) | J71: =+J64*(1-COGS_Assumptions!J14) | K71: =+K64*(1-COGS_Assumptions!K14) | L71: =+L64*(1-COGS_Assumptions!L14) | M71: =+M64*(1-COGS_Assumptions!M14) | AA71: =+SUMIFS(AA$13:AA$58,$C$13:$C$58,$B71) | AB71: =+SUMIFS(AB$13:AB$58,$C$13:$C$58,$B71) | AC71: =+SUMIFS(AC$13:AC$58,$C$13:$C$58,$B71) | AD71: =+SUMIFS(AD$13:AD$58,$C$13:$C$58,$B71) | AE71: =+SUMIFS(AE$13:AE$58,$C$13:$C$58,$B71) | AF71: =+SUMIFS(AF$13:AF$58,$C$13:$C$58,$B71) | AG71: =+SUMIFS(AG$13:AG$58,$C$13:$C$58,$B71) | AH71: =+SUMIFS(AH$13:AH$58,$C$13:$C$58,$B71) | ... BJ71: =+SUMIFS(BJ$13:BJ$58,$C$13:$C$58,$B71) | BK71: =+SUMIFS($F71:$M71,$F$7:$M$7,BK$7)*BK$75 | BL71: =+SUMIFS($F71:$M71,$F$7:$M$7,BL$7)*BL$75 | BM71: =+SUMIFS($F71:$M71,$F$7:$M$7,BM$7)*BM$75 | BN71: =+SUMIFS($F71:$M71,$F$7:$M$7,BN$7)*BN$75 | BO71: =+SUMIFS($F71:$M71,$F$7:$M$7,BO$7)*BO$75 | BP71: =+SUMIFS($F71:$M71,$F$7:$M$7,BP$7)*BP$75 | BQ71: =+SUMIFS($F71:$M71,$F$7:$M$7,BQ$7)*BQ$75 | BR71: =+SUMIFS($F71:$M71,$F$7:$M$7,BR$7)*BR$75 | ... DR71: =+SUMIFS($F71:$M71,$F$7:$M$7,DR$7)*DR$75
B72: Upper Middle Market | F72: =+SUMIFS($AA72:$DR72,$AA$7:$DR$7,F$7) | G72: =+SUMIFS($AA72:$DR72,$AA$7:$DR$7,G$7) | H72: =+SUMIFS($AA72:$DR72,$AA$7:$DR$7,H$7) | I72: =+I65*(1-COGS_Assumptions!I15) | J72: =+J65*(1-COGS_Assumptions!J15) | K72: =+K65*(1-COGS_Assumptions!K15) | L72: =+L65*(1-COGS_Assumptions!L15) | M72: =+M65*(1-COGS_Assumptions!M15) | AA72: =+SUMIFS(AA$13:AA$58,$C$13:$C$58,$B72) | AB72: =+SUMIFS(AB$13:AB$58,$C$13:$C$58,$B72) | AC72: =+SUMIFS(AC$13:AC$58,$C$13:$C$58,$B72) | AD72: =+SUMIFS(AD$13:AD$58,$C$13:$C$58,$B72) | AE72: =+SUMIFS(AE$13:AE$58,$C$13:$C$58,$B72) | AF72: =+SUMIFS(AF$13:AF$58,$C$13:$C$58,$B72) | AG72: =+SUMIFS(AG$13:AG$58,$C$13:$C$58,$B72) | AH72: =+SUMIFS(AH$13:AH$58,$C$13:$C$58,$B72) | ... BJ72: =+SUMIFS(BJ$13:BJ$58,$C$13:$C$58,$B72) | BK72: =+SUMIFS($F72:$M72,$F$7:$M$7,BK$7)*BK$75 | BL72: =+SUMIFS($F72:$M72,$F$7:$M$7,BL$7)*BL$75 | BM72: =+SUMIFS($F72:$M72,$F$7:$M$7,BM$7)*BM$75 | BN72: =+SUMIFS($F72:$M72,$F$7:$M$7,BN$7)*BN$75 | BO72: =+SUMIFS($F72:$M72,$F$7:$M$7,BO$7)*BO$75 | BP72: =+SUMIFS($F72:$M72,$F$7:$M$7,BP$7)*BP$75 | BQ72: =+SUMIFS($F72:$M72,$F$7:$M$7,BQ$7)*BQ$75 | BR72: =+SUMIFS($F72:$M72,$F$7:$M$7,BR$7)*BR$75 | ... DR72: =+SUMIFS($F72:$M72,$F$7:$M$7,DR$7)*DR$75
B73: Lower Middle Market | F73: =+SUMIFS($AA73:$DR73,$AA$7:$DR$7,F$7) | G73: =+SUMIFS($AA73:$DR73,$AA$7:$DR$7,G$7) | H73: =+SUMIFS($AA73:$DR73,$AA$7:$DR$7,H$7) | I73: =+I66*(1-COGS_Assumptions!I16) | J73: =+J66*(1-COGS_Assumptions!J16) | K73: =+K66*(1-COGS_Assumptions!K16) | L73: =+L66*(1-COGS_Assumptions!L16) | M73: =+M66*(1-COGS_Assumptions!M16) | AA73: =+SUMIFS(AA$13:AA$58,$C$13:$C$58,$B73) | AB73: =+SUMIFS(AB$13:AB$58,$C$13:$C$58,$B73) | AC73: =+SUMIFS(AC$13:AC$58,$C$13:$C$58,$B73) | AD73: =+SUMIFS(AD$13:AD$58,$C$13:$C$58,$B73) | AE73: =+SUMIFS(AE$13:AE$58,$C$13:$C$58,$B73) | AF73: =+SUMIFS(AF$13:AF$58,$C$13:$C$58,$B73) | AG73: =+SUMIFS(AG$13:AG$58,$C$13:$C$58,$B73) | AH73: =+SUMIFS(AH$13:AH$58,$C$13:$C$58,$B73) | ... BJ73: =+SUMIFS(BJ$13:BJ$58,$C$13:$C$58,$B73) | BK73: =+SUMIFS($F73:$M73,$F$7:$M$7,BK$7)*BK$75 | BL73: =+SUMIFS($F73:$M73,$F$7:$M$7,BL$7)*BL$75 | BM73: =+SUMIFS($F73:$M73,$F$7:$M$7,BM$7)*BM$75 | BN73: =+SUMIFS($F73:$M73,$F$7:$M$7,BN$7)*BN$75 | BO73: =+SUMIFS($F73:$M73,$F$7:$M$7,BO$7)*BO$75 | BP73: =+SUMIFS($F73:$M73,$F$7:$M$7,BP$7)*BP$75 | BQ73: =+SUMIFS($F73:$M73,$F$7:$M$7,BQ$7)*BQ$75 | BR73: =+SUMIFS($F73:$M73,$F$7:$M$7,BR$7)*BR$75 | ... DR73: =+SUMIFS($F73:$M73,$F$7:$M$7,DR$7)*DR$75
B74: Total | F74: =+SUMIFS($AA74:$DR74,$AA$7:$DR$7,F$7) | G74: =+SUMIFS($AA74:$DR74,$AA$7:$DR$7,G$7) | H74: =+SUMIFS($AA74:$DR74,$AA$7:$DR$7,H$7) | I74: =+SUMIFS($AA74:$DR74,$AA$7:$DR$7,I$7) | J74: =+SUMIFS($AA74:$DR74,$AA$7:$DR$7,J$7) | K74: =+SUMIFS($AA74:$DR74,$AA$7:$DR$7,K$7) | L74: =+SUMIFS($AA74:$DR74,$AA$7:$DR$7,L$7) | M74: =+SUMIFS($AA74:$DR74,$AA$7:$DR$7,M$7) | AA74: =SUM(AA70:AA73) | AB74: =SUM(AB70:AB73) | AC74: =SUM(AC70:AC73) | AD74: =SUM(AD70:AD73) | AE74: =SUM(AE70:AE73) | AF74: =SUM(AF70:AF73) | AG74: =SUM(AG70:AG73) | AH74: =SUM(AH70:AH73) | ... DR74: =SUM(DR70:DR73)
B75: % Seasonality | F75: =+F74/SUMIFS($AA74:$DR74,$AA$7:$DR$7,F$7) | G75: =+G74/SUMIFS($AA74:$DR74,$AA$7:$DR$7,G$7) | H75: =+H74/SUMIFS($AA74:$DR74,$AA$7:$DR$7,H$7) | I75: =+I74/SUMIFS($AA74:$DR74,$AA$7:$DR$7,I$7) | J75: =+J74/SUMIFS($AA74:$DR74,$AA$7:$DR$7,J$7) | K75: =+K74/SUMIFS($AA74:$DR74,$AA$7:$DR$7,K$7) | L75: =+L74/SUMIFS($AA74:$DR74,$AA$7:$DR$7,L$7) | M75: =+M74/SUMIFS($AA74:$DR74,$AA$7:$DR$7,M$7) | AA75: =+AA74/SUMIFS($AA74:$DR74,$AA$7:$DR$7,AA$7) | AB75: =+AB74/SUMIFS($AA74:$DR74,$AA$7:$DR$7,AB$7) | AC75: =+AC74/SUMIFS($AA74:$DR74,$AA$7:$DR$7,AC$7) | AD75: =+AD74/SUMIFS($AA74:$DR74,$AA$7:$DR$7,AD$7) | AE75: =+AE74/SUMIFS($AA74:$DR74,$AA$7:$DR$7,AE$7) | AF75: =+AF74/SUMIFS($AA74:$DR74,$AA$7:$DR$7,AF$7) | AG75: =+AG74/SUMIFS($AA74:$DR74,$AA$7:$DR$7,AG$7) | AH75: =+AH74/SUMIFS($AA74:$DR74,$AA$7:$DR$7,AH$7) | ... BJ75: =+BJ74/SUMIFS($AA74:$DR74,$AA$7:$DR$7,BJ$7) | BK75: =+AVERAGE(AA75,AM75,AY75) | BL75: =+AVERAGE(AB75,AN75,AZ75) | BM75: =+AVERAGE(AC75,AO75,BA75) | BN75: =+AVERAGE(AD75,AP75,BB75) | BO75: =+AVERAGE(AE75,AQ75,BC75) | BP75: =+AVERAGE(AF75,AR75,BD75) | BQ75: =+AVERAGE(AG75,AS75,BE75) | BR75: =+AVERAGE(AH75,AT75,BF75) | ... DR75: =+AVERAGE(CH75,CT75,DF75)
B77: Gross Profit
B78: Mega | F78: =+F63-F70 | G78: =+G63-G70 | H78: =+H63-H70 | I78: =+I63-I70 | J78: =+J63-J70 | K78: =+K63-K70 | L78: =+L63-L70 | M78: =+M63-M70
B79: Major | F79: =+F64-F71 | G79: =+G64-G71 | H79: =+H64-H71 | I79: =+I64-I71 | J79: =+J64-J71 | K79: =+K64-K71 | L79: =+L64-L71 | M79: =+M64-M71
B80: Upper Middle Market | F80: =+F65-F72 | G80: =+G65-G72 | H80: =+H65-H72 | I80: =+I65-I72 | J80: =+J65-J72 | K80: =+K65-K72 | L80: =+L65-L72 | M80: =+M65-M72
B81: Lower Middle Market | F81: =+F66-F73 | G81: =+G66-G73 | H81: =+H66-H73 | I81: =+I66-I73 | J81: =+J66-J73 | K81: =+K66-K73 | L81: =+L66-L73 | M81: =+M66-M73
B82: Total | F82: =SUM(F78:F81) | G82: =SUM(G78:G81) | H82: =SUM(H78:H81) | I82: =SUM(I78:I81) | J82: =SUM(J78:J81) | K82: =SUM(K78:K81) | L82: =SUM(L78:L81) | M82: =SUM(M78:M81)
B84: Gross Margin
B85: Mega | F85: =+F78/F63 | G85: =+G78/G63 | H85: =+H78/H63 | I85: =+I78/I63 | J85: =+J78/J63 | K85: =+K78/K63 | L85: =+L78/L63 | M85: =+M78/M63
B86: Major | F86: =+F79/F64 | G86: =+G79/G64 | H86: =+H79/H64 | I86: =+I79/I64 | J86: =+J79/J64 | K86: =+K79/K64 | L86: =+L79/L64 | M86: =+M79/M64
B87: Upper Middle Market | F87: =+F80/F65 | G87: =+G80/G65 | H87: =+H80/H65 | I87: =+I80/I65 | J87: =+J80/J65 | K87: =+K80/K65 | L87: =+L80/L65 | M87: =+M80/M65
B88: Lower Middle Market | F88: =+F81/F66 | G88: =+G81/G66 | H88: =+H81/H66 | I88: =+I81/I66 | J88: =+J81/J66 | K88: =+K81/K66 | L88: =+L81/L66 | M88: =+M81/M66
B89: Total | F89: =+F82/F67 | G89: =+G82/G67 | H89: =+H82/H67 | I89: =+I82/I67 | J89: =+J82/J67 | K89: =+K82/K67 | L89: =+L82/L67 | M89: =+M82/M67
B91: Hosting
B92: Revenue | F92: =+SUMIFS($AA92:$DR92,$AA$7:$DR$7,F$7) | G92: =+SUMIFS($AA92:$DR92,$AA$7:$DR$7,G$7) | H92: =+SUMIFS($AA92:$DR92,$AA$7:$DR$7,H$7) | I92: =+SUMIFS($AA92:$DR92,$AA$7:$DR$7,I$7) | J92: =+SUMIFS($AA92:$DR92,$AA$7:$DR$7,J$7) | K92: =+SUMIFS($AA92:$DR92,$AA$7:$DR$7,K$7) | L92: =+SUMIFS($AA92:$DR92,$AA$7:$DR$7,L$7) | M92: =+SUMIFS($AA92:$DR92,$AA$7:$DR$7,M$7) | AA92: =+Revenue_Calcs!AA122 | AB92: =+Revenue_Calcs!AB122 | AC92: =+Revenue_Calcs!AC122 | AD92: =+Revenue_Calcs!AD122 | AE92: =+Revenue_Calcs!AE122 | AF92: =+Revenue_Calcs!AF122 | AG92: =+Revenue_Calcs!AG122 | AH92: =+Revenue_Calcs!AH122 | ... DR92: =+Revenue_Calcs!DR122
B93: % of Revenue | F93: =+F94/F92 | G93: =+G94/G92 | H93: =+H94/H92 | I93: =+I94/I92 | J93: =+J94/J92 | K93: =+COGS_Assumptions!K18 | L93: =+COGS_Assumptions!L18 | M93: =+COGS_Assumptions!M18 | AA93: =+AA94/AA92 | AB93: =+AB94/AB92 | AC93: =+AC94/AC92 | AD93: =+AD94/AD92 | AE93: =+AE94/AE92 | AF93: =+AF94/AF92 | AG93: =+AG94/AG92 | AH93: =+AH94/AH92 | ... CH93: =+CH94/CH92 | CI93: =+SUMIFS($F93:$M93,$F$7:$M$7,CI$7) | CJ93: =+SUMIFS($F93:$M93,$F$7:$M$7,CJ$7) | CK93: =+SUMIFS($F93:$M93,$F$7:$M$7,CK$7) | CL93: =+SUMIFS($F93:$M93,$F$7:$M$7,CL$7) | CM93: =+SUMIFS($F93:$M93,$F$7:$M$7,CM$7) | CN93: =+SUMIFS($F93:$M93,$F$7:$M$7,CN$7) | CO93: =+SUMIFS($F93:$M93,$F$7:$M$7,CO$7) | CP93: =+SUMIFS($F93:$M93,$F$7:$M$7,CP$7) | ... DR93: =+SUMIFS($F93:$M93,$F$7:$M$7,DR$7)
B94: Total | F94: =+SUMIFS($AA94:$DR94,$AA$7:$DR$7,F$7) | G94: =+SUMIFS($AA94:$DR94,$AA$7:$DR$7,G$7) | H94: =+SUMIFS($AA94:$DR94,$AA$7:$DR$7,H$7) | I94: =+SUMIFS($AA94:$DR94,$AA$7:$DR$7,I$7) | J94: =+SUMIFS($AA94:$DR94,$AA$7:$DR$7,J$7) | K94: =+K92*K93 | L94: =+L92*L93 | M94: =+M92*M93 | AA94: 88.70992 | AB94: 87.72414 | AC94: 90.07706 | AD94: 88.95716 | AE94: 114.49684 | AF94: 111.20754 | AG94: 101.92651 | AH94: 76.08853 | AI94: 84.88898 | AJ94: 97.77277 | AK94: 90.02633 | AL94: 76.15685 | AM94: 91.7527 | AN94: 90.39665 | AO94: 97.35521 | AP94: 103.91077 | AQ94: 112.22462 | AR94: 123.16744 | AS94: 109.41586 | AT94: 109.96173 | AU94: 121.57349 | AV94: 128.09661 | AW94: 129.77107 | AX94: 129.00786 | AY94: 144.33116 | AZ94: 141.57008 | BA94: 170.55899 | BB94: 146.48361 | BC94: 125.10361 | BD94: 136.09896 | BE94: 135.17979 | BF94: 129.8899 | BG94: 132.2477 | BH94: 132.68108 | BI94: 127.71285 | BJ94: 131.26869 | BK94: 121.502 | BL94: 136.446 | BM94: 128.90282 | BN94: 129.50282 | BO94: 129.60282 | BP94: 130.20282 | BQ94: 134.30282 | BR94: 134.90282 | BS94: 135.00282 | BT94: 135.60282 | BU94: 135.70282 | BV94: 136.30282 | BW94: 144.63462 | BX94: 144.63462 | BY94: 144.63462 | BZ94: 144.63462 | CA94: 144.63462 | CB94: 144.63462 | CC94: 144.63462 | CD94: 144.63462 | CE94: 144.63462 | CF94: 144.63462 | CG94: 144.63462 | CH94: 144.63462 | CI94: =+CI92*CI93 | CJ94: =+CJ92*CJ93 | CK94: =+CK92*CK93 | CL94: =+CL92*CL93 | CM94: =+CM92*CM93 | CN94: =+CN92*CN93 | CO94: =+CO92*CO93 | CP94: =+CP92*CP93 | ... DR94: =+DR92*DR93
B96: Service Costs
B97: Revenue | F97: =+SUMIFS($AA97:$DR97,$AA$7:$DR$7,F$7) | G97: =+SUMIFS($AA97:$DR97,$AA$7:$DR$7,G$7) | H97: =+SUMIFS($AA97:$DR97,$AA$7:$DR$7,H$7) | I97: =+SUMIFS($AA97:$DR97,$AA$7:$DR$7,I$7) | J97: =+SUMIFS($AA97:$DR97,$AA$7:$DR$7,J$7) | K97: =+SUMIFS($AA97:$DR97,$AA$7:$DR$7,K$7) | L97: =+SUMIFS($AA97:$DR97,$AA$7:$DR$7,L$7) | M97: =+SUMIFS($AA97:$DR97,$AA$7:$DR$7,M$7) | AA97: =+Revenue_Calcs!AA122 | AB97: =+Revenue_Calcs!AB122 | AC97: =+Revenue_Calcs!AC122 | AD97: =+Revenue_Calcs!AD122 | AE97: =+Revenue_Calcs!AE122 | AF97: =+Revenue_Calcs!AF122 | AG97: =+Revenue_Calcs!AG122 | AH97: =+Revenue_Calcs!AH122 | ... DR97: =+Revenue_Calcs!DR122
B98: % of Revenue | F98: =+F99/F97 | G98: =+G99/G97 | H98: =+H99/H97 | I98: =+I99/I97 | J98: =+J99/J97 | K98: =+COGS_Assumptions!K19 | L98: =+COGS_Assumptions!L19 | M98: =+COGS_Assumptions!M19 | AA98: =+AA99/AA97 | AB98: =+AB99/AB97 | AC98: =+AC99/AC97 | AD98: =+AD99/AD97 | AE98: =+AE99/AE97 | AF98: =+AF99/AF97 | AG98: =+AG99/AG97 | AH98: =+AH99/AH97 | ... CH98: =+CH99/CH97 | CI98: =+SUMIFS($F98:$M98,$F$7:$M$7,CI$7) | CJ98: =+SUMIFS($F98:$M98,$F$7:$M$7,CJ$7) | CK98: =+SUMIFS($F98:$M98,$F$7:$M$7,CK$7) | CL98: =+SUMIFS($F98:$M98,$F$7:$M$7,CL$7) | CM98: =+SUMIFS($F98:$M98,$F$7:$M$7,CM$7) | CN98: =+SUMIFS($F98:$M98,$F$7:$M$7,CN$7) | CO98: =+SUMIFS($F98:$M98,$F$7:$M$7,CO$7) | CP98: =+SUMIFS($F98:$M98,$F$7:$M$7,CP$7) | ... DR98: =+SUMIFS($F98:$M98,$F$7:$M$7,DR$7)
B99: Total | F99: =+SUMIFS($AA99:$DR99,$AA$7:$DR$7,F$7) | G99: =+SUMIFS($AA99:$DR99,$AA$7:$DR$7,G$7) | H99: =+SUMIFS($AA99:$DR99,$AA$7:$DR$7,H$7) | I99: =+SUMIFS($AA99:$DR99,$AA$7:$DR$7,I$7) | J99: =+SUMIFS($AA99:$DR99,$AA$7:$DR$7,J$7) | K99: =+K97*K98 | L99: =+L97*L98 | M99: =+M97*M98 | AA99: 23.93761 | AB99: 24.58358 | AC99: 21.92623 | AD99: 23.19564 | AE99: 23.61772 | AF99: 23.70361 | AG99: 24.80772 | AH99: 25.82815 | AI99: 23.9233 | AJ99: 25.97929 | AK99: 24.67334 | AL99: 27.86694 | AM99: 25.68089 | AN99: 20.18636 | AO99: 24.32559 | AP99: 22.75321 | AQ99: 45.13158 | AR99: 28.1452 | AS99: 28.88154 | AT99: 30.13597 | AU99: 27.38623 | AV99: 27.86027 | AW99: 30.01027 | AX99: 29.7986 | AY99: 31.60522 | AZ99: 28.26161 | BA99: 25.51025 | BB99: 27.86866 | BC99: 29.06649 | BD99: 28.86649 | BE99: 24.19523 | BF99: 23.18666 | BG99: 23.22283 | BH99: 23.11997 | BI99: 24.46994 | BJ99: 25.32478 | BK99: 25.944 | BL99: 25.482 | BM99: 26.405593 | BN99: 26.605593 | BO99: 30.97226 | BP99: 31.17226 | BQ99: 31.17226 | BR99: 31.17226 | BS99: 31.17226 | BT99: 31.37226 | BU99: 31.37226 | BV99: 31.37226 | BW99: 32 | BX99: 32 | BY99: 32 | BZ99: 32 | CA99: 32 | CB99: 32 | CC99: 32 | CD99: 32 | CE99: 32 | CF99: 32 | CG99: 32 | CH99: 32 | CI99: =+CI97*CI98 | CJ99: =+CJ97*CJ98 | CK99: =+CK97*CK98 | CL99: =+CL97*CL98 | CM99: =+CM97*CM98 | CN99: =+CN97*CN98 | CO99: =+CO97*CO98 | CP99: =+CP97*CP98 | ... DR99: =+DR97*DR98
B101: Contractors
B102: Revenue | F102: =+SUMIFS($AA102:$DR102,$AA$7:$DR$7,F$7) | G102: =+SUMIFS($AA102:$DR102,$AA$7:$DR$7,G$7) | H102: =+SUMIFS($AA102:$DR102,$AA$7:$DR$7,H$7) | I102: =+SUMIFS($AA102:$DR102,$AA$7:$DR$7,I$7) | J102: =+SUMIFS($AA102:$DR102,$AA$7:$DR$7,J$7) | K102: =+SUMIFS($AA102:$DR102,$AA$7:$DR$7,K$7) | L102: =+SUMIFS($AA102:$DR102,$AA$7:$DR$7,L$7) | M102: =+SUMIFS($AA102:$DR102,$AA$7:$DR$7,M$7) | AA102: =+Revenue_Calcs!AA122 | AB102: =+Revenue_Calcs!AB122 | AC102: =+Revenue_Calcs!AC122 | AD102: =+Revenue_Calcs!AD122 | AE102: =+Revenue_Calcs!AE122 | AF102: =+Revenue_Calcs!AF122 | AG102: =+Revenue_Calcs!AG122 | AH102: =+Revenue_Calcs!AH122 | ... DR102: =+Revenue_Calcs!DR122
B103: % of Revenue | F103: =+F104/F102 | G103: =+G104/G102 | H103: =+H104/H102 | I103: =+I104/I102 | J103: =+J104/J102 | K103: =+COGS_Assumptions!K20 | L103: =+COGS_Assumptions!L20 | M103: =+COGS_Assumptions!M20 | AA103: =+AA104/AA102 | AB103: =+AB104/AB102 | AC103: =+AC104/AC102 | AD103: =+AD104/AD102 | AE103: =+AE104/AE102 | AF103: =+AF104/AF102 | AG103: =+AG104/AG102 | AH103: =+AH104/AH102 | ... BV103: =+BV104/BV102 | BW103: =+SUMIFS($F103:$M103,$F$7:$M$7,BW$7) | BX103: =+SUMIFS($F103:$M103,$F$7:$M$7,BX$7) | BY103: =+SUMIFS($F103:$M103,$F$7:$M$7,BY$7) | BZ103: =+SUMIFS($F103:$M103,$F$7:$M$7,BZ$7) | CA103: =+SUMIFS($F103:$M103,$F$7:$M$7,CA$7) | CB103: =+SUMIFS($F103:$M103,$F$7:$M$7,CB$7) | CC103: =+SUMIFS($F103:$M103,$F$7:$M$7,CC$7) | CD103: =+SUMIFS($F103:$M103,$F$7:$M$7,CD$7) | ... DR103: =+SUMIFS($F103:$M103,$F$7:$M$7,DR$7)
B104: Total | F104: =+SUMIFS($AA104:$DR104,$AA$7:$DR$7,F$7) | G104: =+SUMIFS($AA104:$DR104,$AA$7:$DR$7,G$7) | H104: =+SUMIFS($AA104:$DR104,$AA$7:$DR$7,H$7) | I104: =+SUMIFS($AA104:$DR104,$AA$7:$DR$7,I$7) | J104: =+SUMIFS($AA104:$DR104,$AA$7:$DR$7,J$7) | K104: =+SUMIFS($AA104:$DR104,$AA$7:$DR$7,K$7) | L104: =+SUMIFS($AA104:$DR104,$AA$7:$DR$7,L$7) | M104: =+SUMIFS($AA104:$DR104,$AA$7:$DR$7,M$7) | AA104: 0 | AB104: 0 | AC104: 0 | AD104: 0 | AE104: 7 | AF104: 7 | AG104: 14 | AH104: 7 | AI104: -14 | AJ104: 10 | AK104: 10 | AL104: 10 | AM104: 10 | AN104: 10 | AO104: 10 | AP104: 10 | AQ104: 10 | AR104: 10 | AS104: 7.09722 | AT104: 0 | AU104: 0 | AV104: 0 | AW104: 0 | AX104: 0 | AY104: 0 | AZ104: 0 | BA104: 0 | BB104: 0 | BC104: 0 | BD104: 0 | BE104: 0 | BF104: 0 | BG104: 0 | BH104: 0 | BI104: 0 | BJ104: 0 | BK104: 0 | BL104: 0 | BM104: 0 | BN104: 0 | BO104: 0 | BP104: 0 | BQ104: 0 | BR104: 0 | BS104: 0 | BT104: 0 | BU104: 0 | BV104: 0 | BW104: 0 | BX104: 0 | BY104: 0 | BZ104: 0 | CA104: 0 | CB104: 0 | CC104: 0 | CD104: 0 | CE104: 0 | CF104: 0 | CG104: 0 | CH104: 0 | CI104: =+CI102*CI103 | CJ104: =+CJ102*CJ103 | CK104: =+CK102*CK103 | CL104: =+CL102*CL103 | CM104: =+CM102*CM103 | CN104: =+CN102*CN103 | CO104: =+CO102*CO103 | CP104: =+CP102*CP103 | ... DR104: =+DR102*DR103
B107: Total Licensing | F107: =+SUMIFS($AA107:$DR107,$AA$7:$DR$7,F$7) | G107: =+SUMIFS($AA107:$DR107,$AA$7:$DR$7,G$7) | H107: =+SUMIFS($AA107:$DR107,$AA$7:$DR$7,H$7) | I107: =+SUMIFS($AA107:$DR107,$AA$7:$DR$7,I$7) | J107: =+SUMIFS($AA107:$DR107,$AA$7:$DR$7,J$7) | K107: =+SUMIFS($AA107:$DR107,$AA$7:$DR$7,K$7) | L107: =+SUMIFS($AA107:$DR107,$AA$7:$DR$7,L$7) | M107: =+SUMIFS($AA107:$DR107,$AA$7:$DR$7,M$7) | AA107: =+SUM(AA74,AA94,AA99,AA104) | AB107: =+SUM(AB74,AB94,AB99,AB104) | AC107: =+SUM(AC74,AC94,AC99,AC104) | AD107: =+SUM(AD74,AD94,AD99,AD104) | AE107: =+SUM(AE74,AE94,AE99,AE104) | AF107: =+SUM(AF74,AF94,AF99,AF104) | AG107: =+SUM(AG74,AG94,AG99,AG104) | AH107: =+SUM(AH74,AH94,AH99,AH104) | ... DR107: =+SUM(DR74,DR94,DR99,DR104)
B108: % Margin | F108: =+(1-F107/F67) | G108: =+(1-G107/G67) | H108: =+(1-H107/H67) | I108: =+(1-I107/I67) | J108: =+(1-J107/J67) | K108: =+(1-K107/K67) | L108: =+(1-L107/L67) | M108: =+(1-M107/M67)
B110: Managed Services
B112: AACN | C112: Lower Middle Market | F112: =+SUMIFS($AA112:$DR112,$AA$7:$DR$7,F$7) | G112: =+SUMIFS($AA112:$DR112,$AA$7:$DR$7,G$7) | H112: =+SUMIFS($AA112:$DR112,$AA$7:$DR$7,H$7) | I112: =+SUMIFS($AA112:$DR112,$AA$7:$DR$7,I$7) | J112: =+SUMIFS($AA112:$DR112,$AA$7:$DR$7,J$7) | K112: =+SUMIFS($AA112:$DR112,$AA$7:$DR$7,K$7) | L112: =+SUMIFS($AA112:$DR112,$AA$7:$DR$7,L$7) | M112: =+SUMIFS($AA112:$DR112,$AA$7:$DR$7,M$7) | AA112: 0 | AB112: 0 | AC112: 0 | AD112: 0 | AE112: 0 | AF112: 0 | AG112: 0 | AH112: 0 | AI112: 0 | AJ112: 0 | AK112: 0 | AL112: 0 | AM112: 0.012729062 | AN112: 0.095424124 | AO112: 0.1476754 | AP112: 0.018087962 | AQ112: 0.1458276 | AR112: 0.22633237 | AS112: 0.22877023 | AT112: 0.25712868 | AU112: 0.61317959 | AV112: 1.4581957 | AW112: 0.36993187 | AX112: 0.21694388 | AY112: 0.80696372 | AZ112: 0.34862536 | BA112: 0.22033331 | BB112: 0.31619262 | BC112: 0.21102277 | BD112: 0 | BE112: 0.7226352 | BF112: 0.54698455 | BG112: 0.18359029 | BH112: 0.085979898 | BI112: 0 | BJ112: 0.025312296
B113: AACR | C113: Lower Middle Market | F113: =+SUMIFS($AA113:$DR113,$AA$7:$DR$7,F$7) | G113: =+SUMIFS($AA113:$DR113,$AA$7:$DR$7,G$7) | H113: =+SUMIFS($AA113:$DR113,$AA$7:$DR$7,H$7) | I113: =+SUMIFS($AA113:$DR113,$AA$7:$DR$7,I$7) | J113: =+SUMIFS($AA113:$DR113,$AA$7:$DR$7,J$7) | K113: =+SUMIFS($AA113:$DR113,$AA$7:$DR$7,K$7) | L113: =+SUMIFS($AA113:$DR113,$AA$7:$DR$7,L$7) | M113: =+SUMIFS($AA113:$DR113,$AA$7:$DR$7,M$7) | AA113: 0 | AB113: 0 | AC113: 0 | AD113: 0 | AE113: 0 | AF113: 0 | AG113: 0 | AH113: 0 | AI113: 0 | AJ113: 0 | AK113: 0 | AL113: 0 | AM113: 0 | AN113: 0 | AO113: 0 | AP113: 0 | AQ113: 0 | AR113: 0 | AS113: 0 | AT113: 0 | AU113: 0 | AV113: 0 | AW113: 0 | AX113: 0 | AY113: 0 | AZ113: 0 | BA113: 0 | BB113: 0 | BC113: 0.21435827 | BD113: 2.7435031 | BE113: 1.319769 | BF113: 0.4274196 | BG113: 1.0284312 | BH113: 4.9506385 | BI113: 2.4571836 | BJ113: 1.522794
B114: AAI | C114: Lower Middle Market | F114: =+SUMIFS($AA114:$DR114,$AA$7:$DR$7,F$7) | G114: =+SUMIFS($AA114:$DR114,$AA$7:$DR$7,G$7) | H114: =+SUMIFS($AA114:$DR114,$AA$7:$DR$7,H$7) | I114: =+SUMIFS($AA114:$DR114,$AA$7:$DR$7,I$7) | J114: =+SUMIFS($AA114:$DR114,$AA$7:$DR$7,J$7) | K114: =+SUMIFS($AA114:$DR114,$AA$7:$DR$7,K$7) | L114: =+SUMIFS($AA114:$DR114,$AA$7:$DR$7,L$7) | M114: =+SUMIFS($AA114:$DR114,$AA$7:$DR$7,M$7) | AA114: 0 | AB114: 0 | AC114: 0 | AD114: 0 | AE114: 0 | AF114: 0 | AG114: 0 | AH114: 0 | AI114: 0 | AJ114: 0 | AK114: 0 | AL114: 0 | AM114: 0 | AN114: 0 | AO114: 0 | AP114: 0 | AQ114: 0 | AR114: 0 | AS114: 0 | AT114: 0 | AU114: 0 | AV114: 0 | AW114: 0 | AX114: 0 | AY114: 0 | AZ114: 0 | BA114: 0 | BB114: 0 | BC114: 0 | BD114: 0 | BE114: 0 | BF114: 0 | BG114: 0 | BH114: 0 | BI114: 0 | BJ114: 0
B115: AAOS | C115: Upper Middle Market | F115: =+SUMIFS($AA115:$DR115,$AA$7:$DR$7,F$7) | G115: =+SUMIFS($AA115:$DR115,$AA$7:$DR$7,G$7) | H115: =+SUMIFS($AA115:$DR115,$AA$7:$DR$7,H$7) | I115: =+SUMIFS($AA115:$DR115,$AA$7:$DR$7,I$7) | J115: =+SUMIFS($AA115:$DR115,$AA$7:$DR$7,J$7) | K115: =+SUMIFS($AA115:$DR115,$AA$7:$DR$7,K$7) | L115: =+SUMIFS($AA115:$DR115,$AA$7:$DR$7,L$7) | M115: =+SUMIFS($AA115:$DR115,$AA$7:$DR$7,M$7) | AA115: 0 | AB115: 0 | AC115: 0 | AD115: 0 | AE115: 0 | AF115: 0 | AG115: 0 | AH115: 0 | AI115: 0 | AJ115: 0 | AK115: 0 | AL115: 0 | AM115: 0 | AN115: 0 | AO115: 0 | AP115: 0 | AQ115: 0 | AR115: 1.7020765 | AS115: 2.2836896 | AT115: 0.20820407 | AU115: 2.8449667 | AV115: 2.3278208 | AW115: 4.1185862 | AX115: 3.2739992 | AY115: 4.7828582 | AZ115: 8.6895405 | BA115: 17.990669 | BB115: 21.826223 | BC115: 19.295887 | BD115: 5.0936977 | BE115: 5.2568358 | BF115: 2.7182292 | BG115: 4.1056527 | BH115: 6.5089055 | BI115: 1.5068321 | BJ115: 0.78186344
B116: AAP | C116: Major | F116: =+SUMIFS($AA116:$DR116,$AA$7:$DR$7,F$7) | G116: =+SUMIFS($AA116:$DR116,$AA$7:$DR$7,G$7) | H116: =+SUMIFS($AA116:$DR116,$AA$7:$DR$7,H$7) | I116: =+SUMIFS($AA116:$DR116,$AA$7:$DR$7,I$7) | J116: =+SUMIFS($AA116:$DR116,$AA$7:$DR$7,J$7) | K116: =+SUMIFS($AA116:$DR116,$AA$7:$DR$7,K$7) | L116: =+SUMIFS($AA116:$DR116,$AA$7:$DR$7,L$7) | M116: =+SUMIFS($AA116:$DR116,$AA$7:$DR$7,M$7) | AA116: 1.1918211 | AB116: 0.83510719 | AC116: 1.8023812 | AD116: 2.7463138 | AE116: 2.3189027 | AF116: 8.9771312 | AG116: 16.15963 | AH116: 16.317084 | AI116: 7.4706613 | AJ116: 4.3434424 | AK116: 2.5155419 | AL116: 3.0994706 | AM116: 4.3071865 | AN116: 5.2836062 | AO116: 4.9287659 | AP116: 4.7642042 | AQ116: 5.0457579 | AR116: 2.014378 | AS116: 2.5076862 | AT116: 1.1682456 | AU116: 1.164192 | AV116: 1.9975453 | AW116: 0.24925302 | AX116: 0.012303971 | AY116: 0 | AZ116: 1.686913 | BA116: 2.0995871 | BB116: 6.1174083 | BC116: 8.4891212 | BD116: 9.6825424 | BE116: 27.816174 | BF116: 18.496495 | BG116: 27.004726 | BH116: 19.876831 | BI116: 8.8438454 | BJ116: 1.9344083
B117: ADA | C117: Lower Middle Market | F117: =+SUMIFS($AA117:$DR117,$AA$7:$DR$7,F$7) | G117: =+SUMIFS($AA117:$DR117,$AA$7:$DR$7,G$7) | H117: =+SUMIFS($AA117:$DR117,$AA$7:$DR$7,H$7) | I117: =+SUMIFS($AA117:$DR117,$AA$7:$DR$7,I$7) | J117: =+SUMIFS($AA117:$DR117,$AA$7:$DR$7,J$7) | K117: =+SUMIFS($AA117:$DR117,$AA$7:$DR$7,K$7) | L117: =+SUMIFS($AA117:$DR117,$AA$7:$DR$7,L$7) | M117: =+SUMIFS($AA117:$DR117,$AA$7:$DR$7,M$7) | AA117: 0 | AB117: 0 | AC117: 0 | AD117: 0 | AE117: 0 | AF117: 0 | AG117: 0 | AH117: 0 | AI117: 0 | AJ117: 0 | AK117: 0 | AL117: 0 | AM117: 0 | AN117: 0 | AO117: 0 | AP117: 0 | AQ117: 0 | AR117: 0 | AS117: 0 | AT117: 0 | AU117: 0 | AV117: 0 | AW117: 0 | AX117: 0 | AY117: 0 | AZ117: 0 | BA117: 0 | BB117: 0 | BC117: 0 | BD117: 0 | BE117: 0.12747527 | BF117: 1.789368 | BG117: 3.2221716 | BH117: 1.5673334 | BI117: 1.9148897 | BJ117: 0.29798457
B118: AHRQ | C118: Lower Middle Market | F118: =+SUMIFS($AA118:$DR118,$AA$7:$DR$7,F$7) | G118: =+SUMIFS($AA118:$DR118,$AA$7:$DR$7,G$7) | H118: =+SUMIFS($AA118:$DR118,$AA$7:$DR$7,H$7) | I118: =+SUMIFS($AA118:$DR118,$AA$7:$DR$7,I$7) | J118: =+SUMIFS($AA118:$DR118,$AA$7:$DR$7,J$7) | K118: =+SUMIFS($AA118:$DR118,$AA$7:$DR$7,K$7) | L118: =+SUMIFS($AA118:$DR118,$AA$7:$DR$7,L$7) | M118: =+SUMIFS($AA118:$DR118,$AA$7:$DR$7,M$7) | AA118: 0 | AB118: 0 | AC118: 0 | AD118: 0 | AE118: 0 | AF118: 0 | AG118: 0 | AH118: 0 | AI118: 0 | AJ118: 0 | AK118: 0 | AL118: 0 | AM118: 0 | AN118: 0 | AO118: 0 | AP118: 0 | AQ118: 0 | AR118: 0 | AS118: 0 | AT118: 0 | AU118: 0 | AV118: 0 | AW118: 0 | AX118: 0 | AY118: 0 | AZ118: 0 | BA118: 0 | BB118: 0 | BC118: 0 | BD118: 0 | BE118: 0 | BF118: 0 | BG118: 0 | BH118: 0 | BI118: 0 | BJ118: 0
B119: AIPP | C119: Major | F119: =+SUMIFS($AA119:$DR119,$AA$7:$DR$7,F$7) | G119: =+SUMIFS($AA119:$DR119,$AA$7:$DR$7,G$7) | H119: =+SUMIFS($AA119:$DR119,$AA$7:$DR$7,H$7) | I119: =+SUMIFS($AA119:$DR119,$AA$7:$DR$7,I$7) | J119: =+SUMIFS($AA119:$DR119,$AA$7:$DR$7,J$7) | K119: =+SUMIFS($AA119:$DR119,$AA$7:$DR$7,K$7) | L119: =+SUMIFS($AA119:$DR119,$AA$7:$DR$7,L$7) | M119: =+SUMIFS($AA119:$DR119,$AA$7:$DR$7,M$7) | AA119: 0 | AB119: 0 | AC119: 0 | AD119: 0 | AE119: 0 | AF119: 0 | AG119: 0 | AH119: 0 | AI119: 0 | AJ119: 0 | AK119: 0 | AL119: 0 | AM119: 0 | AN119: 0 | AO119: 0 | AP119: 0 | AQ119: 0 | AR119: 0 | AS119: 0 | AT119: 0 | AU119: 0 | AV119: 0 | AW119: 0 | AX119: 0 | AY119: 0 | AZ119: 0 | BA119: 0 | BB119: 0 | BC119: 0 | BD119: 0 | BE119: 0 | BF119: 0 | BG119: 0 | BH119: 0 | BI119: 0 | BJ119: 0
B120: ALLEN | C120: Upper Middle Market | F120: =+SUMIFS($AA120:$DR120,$AA$7:$DR$7,F$7) | G120: =+SUMIFS($AA120:$DR120,$AA$7:$DR$7,G$7) | H120: =+SUMIFS($AA120:$DR120,$AA$7:$DR$7,H$7) | I120: =+SUMIFS($AA120:$DR120,$AA$7:$DR$7,I$7) | J120: =+SUMIFS($AA120:$DR120,$AA$7:$DR$7,J$7) | K120: =+SUMIFS($AA120:$DR120,$AA$7:$DR$7,K$7) | L120: =+SUMIFS($AA120:$DR120,$AA$7:$DR$7,L$7) | M120: =+SUMIFS($AA120:$DR120,$AA$7:$DR$7,M$7) | AA120: 0 | AB120: 0 | AC120: 0 | AD120: 0 | AE120: 0 | AF120: 0 | AG120: 0 | AH120: 0 | AI120: 0 | AJ120: 0 | AK120: 0 | AL120: 0 | AM120: 0 | AN120: 0 | AO120: 0 | AP120: 0 | AQ120: 0.071556116 | AR120: 1.2392102 | AS120: 2.1017242 | AT120: 5.2720974 | AU120: 1.0006851 | AV120: 1.0229593 | AW120: 0.21907054 | AX120: 0.38322045 | AY120: 0.3067692 | AZ120: 3.7381287 | BA120: 3.42294 | BB120: 1.4068406 | BC120: 0.68920293 | BD120: 3.6546109 | BE120: 3.0856868 | BF120: 1.4939537 | BG120: 2.5653028 | BH120: 1.2392553 | BI120: 1.4867843 | BJ120: 0.1884191
B121: AMA | C121: Mega | F121: =+SUMIFS($AA121:$DR121,$AA$7:$DR$7,F$7) | G121: =+SUMIFS($AA121:$DR121,$AA$7:$DR$7,G$7) | H121: =+SUMIFS($AA121:$DR121,$AA$7:$DR$7,H$7) | I121: =+SUMIFS($AA121:$DR121,$AA$7:$DR$7,I$7) | J121: =+SUMIFS($AA121:$DR121,$AA$7:$DR$7,J$7) | K121: =+SUMIFS($AA121:$DR121,$AA$7:$DR$7,K$7) | L121: =+SUMIFS($AA121:$DR121,$AA$7:$DR$7,L$7) | M121: =+SUMIFS($AA121:$DR121,$AA$7:$DR$7,M$7) | AA121: 50.413887 | AB121: 47.177468 | AC121: 62.374997 | AD121: 41.45573 | AE121: 43.898594 | AF121: 55.959199 | AG121: 43.845768 | AH121: 65.349334 | AI121: 72.341042 | AJ121: 66.717865 | AK121: 56.129503 | AL121: 43.08235 | AM121: 54.042708 | AN121: 34.884647 | AO121: 45.706344 | AP121: 34.153453 | AQ121: 34.963656 | AR121: 44.6746 | AS121: 56.129025 | AT121: 60.112826 | AU121: 64.622768 | AV121: 53.547327 | AW121: 40.429141 | AX121: 49.498776 | AY121: 43.646784 | AZ121: 44.090911 | BA121: 48.780135 | BB121: 54.620231 | BC121: 43.158431 | BD121: 50.78702 | BE121: 45.224269 | BF121: 43.653205 | BG121: 41.779949 | BH121: 41.074099 | BI121: 30.811059 | BJ121: 30.702432
B122: AORN | C122: Lower Middle Market | F122: =+SUMIFS($AA122:$DR122,$AA$7:$DR$7,F$7) | G122: =+SUMIFS($AA122:$DR122,$AA$7:$DR$7,G$7) | H122: =+SUMIFS($AA122:$DR122,$AA$7:$DR$7,H$7) | I122: =+SUMIFS($AA122:$DR122,$AA$7:$DR$7,I$7) | J122: =+SUMIFS($AA122:$DR122,$AA$7:$DR$7,J$7) | K122: =+SUMIFS($AA122:$DR122,$AA$7:$DR$7,K$7) | L122: =+SUMIFS($AA122:$DR122,$AA$7:$DR$7,L$7) | M122: =+SUMIFS($AA122:$DR122,$AA$7:$DR$7,M$7) | AA122: 2.4210339 | AB122: 1.4392522 | AC122: 0.60997633 | AD122: 0.11071072 | AE122: 0.16808072 | AF122: 0.52745568 | AG122: 0.28261958 | AH122: 0.17026398 | AI122: 1.8193048 | AJ122: 2.6339544 | AK122: 6.1033894 | AL122: 0.62741847 | AM122: 1.3404918 | AN122: 4.330792 | AO122: 5.4941127 | AP122: 6.2403484 | AQ122: 5.5780854 | AR122: 5.0201914 | AS122: 0.24327434 | AT122: 0.21374167 | AU122: 0.13796338 | AV122: 0.79970261 | AW122: 1.3497291 | AX122: 1.0712614 | AY122: 1.4282088 | AZ122: 2.2554134 | BA122: 4.9828545 | BB122: 7.6199812 | BC122: 3.1591084 | BD122: 2.154971 | BE122: 1.7072004 | BF122: 1.4455836 | BG122: 1.5084768 | BH122: 0.77033903 | BI122: 1.407736 | BJ122: 1.9559754
B123: AOTA | C123: Lower Middle Market | F123: =+SUMIFS($AA123:$DR123,$AA$7:$DR$7,F$7) | G123: =+SUMIFS($AA123:$DR123,$AA$7:$DR$7,G$7) | H123: =+SUMIFS($AA123:$DR123,$AA$7:$DR$7,H$7) | I123: =+SUMIFS($AA123:$DR123,$AA$7:$DR$7,I$7) | J123: =+SUMIFS($AA123:$DR123,$AA$7:$DR$7,J$7) | K123: =+SUMIFS($AA123:$DR123,$AA$7:$DR$7,K$7) | L123: =+SUMIFS($AA123:$DR123,$AA$7:$DR$7,L$7) | M123: =+SUMIFS($AA123:$DR123,$AA$7:$DR$7,M$7) | AA123: 0 | AB123: 0 | AC123: 0 | AD123: 0.18696047 | AE123: 0.1772888 | AF123: 0.070552713 | AG123: 0.46448089 | AH123: 1.2376262 | AI123: 2.4234727 | AJ123: 6.5008102 | AK123: 1.8925028 | AL123: 0.94257788 | AM123: 0.1375255 | AN123: 1.2815212 | AO123: 2.4718678 | AP123: 0.029888199 | AQ123: 0 | AR123: 0 | AS123: 0 | AT123: 0.14465385 | AU123: 0 | AV123: 0 | AW123: 0 | AX123: 0 | AY123: 0 | AZ123: 0.12464796 | BA123: 0.061779385 | BB123: 0.18887373 | BC123: 0.22245724 | BD123: 0 | BE123: 0 | BF123: 0 | BG123: 0.012338365 | BH123: 0 | BI123: 0 | BJ123: 0
... B157: EL | C157: Lower Middle Market | F157: =+SUMIFS($AA157:$DR157,$AA$7:$DR$7,F$7) | G157: =+SUMIFS($AA157:$DR157,$AA$7:$DR$7,G$7) | H157: =+SUMIFS($AA157:$DR157,$AA$7:$DR$7,H$7) | I157: =+SUMIFS($AA157:$DR157,$AA$7:$DR$7,I$7) | J157: =+SUMIFS($AA157:$DR157,$AA$7:$DR$7,J$7) | K157: =+SUMIFS($AA157:$DR157,$AA$7:$DR$7,K$7) | L157: =+SUMIFS($AA157:$DR157,$AA$7:$DR$7,L$7) | M157: =+SUMIFS($AA157:$DR157,$AA$7:$DR$7,M$7) | AA157: 0 | AB157: 0 | AC157: 0 | AD157: 0 | AE157: 0 | AF157: 0 | AG157: 0 | AH157: 0 | AI157: 0 | AJ157: 0 | AK157: 0 | AL157: 0 | AM157: 0 | AN157: 0 | AO157: 0 | AP157: 0 | AQ157: 0 | AR157: 0 | AS157: 0 | AT157: 0 | AU157: 0 | AV157: 0 | AW157: 0 | AX157: 0 | AY157: 0 | AZ157: 0 | BA157: 0 | BB157: 0 | BC157: 0 | BD157: 0 | BE157: 0 | BF157: 0 | BG157: 0 | BH157: 0 | BI157: 0 | BJ157: 0
B159: Total | F159: =+SUMIFS($AA159:$DR159,$AA$7:$DR$7,F$7) | G159: =+SUMIFS($AA159:$DR159,$AA$7:$DR$7,G$7) | H159: =+SUMIFS($AA159:$DR159,$AA$7:$DR$7,H$7) | I159: =+SUMIFS($AA159:$DR159,$AA$7:$DR$7,I$7) | J159: =+SUMIFS($AA159:$DR159,$AA$7:$DR$7,J$7) | K159: =+SUMIFS($AA159:$DR159,$AA$7:$DR$7,K$7) | L159: =+SUMIFS($AA159:$DR159,$AA$7:$DR$7,L$7) | M159: =+SUMIFS($AA159:$DR159,$AA$7:$DR$7,M$7) | AA159: =SUM(AA112:AA158) | AB159: =SUM(AB112:AB158) | AC159: =SUM(AC112:AC158) | AD159: =SUM(AD112:AD158) | AE159: =SUM(AE112:AE158) | AF159: =SUM(AF112:AF158) | AG159: =SUM(AG112:AG158) | AH159: =SUM(AH112:AH158) | ... DR159: =SUM(DR112:DR158)
B161: Revenue
B162: Mega | F162: =+Revenue_Calcs!F192 | G162: =+Revenue_Calcs!G192 | H162: =+Revenue_Calcs!H192 | I162: =+Revenue_Calcs!I192 | J162: =+Revenue_Calcs!J192 | K162: =+Revenue_Calcs!K192 | L162: =+Revenue_Calcs!L192 | M162: =+Revenue_Calcs!M192
B163: Major | F163: =+Revenue_Calcs!F197 | G163: =+Revenue_Calcs!G197 | H163: =+Revenue_Calcs!H197 | I163: =+Revenue_Calcs!I197 | J163: =+Revenue_Calcs!J197 | K163: =+Revenue_Calcs!K197 | L163: =+Revenue_Calcs!L197 | M163: =+Revenue_Calcs!M197
B164: Upper Middle Market | F164: =+Revenue_Calcs!F202 | G164: =+Revenue_Calcs!G202 | H164: =+Revenue_Calcs!H202 | I164: =+Revenue_Calcs!I202 | J164: =+Revenue_Calcs!J202 | K164: =+Revenue_Calcs!K202 | L164: =+Revenue_Calcs!L202 | M164: =+Revenue_Calcs!M202
B165: Lower Middle Market | F165: =+Revenue_Calcs!F207 | G165: =+Revenue_Calcs!G207 | H165: =+Revenue_Calcs!H207 | I165: =+Revenue_Calcs!I207 | J165: =+Revenue_Calcs!J207 | K165: =+Revenue_Calcs!K207 | L165: =+Revenue_Calcs!L207 | M165: =+Revenue_Calcs!M207
B166: Total | F166: =SUM(F162:F165) | G166: =SUM(G162:G165) | H166: =SUM(H162:H165) | I166: =SUM(I162:I165) | J166: =SUM(J162:J165) | K166: =SUM(K162:K165) | L166: =SUM(L162:L165) | M166: =SUM(M162:M165)
B168: Cost of Sales
B169: Mega | F169: =+SUMIFS($AA169:$DR169,$AA$7:$DR$7,F$7) | G169: =+SUMIFS($AA169:$DR169,$AA$7:$DR$7,G$7) | H169: =+SUMIFS($AA169:$DR169,$AA$7:$DR$7,H$7) | I169: =+I162*(1-COGS_Assumptions!I24) | J169: =+J162*(1-COGS_Assumptions!J24) | K169: =+K162*(1-COGS_Assumptions!K24) | L169: =+L162*(1-COGS_Assumptions!L24) | M169: =+M162*(1-COGS_Assumptions!M24) | AA169: =+SUMIFS(AA$112:AA$157,$C$13:$C$58,$B169) | AB169: =+SUMIFS(AB$112:AB$157,$C$13:$C$58,$B169) | AC169: =+SUMIFS(AC$112:AC$157,$C$13:$C$58,$B169) | AD169: =+SUMIFS(AD$112:AD$157,$C$13:$C$58,$B169) | AE169: =+SUMIFS(AE$112:AE$157,$C$13:$C$58,$B169) | AF169: =+SUMIFS(AF$112:AF$157,$C$13:$C$58,$B169) | AG169: =+SUMIFS(AG$112:AG$157,$C$13:$C$58,$B169) | AH169: =+SUMIFS(AH$112:AH$157,$C$13:$C$58,$B169) | ... BJ169: =+SUMIFS(BJ$112:BJ$157,$C$13:$C$58,$B169) | BK169: =+SUMIFS($F169:$M169,$F$7:$M$7,BK$7)*BK$175 | BL169: =+SUMIFS($F169:$M169,$F$7:$M$7,BL$7)*BL$175 | BM169: =+SUMIFS($F169:$M169,$F$7:$M$7,BM$7)*BM$175 | BN169: =+SUMIFS($F169:$M169,$F$7:$M$7,BN$7)*BN$175 | BO169: =+SUMIFS($F169:$M169,$F$7:$M$7,BO$7)*BO$175 | BP169: =+SUMIFS($F169:$M169,$F$7:$M$7,BP$7)*BP$175 | BQ169: =+SUMIFS($F169:$M169,$F$7:$M$7,BQ$7)*BQ$175 | BR169: =+SUMIFS($F169:$M169,$F$7:$M$7,BR$7)*BR$175 | ... DR169: =+SUMIFS($F169:$M169,$F$7:$M$7,DR$7)*DR$175
B170: Major | F170: =+SUMIFS($AA170:$DR170,$AA$7:$DR$7,F$7) | G170: =+SUMIFS($AA170:$DR170,$AA$7:$DR$7,G$7) | H170: =+SUMIFS($AA170:$DR170,$AA$7:$DR$7,H$7) | I170: =+I163*(1-COGS_Assumptions!I25) | J170: =+J163*(1-COGS_Assumptions!J25) | K170: =+K163*(1-COGS_Assumptions!K25) | L170: =+L163*(1-COGS_Assumptions!L25) | M170: =+M163*(1-COGS_Assumptions!M25) | AA170: =+SUMIFS(AA$112:AA$157,$C$13:$C$58,$B170) | AB170: =+SUMIFS(AB$112:AB$157,$C$13:$C$58,$B170) | AC170: =+SUMIFS(AC$112:AC$157,$C$13:$C$58,$B170) | AD170: =+SUMIFS(AD$112:AD$157,$C$13:$C$58,$B170) | AE170: =+SUMIFS(AE$112:AE$157,$C$13:$C$58,$B170) | AF170: =+SUMIFS(AF$112:AF$157,$C$13:$C$58,$B170) | AG170: =+SUMIFS(AG$112:AG$157,$C$13:$C$58,$B170) | AH170: =+SUMIFS(AH$112:AH$157,$C$13:$C$58,$B170) | ... BJ170: =+SUMIFS(BJ$112:BJ$157,$C$13:$C$58,$B170) | BK170: =+SUMIFS($F170:$M170,$F$7:$M$7,BK$7)*BK$175 | BL170: =+SUMIFS($F170:$M170,$F$7:$M$7,BL$7)*BL$175 | BM170: =+SUMIFS($F170:$M170,$F$7:$M$7,BM$7)*BM$175 | BN170: =+SUMIFS($F170:$M170,$F$7:$M$7,BN$7)*BN$175 | BO170: =+SUMIFS($F170:$M170,$F$7:$M$7,BO$7)*BO$175 | BP170: =+SUMIFS($F170:$M170,$F$7:$M$7,BP$7)*BP$175 | BQ170: =+SUMIFS($F170:$M170,$F$7:$M$7,BQ$7)*BQ$175 | BR170: =+SUMIFS($F170:$M170,$F$7:$M$7,BR$7)*BR$175 | ... DR170: =+SUMIFS($F170:$M170,$F$7:$M$7,DR$7)*DR$175
B171: Upper Middle Market | F171: =+SUMIFS($AA171:$DR171,$AA$7:$DR$7,F$7) | G171: =+SUMIFS($AA171:$DR171,$AA$7:$DR$7,G$7) | H171: =+SUMIFS($AA171:$DR171,$AA$7:$DR$7,H$7) | I171: =+I164*(1-COGS_Assumptions!I26) | J171: =+J164*(1-COGS_Assumptions!J26) | K171: =+K164*(1-COGS_Assumptions!K26) | L171: =+L164*(1-COGS_Assumptions!L26) | M171: =+M164*(1-COGS_Assumptions!M26) | AA171: =+SUMIFS(AA$112:AA$157,$C$13:$C$58,$B171) | AB171: =+SUMIFS(AB$112:AB$157,$C$13:$C$58,$B171) | AC171: =+SUMIFS(AC$112:AC$157,$C$13:$C$58,$B171) | AD171: =+SUMIFS(AD$112:AD$157,$C$13:$C$58,$B171) | AE171: =+SUMIFS(AE$112:AE$157,$C$13:$C$58,$B171) | AF171: =+SUMIFS(AF$112:AF$157,$C$13:$C$58,$B171) | AG171: =+SUMIFS(AG$112:AG$157,$C$13:$C$58,$B171) | AH171: =+SUMIFS(AH$112:AH$157,$C$13:$C$58,$B171) | ... BJ171: =+SUMIFS(BJ$112:BJ$157,$C$13:$C$58,$B171) | BK171: =+SUMIFS($F171:$M171,$F$7:$M$7,BK$7)*BK$75 | BL171: =+SUMIFS($F171:$M171,$F$7:$M$7,BL$7)*BL$75 | BM171: =+SUMIFS($F171:$M171,$F$7:$M$7,BM$7)*BM$75 | BN171: =+SUMIFS($F171:$M171,$F$7:$M$7,BN$7)*BN$75 | BO171: =+SUMIFS($F171:$M171,$F$7:$M$7,BO$7)*BO$75 | BP171: =+SUMIFS($F171:$M171,$F$7:$M$7,BP$7)*BP$75 | BQ171: =+SUMIFS($F171:$M171,$F$7:$M$7,BQ$7)*BQ$75 | BR171: =+SUMIFS($F171:$M171,$F$7:$M$7,BR$7)*BR$75 | ... DR171: =+SUMIFS($F171:$M171,$F$7:$M$7,DR$7)*DR$75
B172: Lower Middle Market | F172: =+SUMIFS($AA172:$DR172,$AA$7:$DR$7,F$7) | G172: =+SUMIFS($AA172:$DR172,$AA$7:$DR$7,G$7) | H172: =+SUMIFS($AA172:$DR172,$AA$7:$DR$7,H$7) | I172: =+I165*(1-COGS_Assumptions!I27) | J172: =+J165*(1-COGS_Assumptions!J27) | K172: =+K165*(1-COGS_Assumptions!K27) | L172: =+L165*(1-COGS_Assumptions!L27) | M172: =+M165*(1-COGS_Assumptions!M27) | AA172: =+SUMIFS(AA$112:AA$157,$C$13:$C$58,$B172) | AB172: =+SUMIFS(AB$112:AB$157,$C$13:$C$58,$B172) | AC172: =+SUMIFS(AC$112:AC$157,$C$13:$C$58,$B172) | AD172: =+SUMIFS(AD$112:AD$157,$C$13:$C$58,$B172) | AE172: =+SUMIFS(AE$112:AE$157,$C$13:$C$58,$B172) | AF172: =+SUMIFS(AF$112:AF$157,$C$13:$C$58,$B172) | AG172: =+SUMIFS(AG$112:AG$157,$C$13:$C$58,$B172) | AH172: =+SUMIFS(AH$112:AH$157,$C$13:$C$58,$B172) | ... BJ172: =+SUMIFS(BJ$112:BJ$157,$C$13:$C$58,$B172) | BK172: =+SUMIFS($F172:$M172,$F$7:$M$7,BK$7)*BK$75 | BL172: =+SUMIFS($F172:$M172,$F$7:$M$7,BL$7)*BL$75 | BM172: =+SUMIFS($F172:$M172,$F$7:$M$7,BM$7)*BM$75 | BN172: =+SUMIFS($F172:$M172,$F$7:$M$7,BN$7)*BN$75 | BO172: =+SUMIFS($F172:$M172,$F$7:$M$7,BO$7)*BO$75 | BP172: =+SUMIFS($F172:$M172,$F$7:$M$7,BP$7)*BP$75 | BQ172: =+SUMIFS($F172:$M172,$F$7:$M$7,BQ$7)*BQ$75 | BR172: =+SUMIFS($F172:$M172,$F$7:$M$7,BR$7)*BR$75 | ... DR172: =+SUMIFS($F172:$M172,$F$7:$M$7,DR$7)*DR$75
B173: Total | F173: =+SUMIFS($AA173:$DR173,$AA$7:$DR$7,F$7) | G173: =+SUMIFS($AA173:$DR173,$AA$7:$DR$7,G$7) | H173: =+SUMIFS($AA173:$DR173,$AA$7:$DR$7,H$7) | I173: =+SUMIFS($AA173:$DR173,$AA$7:$DR$7,I$7) | J173: =+SUMIFS($AA173:$DR173,$AA$7:$DR$7,J$7) | K173: =+SUMIFS($AA173:$DR173,$AA$7:$DR$7,K$7) | L173: =+SUMIFS($AA173:$DR173,$AA$7:$DR$7,L$7) | M173: =+SUMIFS($AA173:$DR173,$AA$7:$DR$7,M$7) | AA173: =SUM(AA169:AA172) | AB173: =SUM(AB169:AB172) | AC173: =SUM(AC169:AC172) | AD173: =SUM(AD169:AD172) | AE173: =SUM(AE169:AE172) | AF173: =SUM(AF169:AF172) | AG173: =SUM(AG169:AG172) | AH173: =SUM(AH169:AH172) | ... DR173: =SUM(DR169:DR172)
B175: % Seasonality | F175: =+F173/SUMIFS($AA173:$DR173,$AA$7:$DR$7,F$7) | G175: =+G173/SUMIFS($AA173:$DR173,$AA$7:$DR$7,G$7) | H175: =+H173/SUMIFS($AA173:$DR173,$AA$7:$DR$7,H$7) | I175: =+I173/SUMIFS($AA173:$DR173,$AA$7:$DR$7,I$7) | J175: =+J173/SUMIFS($AA173:$DR173,$AA$7:$DR$7,J$7) | K175: =+K173/SUMIFS($AA173:$DR173,$AA$7:$DR$7,K$7) | L175: =+L173/SUMIFS($AA173:$DR173,$AA$7:$DR$7,L$7) | M175: =+M173/SUMIFS($AA173:$DR173,$AA$7:$DR$7,M$7) | AA175: =+AA173/SUMIFS($AA173:$DR173,$AA$7:$DR$7,AA$7) | AB175: =+AB173/SUMIFS($AA173:$DR173,$AA$7:$DR$7,AB$7) | AC175: =+AC173/SUMIFS($AA173:$DR173,$AA$7:$DR$7,AC$7) | AD175: =+AD173/SUMIFS($AA173:$DR173,$AA$7:$DR$7,AD$7) | AE175: =+AE173/SUMIFS($AA173:$DR173,$AA$7:$DR$7,AE$7) | AF175: =+AF173/SUMIFS($AA173:$DR173,$AA$7:$DR$7,AF$7) | AG175: =+AG173/SUMIFS($AA173:$DR173,$AA$7:$DR$7,AG$7) | AH175: =+AH173/SUMIFS($AA173:$DR173,$AA$7:$DR$7,AH$7) | ... BJ175: =+BJ173/SUMIFS($AA173:$DR173,$AA$7:$DR$7,BJ$7) | BK175: =+AVERAGE(AA175,AM175,AY175) | BL175: =+AVERAGE(AB175,AN175,AZ175) | BM175: =+AVERAGE(AC175,AO175,BA175) | BN175: =+AVERAGE(AD175,AP175,BB175) | BO175: =+AVERAGE(AE175,AQ175,BC175) | BP175: =+AVERAGE(AF175,AR175,BD175) | BQ175: =+AVERAGE(AG175,AS175,BE175) | BR175: =+AVERAGE(AH175,AT175,BF175) | ... DR175: =+AVERAGE(CH175,CT175,DF175)
B177: Gross Profit
B178: Mega | F178: =+F162-F169 | G178: =+G162-G169 | H178: =+H162-H169 | I178: =+I162-I169 | J178: =+J162-J169 | K178: =+K162-K169 | L178: =+L162-L169 | M178: =+M162-M169
B179: Major | F179: =+F163-F170 | G179: =+G163-G170 | H179: =+H163-H170 | I179: =+I163-I170 | J179: =+J163-J170 | K179: =+K163-K170 | L179: =+L163-L170 | M179: =+M163-M170
B180: Upper Middle Market | F180: =+F164-F171 | G180: =+G164-G171 | H180: =+H164-H171 | I180: =+I164-I171 | J180: =+J164-J171 | K180: =+K164-K171 | L180: =+L164-L171 | M180: =+M164-M171
B181: Lower Middle Market | F181: =+F165-F172 | G181: =+G165-G172 | H181: =+H165-H172 | I181: =+I165-I172 | J181: =+J165-J172 | K181: =+K165-K172 | L181: =+L165-L172 | M181: =+M165-M172
B182: Total | F182: =SUM(F178:F181) | G182: =SUM(G178:G181) | H182: =SUM(H178:H181) | I182: =SUM(I178:I181) | J182: =SUM(J178:J181) | K182: =SUM(K178:K181) | L182: =SUM(L178:L181) | M182: =SUM(M178:M181)
B184: Gross Margin
B185: Mega | F185: =+F178/F162 | G185: =+G178/G162 | H185: =+H178/H162 | I185: =+I178/I162 | J185: =+J178/J162 | K185: =+K178/K162 | L185: =+L178/L162 | M185: =+M178/M162
B186: Major | F186: =+F179/F163 | G186: =+G179/G163 | H186: =+H179/H163 | I186: =+I179/I163 | J186: =+J179/J163 | K186: =+K179/K163 | L186: =+L179/L163 | M186: =+M179/M163
B187: Upper Middle Market | F187: =+F180/F164 | G187: =+G180/G164 | H187: =+H180/H164 | I187: =+I180/I164 | J187: =+J180/J164 | K187: =+K180/K164 | L187: =+L180/L164 | M187: =+M180/M164
B188: Lower Middle Market | F188: =+F181/F165 | G188: =+G181/G165 | H188: =+H181/H165 | I188: =+I181/I165 | J188: =+J181/J165 | K188: =+K181/K165 | L188: =+L181/L165 | M188: =+M181/M165
...

Sheet Opex_Calcs
B2: Project Shasta
B3: {=MID(CELL("filename",A1),FIND("]",CELL("filename",A1))+1,255)}
B4: Spring 2022
B5: CONFIDENTIAL
F7: 2019 | G7: =+F7+1 | H7: =+G7+1 | I7: =+H7+1 | J7: =+I7+1 | K7: =+J7+1 | L7: =+K7+1 | M7: =+L7+1 | AA7: =+YEAR(AA8) | AB7: =+YEAR(AB8) | AC7: =+YEAR(AC8) | AD7: =+YEAR(AD8) | AE7: =+YEAR(AE8) | AF7: =+YEAR(AF8) | AG7: =+YEAR(AG8) | AH7: =+YEAR(AH8) | ... DR7: =+YEAR(DR8)
F8: =+DATE(F7,12,31) | G8: =+DATE(G7,12,31) | H8: =+DATE(H7,12,31) | I8: =+DATE(I7,12,31) | J8: =+DATE(J7,12,31) | K8: =+DATE(K7,12,31) | L8: =+DATE(L7,12,31) | M8: =+DATE(M7,12,31) | AA8: 43496 | AB8: =+EOMONTH(AA8,1) | AC8: =+EOMONTH(AB8,1) | AD8: =+EOMONTH(AC8,1) | AE8: =+EOMONTH(AD8,1) | AF8: =+EOMONTH(AE8,1) | AG8: =+EOMONTH(AF8,1) | AH8: =+EOMONTH(AG8,1) | AI8: =+EOMONTH(AH8,1) | ... DR8: =+EOMONTH(DQ8,1)
B9: $ in thousands | F9: Actual | G9: Actual | H9: Actual | I9: Budget | J9: Projection | K9: Projection | L9: Projection | M9: Projection | AA9: Actual | AB9: Actual | AC9: Actual | AD9: Actual | AE9: Actual | AF9: Actual | AG9: Actual | AH9: Actual | AI9: Actual | AJ9: Actual | AK9: Actual | AL9: Actual | AM9: Actual | AN9: Actual | AO9: Actual | AP9: Actual | AQ9: Actual | AR9: Actual | AS9: Actual | AT9: Actual | AU9: Actual | AV9: Actual | AW9: Actual | AX9: Actual | AY9: Actual | AZ9: Actual | BA9: Actual | BB9: Actual | BC9: Actual | BD9: Actual | BE9: Actual | BF9: Actual | BG9: Actual | BH9: Actual | BI9: Actual | BJ9: Actual | BK9: Actual | BL9: Actual | BM9: Actual | BN9: Budget | BO9: Budget | BP9: Budget | BQ9: Budget | BR9: Budget | BS9: Budget | BT9: Budget | BU9: Budget | BV9: Budget | BW9: Projection | BX9: Projection | BY9: Projection | BZ9: Projection | CA9: Projection | CB9: Projection | CC9: Projection | CD9: Projection | CE9: Projection | CF9: Projection | CG9: Projection | CH9: Projection | CI9: Projection | CJ9: Projection | CK9: Projection | CL9: Projection | CM9: Projection | CN9: Projection | CO9: Projection | CP9: Projection | CQ9: Projection | CR9: Projection | CS9: Projection | CT9: Projection | CU9: Projection | CV9: Projection | CW9: Projection | CX9: Projection | CY9: Projection | CZ9: Projection | DA9: Projection | DB9: Projection | DC9: Projection | DD9: Projection | DE9: Projection | DF9: Projection | DG9: Projection | DH9: Projection | DI9: Projection | DJ9: Projection | DK9: Projection | DL9: Projection | DM9: Projection | DN9: Projection | DO9: Projection | DP9: Projection | DQ9: Projection | DR9: Projection
B11: Headcount(1)
B12: Delivery | F12: =+F28/F22 | G12: =+G28/G22 | H12: =+H28/H22 | I12: =+I28/I22 | J12: =+J28/J22 | K12: =+K28/K22 | L12: =+L28/L22 | M12: =+M28/M22 | AA12: 106 | AB12: 108 | AC12: 111 | AD12: 113 | AE12: 114 | AF12: 122 | AG12: 124 | AH12: 125 | AI12: 126 | AJ12: 133 | AK12: 132 | AL12: 129 | AM12: 127 | AN12: 128 | AO12: 123 | AP12: 122 | AQ12: 122 | AR12: 122 | AS12: 118 | AT12: 116 | AU12: 115 | AV12: 112 | AW12: 109 | AX12: 98 | AY12: 97 | AZ12: 96 | BA12: 97 | BB12: 95 | BC12: 94 | BD12: 94 | BE12: 96 | BF12: 95 | BG12: 88 | BH12: 86 | BI12: 89 | BJ12: 88 | BK12: 92 | BL12: 93 | BM12: 95 | BN12: 97 | BO12: 97 | BP12: 98 | BQ12: 101 | BR12: 102 | BS12: 102 | BT12: 102 | BU12: 102 | BV12: 102 | BW12: 106 | BX12: 107 | BY12: 108 | BZ12: 111 | CA12: 112 | CB12: 113 | CC12: 114 | CD12: 116 | CE12: 117 | CF12: 118 | CG12: 119 | CH12: 120 | CI12: =+SUMIFS(Opex_Assumptions!$F12:$M12,Opex_Assumptions!$F$7:$M$7,CI$7)/12+CH12 | CJ12: =+SUMIFS(Opex_Assumptions!$F12:$M12,Opex_Assumptions!$F$7:$M$7,CJ$7)/12+CI12 | CK12: =+SUMIFS(Opex_Assumptions!$F12:$M12,Opex_Assumptions!$F$7:$M$7,CK$7)/12+CJ12 | CL12: =+SUMIFS(Opex_Assumptions!$F12:$M12,Opex_Assumptions!$F$7:$M$7,CL$7)/12+CK12 | CM12: =+SUMIFS(Opex_Assumptions!$F12:$M12,Opex_Assumptions!$F$7:$M$7,CM$7)/12+CL12 | CN12: =+SUMIFS(Opex_Assumptions!$F12:$M12,Opex_Assumptions!$F$7:$M$7,CN$7)/12+CM12 | CO12: =+SUMIFS(Opex_Assumptions!$F12:$M12,Opex_Assumptions!$F$7:$M$7,CO$7)/12+CN12 | CP12: =+SUMIFS(Opex_Assumptions!$F12:$M12,Opex_Assumptions!$F$7:$M$7,CP$7)/12+CO12 | ... DR12: =+SUMIFS(Opex_Assumptions!$F12:$M12,Opex_Assumptions!$F$7:$M$7,DR$7)/12+DQ12
B13: Sales & CS | F13: =+F29/F23 | G13: =+G29/G23 | H13: =+H29/H23 | I13: =+I29/I23 | J13: =+J29/J23 | K13: =+K29/K23 | L13: =+L29/L23 | M13: =+M29/M23 | AA13: 9 | AB13: 9 | AC13: 9 | AD13: 10 | AE13: 9 | AF13: 8 | AG13: 10 | AH13: 10 | AI13: 10 | AJ13: 11 | AK13: 10 | AL13: 8 | AM13: 9 | AN13: 9 | AO13: 9 | AP13: 9 | AQ13: 9 | AR13: 9 | AS13: 9 | AT13: 9 | AU13: 9 | AV13: 8 | AW13: 9 | AX13: 8 | AY13: 8 | AZ13: 7 | BA13: 7 | BB13: 7 | BC13: 7 | BD13: 7 | BE13: 7 | BF13: 7 | BG13: 7 | BH13: 9 | BI13: 10 | BJ13: 10 | BK13: 10 | BL13: 10 | BM13: 10 | BN13: 8 | BO13: 8 | BP13: 8 | BQ13: 8 | BR13: 8 | BS13: 8 | BT13: 8 | BU13: 8 | BV13: 8 | BW13: 9 | BX13: 9 | BY13: 10 | BZ13: 10 | CA13: 10 | CB13: 10 | CC13: 10 | CD13: 10 | CE13: 10 | CF13: 10 | CG13: 10 | CH13: 10 | CI13: =+SUMIFS(Opex_Assumptions!$F13:$M13,Opex_Assumptions!$F$7:$M$7,CI$7)/12+CH13 | CJ13: =+SUMIFS(Opex_Assumptions!$F13:$M13,Opex_Assumptions!$F$7:$M$7,CJ$7)/12+CI13 | CK13: =+SUMIFS(Opex_Assumptions!$F13:$M13,Opex_Assumptions!$F$7:$M$7,CK$7)/12+CJ13 | CL13: =+SUMIFS(Opex_Assumptions!$F13:$M13,Opex_Assumptions!$F$7:$M$7,CL$7)/12+CK13 | CM13: =+SUMIFS(Opex_Assumptions!$F13:$M13,Opex_Assumptions!$F$7:$M$7,CM$7)/12+CL13 | CN13: =+SUMIFS(Opex_Assumptions!$F13:$M13,Opex_Assumptions!$F$7:$M$7,CN$7)/12+CM13 | CO13: =+SUMIFS(Opex_Assumptions!$F13:$M13,Opex_Assumptions!$F$7:$M$7,CO$7)/12+CN13 | CP13: =+SUMIFS(Opex_Assumptions!$F13:$M13,Opex_Assumptions!$F$7:$M$7,CP$7)/12+CO13 | ... DR13: =+SUMIFS(Opex_Assumptions!$F13:$M13,Opex_Assumptions!$F$7:$M$7,DR$7)/12+DQ13
B14: Executive | F14: =+F30/F24 | G14: =+G30/G24 | H14: =+H30/H24 | I14: =+I30/I24 | J14: =+J30/J24 | K14: =+K30/K24 | L14: =+L30/L24 | M14: =+M30/M24 | AA14: 8 | AB14: 9 | AC14: 9 | AD14: 8 | AE14: 8 | AF14: 8 | AG14: 8 | AH14: 8 | AI14: 8 | AJ14: 8 | AK14: 8 | AL14: 8 | AM14: 8 | AN14: 8 | AO14: 8 | AP14: 8 | AQ14: 8 | AR14: 8 | AS14: 8 | AT14: 8 | AU14: 8 | AV14: 8 | AW14: 8 | AX14: 8 | AY14: 8 | AZ14: 8 | BA14: 7 | BB14: 7 | BC14: 7 | BD14: 7 | BE14: 7 | BF14: 7 | BG14: 7 | BH14: 7 | BI14: 7 | BJ14: 7 | BK14: 7 | BL14: 7 | BM14: 7 | BN14: 7 | BO14: 7 | BP14: 7 | BQ14: 7 | BR14: 7 | BS14: 7 | BT14: 7 | BU14: 7 | BV14: 7 | BW14: 7 | BX14: 7 | BY14: 7 | BZ14: 7 | CA14: 7 | CB14: 7 | CC14: 7 | CD14: 7 | CE14: 7 | CF14: 7 | CG14: 7 | CH14: 7 | CI14: =+SUMIFS(Opex_Assumptions!$F14:$M14,Opex_Assumptions!$F$7:$M$7,CI$7)/12+CH14 | CJ14: =+SUMIFS(Opex_Assumptions!$F14:$M14,Opex_Assumptions!$F$7:$M$7,CJ$7)/12+CI14 | CK14: =+SUMIFS(Opex_Assumptions!$F14:$M14,Opex_Assumptions!$F$7:$M$7,CK$7)/12+CJ14 | CL14: =+SUMIFS(Opex_Assumptions!$F14:$M14,Opex_Assumptions!$F$7:$M$7,CL$7)/12+CK14 | CM14: =+SUMIFS(Opex_Assumptions!$F14:$M14,Opex_Assumptions!$F$7:$M$7,CM$7)/12+CL14 | CN14: =+SUMIFS(Opex_Assumptions!$F14:$M14,Opex_Assumptions!$F$7:$M$7,CN$7)/12+CM14 | CO14: =+SUMIFS(Opex_Assumptions!$F14:$M14,Opex_Assumptions!$F$7:$M$7,CO$7)/12+CN14 | CP14: =+SUMIFS(Opex_Assumptions!$F14:$M14,Opex_Assumptions!$F$7:$M$7,CP$7)/12+CO14 | ... DR14: =+SUMIFS(Opex_Assumptions!$F14:$M14,Opex_Assumptions!$F$7:$M$7,DR$7)/12+DQ14
B15: Admin | F15: =+F31/F25 | G15: =+G31/G25 | H15: =+H31/H25 | I15: =+I31/I25 | J15: =+J31/J25 | K15: =+K31/K25 | L15: =+L31/L25 | M15: =+M31/M25 | AA15: 11 | AB15: 11 | AC15: 11 | AD15: 12 | AE15: 10 | AF15: 10 | AG15: 12 | AH15: 13 | AI15: 12 | AJ15: 14 | AK15: 14 | AL15: 14 | AM15: 15 | AN15: 14 | AO15: 14 | AP15: 13 | AQ15: 13 | AR15: 13 | AS15: 13 | AT15: 13 | AU15: 13 | AV15: 14 | AW15: 14 | AX15: 14 | AY15: 12 | AZ15: 12 | BA15: 12 | BB15: 12 | BC15: 12 | BD15: 12 | BE15: 12 | BF15: 12 | BG15: 12 | BH15: 11 | BI15: 12 | BJ15: 12 | BK15: 12 | BL15: 13 | BM15: 13 | BN15: 12 | BO15: 11 | BP15: 11 | BQ15: 11 | BR15: 11 | BS15: 11 | BT15: 11 | BU15: 11 | BV15: 11 | BW15: 11 | BX15: 11 | BY15: 11 | BZ15: 11 | CA15: 11 | CB15: 11 | CC15: 11 | CD15: 11 | CE15: 11 | CF15: 11 | CG15: 11 | CH15: 11 | CI15: =+SUMIFS(Opex_Assumptions!$F15:$M15,Opex_Assumptions!$F$7:$M$7,CI$7)/12+CH15 | CJ15: =+SUMIFS(Opex_Assumptions!$F15:$M15,Opex_Assumptions!$F$7:$M$7,CJ$7)/12+CI15 | CK15: =+SUMIFS(Opex_Assumptions!$F15:$M15,Opex_Assumptions!$F$7:$M$7,CK$7)/12+CJ15 | CL15: =+SUMIFS(Opex_Assumptions!$F15:$M15,Opex_Assumptions!$F$7:$M$7,CL$7)/12+CK15 | CM15: =+SUMIFS(Opex_Assumptions!$F15:$M15,Opex_Assumptions!$F$7:$M$7,CM$7)/12+CL15 | CN15: =+SUMIFS(Opex_Assumptions!$F15:$M15,Opex_Assumptions!$F$7:$M$7,CN$7)/12+CM15 | CO15: =+SUMIFS(Opex_Assumptions!$F15:$M15,Opex_Assumptions!$F$7:$M$7,CO$7)/12+CN15 | CP15: =+SUMIFS(Opex_Assumptions!$F15:$M15,Opex_Assumptions!$F$7:$M$7,CP$7)/12+CO15 | ... DR15: =+SUMIFS(Opex_Assumptions!$F15:$M15,Opex_Assumptions!$F$7:$M$7,DR$7)/12+DQ15
B16: Total | F16: =SUM(F12:F15) | G16: =SUM(G12:G15) | H16: =SUM(H12:H15) | I16: =SUM(I12:I15) | J16: =SUM(J12:J15) | K16: =SUM(K12:K15) | L16: =SUM(L12:L15) | M16: =SUM(M12:M15) | AA16: =SUM(AA12:AA15) | AB16: =SUM(AB12:AB15) | AC16: =SUM(AC12:AC15) | AD16: =SUM(AD12:AD15) | AE16: =SUM(AE12:AE15) | AF16: =SUM(AF12:AF15) | AG16: =SUM(AG12:AG15) | AH16: =SUM(AH12:AH15) | ... DR16: =SUM(DR12:DR15)
B18: Memo: Revenue / Delivery Headcount | F18: =+'Income Statement'!F$16/F12 | G18: =+'Income Statement'!G$16/G12 | H18: =+'Income Statement'!H$16/H12 | I18: =+'Income Statement'!I$16/I12 | J18: =+'Income Statement'!J$16/J12 | K18: =+'Income Statement'!K$16/K12 | L18: =+'Income Statement'!L$16/L12 | M18: =+'Income Statement'!M$16/M12 | AA18: =+'Income Statement'!Q$16/AA12 | AB18: =+'Income Statement'!R$16/AB12 | AC18: =+'Income Statement'!S$16/AC12 | AD18: =+'Income Statement'!T$16/AD12 | AE18: =+'Income Statement'!U$16/AE12 | AF18: =+'Income Statement'!V$16/AF12 | AG18: =+'Income Statement'!W$16/AG12 | AH18: =+'Income Statement'!X$16/AH12 | ... DR18: =+'Income Statement'!DH$16/DR12
B19: Memo: Revenue / Sales & CS Headcount | F19: =+'Income Statement'!F$16/F13 | G19: =+'Income Statement'!G$16/G13 | H19: =+'Income Statement'!H$16/H13 | I19: =+'Income Statement'!I$16/I13 | J19: =+'Income Statement'!J$16/J13 | K19: =+'Income Statement'!K$16/K13 | L19: =+'Income Statement'!L$16/L13 | M19: =+'Income Statement'!M$16/M13 | AA19: =+'Income Statement'!Q$16/AA13 | AB19: =+'Income Statement'!R$16/AB13 | AC19: =+'Income Statement'!S$16/AC13 | AD19: =+'Income Statement'!T$16/AD13 | AE19: =+'Income Statement'!U$16/AE13 | AF19: =+'Income Statement'!V$16/AF13 | AG19: =+'Income Statement'!W$16/AG13 | AH19: =+'Income Statement'!X$16/AH13 | ... DR19: =+'Income Statement'!DH$16/DR13
B21: Average Salary(1)
B22: Delivery | F22: =+SUMIFS($AA22:$DR22,$AA$7:$DR$7,F$7) | G22: =+SUMIFS($AA22:$DR22,$AA$7:$DR$7,G$7) | H22: =+SUMIFS($AA22:$DR22,$AA$7:$DR$7,H$7) | I22: =+SUMIFS($AA22:$DR22,$AA$7:$DR$7,I$7) | J22: =+SUMIFS($AA22:$DR22,$AA$7:$DR$7,J$7) | K22: =+SUMIFS($AA22:$DR22,$AA$7:$DR$7,K$7) | L22: =+SUMIFS($AA22:$DR22,$AA$7:$DR$7,L$7) | M22: =+SUMIFS($AA22:$DR22,$AA$7:$DR$7,M$7) | AA22: =+AA28/AA12 | AB22: =+AB28/AB12 | AC22: =+AC28/AC12 | AD22: =+AD28/AD12 | AE22: =+AE28/AE12 | AF22: =+AF28/AF12 | AG22: =+AG28/AG12 | AH22: =+AH28/AH12 | ... CH22: =+CH28/CH12 | CI22: =+SUMIFS(Opex_Assumptions!$F18:$M18,Opex_Assumptions!$F$7:$M$7,CI$7)/12 | CJ22: =+SUMIFS(Opex_Assumptions!$F18:$M18,Opex_Assumptions!$F$7:$M$7,CJ$7)/12 | CK22: =+SUMIFS(Opex_Assumptions!$F18:$M18,Opex_Assumptions!$F$7:$M$7,CK$7)/12 | CL22: =+SUMIFS(Opex_Assumptions!$F18:$M18,Opex_Assumptions!$F$7:$M$7,CL$7)/12 | CM22: =+SUMIFS(Opex_Assumptions!$F18:$M18,Opex_Assumptions!$F$7:$M$7,CM$7)/12 | CN22: =+SUMIFS(Opex_Assumptions!$F18:$M18,Opex_Assumptions!$F$7:$M$7,CN$7)/12 | CO22: =+SUMIFS(Opex_Assumptions!$F18:$M18,Opex_Assumptions!$F$7:$M$7,CO$7)/12 | CP22: =+SUMIFS(Opex_Assumptions!$F18:$M18,Opex_Assumptions!$F$7:$M$7,CP$7)/12 | ... DR22: =+SUMIFS(Opex_Assumptions!$F18:$M18,Opex_Assumptions!$F$7:$M$7,DR$7)/12
B23: Sales & CS | F23: =+SUMIFS($AA23:$DR23,$AA$7:$DR$7,F$7) | G23: =+SUMIFS($AA23:$DR23,$AA$7:$DR$7,G$7) | H23: =+SUMIFS($AA23:$DR23,$AA$7:$DR$7,H$7) | I23: =+SUMIFS($AA23:$DR23,$AA$7:$DR$7,I$7) | J23: =+SUMIFS($AA23:$DR23,$AA$7:$DR$7,J$7) | K23: =+SUMIFS($AA23:$DR23,$AA$7:$DR$7,K$7) | L23: =+SUMIFS($AA23:$DR23,$AA$7:$DR$7,L$7) | M23: =+SUMIFS($AA23:$DR23,$AA$7:$DR$7,M$7) | AA23: =+AA29/AA13 | AB23: =+AB29/AB13 | AC23: =+AC29/AC13 | AD23: =+AD29/AD13 | AE23: =+AE29/AE13 | AF23: =+AF29/AF13 | AG23: =+AG29/AG13 | AH23: =+AH29/AH13 | ... CH23: =+CH29/CH13 | CI23: =+SUMIFS(Opex_Assumptions!$F19:$M19,Opex_Assumptions!$F$7:$M$7,CI$7)/12 | CJ23: =+SUMIFS(Opex_Assumptions!$F19:$M19,Opex_Assumptions!$F$7:$M$7,CJ$7)/12 | CK23: =+SUMIFS(Opex_Assumptions!$F19:$M19,Opex_Assumptions!$F$7:$M$7,CK$7)/12 | CL23: =+SUMIFS(Opex_Assumptions!$F19:$M19,Opex_Assumptions!$F$7:$M$7,CL$7)/12 | CM23: =+SUMIFS(Opex_Assumptions!$F19:$M19,Opex_Assumptions!$F$7:$M$7,CM$7)/12 | CN23: =+SUMIFS(Opex_Assumptions!$F19:$M19,Opex_Assumptions!$F$7:$M$7,CN$7)/12 | CO23: =+SUMIFS(Opex_Assumptions!$F19:$M19,Opex_Assumptions!$F$7:$M$7,CO$7)/12 | CP23: =+SUMIFS(Opex_Assumptions!$F19:$M19,Opex_Assumptions!$F$7:$M$7,CP$7)/12 | ... DR23: =+SUMIFS(Opex_Assumptions!$F19:$M19,Opex_Assumptions!$F$7:$M$7,DR$7)/12
B24: Executive | F24: =+SUMIFS($AA24:$DR24,$AA$7:$DR$7,F$7) | G24: =+SUMIFS($AA24:$DR24,$AA$7:$DR$7,G$7) | H24: =+SUMIFS($AA24:$DR24,$AA$7:$DR$7,H$7) | I24: =+SUMIFS($AA24:$DR24,$AA$7:$DR$7,I$7) | J24: =+SUMIFS($AA24:$DR24,$AA$7:$DR$7,J$7) | K24: =+SUMIFS($AA24:$DR24,$AA$7:$DR$7,K$7) | L24: =+SUMIFS($AA24:$DR24,$AA$7:$DR$7,L$7) | M24: =+SUMIFS($AA24:$DR24,$AA$7:$DR$7,M$7) | AA24: =+AA30/AA14 | AB24: =+AB30/AB14 | AC24: =+AC30/AC14 | AD24: =+AD30/AD14 | AE24: =+AE30/AE14 | AF24: =+AF30/AF14 | AG24: =+AG30/AG14 | AH24: =+AH30/AH14 | ... CH24: =+CH30/CH14 | CI24: =+SUMIFS(Opex_Assumptions!$F20:$M20,Opex_Assumptions!$F$7:$M$7,CI$7)/12 | CJ24: =+SUMIFS(Opex_Assumptions!$F20:$M20,Opex_Assumptions!$F$7:$M$7,CJ$7)/12 | CK24: =+SUMIFS(Opex_Assumptions!$F20:$M20,Opex_Assumptions!$F$7:$M$7,CK$7)/12 | CL24: =+SUMIFS(Opex_Assumptions!$F20:$M20,Opex_Assumptions!$F$7:$M$7,CL$7)/12 | CM24: =+SUMIFS(Opex_Assumptions!$F20:$M20,Opex_Assumptions!$F$7:$M$7,CM$7)/12 | CN24: =+SUMIFS(Opex_Assumptions!$F20:$M20,Opex_Assumptions!$F$7:$M$7,CN$7)/12 | CO24: =+SUMIFS(Opex_Assumptions!$F20:$M20,Opex_Assumptions!$F$7:$M$7,CO$7)/12 | CP24: =+SUMIFS(Opex_Assumptions!$F20:$M20,Opex_Assumptions!$F$7:$M$7,CP$7)/12 | ... DR24: =+SUMIFS(Opex_Assumptions!$F20:$M20,Opex_Assumptions!$F$7:$M$7,DR$7)/12
B25: Admin | F25: =+SUMIFS($AA25:$DR25,$AA$7:$DR$7,F$7) | G25: =+SUMIFS($AA25:$DR25,$AA$7:$DR$7,G$7) | H25: =+SUMIFS($AA25:$DR25,$AA$7:$DR$7,H$7) | I25: =+SUMIFS($AA25:$DR25,$AA$7:$DR$7,I$7) | J25: =+SUMIFS($AA25:$DR25,$AA$7:$DR$7,J$7) | K25: =+SUMIFS($AA25:$DR25,$AA$7:$DR$7,K$7) | L25: =+SUMIFS($AA25:$DR25,$AA$7:$DR$7,L$7) | M25: =+SUMIFS($AA25:$DR25,$AA$7:$DR$7,M$7) | AA25: =+AA31/AA15 | AB25: =+AB31/AB15 | AC25: =+AC31/AC15 | AD25: =+AD31/AD15 | AE25: =+AE31/AE15 | AF25: =+AF31/AF15 | AG25: =+AG31/AG15 | AH25: =+AH31/AH15 | ... CH25: =+CH31/CH15 | CI25: =+SUMIFS(Opex_Assumptions!$F21:$M21,Opex_Assumptions!$F$7:$M$7,CI$7)/12 | CJ25: =+SUMIFS(Opex_Assumptions!$F21:$M21,Opex_Assumptions!$F$7:$M$7,CJ$7)/12 | CK25: =+SUMIFS(Opex_Assumptions!$F21:$M21,Opex_Assumptions!$F$7:$M$7,CK$7)/12 | CL25: =+SUMIFS(Opex_Assumptions!$F21:$M21,Opex_Assumptions!$F$7:$M$7,CL$7)/12 | CM25: =+SUMIFS(Opex_Assumptions!$F21:$M21,Opex_Assumptions!$F$7:$M$7,CM$7)/12 | CN25: =+SUMIFS(Opex_Assumptions!$F21:$M21,Opex_Assumptions!$F$7:$M$7,CN$7)/12 | CO25: =+SUMIFS(Opex_Assumptions!$F21:$M21,Opex_Assumptions!$F$7:$M$7,CO$7)/12 | CP25: =+SUMIFS(Opex_Assumptions!$F21:$M21,Opex_Assumptions!$F$7:$M$7,CP$7)/12 | ... DR25: =+SUMIFS(Opex_Assumptions!$F21:$M21,Opex_Assumptions!$F$7:$M$7,DR$7)/12
B27: Total Salary(1)
B28: Delivery | F28: =+SUMIFS($AA28:$DR28,$AA$7:$DR$7,F$7) | G28: =+SUMIFS($AA28:$DR28,$AA$7:$DR$7,G$7) | H28: =+SUMIFS($AA28:$DR28,$AA$7:$DR$7,H$7) | I28: =+SUMIFS($AA28:$DR28,$AA$7:$DR$7,I$7) | J28: =+SUMIFS($AA28:$DR28,$AA$7:$DR$7,J$7) | K28: =+SUMIFS($AA28:$DR28,$AA$7:$DR$7,K$7) | L28: =+SUMIFS($AA28:$DR28,$AA$7:$DR$7,L$7) | M28: =+SUMIFS($AA28:$DR28,$AA$7:$DR$7,M$7) | AA28: 742.0827 | AB28: 797.55628 | AC28: 759.24998 | AD28: 782.06817 | AE28: 823.7937 | AF28: 922.52755 | AG28: 937.42067 | AH28: 952.44916 | AI28: 884.94462 | AJ28: 940.85336 | AK28: 909.25027 | AL28: 945.20088 | AM28: 935.70558 | AN28: 910.84501 | AO28: 865.51169 | AP28: 780.67667 | AQ28: 773.44951 | AR28: 787.70807 | AS28: 777.0328 | AT28: 774.30916 | AU28: 754.68672 | AV28: 710.48763 | AW28: 639.71293 | AX28: 678.10155 | AY28: 667.18875 | AZ28: 646.46605 | BA28: 676.94196 | BB28: 699.79271 | BC28: 697.96158 | BD28: 709.07004 | BE28: 723.4926 | BF28: 707.61818 | BG28: 667.77865 | BH28: 690.50111 | BI28: 684.13281 | BJ28: 672.68364 | BK28: 738.58844 | BL28: 738.09021 | BM28: 757.98741 | BN28: 782.71108 | BO28: 793.51108 | BP28: 800.91 | BQ28: 801.27733 | BR28: 796.77733 | BS28: 796.77733 | BT28: 796.77733 | BU28: 796.77733 | BV28: 796.77733 | BW28: 852.48629 | BX28: 860.21129 | BY28: 870.93629 | BZ28: 896.68629 | CA28: 904.41129 | CB28: 912.13629 | CC28: 919.86129 | CD28: 938.31546 | CE28: 946.04046 | CF28: 953.76546 | CG28: 961.49046 | CH28: 969.21546 | CI28: =+CI12*CI22 | CJ28: =+CJ12*CJ22 | CK28: =+CK12*CK22 | CL28: =+CL12*CL22 | CM28: =+CM12*CM22 | CN28: =+CN12*CN22 | CO28: =+CO12*CO22 | CP28: =+CP12*CP22 | ... DR28: =+DR12*DR22
B29: Sales & CS | F29: =+SUMIFS($AA29:$DR29,$AA$7:$DR$7,F$7) | G29: =+SUMIFS($AA29:$DR29,$AA$7:$DR$7,G$7) | H29: =+SUMIFS($AA29:$DR29,$AA$7:$DR$7,H$7) | I29: =+SUMIFS($AA29:$DR29,$AA$7:$DR$7,I$7) | J29: =+SUMIFS($AA29:$DR29,$AA$7:$DR$7,J$7) | K29: =+SUMIFS($AA29:$DR29,$AA$7:$DR$7,K$7) | L29: =+SUMIFS($AA29:$DR29,$AA$7:$DR$7,L$7) | M29: =+SUMIFS($AA29:$DR29,$AA$7:$DR$7,M$7) | AA29: 64.853264 | AB29: 61.97111 | AC29: 63.522662 | AD29: 64.887592 | AE29: 64.577582 | AF29: 61.423537 | AG29: 68.008674 | AH29: 68.008674 | AI29: 68.008674 | AJ29: 74.772982 | AK29: 60.058786 | AL29: 48.581044 | AM29: 55.986406 | AN29: 59.734817 | AO29: 59.184083 | AP29: 59.184083 | AQ29: 59.184083 | AR29: 59.184083 | AS29: 59.184083 | AT29: 59.184083 | AU29: 55.09127 | AV29: 50.761458 | AW29: 54.17904 | AX29: 53.791326 | AY29: 50.580621 | AZ29: 42.458241 | BA29: 42.176011 | BB29: 42.176011 | BC29: 42.176011 | BD29: 42.176011 | BE29: 42.176011 | BF29: 43.029699 | BG29: 35.152135 | BH29: 50.347084 | BI29: 55.527404 | BJ29: 57.522916 | BK29: 48.89866 | BL29: 48.89866 | BM29: 50.34055 | BN29: 39.93575 | BO29: 39.93575 | BP29: 39.93575 | BQ29: 39.93575 | BR29: 39.93575 | BS29: 39.93575 | BT29: 39.93575 | BU29: 39.93575 | BV29: 39.93575 | BW29: 47.571322 | BX29: 47.571322 | BY29: 47.571322 | BZ29: 47.571322 | CA29: 47.571322 | CB29: 47.571322 | CC29: 47.571322 | CD29: 47.571322 | CE29: 47.571322 | CF29: 47.571322 | CG29: 47.571322 | CH29: 47.571322 | CI29: =+CI13*CI23 | CJ29: =+CJ13*CJ23 | CK29: =+CK13*CK23 | CL29: =+CL13*CL23 | CM29: =+CM13*CM23 | CN29: =+CN13*CN23 | CO29: =+CO13*CO23 | CP29: =+CP13*CP23 | ... DR29: =+DR13*DR23
B30: Executive | F30: =+SUMIFS($AA30:$DR30,$AA$7:$DR$7,F$7) | G30: =+SUMIFS($AA30:$DR30,$AA$7:$DR$7,G$7) | H30: =+SUMIFS($AA30:$DR30,$AA$7:$DR$7,H$7) | I30: =+SUMIFS($AA30:$DR30,$AA$7:$DR$7,I$7) | J30: =+SUMIFS($AA30:$DR30,$AA$7:$DR$7,J$7) | K30: =+SUMIFS($AA30:$DR30,$AA$7:$DR$7,K$7) | L30: =+SUMIFS($AA30:$DR30,$AA$7:$DR$7,L$7) | M30: =+SUMIFS($AA30:$DR30,$AA$7:$DR$7,M$7) | AA30: 139.13106 | AB30: 136.84322 | AC30: 137.23457 | AD30: 134.06412 | AE30: 134.06412 | AF30: 134.06412 | AG30: 134.06412 | AH30: 134.06412 | AI30: 134.06412 | AJ30: 134.06412 | AK30: 134.23324 | AL30: 134.06412 | AM30: 142.04623 | AN30: 142.04623 | AO30: 142.04623 | AP30: 142.04623 | AQ30: 142.04623 | AR30: 142.04623 | AS30: 143.61278 | AT30: 143.51612 | AU30: 143.51612 | AV30: 143.51612 | AW30: 143.51612 | AX30: 143.51612 | AY30: 139.03072 | AZ30: 142.29788 | BA30: 137.29778 | BB30: 137.29778 | BC30: 138.64305 | BD30: 138.64305 | BE30: 138.64305 | BF30: 138.64305 | BG30: 138.64299 | BH30: 138.64297 | BI30: 138.64297 | BJ30: 138.64297 | BK30: 152.84352 | BL30: 152.84354 | BM30: 152.84354 | BN30: 152.84351 | BO30: 152.84351 | BP30: 152.84351 | BQ30: 152.84351 | BR30: 152.84351 | BS30: 152.84351 | BT30: 152.84351 | BU30: 152.84351 | BV30: 152.84351 | BW30: 156.46298 | BX30: 156.46298 | BY30: 156.46298 | BZ30: 156.46298 | CA30: 156.46298 | CB30: 156.46298 | CC30: 156.46298 | CD30: 156.46298 | CE30: 156.46298 | CF30: 156.46298 | CG30: 156.46298 | CH30: 156.46298 | CI30: =+CI14*CI24 | CJ30: =+CJ14*CJ24 | CK30: =+CK14*CK24 | CL30: =+CL14*CL24 | CM30: =+CM14*CM24 | CN30: =+CN14*CN24 | CO30: =+CO14*CO24 | CP30: =+CP14*CP24 | ... DR30: =+DR14*DR24
B31: Admin | F31: =+SUMIFS($AA31:$DR31,$AA$7:$DR$7,F$7) | G31: =+SUMIFS($AA31:$DR31,$AA$7:$DR$7,G$7) | H31: =+SUMIFS($AA31:$DR31,$AA$7:$DR$7,H$7) | I31: =+SUMIFS($AA31:$DR31,$AA$7:$DR$7,I$7) | J31: =+SUMIFS($AA31:$DR31,$AA$7:$DR$7,J$7) | K31: =+SUMIFS($AA31:$DR31,$AA$7:$DR$7,K$7) | L31: =+SUMIFS($AA31:$DR31,$AA$7:$DR$7,L$7) | M31: =+SUMIFS($AA31:$DR31,$AA$7:$DR$7,M$7) | AA31: 72.147893 | AB31: 69.155842 | AC31: 69.558325 | AD31: 74.699595 | AE31: 77.090668 | AF31: 77.090668 | AG31: 83.76904 | AH31: 89.991364 | AI31: 88.734638 | AJ31: 103.55498 | AK31: 107.69382 | AL31: 107.35571 | AM31: 107.55712 | AN31: 112.456 | AO31: 105.89511 | AP31: 105.22845 | AQ31: 105.22845 | AR31: 105.22845 | AS31: 105.22845 | AT31: 105.22845 | AU31: 105.53021 | AV31: 106.40305 | AW31: 114.25029 | AX31: 119.47123 | AY31: 97.760169 | AZ31: 101.79103 | BA31: 97.770461 | BB31: 100.49439 | BC31: 101.27834 | BD31: 102.0623 | BE31: 102.23389 | BF31: 105.28602 | BG31: 101.6873 | BH31: 97.454149 | BI31: 100.66119 | BJ31: 103.33373 | BK31: 114.30671 | BL31: 117.99992 | BM31: 116.20951 | BN31: 115.93542 | BO31: 101.04258 | BP31: 101.04258 | BQ31: 101.04258 | BR31: 101.04258 | BS31: 101.04258 | BT31: 101.04258 | BU31: 101.04258 | BV31: 101.04258 | BW31: 104.07386 | BX31: 104.07386 | BY31: 104.07386 | BZ31: 104.07386 | CA31: 104.07386 | CB31: 104.07386 | CC31: 104.07386 | CD31: 104.07386 | CE31: 104.07386 | CF31: 104.07386 | CG31: 104.07386 | CH31: 104.07386 | CI31: =+CI15*CI25 | CJ31: =+CJ15*CJ25 | CK31: =+CK15*CK25 | CL31: =+CL15*CL25 | CM31: =+CM15*CM25 | CN31: =+CN15*CN25 | CO31: =+CO15*CO25 | CP31: =+CP15*CP25 | ... DR31: =+DR15*DR25
B32: Total Salary | F32: =+SUMIFS($AA32:$DR32,$AA$7:$DR$7,F$7) | G32: =+SUMIFS($AA32:$DR32,$AA$7:$DR$7,G$7) | H32: =+SUMIFS($AA32:$DR32,$AA$7:$DR$7,H$7) | I32: =+SUMIFS($AA32:$DR32,$AA$7:$DR$7,I$7) | J32: =+SUMIFS($AA32:$DR32,$AA$7:$DR$7,J$7) | K32: =+SUMIFS($AA32:$DR32,$AA$7:$DR$7,K$7) | L32: =+SUMIFS($AA32:$DR32,$AA$7:$DR$7,L$7) | M32: =+SUMIFS($AA32:$DR32,$AA$7:$DR$7,M$7) | AA32: =SUM(AA28:AA31) | AB32: =SUM(AB28:AB31) | AC32: =SUM(AC28:AC31) | AD32: =SUM(AD28:AD31) | AE32: =SUM(AE28:AE31) | AF32: =SUM(AF28:AF31) | AG32: =SUM(AG28:AG31) | AH32: =SUM(AH28:AH31) | ... DR32: =SUM(DR28:DR31)
B34: Direct Labor | F34: =+SUMIFS($AA34:$DR34,$AA$7:$DR$7,F$7) | G34: =+SUMIFS($AA34:$DR34,$AA$7:$DR$7,G$7) | H34: =+SUMIFS($AA34:$DR34,$AA$7:$DR$7,H$7) | I34: =+SUMIFS($AA34:$DR34,$AA$7:$DR$7,I$7) | J34: =+SUMIFS($AA34:$DR34,$AA$7:$DR$7,J$7) | K34: =+SUMIFS($AA34:$DR34,$AA$7:$DR$7,K$7) | L34: =+SUMIFS($AA34:$DR34,$AA$7:$DR$7,L$7) | M34: =+SUMIFS($AA34:$DR34,$AA$7:$DR$7,M$7) | AA34: =+SUM(COGS_Calcs!AA74,COGS_Calcs!AA104,COGS_Calcs!AA173,COGS_Calcs!AA256,COGS_Calcs!AA276) | AB34: =+SUM(COGS_Calcs!AB74,COGS_Calcs!AB104,COGS_Calcs!AB173,COGS_Calcs!AB256,COGS_Calcs!AB276) | AC34: =+SUM(COGS_Calcs!AC74,COGS_Calcs!AC104,COGS_Calcs!AC173,COGS_Calcs!AC256,COGS_Calcs!AC276) | AD34: =+SUM(COGS_Calcs!AD74,COGS_Calcs!AD104,COGS_Calcs!AD173,COGS_Calcs!AD256,COGS_Calcs!AD276) | AE34: =+SUM(COGS_Calcs!AE74,COGS_Calcs!AE104,COGS_Calcs!AE173,COGS_Calcs!AE256,COGS_Calcs!AE276) | AF34: =+SUM(COGS_Calcs!AF74,COGS_Calcs!AF104,COGS_Calcs!AF173,COGS_Calcs!AF256,COGS_Calcs!AF276) | AG34: =+SUM(COGS_Calcs!AG74,COGS_Calcs!AG104,COGS_Calcs!AG173,COGS_Calcs!AG256,COGS_Calcs!AG276) | AH34: =+SUM(COGS_Calcs!AH74,COGS_Calcs!AH104,COGS_Calcs!AH173,COGS_Calcs!AH256,COGS_Calcs!AH276) | ... DR34: =+SUM(COGS_Calcs!DR74,COGS_Calcs!DR104,COGS_Calcs!DR173,COGS_Calcs!DR256,COGS_Calcs!DR276)
B35: Memo: Direct Labor Allocation | F35: =+F34/F32 | G35: =+G34/G32 | H35: =+H34/H32 | I35: =+I34/I32 | J35: =+J34/J32 | K35: =+K34/K32 | L35: =+L34/L32 | M35: =+M34/M32 | AA35: =+AA34/AA32 | AB35: =+AB34/AB32 | AC35: =+AC34/AC32 | AD35: =+AD34/AD32 | AE35: =+AE34/AE32 | AF35: =+AF34/AF32 | AG35: =+AG34/AG32 | AH35: =+AH34/AH32 | ... DR35: =+DR34/DR32
B37: Overhead Salary | F37: =+SUMIFS($AA37:$DR37,$AA$7:$DR$7,F$7) | G37: =+SUMIFS($AA37:$DR37,$AA$7:$DR$7,G$7) | H37: =+SUMIFS($AA37:$DR37,$AA$7:$DR$7,H$7) | I37: =+SUMIFS($AA37:$DR37,$AA$7:$DR$7,I$7) | J37: =+SUMIFS($AA37:$DR37,$AA$7:$DR$7,J$7) | K37: =+SUMIFS($AA37:$DR37,$AA$7:$DR$7,K$7) | L37: =+SUMIFS($AA37:$DR37,$AA$7:$DR$7,L$7) | M37: =+SUMIFS($AA37:$DR37,$AA$7:$DR$7,M$7) | AA37: =+AA32-AA34 | AB37: =+AB32-AB34 | AC37: =+AC32-AC34 | AD37: =+AD32-AD34 | AE37: =+AE32-AE34 | AF37: =+AF32-AF34 | AG37: =+AG32-AG34 | AH37: =+AH32-AH34 | ... DR37: =+DR32-DR34
B38: Bonus | F38: =+SUMIFS($AA38:$DR38,$AA$7:$DR$7,F$7) | G38: =+SUMIFS($AA38:$DR38,$AA$7:$DR$7,G$7) | H38: =+SUMIFS($AA38:$DR38,$AA$7:$DR$7,H$7) | I38: =+SUMIFS($AA38:$DR38,$AA$7:$DR$7,I$7) | J38: =+SUMIFS($AA38:$DR38,$AA$7:$DR$7,J$7) | K38: =+SUMIFS($AA38:$DR38,$AA$7:$DR$7,K$7) | L38: =+SUMIFS($AA38:$DR38,$AA$7:$DR$7,L$7) | M38: =+SUMIFS($AA38:$DR38,$AA$7:$DR$7,M$7) | AA38: 6.25 | AB38: 6.25 | AC38: 6.25 | AD38: 6.25 | AE38: 6.25 | AF38: 6.25 | AG38: 6.25 | AH38: 6.25 | AI38: 6.25 | AJ38: 6.25 | AK38: 6.25 | AL38: 8.11876 | AM38: 6.25 | AN38: 6.97728 | AO38: 6.97728 | AP38: 6.97728 | AQ38: 6.97728 | AR38: 6.97727 | AS38: 6.97727 | AT38: 6.97727 | AU38: 6.97727 | AV38: 6.97727 | AW38: 6.97727 | AX38: 21.48651 | AY38: 41.25 | AZ38: 41.25 | BA38: 41.25 | BB38: 41.25 | BC38: 45 | BD38: 48.60352 | BE38: 48.60352 | BF38: 48.60352 | BG38: 43.58576 | BH38: 42.58576 | BI38: 42.58576 | BJ38: 48.88911 | BK38: 47.083 | BL38: 77.516 | BM38: 47.5401 | BN38: 47.5401 | BO38: 47.5401 | BP38: 47.5401 | BQ38: 47.5401 | BR38: 47.5401 | BS38: 47.5401 | BT38: 47.5401 | BU38: 47.5401 | BV38: 47.5401 | BW38: 50 | BX38: 50 | BY38: 50 | BZ38: 50 | CA38: 50 | CB38: 50 | CC38: 50 | CD38: 50 | CE38: 50 | CF38: 50 | CG38: 50 | CH38: 50 | CI38: =+SUMIFS(Opex_Assumptions!$F24:$M24,Opex_Assumptions!$F$7:$M$7,CI$7)*'Income Statement'!BY$16 | CJ38: =+SUMIFS(Opex_Assumptions!$F24:$M24,Opex_Assumptions!$F$7:$M$7,CJ$7)*'Income Statement'!BZ$16 | CK38: =+SUMIFS(Opex_Assumptions!$F24:$M24,Opex_Assumptions!$F$7:$M$7,CK$7)*'Income Statement'!CA$16 | CL38: =+SUMIFS(Opex_Assumptions!$F24:$M24,Opex_Assumptions!$F$7:$M$7,CL$7)*'Income Statement'!CB$16 | CM38: =+SUMIFS(Opex_Assumptions!$F24:$M24,Opex_Assumptions!$F$7:$M$7,CM$7)*'Income Statement'!CC$16 | CN38: =+SUMIFS(Opex_Assumptions!$F24:$M24,Opex_Assumptions!$F$7:$M$7,CN$7)*'Income Statement'!CD$16 | CO38: =+SUMIFS(Opex_Assumptions!$F24:$M24,Opex_Assumptions!$F$7:$M$7,CO$7)*'Income Statement'!CE$16 | CP38: =+SUMIFS(Opex_Assumptions!$F24:$M24,Opex_Assumptions!$F$7:$M$7,CP$7)*'Income Statement'!CF$16 | ... DR38: =+SUMIFS(Opex_Assumptions!$F24:$M24,Opex_Assumptions!$F$7:$M$7,DR$7)*'Income Statement'!DH$16
B39: Payroll Taxes | F39: =+SUMIFS($AA39:$DR39,$AA$7:$DR$7,F$7) | G39: =+SUMIFS($AA39:$DR39,$AA$7:$DR$7,G$7) | H39: =+SUMIFS($AA39:$DR39,$AA$7:$DR$7,H$7) | I39: =+SUMIFS($AA39:$DR39,$AA$7:$DR$7,I$7) | J39: =+SUMIFS($AA39:$DR39,$AA$7:$DR$7,J$7) | K39: =+SUMIFS($AA39:$DR39,$AA$7:$DR$7,K$7) | L39: =+SUMIFS($AA39:$DR39,$AA$7:$DR$7,L$7) | M39: =+SUMIFS($AA39:$DR39,$AA$7:$DR$7,M$7) | AA39: 60.552332 | AB39: 56.658365 | AC39: 44.501384 | AD39: 50.177867 | AE39: 46.279442 | AF39: 45.870312 | AG39: 51.41522 | AH39: 43.115465 | AI39: 45.672247 | AJ39: 43.271062 | AK39: 44.179432 | AL39: 49.990943 | AM39: 73.898092 | AN39: 61.981946 | AO39: 53.490804 | AP39: 53.055752 | AQ39: 56.456379 | AR39: 55.633868 | AS39: 54.915292 | AT39: 52.004455 | AU39: 48.458021 | AV39: 49.776036 | AW39: 48.812296 | AX39: 49.583527 | AY39: 63.929311 | AZ39: 56.468352 | BA39: 45.267013 | BB39: 45.771873 | BC39: 44.728165 | BD39: 54.787827 | BE39: 44.449302 | BF39: 43.147998 | BG39: 38.402983 | BH39: 52.841979 | BI39: 44.21465 | BJ39: 54.530706 | BK39: 96.135 | BL39: 84.945 | BM39: 79.794484 | BN39: 79.794484 | BO39: 79.794484 | BP39: 79.794484 | BQ39: 79.794484 | BR39: 79.794484 | BS39: 79.794484 | BT39: 79.794484 | BU39: 79.794484 | BV39: 79.794484 | BW39: 90.879287 | BX39: 90.879287 | BY39: 90.879287 | BZ39: 90.879287 | CA39: 90.879287 | CB39: 90.879287 | CC39: 90.879287 | CD39: 90.879287 | CE39: 90.879287 | CF39: 90.879287 | CG39: 90.879287 | CH39: 90.879287 | CI39: =+SUMIFS(Opex_Assumptions!$F25:$M25,Opex_Assumptions!$F$7:$M$7,CI$7)*CI$32 | CJ39: =+SUMIFS(Opex_Assumptions!$F25:$M25,Opex_Assumptions!$F$7:$M$7,CJ$7)*CJ$32 | CK39: =+SUMIFS(Opex_Assumptions!$F25:$M25,Opex_Assumptions!$F$7:$M$7,CK$7)*CK$32 | CL39: =+SUMIFS(Opex_Assumptions!$F25:$M25,Opex_Assumptions!$F$7:$M$7,CL$7)*CL$32 | CM39: =+SUMIFS(Opex_Assumptions!$F25:$M25,Opex_Assumptions!$F$7:$M$7,CM$7)*CM$32 | CN39: =+SUMIFS(Opex_Assumptions!$F25:$M25,Opex_Assumptions!$F$7:$M$7,CN$7)*CN$32 | CO39: =+SUMIFS(Opex_Assumptions!$F25:$M25,Opex_Assumptions!$F$7:$M$7,CO$7)*CO$32 | CP39: =+SUMIFS(Opex_Assumptions!$F25:$M25,Opex_Assumptions!$F$7:$M$7,CP$7)*CP$32 | ... DR39: =+SUMIFS(Opex_Assumptions!$F25:$M25,Opex_Assumptions!$F$7:$M$7,DR$7)*DR$32
B40: Commission | F40: =+SUMIFS($AA40:$DR40,$AA$7:$DR$7,F$7) | G40: =+SUMIFS($AA40:$DR40,$AA$7:$DR$7,G$7) | H40: =+SUMIFS($AA40:$DR40,$AA$7:$DR$7,H$7) | I40: =+SUMIFS($AA40:$DR40,$AA$7:$DR$7,I$7) | J40: =+SUMIFS($AA40:$DR40,$AA$7:$DR$7,J$7) | K40: =+SUMIFS($AA40:$DR40,$AA$7:$DR$7,K$7) | L40: =+SUMIFS($AA40:$DR40,$AA$7:$DR$7,L$7) | M40: =+SUMIFS($AA40:$DR40,$AA$7:$DR$7,M$7) | AA40: 10.54534 | AB40: 10.417 | AC40: 10.417 | AD40: 10.417 | AE40: 10.417 | AF40: 10.417 | AG40: 10.417 | AH40: 10.417 | AI40: 10.417 | AJ40: 10.417 | AK40: 10.417 | AL40: -90.015 | AM40: 10.41667 | AN40: 10.41667 | AO40: 10.41667 | AP40: 10.41667 | AQ40: 1.04167 | AR40: 1.04167 | AS40: 1.04167 | AT40: 1.04167 | AU40: 1.04166 | AV40: 1.04166 | AW40: 1.04166 | AX40: -21.60334 | AY40: 2.916 | AZ40: 2.916 | BA40: 2.916 | BB40: 2.916 | BC40: 1.042 | BD40: 1.042 | BE40: 1.042 | BF40: 1.042 | BG40: 1.042 | BH40: 1.042 | BI40: 1.042 | BJ40: -13.908 | BK40: 2.083 | BL40: 2.083 | BM40: 3.0834 | BN40: 3.0834 | BO40: 3.0834 | BP40: 3.0834 | BQ40: 3.0834 | BR40: 3.0834 | BS40: 3.0834 | BT40: 3.0834 | BU40: 3.0834 | BV40: 3.0834 | BW40: 3.0041667 | BX40: 3.0041667 | BY40: 3.0041667 | BZ40: 3.0041667 | CA40: 3.0041667 | CB40: 3.0041667 | CC40: 3.0041667 | CD40: 3.0041667 | CE40: 3.0041667 | CF40: 3.0041667 | CG40: 3.0041667 | CH40: 3.0041667 | CI40: =+SUMIFS(Opex_Assumptions!$F26:$M26,Opex_Assumptions!$F$7:$M$7,CI$7)*'Income Statement'!BY$16 | CJ40: =+SUMIFS(Opex_Assumptions!$F26:$M26,Opex_Assumptions!$F$7:$M$7,CJ$7)*'Income Statement'!BZ$16 | CK40: =+SUMIFS(Opex_Assumptions!$F26:$M26,Opex_Assumptions!$F$7:$M$7,CK$7)*'Income Statement'!CA$16 | CL40: =+SUMIFS(Opex_Assumptions!$F26:$M26,Opex_Assumptions!$F$7:$M$7,CL$7)*'Income Statement'!CB$16 | CM40: =+SUMIFS(Opex_Assumptions!$F26:$M26,Opex_Assumptions!$F$7:$M$7,CM$7)*'Income Statement'!CC$16 | CN40: =+SUMIFS(Opex_Assumptions!$F26:$M26,Opex_Assumptions!$F$7:$M$7,CN$7)*'Income Statement'!CD$16 | CO40: =+SUMIFS(Opex_Assumptions!$F26:$M26,Opex_Assumptions!$F$7:$M$7,CO$7)*'Income Statement'!CE$16 | CP40: =+SUMIFS(Opex_Assumptions!$F26:$M26,Opex_Assumptions!$F$7:$M$7,CP$7)*'Income Statement'!CF$16 | ... DR40: =+SUMIFS(Opex_Assumptions!$F26:$M26,Opex_Assumptions!$F$7:$M$7,DR$7)*'Income Statement'!DH$16
B41: Severance | F41: =+SUMIFS($AA41:$DR41,$AA$7:$DR$7,F$7) | G41: =+SUMIFS($AA41:$DR41,$AA$7:$DR$7,G$7) | H41: =+SUMIFS($AA41:$DR41,$AA$7:$DR$7,H$7) | I41: =+SUMIFS($AA41:$DR41,$AA$7:$DR$7,I$7) | J41: =+SUMIFS($AA41:$DR41,$AA$7:$DR$7,J$7) | K41: =+SUMIFS($AA41:$DR41,$AA$7:$DR$7,K$7) | L41: =+SUMIFS($AA41:$DR41,$AA$7:$DR$7,L$7) | M41: =+SUMIFS($AA41:$DR41,$AA$7:$DR$7,M$7) | AA41: 0 | AB41: 2.9 | AC41: 0 | AD41: 1.962 | AE41: 0 | AF41: 1.284 | AG41: 3.204 | AH41: 3.204 | AI41: 0 | AJ41: 1.534 | AK41: 0 | AL41: 1.865 | AM41: 1.442 | AN41: 4.95879 | AO41: 14.47558 | AP41: 8.01063 | AQ41: 0 | AR41: 1.692 | AS41: 3.111 | AT41: 2.247 | AU41: 1.127 | AV41: 2.761 | AW41: 56.495 | AX41: 14.874 | AY41: 0 | AZ41: 0 | BA41: 0 | BB41: 0 | BC41: 0 | BD41: 0 | BE41: 0 | BF41: 11.53764 | BG41: 24.26246 | BH41: 0 | BI41: 0 | BJ41: 0 | BK41: 0 | BL41: 0 | BM41: 1.5 | BN41: 1.5 | BO41: 1.5 | BP41: 1.5 | BQ41: 1.5 | BR41: 1.5 | BS41: 1.5 | BT41: 1.5 | BU41: 1.5 | BV41: 1.5 | BW41: 1.25 | BX41: 1.25 | BY41: 1.25 | BZ41: 1.25 | CA41: 1.25 | CB41: 1.25 | CC41: 1.25 | CD41: 1.25 | CE41: 1.25 | CF41: 1.25 | CG41: 1.25 | CH41: 1.25 | CI41: =+SUMIFS(Opex_Assumptions!$F27:$M27,Opex_Assumptions!$F$7:$M$7,CI$7)*CI$32 | CJ41: =+SUMIFS(Opex_Assumptions!$F27:$M27,Opex_Assumptions!$F$7:$M$7,CJ$7)*CJ$32 | CK41: =+SUMIFS(Opex_Assumptions!$F27:$M27,Opex_Assumptions!$F$7:$M$7,CK$7)*CK$32 | CL41: =+SUMIFS(Opex_Assumptions!$F27:$M27,Opex_Assumptions!$F$7:$M$7,CL$7)*CL$32 | CM41: =+SUMIFS(Opex_Assumptions!$F27:$M27,Opex_Assumptions!$F$7:$M$7,CM$7)*CM$32 | CN41: =+SUMIFS(Opex_Assumptions!$F27:$M27,Opex_Assumptions!$F$7:$M$7,CN$7)*CN$32 | CO41: =+SUMIFS(Opex_Assumptions!$F27:$M27,Opex_Assumptions!$F$7:$M$7,CO$7)*CO$32 | CP41: =+SUMIFS(Opex_Assumptions!$F27:$M27,Opex_Assumptions!$F$7:$M$7,CP$7)*CP$32 | ... DR41: =+SUMIFS(Opex_Assumptions!$F27:$M27,Opex_Assumptions!$F$7:$M$7,DR$7)*DR$32
B42: Benefits | F42: =+SUMIFS($AA42:$DR42,$AA$7:$DR$7,F$7) | G42: =+SUMIFS($AA42:$DR42,$AA$7:$DR$7,G$7) | H42: =+SUMIFS($AA42:$DR42,$AA$7:$DR$7,H$7) | I42: =+SUMIFS($AA42:$DR42,$AA$7:$DR$7,I$7) | J42: =+SUMIFS($AA42:$DR42,$AA$7:$DR$7,J$7) | K42: =+SUMIFS($AA42:$DR42,$AA$7:$DR$7,K$7) | L42: =+SUMIFS($AA42:$DR42,$AA$7:$DR$7,L$7) | M42: =+SUMIFS($AA42:$DR42,$AA$7:$DR$7,M$7) | AA42: 25.865805 | AB42: 24.971683 | AC42: 23.866328 | AD42: 26.021176 | AE42: 24.789342 | AF42: 22.752325 | AG42: 24.526407 | AH42: 21.397958 | AI42: 22.871615 | AJ42: 22.641084 | AK42: 22.719529 | AL42: 30.162171 | AM42: 28.54002 | AN42: 26.945789 | AO42: 31.148391 | AP42: 28.14948 | AQ42: 30.855865 | AR42: 40.49791 | AS42: 24.572006 | AT42: 32.69893 | AU42: 33.790297 | AV42: 28.357617 | AW42: 36.46107 | AX42: 35.690581 | AY42: 36.601952 | AZ42: 27.743828 | BA42: 30.043604 | BB42: 29.373668 | BC42: 28.395411 | BD42: 33.975106 | BE42: 26.01429 | BF42: 28.67577 | BG42: 32.348766 | BH42: 20.771173 | BI42: 24.513491 | BJ42: 31.10246 | BK42: 48.807 | BL42: 44.172 | BM42: 51.022157 | BN42: 51.022157 | BO42: 51.022157 | BP42: 51.022157 | BQ42: 51.022157 | BR42: 51.022157 | BS42: 51.022157 | BT42: 51.022157 | BU42: 51.022157 | BV42: 51.022157 | BW42: 57.473848 | BX42: 57.473848 | BY42: 57.473848 | BZ42: 57.473848 | CA42: 57.473848 | CB42: 57.473848 | CC42: 57.473848 | CD42: 57.473848 | CE42: 57.473848 | CF42: 57.473848 | CG42: 57.473848 | CH42: 57.473848 | CI42: =+SUMIFS(Opex_Assumptions!$F28:$M28,Opex_Assumptions!$F$7:$M$7,CI$7)*CI$32 | CJ42: =+SUMIFS(Opex_Assumptions!$F28:$M28,Opex_Assumptions!$F$7:$M$7,CJ$7)*CJ$32 | CK42: =+SUMIFS(Opex_Assumptions!$F28:$M28,Opex_Assumptions!$F$7:$M$7,CK$7)*CK$32 | CL42: =+SUMIFS(Opex_Assumptions!$F28:$M28,Opex_Assumptions!$F$7:$M$7,CL$7)*CL$32 | CM42: =+SUMIFS(Opex_Assumptions!$F28:$M28,Opex_Assumptions!$F$7:$M$7,CM$7)*CM$32 | CN42: =+SUMIFS(Opex_Assumptions!$F28:$M28,Opex_Assumptions!$F$7:$M$7,CN$7)*CN$32 | CO42: =+SUMIFS(Opex_Assumptions!$F28:$M28,Opex_Assumptions!$F$7:$M$7,CO$7)*CO$32 | CP42: =+SUMIFS(Opex_Assumptions!$F28:$M28,Opex_Assumptions!$F$7:$M$7,CP$7)*CP$32 | ... DR42: =+SUMIFS(Opex_Assumptions!$F28:$M28,Opex_Assumptions!$F$7:$M$7,DR$7)*DR$32
B43: Payroll Processing Costs | F43: =+SUMIFS($AA43:$DR43,$AA$7:$DR$7,F$7) | G43: =+SUMIFS($AA43:$DR43,$AA$7:$DR$7,G$7) | H43: =+SUMIFS($AA43:$DR43,$AA$7:$DR$7,H$7) | I43: =+SUMIFS($AA43:$DR43,$AA$7:$DR$7,I$7) | J43: =+SUMIFS($AA43:$DR43,$AA$7:$DR$7,J$7) | K43: =+SUMIFS($AA43:$DR43,$AA$7:$DR$7,K$7) | L43: =+SUMIFS($AA43:$DR43,$AA$7:$DR$7,L$7) | M43: =+SUMIFS($AA43:$DR43,$AA$7:$DR$7,M$7) | AA43: 16.98665 | AB43: 4.51699 | AC43: 9.40076 | AD43: 5.40385 | AE43: 6.36237 | AF43: 2.55402 | AG43: 9.93554 | AH43: 2.67452 | AI43: 1.94859 | AJ43: 16.82217 | AK43: 13.80581 | AL43: -28.4151 | AM43: 11.59276 | AN43: 4.27864 | AO43: 2.71976 | AP43: 3.00188 | AQ43: 3.6677 | AR43: 2.51254 | AS43: 2.87113 | AT43: 2.74359 | AU43: 2.73942 | AV43: 2.40357 | AW43: 2.52347 | AX43: 3.28616 | AY43: 3.82368 | AZ43: 2.47282 | BA43: 4.16254 | BB43: 2.52833 | BC43: 2.21195 | BD43: 5.41118 | BE43: 6.69116 | BF43: 10.86671 | BG43: 15.84396 | BH43: 5.29888 | BI43: 6.39586 | BJ43: 7.47858 | BK43: =+BJ43 | BL43: =+BK43 | BM43: =+BL43 | BN43: =+BM43 | BO43: =+BN43 | BP43: =+BO43 | BQ43: =+BP43 | BR43: =+BQ43 | ... CH43: =+CG43 | CI43: =+SUMIFS(Opex_Assumptions!$F29:$M29,Opex_Assumptions!$F$7:$M$7,CI$7)*CI$32 | CJ43: =+SUMIFS(Opex_Assumptions!$F29:$M29,Opex_Assumptions!$F$7:$M$7,CJ$7)*CJ$32 | CK43: =+SUMIFS(Opex_Assumptions!$F29:$M29,Opex_Assumptions!$F$7:$M$7,CK$7)*CK$32 | CL43: =+SUMIFS(Opex_Assumptions!$F29:$M29,Opex_Assumptions!$F$7:$M$7,CL$7)*CL$32 | CM43: =+SUMIFS(Opex_Assumptions!$F29:$M29,Opex_Assumptions!$F$7:$M$7,CM$7)*CM$32 | CN43: =+SUMIFS(Opex_Assumptions!$F29:$M29,Opex_Assumptions!$F$7:$M$7,CN$7)*CN$32 | CO43: =+SUMIFS(Opex_Assumptions!$F29:$M29,Opex_Assumptions!$F$7:$M$7,CO$7)*CO$32 | CP43: =+SUMIFS(Opex_Assumptions!$F29:$M29,Opex_Assumptions!$F$7:$M$7,CP$7)*CP$32 | ... DR43: =+SUMIFS(Opex_Assumptions!$F29:$M29,Opex_Assumptions!$F$7:$M$7,DR$7)*DR$32
B44: Payroll & Benefits | F44: =+SUMIFS($AA44:$DR44,$AA$7:$DR$7,F$7) | G44: =+SUMIFS($AA44:$DR44,$AA$7:$DR$7,G$7) | H44: =+SUMIFS($AA44:$DR44,$AA$7:$DR$7,H$7) | I44: =+SUMIFS($AA44:$DR44,$AA$7:$DR$7,I$7) | J44: =+SUMIFS($AA44:$DR44,$AA$7:$DR$7,J$7) | K44: =+SUMIFS($AA44:$DR44,$AA$7:$DR$7,K$7) | L44: =+SUMIFS($AA44:$DR44,$AA$7:$DR$7,L$7) | M44: =+SUMIFS($AA44:$DR44,$AA$7:$DR$7,M$7) | AA44: =SUM(AA37:AA43) | AB44: =SUM(AB37:AB43) | AC44: =SUM(AC37:AC43) | AD44: =SUM(AD37:AD43) | AE44: =SUM(AE37:AE43) | AF44: =SUM(AF37:AF43) | AG44: =SUM(AG37:AG43) | AH44: =SUM(AH37:AH43) | ... DR44: =SUM(DR37:DR43)
