Workbook
Name _____________________MHA1: {"rtn",#N/A,FALSE,"RTN";"tables",#N/A,FALSE,"RTN";"cf",#N/A,FALSE,"CF";"stats",#N/A,FALSE,"Stats";"prop",#N/A,FALSE,"Prop"}
Name _____________________T123456: {"COUNT",#N/A,FALSE,"AB"}
Name _____________________T12347: {"COUNT",#N/A,FALSE,"AB"}
Name __________________T123456: {"COUNT",#N/A,FALSE,"AB"}
Name __________________T12347: {"COUNT",#N/A,FALSE,"AB"}
Name ________________MHA1: {"rtn",#N/A,FALSE,"RTN";"tables",#N/A,FALSE,"RTN";"cf",#N/A,FALSE,"CF";"stats",#N/A,FALSE,"Stats";"prop",#N/A,FALSE,"Prop"}
Name ______________T123456: {"COUNT",#N/A,FALSE,"AB"}
Name ______________T12347: {"COUNT",#N/A,FALSE,"AB"}
Name _____________MHA1: {"rtn",#N/A,FALSE,"RTN";"tables",#N/A,FALSE,"RTN";"cf",#N/A,FALSE,"CF";"stats",#N/A,FALSE,"Stats";"prop",#N/A,FALSE,"Prop"}
Name ___________MHA1: {"rtn",#N/A,FALSE,"RTN";"tables",#N/A,FALSE,"RTN";"cf",#N/A,FALSE,"CF";"stats",#N/A,FALSE,"Stats";"prop",#N/A,FALSE,"Prop"}
Name __________MHA1: {"rtn",#N/A,FALSE,"RTN";"tables",#N/A,FALSE,"RTN";"cf",#N/A,FALSE,"CF";"stats",#N/A,FALSE,"Stats";"prop",#N/A,FALSE,"Prop"}
Name _________MHA1: {"rtn",#N/A,FALSE,"RTN";"tables",#N/A,FALSE,"RTN";"cf",#N/A,FALSE,"CF";"stats",#N/A,FALSE,"Stats";"prop",#N/A,FALSE,"Prop"}
Name _________MHA1_1: {"rtn",#N/A,FALSE,"RTN";"tables",#N/A,FALSE,"RTN";"cf",#N/A,FALSE,"CF";"stats",#N/A,FALSE,"Stats";"prop",#N/A,FALSE,"Prop"}
Name ________MHA1: {"rtn",#N/A,FALSE,"RTN";"tables",#N/A,FALSE,"RTN";"cf",#N/A,FALSE,"CF";"stats",#N/A,FALSE,"Stats";"prop",#N/A,FALSE,"Prop"}
Name ________MHA1_1: {"rtn",#N/A,FALSE,"RTN";"tables",#N/A,FALSE,"RTN";"cf",#N/A,FALSE,"CF";"stats",#N/A,FALSE,"Stats";"prop",#N/A,FALSE,"Prop"}
Name _______MHA1: {"rtn",#N/A,FALSE,"RTN";"tables",#N/A,FALSE,"RTN";"cf",#N/A,FALSE,"CF";"stats",#N/A,FALSE,"Stats";"prop",#N/A,FALSE,"Prop"}
Name _______MHA1_1: {"rtn",#N/A,FALSE,"RTN";"tables",#N/A,FALSE,"RTN";"cf",#N/A,FALSE,"CF";"stats",#N/A,FALSE,"Stats";"prop",#N/A,FALSE,"Prop"}
Name _______T123456: {"COUNT",#N/A,FALSE,"AB"}
Name _______T12347: {"COUNT",#N/A,FALSE,"AB"}
Name ______MHA1: {"rtn",#N/A,FALSE,"RTN";"tables",#N/A,FALSE,"RTN";"cf",#N/A,FALSE,"CF";"stats",#N/A,FALSE,"Stats";"prop",#N/A,FALSE,"Prop"}
Name ______MHA1_1: {"rtn",#N/A,FALSE,"RTN";"tables",#N/A,FALSE,"RTN";"cf",#N/A,FALSE,"CF";"stats",#N/A,FALSE,"Stats";"prop",#N/A,FALSE,"Prop"}
Name _____MHA1: {"rtn",#N/A,FALSE,"RTN";"tables",#N/A,FALSE,"RTN";"cf",#N/A,FALSE,"CF";"stats",#N/A,FALSE,"Stats";"prop",#N/A,FALSE,"Prop"}
Name _____MHA1_1: {"rtn",#N/A,FALSE,"RTN";"tables",#N/A,FALSE,"RTN";"cf",#N/A,FALSE,"CF";"stats",#N/A,FALSE,"Stats";"prop",#N/A,FALSE,"Prop"}
Name _____New2: {"TOTAL",#N/A,FALSE,"A";"FISCAL94",#N/A,FALSE,"A";"FISCAL95",#N/A,FALSE,"A";"FISCAL96",#N/A,FALSE,"A";"misc page",#N/A,FALSE,"A"}
Name _____R: {#N/A,#N/A,FALSE,"Minors";#N/A,#N/A,FALSE,"96CAPREV"}
Name _____T123456: {"COUNT",#N/A,FALSE,"AB"}
Name _____T12347: {"COUNT",#N/A,FALSE,"AB"}
Name ____DCF2: {#N/A,#N/A,TRUE,"DCF Summary (2)";#N/A,#N/A,TRUE,"DCF Summary";#N/A,"Middle Case Drivers",TRUE,"DCF"}
Name ____JLC1: {#N/A,#N/A,TRUE,"97plnfpg"}
Name ____JLC3: {#N/A,#N/A,FALSE,"J97plnfp"}
Name ____MHA1: {"rtn",#N/A,FALSE,"RTN";"tables",#N/A,FALSE,"RTN";"cf",#N/A,FALSE,"CF";"stats",#N/A,FALSE,"Stats";"prop",#N/A,FALSE,"Prop"}
Name ____MHA1_1: {"rtn",#N/A,FALSE,"RTN";"tables",#N/A,FALSE,"RTN";"cf",#N/A,FALSE,"CF";"stats",#N/A,FALSE,"Stats";"prop",#N/A,FALSE,"Prop"}
Name ____New2: {"TOTAL",#N/A,FALSE,"A";"FISCAL94",#N/A,FALSE,"A";"FISCAL95",#N/A,FALSE,"A";"FISCAL96",#N/A,FALSE,"A";"misc page",#N/A,FALSE,"A"}
Name ____R: {#N/A,#N/A,FALSE,"Minors";#N/A,#N/A,FALSE,"96CAPREV"}
Name ____T123456: {"COUNT",#N/A,FALSE,"AB"}
Name ____T12347: {"COUNT",#N/A,FALSE,"AB"}
Name ____wrn2: {#N/A,#N/A,FALSE,"ASSUMPTIONS";#N/A,#N/A,FALSE,"Valuation Summary";"page1",#N/A,FALSE,"PRESENTATION";"page2",#N/A,FALSE,"PRESENTATION";#N/A,#N/A,FALSE,"ORIGINAL_ROLLBACK"}
Name ____wrn3: {#N/A,#N/A,FALSE,"ASSUMPTIONS";#N/A,#N/A,FALSE,"Valuation Summary";"page1",#N/A,FALSE,"PRESENTATION";"page2",#N/A,FALSE,"PRESENTATION";#N/A,#N/A,FALSE,"ORIGINAL_ROLLBACK"}
Name ___aaa1: {#N/A,#N/A,FALSE,"Model";#N/A,#N/A,FALSE,"Division"}
Name ___c: {#N/A,#N/A,FALSE,"Layout Cash Flow"}
Name ___DCF2: {#N/A,#N/A,TRUE,"DCF Summary (2)";#N/A,#N/A,TRUE,"DCF Summary";#N/A,"Middle Case Drivers",TRUE,"DCF"}
Name ___fy97: {#N/A,#N/A,FALSE,"FY97";#N/A,#N/A,FALSE,"FY98";#N/A,#N/A,FALSE,"FY99";#N/A,#N/A,FALSE,"FY00";#N/A,#N/A,FALSE,"FY01"}
Name ___MHA1: {"rtn",#N/A,FALSE,"RTN";"tables",#N/A,FALSE,"RTN";"cf",#N/A,FALSE,"CF";"stats",#N/A,FALSE,"Stats";"prop",#N/A,FALSE,"Prop"}
Name ___MHA1_1: {"rtn",#N/A,FALSE,"RTN";"tables",#N/A,FALSE,"RTN";"cf",#N/A,FALSE,"CF";"stats",#N/A,FALSE,"Stats";"prop",#N/A,FALSE,"Prop"}
Name ___New2: {"TOTAL",#N/A,FALSE,"A";"FISCAL94",#N/A,FALSE,"A";"FISCAL95",#N/A,FALSE,"A";"FISCAL96",#N/A,FALSE,"A";"misc page",#N/A,FALSE,"A"}
Name ___r: {"consolidated",#N/A,FALSE,"Sheet1";"cms",#N/A,FALSE,"Sheet1";"fse",#N/A,FALSE,"Sheet1"}
Name ___T12347: {"COUNT",#N/A,FALSE,"AB"}
Name ___wrn1: {#N/A,#N/A,FALSE,"DCF";#N/A,#N/A,FALSE,"WACC";#N/A,#N/A,FALSE,"Sales_EBIT";#N/A,#N/A,FALSE,"Capex_Depreciation";#N/A,#N/A,FALSE,"WC";#N/A,#N/A,FALSE,"Interest";#N/A,#N/A,FALSE,"Assumptions"}
Name __a1: {#N/A,#N/A,FALSE,"Pharm";#N/A,#N/A,FALSE,"WWCM"}
Name __A11: {#N/A,#N/A,FALSE,"Umsatz 99";#N/A,#N/A,FALSE,"ER 99 "}
Name __aaa1: {#N/A,#N/A,FALSE,"REPORT"}
Name __aas1: {#N/A,#N/A,FALSE,"REPORT"}
Name __ACS2000: {#N/A,#N/A,FALSE,"REPORT"}
Name __APW_RESTORE_DATA104__: #REF!,#REF!,#REF!,#REF!,#REF!,#REF!,#REF!,#REF!,#REF!,#REF!
Name __APW_RESTORE_DATA105__: #REF!,#REF!,#REF!,#REF!,#REF!,#REF!,#REF!,#REF!,#REF!,#REF!
Name __APW_RESTORE_DATA106__: #REF!,#REF!,#REF!,#REF!,#REF!,#REF!,#REF!,#REF!,#REF!,#REF!
Name __APW_RESTORE_DATA107__: #REF!,#REF!,#REF!,#REF!,#REF!,#REF!,#REF!,#REF!,#REF!,#REF!
Name __b111: {#N/A,#N/A,FALSE,"Pharm";#N/A,#N/A,FALSE,"WWCM"}
Name __c: {"Fiesta Facer Page",#N/A,FALSE,"Q_C_S";"Fiesta Main Page",#N/A,FALSE,"V_L";"Fiesta 95BP Struct",#N/A,FALSE,"StructBP";"Fiesta Post 95BP Struct",#N/A,FALSE,"AdjStructBP"}
Name __DCF2: {#N/A,#N/A,TRUE,"DCF Summary (2)";#N/A,#N/A,TRUE,"DCF Summary";#N/A,"Middle Case Drivers",TRUE,"DCF"}

Sheet Cover
B5: Financial Databook
B7: Table of Contents:
B8: Summary
B9: Income Statement
B10: Calculations
B11: Revenue_Calcs
B12: COGS_Calcs
B13: Opex_Calcs
B14: Bookings to Revenue_Calcs
B15: Assumptions
B16: Revenue_Assumptions
B17: COGS_Assumptions
B18: Opex_Assumptions
B20: As of: | C20: 44286

Sheet Summary
B2: Summary Income Statement | H2: 2022 Run-Rate
B3: ($ in millions) | D3: 2019 | E3: =+D3+1 -> 2020 | F3: =+E3+1 -> 2021 | G3: =+F3+1 -> 2022 | H3: Run-Rate | I3: =+G3+1 -> 2023 | J3: =+I3+1 -> 2024 | K3: =+J3+1 -> 2025 | L3: =+K3+1 -> 2026
B5: =+'Income Statement'!B12 -> Licensing | D5: =+'Income Statement'!F12/10^3 -> 0 | E5: =+'Income Statement'!G12/10^3 -> 0 | F5: =+'Income Statement'!H12/10^3 -> 0 | G5: =+'Income Statement'!I12/10^3 -> 0 | H5: =+'Income Statement'!O12/10^3 -> 0.992899 | I5: =+'Income Statement'!J12/10^3 -> 0 | J5: =+'Income Statement'!K12/10^3 -> 0 | K5: =+'Income Statement'!L12/10^3 -> 0 | L5: =+'Income Statement'!M12/10^3 -> 0
B6: =+'Income Statement'!B13 -> Managed Services | D6: =+'Income Statement'!F13/10^3 -> 0 | E6: =+'Income Statement'!G13/10^3 -> 0 | F6: =+'Income Statement'!H13/10^3 -> 0 | G6: =+'Income Statement'!I13/10^3 -> 0 | H6: =+'Income Statement'!O13/10^3 -> 0 | I6: =+'Income Statement'!J13/10^3 -> 0 | J6: =+'Income Statement'!K13/10^3 -> 0 | K6: =+'Income Statement'!L13/10^3 -> 0 | L6: =+'Income Statement'!M13/10^3 -> 0
B7: =+'Income Statement'!B14 -> Implementation | D7: =+'Income Statement'!F14/10^3 -> 0 | E7: =+'Income Statement'!G14/10^3 -> 0 | F7: =+'Income Statement'!H14/10^3 -> 0 | G7: =+'Income Statement'!I14/10^3 -> 0 | H7: =+'Income Statement'!O14/10^3 -> 0 | I7: =+'Income Statement'!J14/10^3 -> 0 | J7: =+'Income Statement'!K14/10^3 -> 0 | K7: =+'Income Statement'!L14/10^3 -> 0 | L7: =+'Income Statement'!M14/10^3 -> 0
B8: =+'Income Statement'!B15 -> Other Revenue | D8: =+'Income Statement'!F15/10^3 -> 0 | E8: =+'Income Statement'!G15/10^3 -> 0 | F8: =+'Income Statement'!H15/10^3 -> 0 | G8: =+'Income Statement'!I15/10^3 -> 0 | H8: =+'Income Statement'!O15/10^3 -> 0 | I8: =+'Income Statement'!J15/10^3 -> 0 | J8: =+'Income Statement'!K15/10^3 -> 0 | K8: =+'Income Statement'!L15/10^3 -> 0 | L8: =+'Income Statement'!M15/10^3 -> 0
B9: =+'Income Statement'!B16 -> Total Revenue | D9: =+'Income Statement'!F16/10^3 -> 0 | E9: =+'Income Statement'!G16/10^3 -> 0 | F9: =+'Income Statement'!H16/10^3 -> 0 | G9: =+'Income Statement'!I16/10^3 -> 0 | H9: =+'Income Statement'!O16/10^3 -> 0.992899 | I9: =+'Income Statement'!J16/10^3 -> 0 | J9: =+'Income Statement'!K16/10^3 -> 0 | K9: =+'Income Statement'!L16/10^3 -> 0 | L9: =+'Income Statement'!M16/10^3 -> 0
B10: % Growth | E10: =+E9/D9-1 -> #DIV/0! | F10: =+F9/E9-1 -> #DIV/0! | G10: =+G9/F9-1 -> #DIV/0! | I10: =+I9/G9-1 -> #DIV/0! | J10: =+J9/I9-1 -> #DIV/0! | K10: =+K9/J9-1 -> #DIV/0! | L10: =+L9/K9-1 -> #DIV/0!
B12: Cost of Sales | D12: =+'Income Statement'!F22/10^3 -> 0 | E12: =+'Income Statement'!G22/10^3 -> 0 | F12: =+'Income Statement'!H22/10^3 -> 0 | G12: =+'Income Statement'!I22/10^3 -> 0 | H12: =+'Income Statement'!O22/10^3 -> 0.10921889 | I12: =+'Income Statement'!J22/10^3 -> 0 | J12: =+'Income Statement'!K22/10^3 -> 0 | K12: =+'Income Statement'!L22/10^3 -> 0 | L12: =+'Income Statement'!M22/10^3 -> 0
B13: Gross Profit | D13: =+D9-D12 -> 0 | E13: =+E9-E12 -> 0 | F13: =+F9-F12 -> 0 | G13: =+G9-G12 -> 0 | H13: =+H9-H12 -> 0.88368011 | I13: =+I9-I12 -> 0 | J13: =+J9-J12 -> 0 | K13: =+K9-K12 -> 0 | L13: =+L9-L12 -> 0
B14: % Gross Margin | D14: =+D13/D$9 -> #DIV/0! | E14: =+E13/E$9 -> #DIV/0! | F14: =+F13/F$9 -> #DIV/0! | G14: =+G13/G$9 -> #DIV/0! | H14: =+H13/H$9 -> 0.89 | I14: =+I13/I$9 -> #DIV/0! | J14: =+J13/J$9 -> #DIV/0! | K14: =+K13/K$9 -> #DIV/0! | L14: =+L13/L$9 -> #DIV/0!
B16: =+'Income Statement'!B27 -> Payroll & Benefits | D16: =+'Income Statement'!F27/10^3 -> 0 | E16: =+'Income Statement'!G27/10^3 -> 0 | F16: =+'Income Statement'!H27/10^3 -> 0 | G16: =+'Income Statement'!I27/10^3 -> 0 | H16: =+'Income Statement'!O27/10^3 -> 0 | I16: =+'Income Statement'!J27/10^3 -> 0 | J16: =+'Income Statement'!K27/10^3 -> 0 | K16: =+'Income Statement'!L27/10^3 -> 0 | L16: =+'Income Statement'!M27/10^3 -> 0
B17: Rent | D17: =+'Income Statement'!F28/10^3 -> 0 | E17: =+'Income Statement'!G28/10^3 -> 0 | F17: =+'Income Statement'!H28/10^3 -> 0 | G17: =+'Income Statement'!I28/10^3 -> 0 | H17: =+'Income Statement'!O28/10^3 -> 0 | I17: =+'Income Statement'!J28/10^3 -> 0 | J17: =+'Income Statement'!K28/10^3 -> 0 | K17: =+'Income Statement'!L28/10^3 -> 0 | L17: =+'Income Statement'!M28/10^3 -> 0
B18: Sales & Marketing | D18: =+'Income Statement'!F30/10^3 -> 0 | E18: =+'Income Statement'!G30/10^3 -> 0 | F18: =+'Income Statement'!H30/10^3 -> 0 | G18: =+'Income Statement'!I30/10^3 -> 0 | H18: =+'Income Statement'!O30/10^3 -> 0 | I18: =+'Income Statement'!J30/10^3 -> 0 | J18: =+'Income Statement'!K30/10^3 -> 0 | K18: =+'Income Statement'!L30/10^3 -> 0 | L18: =+'Income Statement'!M30/10^3 -> 0
B19: Other Opex | D19: =+SUM('Income Statement'!F29,'Income Statement'!F31:F33)/10^3 -> 0 | E19: =+SUM('Income Statement'!G29,'Income Statement'!G31:G33)/10^3 -> 0 | F19: =+SUM('Income Statement'!H29,'Income Statement'!H31:H33)/10^3 -> 0 | G19: =+SUM('Income Statement'!I29,'Income Statement'!I31:I33)/10^3 -> 0 | H19: =+SUM('Income Statement'!O29,'Income Statement'!O31:O33)/10^3 -> 0 | I19: =+SUM('Income Statement'!J29,'Income Statement'!J31:J33)/10^3 -> 0 | J19: =+SUM('Income Statement'!K29,'Income Statement'!K31:K33)/10^3 -> 0 | K19: =+SUM('Income Statement'!L29,'Income Statement'!L31:L33)/10^3 -> 0 | L19: =+SUM('Income Statement'!M29,'Income Statement'!M31:M33)/10^3 -> 0
B20: Other I/E | D20: =+'Income Statement'!F35/10^3 -> 0 | E20: =+'Income Statement'!G35/10^3 -> 0 | F20: =+'Income Statement'!H35/10^3 -> 0 | G20: =+'Income Statement'!I35/10^3 -> 0 | H20: =+'Income Statement'!O35/10^3 -> 0 | I20: =+'Income Statement'!J35/10^3 -> 0 | J20: =+'Income Statement'!K35/10^3 -> 0 | K20: =+'Income Statement'!L35/10^3 -> 0 | L20: =+'Income Statement'!M35/10^3 -> 0
B21: Reported EBITDA | D21: =+D13-SUM(D16:D20) -> 0 | E21: =+E13-SUM(E16:E20) -> 0 | F21: =+F13-SUM(F16:F20) -> 0 | G21: =+G13-SUM(G16:G20) -> 0 | H21: =+H13-SUM(H16:H20) -> 0.88368011 | I21: =+I13-SUM(I16:I20) -> 0 | J21: =+J13-SUM(J16:J20) -> 0 | K21: =+K13-SUM(K16:K20) -> 0 | L21: =+L13-SUM(L16:L20) -> 0
B22: % Margin | D22: =+D21/D$9 -> #DIV/0! | E22: =+E21/E$9 -> #DIV/0! | F22: =+F21/F$9 -> #DIV/0! | G22: =+G21/G$9 -> #DIV/0! | H22: =+H21/H$9 -> 0.89 | I22: =+I21/I$9 -> #DIV/0! | J22: =+J21/J$9 -> #DIV/0! | K22: =+K21/K$9 -> #DIV/0! | L22: =+L21/L$9 -> #DIV/0!
B24: Adjustments | D24: =+'Income Statement'!F48/10^3 -> 0 | E24: =+'Income Statement'!G48/10^3 -> 0 | F24: =+'Income Statement'!H48/10^3 -> 0 | G24: =+'Income Statement'!I48/10^3 -> 0 | H24: =+'Income Statement'!O48/10^3 -> 0 | I24: =+'Income Statement'!J48/10^3 -> 0 | J24: =+'Income Statement'!K48/10^3 -> 0 | K24: =+'Income Statement'!L48/10^3 -> 0 | L24: =+'Income Statement'!M48/10^3 -> 0
B25: Adjusted EBITDA | D25: =+D21+D24 -> 0 | E25: =+E21+E24 -> 0 | F25: =+F21+F24 -> 0 | G25: =+G21+G24 -> 0 | H25: =+H21+H24 -> 0.88368011 | I25: =+I21+I24 -> 0 | J25: =+J21+J24 -> 0 | K25: =+K21+K24 -> 0 | L25: =+L21+L24 -> 0
B26: % Margin | D26: =+D25/D$9 -> #DIV/0! | E26: =+E25/E$9 -> #DIV/0! | F26: =+F25/F$9 -> #DIV/0! | G26: =+G25/G$9 -> #DIV/0! | H26: =+H25/H$9 -> 0.89 | I26: =+I25/I$9 -> #DIV/0! | J26: =+J25/J$9 -> #DIV/0! | K26: =+K25/K$9 -> #DIV/0! | L26: =+L25/L$9 -> #DIV/0!
B27: Check | D27: =+D25-'Income Statement'!F50/10^3 -> 0 | E27: =+E25-'Income Statement'!G50/10^3 -> 0 | F27: =+F25-'Income Statement'!H50/10^3 -> 0 | G27: =+G25-'Income Statement'!I50/10^3 -> 0 | H27: =+H25-'Income Statement'!O50/10^3 -> 0 | I27: =+I25-'Income Statement'!J50/10^3 -> 0 | J27: =+J25-'Income Statement'!K50/10^3 -> 0 | K27: =+K25-'Income Statement'!L50/10^3 -> 0 | L27: =+L25-'Income Statement'!M50/10^3 -> 0 | M27: =+M25-'Income Statement'!N50/10^3 -> 0

Sheet Model ->

Sheet Income Statement
B2: Project Shasta
B3: {=MID(CELL("filename",A1),FIND("]",CELL("filename",A1))+1,255)} -> #VALUE!
B4: Spring 2022
B5: CONFIDENTIAL
F7: 2019 | G7: =+F7+1 -> 2020 | H7: =+G7+1 -> 2021 | I7: =+H7+1 -> 2022 | J7: =+I7+1 -> 2023 | K7: =+J7+1 -> 2024 | L7: =+K7+1 -> 2025 | M7: =+L7+1 -> 2026 | O7: =+I7 -> 2022 | Q7: =+YEAR(Q8) -> 2019 | R7: =+YEAR(R8) -> 2019 | S7: =+YEAR(S8) -> 2019 | T7: =+YEAR(T8) -> 2019 | U7: =+YEAR(U8) -> 2019 | V7: =+YEAR(V8) -> 2019 | W7: =+YEAR(W8) -> 2019 | X7: =+YEAR(X8) -> 2019 | ... DH7: =+YEAR(DH8) -> 2026 | DJ7: Growth / Margin Analysis
F8: =+DATE(F7,12,31) -> 43830 | G8: =+DATE(G7,12,31) -> 44196 | H8: =+DATE(H7,12,31) -> 44561 | I8: =+DATE(I7,12,31) -> 44926 | J8: =+DATE(J7,12,31) -> 45291 | K8: =+DATE(K7,12,31) -> 45657 | L8: =+DATE(L7,12,31) -> 46022 | M8: =+DATE(M7,12,31) -> 46387 | O8: =+I8 -> 44926 | Q8: 43496 | R8: =+EOMONTH(Q8,1) -> 43524 | S8: =+EOMONTH(R8,1) -> 43555 | T8: =+EOMONTH(S8,1) -> 43585 | U8: =+EOMONTH(T8,1) -> 43616 | V8: =+EOMONTH(U8,1) -> 43646 | W8: =+EOMONTH(V8,1) -> 43677 | X8: =+EOMONTH(W8,1) -> 43708 | Y8: =+EOMONTH(X8,1) -> 43738 | ... DH8: =+EOMONTH(DG8,1) -> 46387 | DJ8: 2019 | DK8: =+DJ8+1 -> 2020 | DL8: =+DK8+1 -> 2021 | DM8: =+DL8+1 -> 2022 | DN8: =+DM8+1 -> 2023 | DO8: =+DN8+1 -> 2024 | DP8: =+DO8+1 -> 2025 | DQ8: =+DP8+1 -> 2026
B9: $ in thousands | F9: Actual | G9: Actual | H9: Actual | I9: Budget | J9: Projection | K9: Projection | L9: Projection | M9: Projection | O9: Run Rate | Q9: Actual | R9: Actual | S9: Actual | T9: Actual | U9: Actual | V9: Actual | W9: Actual | X9: Actual | Y9: Actual | Z9: Actual | AA9: Actual | AB9: Actual | AC9: Actual | AD9: Actual | AE9: Actual | AF9: Actual | AG9: Actual | AH9: Actual | AI9: Actual | AJ9: Actual | AK9: Actual | AL9: Actual | AM9: Actual | AN9: Actual | AO9: Actual | AP9: Actual | AQ9: Actual | AR9: Actual | AS9: Actual | AT9: Actual | AU9: Actual | AV9: Actual | AW9: Actual | AX9: Actual | AY9: Actual | AZ9: Actual | BA9: Actual | BB9: Actual | BC9: Actual | BD9: Budget | BE9: Budget | BF9: Budget | BG9: Budget | BH9: Budget | BI9: Budget | BJ9: Budget | BK9: Budget | BL9: Budget | BM9: Projection | BN9: Projection | BO9: Projection | BP9: Projection | BQ9: Projection | BR9: Projection | BS9: Projection | BT9: Projection | BU9: Projection | BV9: Projection | BW9: Projection | BX9: Projection | BY9: Projection | BZ9: Projection | CA9: Projection | CB9: Projection | CC9: Projection | CD9: Projection | CE9: Projection | CF9: Projection | CG9: Projection | CH9: Projection | CI9: Projection | CJ9: Projection | CK9: Projection | CL9: Projection | CM9: Projection | CN9: Projection | CO9: Projection | CP9: Projection | CQ9: Projection | CR9: Projection | CS9: Projection | CT9: Projection | CU9: Projection | CV9: Projection | CW9: Projection | CX9: Projection | CY9: Projection | CZ9: Projection | DA9: Projection | DB9: Projection | DC9: Projection | DD9: Projection | DE9: Projection | DF9: Projection | DG9: Projection | DH9: Projection | DJ9: Actual | DK9: Actual | DL9: Actual | DM9: Budget | DN9: Projection | DO9: Projection | DP9: Projection | DQ9: Projection
B11: Revenue | DJ11: Growth Analysis
B12: Licensing | O12: =I12+992.899 -> 992.899 | DK12: =+IFERROR(G12/F12-1,0) -> 0 | DL12: =+IFERROR(H12/G12-1,0) -> 0 | DM12: =+IFERROR(I12/H12-1,0) -> 0 | DN12: =+IFERROR(J12/I12-1,0) -> 0 | DP12: =+IFERROR(L12/K12-1,0) -> 0 | DQ12: =+IFERROR(M12/L12-1,0) -> 0
B13: Managed Services | O13: =+I13 | DK13: =+IFERROR(G13/F13-1,0) -> 0 | DL13: =+IFERROR(H13/G13-1,0) -> 0 | DM13: =+IFERROR(I13/H13-1,0) -> 0 | DN13: =+IFERROR(J13/I13-1,0) -> 0 | DP13: =+IFERROR(L13/K13-1,0) -> 0 | DQ13: =+IFERROR(M13/L13-1,0) -> 0
B14: Implementation | O14: =+I14 | DK14: =+IFERROR(G14/F14-1,0) -> 0 | DL14: =+IFERROR(H14/G14-1,0) -> 0 | DM14: =+IFERROR(I14/H14-1,0) -> 0 | DN14: =+IFERROR(J14/I14-1,0) -> 0 | DP14: =+IFERROR(L14/K14-1,0) -> 0 | DQ14: =+IFERROR(M14/L14-1,0) -> 0
B15: Other Revenue | O15: =+I15 | DK15: =+IFERROR(G15/F15-1,0) -> 0 | DL15: =+IFERROR(H15/G15-1,0) -> 0 | DM15: =+IFERROR(I15/H15-1,0) -> 0 | DN15: =+IFERROR(J15/I15-1,0) -> 0 | DP15: =+IFERROR(L15/K15-1,0) -> 0 | DQ15: =+IFERROR(M15/L15-1,0) -> 0
B16: Total Revenue | O16: =SUM(O12:O15) -> 992.899 | DK16: =+G16/F16-1 -> #DIV/0! | DL16: =+H16/G16-1 -> #DIV/0! | DM16: =+I16/H16-1 -> #DIV/0! | DN16: =+J16/I16-1 -> #DIV/0! | DP16: =+L16/K16-1 -> #DIV/0! | DQ16: =+M16/L16-1 -> #DIV/0!
B18: Cost of Sales | DJ18: Margin Analysis
B19: Licensing | O19: =+I19+((O12-I12)*0.11) -> 109.21889 | DJ19: =+F19/F$16 -> #DIV/0! | DK19: =+G19/G$16 -> #DIV/0! | DL19: =+H19/H$16 -> #DIV/0! | DM19: =+I19/I$16 -> #DIV/0! | DN19: =+J19/J$16 -> #DIV/0! | DP19: =+L19/L$16 -> #DIV/0! | DQ19: =+M19/M$16 -> #DIV/0!
B20: Managed Services | O20: =+I20 | DJ20: =+F20/F$16 -> #DIV/0! | DK20: =+G20/G$16 -> #DIV/0! | DL20: =+H20/H$16 -> #DIV/0! | DM20: =+I20/I$16 -> #DIV/0! | DN20: =+J20/J$16 -> #DIV/0! | DP20: =+L20/L$16 -> #DIV/0! | DQ20: =+M20/M$16 -> #DIV/0!
B21: Implementation | O21: =+I21 | DJ21: =+F21/F$16 -> #DIV/0! | DK21: =+G21/G$16 -> #DIV/0! | DL21: =+H21/H$16 -> #DIV/0! | DM21: =+I21/I$16 -> #DIV/0! | DN21: =+J21/J$16 -> #DIV/0! | DP21: =+L21/L$16 -> #DIV/0! | DQ21: =+M21/M$16 -> #DIV/0!
B22: Total Cost of Sales | O22: =SUM(O19:O21) -> 109.21889 | DJ22: =+F22/F$16 -> #DIV/0! | DK22: =+G22/G$16 -> #DIV/0! | DL22: =+H22/H$16 -> #DIV/0! | DM22: =+I22/I$16 -> #DIV/0! | DN22: =+J22/J$16 -> #DIV/0! | DP22: =+L22/L$16 -> #DIV/0! | DQ22: =+M22/M$16 -> #DIV/0!
B24: Gross Profit | O24: =+SUM(O16,-O22) -> 883.68011 | DJ24: =+F24/F$16 -> #DIV/0! | DK24: =+G24/G$16 -> #DIV/0! | DL24: =+H24/H$16 -> #DIV/0! | DM24: =+I24/I$16 -> #DIV/0! | DN24: =+J24/J$16 -> #DIV/0! | DP24: =+L24/L$16 -> #DIV/0! | DQ24: =+M24/M$16 -> #DIV/0!
B26: Operating Expenses
B27: Payroll & Benefits | O27: =+I27 | DJ27: =+F27/F$16 -> #DIV/0! | DK27: =+G27/G$16 -> #DIV/0! | DL27: =+H27/H$16 -> #DIV/0! | DM27: =+I27/I$16 -> #DIV/0! | DN27: =+J27/J$16 -> #DIV/0! | DP27: =+L27/L$16 -> #DIV/0! | DQ27: =+M27/M$16 -> #DIV/0!
B28: Office and Occupancy | O28: =+I28 | DJ28: =+F28/F$16 -> #DIV/0! | DK28: =+G28/G$16 -> #DIV/0! | DL28: =+H28/H$16 -> #DIV/0! | DM28: =+I28/I$16 -> #DIV/0! | DN28: =+J28/J$16 -> #DIV/0! | DP28: =+L28/L$16 -> #DIV/0! | DQ28: =+M28/M$16 -> #DIV/0!
B29: HR Other | O29: =+I29 | DJ29: =+F29/F$16 -> #DIV/0! | DK29: =+G29/G$16 -> #DIV/0! | DL29: =+H29/H$16 -> #DIV/0! | DM29: =+I29/I$16 -> #DIV/0! | DN29: =+J29/J$16 -> #DIV/0! | DP29: =+L29/L$16 -> #DIV/0! | DQ29: =+M29/M$16 -> #DIV/0!
B30: Sales and Marketing | O30: =+I30 | DJ30: =+F30/F$16 -> #DIV/0! | DK30: =+G30/G$16 -> #DIV/0! | DL30: =+H30/H$16 -> #DIV/0! | DM30: =+I30/I$16 -> #DIV/0! | DN30: =+J30/J$16 -> #DIV/0! | DP30: =+L30/L$16 -> #DIV/0! | DQ30: =+M30/M$16 -> #DIV/0!
B31: Other G&A | O31: =+I31 | DJ31: =+F31/F$16 -> #DIV/0! | DK31: =+G31/G$16 -> #DIV/0! | DL31: =+H31/H$16 -> #DIV/0! | DM31: =+I31/I$16 -> #DIV/0! | DN31: =+J31/J$16 -> #DIV/0! | DP31: =+L31/L$16 -> #DIV/0! | DQ31: =+M31/M$16 -> #DIV/0!
B32: Professional Fees | O32: =+I32 | DJ32: =+F32/F$16 -> #DIV/0! | DK32: =+G32/G$16 -> #DIV/0! | DL32: =+H32/H$16 -> #DIV/0! | DM32: =+I32/I$16 -> #DIV/0! | DN32: =+J32/J$16 -> #DIV/0! | DP32: =+L32/L$16 -> #DIV/0! | DQ32: =+M32/M$16 -> #DIV/0!
B33: Service Costs | O33: =+I33 | DJ33: =+F33/F$16 -> #DIV/0! | DK33: =+G33/G$16 -> #DIV/0! | DL33: =+H33/H$16 -> #DIV/0! | DM33: =+I33/I$16 -> #DIV/0! | DN33: =+J33/J$16 -> #DIV/0! | DP33: =+L33/L$16 -> #DIV/0! | DQ33: =+M33/M$16 -> #DIV/0!
B34: Total Operating Expenses | O34: =+I34 | DJ34: =+F34/F$16 -> #DIV/0! | DK34: =+G34/G$16 -> #DIV/0! | DL34: =+H34/H$16 -> #DIV/0! | DM34: =+I34/I$16 -> #DIV/0! | DN34: =+J34/J$16 -> #DIV/0! | DP34: =+L34/L$16 -> #DIV/0! | DQ34: =+M34/M$16 -> #DIV/0!
B35: Other Income / Expenses | O35: =+I35 | DJ35: =+F35/F$16 -> #DIV/0! | DK35: =+G35/G$16 -> #DIV/0! | DL35: =+H35/H$16 -> #DIV/0! | DM35: =+I35/I$16 -> #DIV/0! | DN35: =+J35/J$16 -> #DIV/0! | DP35: =+L35/L$16 -> #DIV/0! | DQ35: =+M35/M$16 -> #DIV/0!
B37: Reported EBITDA | O37: =+SUM(O24,-O34,-O35) -> 883.68011 | DJ37: =+F37/F$16 -> #DIV/0! | DK37: =+G37/G$16 -> #DIV/0! | DL37: =+H37/H$16 -> #DIV/0! | DM37: =+I37/I$16 -> #DIV/0! | DN37: =+J37/J$16 -> #DIV/0! | DP37: =+L37/L$16 -> #DIV/0! | DQ37: =+M37/M$16 -> #DIV/0!
B39: Adjustments
B40: Non-cash Stock-based Compensation | O40: =+I40 | Q40: 20.833 | R40: 20.833 | S40: 20.833 | T40: 20.833 | U40: 20.833 | V40: 20.833 | W40: 20.833 | X40: 20.833 | Y40: 20.833 | Z40: 20.833 | AA40: 20.833 | AB40: -204.124 | AC40: 8.33333 | AD40: 8.33333 | AE40: 8.33333 | AF40: 8.33333 | AG40: 8.33333 | AH40: 8.33333 | AI40: 8.33333 | AJ40: 8.33333 | AK40: 8.33333 | AL40: 8.33333 | AM40: 8.33333 | AN40: -27.88063 | AO40: 2.08333 | AP40: 2.08333 | AQ40: 2.08333 | AR40: 2.08333 | AS40: 2.08333 | AT40: 2.08333 | AU40: 2.08333 | AV40: 2.08333 | AW40: 2.08333 | AX40: 2.08333 | AY40: 2.08333 | AZ40: 237.01437 | BA40: 0 | BB40: 0 | BC40: 0 | BD40: 0 | BE40: 0 | BF40: 0 | BG40: 0 | BH40: 0 | BI40: 0 | BJ40: 0 | BK40: 0 | BL40: 0 | BM40: 0 | BN40: 0 | BO40: 0 | BP40: 0 | BQ40: 0 | BR40: 0 | BS40: 0 | BT40: 0 | BU40: 0 | BV40: 0 | BW40: 0 | BX40: 0 | BY40: 0 | BZ40: 0 | CA40: 0 | CB40: 0 | CC40: 0 | CD40: 0 | CE40: 0 | CF40: 0 | CG40: 0 | CH40: 0 | CI40: 0 | CJ40: 0 | CK40: 0 | CL40: 0 | CM40: 0 | CN40: 0 | CO40: 0 | CP40: 0 | CQ40: 0 | CR40: 0 | CS40: 0 | CT40: 0 | CU40: 0 | CV40: 0 | CW40: 0 | CX40: 0 | CY40: 0 | CZ40: 0 | DA40: 0 | DB40: 0 | DC40: 0 | DD40: 0 | DE40: 0 | DF40: 0 | DG40: 0 | DH40: 0 | DJ40: =+F40/F$16 -> #DIV/0! | DK40: =+G40/G$16 -> #DIV/0! | DL40: =+H40/H$16 -> #DIV/0! | DM40: =+I40/I$16 -> #DIV/0! | DN40: =+J40/J$16 -> #DIV/0! | DP40: =+L40/L$16 -> #DIV/0! | DQ40: =+M40/M$16 -> #DIV/0!
B41: Other Miscellaneous Items | O41: =+I41 | Q41: 9.25165 | R41: 3.01295 | S41: 16.41295 | T41: -4.58705 | U41: 4.78698 | V41: 3.01295 | W41: 13.01295 | X41: 20.44512 | Y41: 17.51013 | Z41: 1.88017 | AA41: 11.52846 | AB41: 14.82482 | AC41: 12.5 | AD41: 13.65994 | AE41: 22.392 | AF41: 19.868 | AG41: 4.9663 | AH41: 18.383 | AI41: -69.84 | AJ41: 2.502 | AK41: 2.549 | AL41: 3.96917 | AM41: 3.8983 | AN41: 11.64995 | AO41: 0.76966667 | AP41: 0.76966667 | AQ41: 1.5246667 | AR41: 0.75466667 | AS41: 2.2554467 | AT41: -5.2453333 | AU41: -0.29328333 | AV41: 3.3546667 | AW41: 15.004667 | AX41: 14.5 | AY41: 1.38931 | AZ41: 0 | BA41: 0 | BB41: 0 | BC41: 0 | BD41: 0 | BE41: 0 | BF41: 0 | BG41: 0 | BH41: 0 | BI41: 0 | BJ41: 0 | BK41: 0 | BL41: 0 | BM41: 0 | BN41: 0 | BO41: 0 | BP41: 0 | BQ41: 0 | BR41: 0 | BS41: 0 | BT41: 0 | BU41: 0 | BV41: 0 | BW41: 0 | BX41: 0 | BY41: 0 | BZ41: 0 | CA41: 0 | CB41: 0 | CC41: 0 | CD41: 0 | CE41: 0 | CF41: 0 | CG41: 0 | CH41: 0 | CI41: 0 | CJ41: 0 | CK41: 0 | CL41: 0 | CM41: 0 | CN41: 0 | CO41: 0 | CP41: 0 | CQ41: 0 | CR41: 0 | CS41: 0 | CT41: 0 | CU41: 0 | CV41: 0 | CW41: 0 | CX41: 0 | CY41: 0 | CZ41: 0 | DA41: 0 | DB41: 0 | DC41: 0 | DD41: 0 | DE41: 0 | DF41: 0 | DG41: 0 | DH41: 0 | DJ41: =+F41/F$16 -> #DIV/0! | DK41: =+G41/G$16 -> #DIV/0! | DL41: =+H41/H$16 -> #DIV/0! | DM41: =+I41/I$16 -> #DIV/0! | DN41: =+J41/J$16 -> #DIV/0! | DP41: =+L41/L$16 -> #DIV/0! | DQ41: =+M41/M$16 -> #DIV/0!
B42: Employee Related Expenses | O42: =+I42 | Q42: 8.4869783 | R42: 38.358638 | S42: 8.3586383 | T42: 10.358638 | U42: 8.3586383 | V42: 8.3586383 | W42: 11.358638 | X42: 18.858638 | Y42: 17.358638 | Z42: 13.983638 | AA42: 19.014638 | AB42: -79.323362 | AC42: 13.517087 | AD42: 13.095877 | AE42: 18.054667 | AF42: 16.147717 | AG42: 3.7620867 | AH42: -1.2379133 | AI42: -1.2379133 | AJ42: -1.2379133 | AK42: -1.2379233 | AL42: -1.2379233 | AM42: 55.257077 | AN42: -9.0089233 | AO42: 8.04 | AP42: 0.52568 | AQ42: 0 | AR42: 0 | AS42: 0 | AT42: 0.28933 | AU42: 0 | AV42: 5 | AW42: 17.11879 | AX42: 0 | AY42: 0 | AZ42: 0 | BA42: 0 | BB42: 0 | BC42: 0 | BD42: 0 | BE42: 0 | BF42: 0 | BG42: 0 | BH42: 0 | BI42: 0 | BJ42: 0 | BK42: 0 | BL42: 0 | BM42: 0 | BN42: 0 | BO42: 0 | BP42: 0 | BQ42: 0 | BR42: 0 | BS42: 0 | BT42: 0 | BU42: 0 | BV42: 0 | BW42: 0 | BX42: 0 | BY42: 0 | BZ42: 0 | CA42: 0 | CB42: 0 | CC42: 0 | CD42: 0 | CE42: 0 | CF42: 0 | CG42: 0 | CH42: 0 | CI42: 0 | CJ42: 0 | CK42: 0 | CL42: 0 | CM42: 0 | CN42: 0 | CO42: 0 | CP42: 0 | CQ42: 0 | CR42: 0 | CS42: 0 | CT42: 0 | CU42: 0 | CV42: 0 | CW42: 0 | CX42: 0 | CY42: 0 | CZ42: 0 | DA42: 0 | DB42: 0 | DC42: 0 | DD42: 0 | DE42: 0 | DF42: 0 | DG42: 0 | DH42: 0 | DJ42: =+F42/F$16 -> #DIV/0! | DK42: =+G42/G$16 -> #DIV/0! | DL42: =+H42/H$16 -> #DIV/0! | DM42: =+I42/I$16 -> #DIV/0! | DN42: =+J42/J$16 -> #DIV/0! | DP42: =+L42/L$16 -> #DIV/0! | DQ42: =+M42/M$16 -> #DIV/0!
B43: Non-recurring Build Subsidies | O43: =+I43 | Q43: 135.84913 | R43: 219.74271 | S43: 294.61578 | T43: 237.61969 | U43: 282.9635 | V43: 333.30398 | W43: 341.19059 | X43: 405.02271 | Y43: 323.66688 | Z43: 428.12455 | AA43: 312.23943 | AB43: 277.35696 | AC43: 290.11101 | AD43: 288.41538 | AE43: 370.12266 | AF43: 315.70853 | AG43: 291.44613 | AH43: 213.13591 | AI43: 169.27227 | AJ43: 137.43883 | AK43: 120.37583 | AL43: 83.636543 | AM43: -6.8386667 | AN43: -3.91747 | AO43: 61.8405 | AP43: 37.405 | AQ43: 51.271 | AR43: 47.215 | AS43: 48.908 | AT43: -15.65 | AU43: -14.851 | AV43: 61.208 | AW43: -0.169 | AX43: 30.794 | AY43: 26.507 | AZ43: 23.922 | BA43: 12.1 | BB43: 13.695 | BC43: 52.25 | BD43: 34.241182 | BE43: 13.521848 | BF43: 24.521848 | BG43: 27.271848 | BH43: 39.741182 | BI43: 36.991182 | BJ43: 23.241182 | BK43: 19.721182 | BL43: 12.241182 | BM43: 13.441182 | BN43: 7.6411818 | BO43: 8.7 | BP43: 5.8 | BQ43: 2.9 | BR43: 0 | BS43: 0 | BT43: 0 | BU43: 0 | BV43: 0 | BW43: 0 | BX43: 0 | BY43: 0 | BZ43: 0 | CA43: 0 | CB43: 0 | CC43: 0 | CD43: 0 | CE43: 0 | CF43: 0 | CG43: 0 | CH43: 0 | CI43: 0 | CJ43: 0 | CK43: 0 | CL43: 0 | CM43: 0 | CN43: 0 | CO43: 0 | CP43: 0 | CQ43: 0 | CR43: 0 | CS43: 0 | CT43: 0 | CU43: 0 | CV43: 0 | CW43: 0 | CX43: 0 | CY43: 0 | CZ43: 0 | DA43: 0 | DB43: 0 | DC43: 0 | DD43: 0 | DE43: 0 | DF43: 0 | DG43: 0 | DH43: 0 | DJ43: =+F43/F$16 -> #DIV/0! | DK43: =+G43/G$16 -> #DIV/0! | DL43: =+H43/H$16 -> #DIV/0! | DM43: =+I43/I$16 -> #DIV/0! | DN43: =+J43/J$16 -> #DIV/0! | DP43: =+L43/L$16 -> #DIV/0! | DQ43: =+M43/M$16 -> #DIV/0!
B44: Duplicative Hosting Costs | O44: =+I44 | Q44: 0 | R44: 0 | S44: 0 | T44: 0 | U44: 0 | V44: 0 | W44: 0 | X44: 0 | Y44: 0 | Z44: 0 | AA44: 0 | AB44: 0 | AC44: 0 | AD44: 0 | AE44: 3.51225 | AF44: 3.51225 | AG44: 3.51225 | AH44: 29.2315 | AI44: 1.6034413 | AJ44: 1.6034413 | AK44: 3.9133879 | AL44: 5.2761676 | AM44: 5.1352645 | AN44: 7.4517559 | AO44: 14.374712 | AP44: 11.373587 | AQ44: 23.293 | AR44: 22.4 | AS44: 9.028 | AT44: 6.87705 | AU44: 6.44708 | AV44: 6.44708 | AW44: 6.44708 | AX44: 6.44708 | AY44: 6.44708 | AZ44: 6.44708 | BA44: 0 | BB44: 0 | BC44: 0 | BD44: 0 | BE44: 0 | BF44: 0 | BG44: 0 | BH44: 0 | BI44: 0 | BJ44: 0 | BK44: 0 | BL44: 0 | BM44: 0 | BN44: 0 | BO44: 0 | BP44: 0 | BQ44: 0 | BR44: 0 | BS44: 0 | BT44: 0 | BU44: 0 | BV44: 0 | BW44: 0 | BX44: 0 | BY44: 0 | BZ44: 0 | CA44: 0 | CB44: 0 | CC44: 0 | CD44: 0 | CE44: 0 | CF44: 0 | CG44: 0 | CH44: 0 | CI44: 0 | CJ44: 0 | CK44: 0 | CL44: 0 | CM44: 0 | CN44: 0 | CO44: 0 | CP44: 0 | CQ44: 0 | CR44: 0 | CS44: 0 | CT44: 0 | CU44: 0 | CV44: 0 | CW44: 0 | CX44: 0 | CY44: 0 | CZ44: 0 | DA44: 0 | DB44: 0 | DC44: 0 | DD44: 0 | DE44: 0 | DF44: 0 | DG44: 0 | DH44: 0 | DJ44: =+F44/F$16 -> #DIV/0! | DK44: =+G44/G$16 -> #DIV/0! | DL44: =+H44/H$16 -> #DIV/0! | DM44: =+I44/I$16 -> #DIV/0! | DN44: =+J44/J$16 -> #DIV/0! | DP44: =+L44/L$16 -> #DIV/0! | DQ44: =+M44/M$16 -> #DIV/0!
B45: COVID-19 Marketing Cost Savings | O45: =+I45 | Q45: 0 | R45: 0 | S45: 0 | T45: 0 | U45: 0 | V45: 0 | W45: 0 | X45: 0 | Y45: 147.40685 | Z45: 63.98637 | AA45: 0 | AB45: 0 | AC45: 0 | AD45: 0 | AE45: 0 | AF45: 0 | AG45: 0 | AH45: 0 | AI45: 0 | AJ45: 0 | AK45: 0 | AL45: 0 | AM45: 0 | AN45: 0 | AO45: 0 | AP45: 0 | AQ45: 11.452 | AR45: 0 | AS45: 0 | AT45: 0 | AU45: 0 | AV45: 0 | AW45: 0 | AX45: 0 | AY45: 0 | AZ45: 0 | BA45: 0 | BB45: 0 | BC45: 0 | BD45: 0 | BE45: 0 | BF45: 0 | BG45: 0 | BH45: 0 | BI45: 0 | BJ45: 0 | BK45: 0 | BL45: 0 | BM45: 0 | BN45: 0 | BO45: 0 | BP45: 0 | BQ45: 0 | BR45: 0 | BS45: 0 | BT45: 0 | BU45: 0 | BV45: 0 | BW45: 0 | BX45: 0 | BY45: 0 | BZ45: 0 | CA45: 0 | CB45: 0 | CC45: 0 | CD45: 0 | CE45: 0 | CF45: 0 | CG45: 0 | CH45: 0 | CI45: 0 | CJ45: 0 | CK45: 0 | CL45: 0 | CM45: 0 | CN45: 0 | CO45: 0 | CP45: 0 | CQ45: 0 | CR45: 0 | CS45: 0 | CT45: 0 | CU45: 0 | CV45: 0 | CW45: 0 | CX45: 0 | CY45: 0 | CZ45: 0 | DA45: 0 | DB45: 0 | DC45: 0 | DD45: 0 | DE45: 0 | DF45: 0 | DG45: 0 | DH45: 0 | DJ45: =+F45/F$16 -> #DIV/0! | DK45: =+G45/G$16 -> #DIV/0! | DL45: =+H45/H$16 -> #DIV/0! | DM45: =+I45/I$16 -> #DIV/0! | DN45: =+J45/J$16 -> #DIV/0! | DP45: =+L45/L$16 -> #DIV/0! | DQ45: =+M45/M$16 -> #DIV/0!
B46: Normalized Legal Fees | O46: =+I46 | Q46: 14.423127 | R46: 14.423127 | S46: 39.423127 | T46: 17.423127 | U46: 17.423127 | V46: -2.5768733 | W46: -2.5768733 | X46: -40.012373 | Y46: 4.0137367 | Z46: -2.7363733 | AA46: -1.4603733 | AB46: -7.2245233 | AC46: 18.256457 | AD46: 18.256457 | AE46: 16.441457 | AF46: 8.2929467 | AG46: 16.230577 | AH46: 13.560577 | AI46: 16.230577 | AJ46: 15.223577 | AK46: 11.818587 | AL46: -128.77147 | AM46: -2.2628733 | AN46: -2.5768733 | AO46: 0 | AP46: 0 | AQ46: 0 | AR46: 0 | AS46: 0 | AT46: 0 | AU46: 0 | AV46: 0 | AW46: 0 | AX46: 0 | AY46: 0 | AZ46: 0 | BA46: 0 | BB46: 0 | BC46: 0 | BD46: 0 | BE46: 0 | BF46: 0 | BG46: 0 | BH46: 0 | BI46: 0 | BJ46: 0 | BK46: 0 | BL46: 0 | BM46: 0 | BN46: 0 | BO46: 0 | BP46: 0 | BQ46: 0 | BR46: 0 | BS46: 0 | BT46: 0 | BU46: 0 | BV46: 0 | BW46: 0 | BX46: 0 | BY46: 0 | BZ46: 0 | CA46: 0 | CB46: 0 | CC46: 0 | CD46: 0 | CE46: 0 | CF46: 0 | CG46: 0 | CH46: 0 | CI46: 0 | CJ46: 0 | CK46: 0 | CL46: 0 | CM46: 0 | CN46: 0 | CO46: 0 | CP46: 0 | CQ46: 0 | CR46: 0 | CS46: 0 | CT46: 0 | CU46: 0 | CV46: 0 | CW46: 0 | CX46: 0 | CY46: 0 | CZ46: 0 | DA46: 0 | DB46: 0 | DC46: 0 | DD46: 0 | DE46: 0 | DF46: 0 | DG46: 0 | DH46: 0 | DJ46: =+F46/F$16 -> #DIV/0! | DK46: =+G46/G$16 -> #DIV/0! | DL46: =+H46/H$16 -> #DIV/0! | DM46: =+I46/I$16 -> #DIV/0! | DN46: =+J46/J$16 -> #DIV/0! | DP46: =+L46/L$16 -> #DIV/0! | DQ46: =+M46/M$16 -> #DIV/0!
B47: Eligible Costs for Capitalization | O47: =+I47 | DJ47: =+F47/F$16 -> #DIV/0! | DK47: =+G47/G$16 -> #DIV/0! | DL47: =+H47/H$16 -> #DIV/0! | DM47: =+I47/I$16 -> #DIV/0! | DN47: =+J47/J$16 -> #DIV/0! | DP47: =+L47/L$16 -> #DIV/0! | DQ47: =+M47/M$16 -> #DIV/0!
B48: Total Adjustments | O48: =+I48 | Q48: =SUM(Q40:Q46) -> 188.84389 | DJ48: =+F48/F$16 -> #DIV/0! | DK48: =+G48/G$16 -> #DIV/0! | DL48: =+H48/H$16 -> #DIV/0! | DM48: =+I48/I$16 -> #DIV/0! | DN48: =+J48/J$16 -> #DIV/0! | DP48: =+L48/L$16 -> #DIV/0! | DQ48: =+M48/M$16 -> #DIV/0!
B50: Adjusted EBITDA | O50: =+SUM(O37,O48) -> 883.68011 | Q50: =+SUM(Q37,Q48) -> 188.84389 | R50: =+SUM(R37,R48) -> 0 | S50: =+SUM(S37,S48) -> 0 | T50: =+SUM(T37,T48) -> 0 | U50: =+SUM(U37,U48) -> 0 | V50: =+SUM(V37,V48) -> 0 | W50: =+SUM(W37,W48) -> 0 | X50: =+SUM(X37,X48) -> 0 | ... DH50: =+SUM(DH37,DH48) -> 0 | DJ50: =+F50/F$16 -> #DIV/0! | DK50: =+G50/G$16 -> #DIV/0! | DL50: =+H50/H$16 -> #DIV/0! | DM50: =+I50/I$16 -> #DIV/0! | DN50: =+J50/J$16 -> #DIV/0! | DP50: =+L50/L$16 -> #DIV/0! | DQ50: =+M50/M$16 -> #DIV/0!

Sheet Calculations ->

Sheet Revenue_Calcs
B2: Project Shasta
B3: {=MID(CELL("filename",A1),FIND("]",CELL("filename",A1))+1,255)} -> #VALUE!
B4: Spring 2022
B5: CONFIDENTIAL
E7: 2018 | F7: =+E7+1 -> 2019 | G7: =+F7+1 -> 2020 | H7: =+G7+1 -> 2021 | I7: =+H7+1 -> 2022 | J7: =+I7+1 -> 2023 | K7: =+J7+1 -> 2024 | L7: =+K7+1 -> 2025 | M7: =+L7+1 -> 2026 | O7: =+YEAR(O8) -> 2018 | P7: =+YEAR(P8) -> 2018 | Q7: =+YEAR(Q8) -> 2018 | R7: =+YEAR(R8) -> 2018 | S7: =+YEAR(S8) -> 2018 | T7: =+YEAR(T8) -> 2018 | U7: =+YEAR(U8) -> 2018 | V7: =+YEAR(V8) -> 2018 | ... DR7: =+YEAR(DR8) -> 2026
E8: =+DATE(E7,12,31) -> 43465 | F8: =+DATE(F7,12,31) -> 43830 | G8: =+DATE(G7,12,31) -> 44196 | H8: =+DATE(H7,12,31) -> 44561 | I8: =+DATE(I7,12,31) -> 44926 | J8: =+DATE(J7,12,31) -> 45291 | K8: =+DATE(K7,12,31) -> 45657 | L8: =+DATE(L7,12,31) -> 46022 | M8: =+DATE(M7,12,31) -> 46387 | O8: 43131 | P8: =+EOMONTH(O8,1) -> 43159 | Q8: =+EOMONTH(P8,1) -> 43190 | R8: =+EOMONTH(Q8,1) -> 43220 | S8: =+EOMONTH(R8,1) -> 43251 | T8: =+EOMONTH(S8,1) -> 43281 | U8: =+EOMONTH(T8,1) -> 43312 | V8: =+EOMONTH(U8,1) -> 43343 | W8: =+EOMONTH(V8,1) -> 43373 | ... DR8: =+EOMONTH(DQ8,1) -> 46387 | DT8: Upsell / Downsell
B9: $ in thousands | E9: Actual | F9: Actual | G9: Actual | H9: Actual | I9: Budget | J9: Projection | K9: Projection | L9: Projection | M9: Projection | O9: Actual | P9: Actual | Q9: Actual | R9: Actual | S9: Actual | T9: Actual | U9: Actual | V9: Actual | W9: Actual | X9: Actual | Y9: Actual | Z9: Actual | AA9: Actual | AB9: Actual | AC9: Actual | AD9: Actual | AE9: Actual | AF9: Actual | AG9: Actual | AH9: Actual | AI9: Actual | AJ9: Actual | AK9: Actual | AL9: Actual | AM9: Actual | AN9: Actual | AO9: Actual | AP9: Actual | AQ9: Actual | AR9: Actual | AS9: Actual | AT9: Actual | AU9: Actual | AV9: Actual | AW9: Actual | AX9: Actual | AY9: Actual | AZ9: Actual | BA9: Actual | BB9: Actual | BC9: Actual | BD9: Actual | BE9: Actual | BF9: Actual | BG9: Actual | BH9: Actual | BI9: Actual | BJ9: Actual | BK9: Actual | BL9: Actual | BM9: Actual | BN9: Projection | BO9: Projection | BP9: Projection | BQ9: Projection | BR9: Projection | BS9: Projection | BT9: Projection | BU9: Projection | BV9: Projection | BW9: Projection | BX9: Projection | BY9: Projection | BZ9: Projection | CA9: Projection | CB9: Projection | CC9: Projection | CD9: Projection | CE9: Projection | CF9: Projection | CG9: Projection | CH9: Projection | CI9: Projection | CJ9: Projection | CK9: Projection | CL9: Projection | CM9: Projection | CN9: Projection | CO9: Projection | CP9: Projection | CQ9: Projection | CR9: Projection | CS9: Projection | CT9: Projection | CU9: Projection | CV9: Projection | CW9: Projection | CX9: Projection | CY9: Projection | CZ9: Projection | DA9: Projection | DB9: Projection | DC9: Projection | DD9: Projection | DE9: Projection | DF9: Projection | DG9: Projection | DH9: Projection | DI9: Projection | DJ9: Projection | DK9: Projection | DL9: Projection | DM9: Projection | DN9: Projection | DO9: Projection | DP9: Projection | DQ9: Projection | DR9: Projection | DT9: 2019 | DU9: 2020 | DV9: 2021 | DW9: 2022
B11: Licensing
B13: AACN | C13: Lower Middle Market | E13: =+SUMIFS($O13:$DR13,$O$7:$DR$7,E$7) -> 0 | F13: =+SUMIFS($O13:$DR13,$O$7:$DR$7,F$7) -> 13.416 | G13: =+SUMIFS($O13:$DR13,$O$7:$DR$7,G$7) -> 113.936 | H13: =+SUMIFS($O13:$DR13,$O$7:$DR$7,H$7) -> 118.74613 | I13: =+SUMIFS($O13:$DR13,$O$7:$DR$7,I$7) -> 122.30851 | J13: =+SUMIFS($O13:$DR13,$O$7:$DR$7,J$7) -> 125.97776 | K13: =+SUMIFS($O13:$DR13,$O$7:$DR$7,K$7) -> 118.64739 | L13: =+SUMIFS($O13:$DR13,$O$7:$DR$7,L$7) -> 0 | M13: =+SUMIFS($O13:$DR13,$O$7:$DR$7,M$7) -> 0 | O13: 0 | P13: 0 | Q13: 0 | R13: 0 | S13: 0 | T13: 0 | U13: 0 | V13: 0 | W13: 0 | X13: 0 | Y13: 0 | Z13: 0 | AA13: 0 | AB13: 0 | AC13: 0 | AD13: 0 | AE13: 0 | AF13: 0 | AG13: 0 | AH13: 0 | AI13: 0 | AJ13: 0 | AK13: 0 | AL13: 13.416 | AM13: 9.584 | AN13: 9.583 | AO13: 9.583 | AP13: 9.583 | AQ13: 9.583 | AR13: 9.584 | AS13: 9.584 | AT13: 9.584 | AU13: 8.23 | AV13: 9.583 | AW13: 9.584 | AX13: 9.871 | AY13: 9.8708333 | AZ13: 9.8708333 | BA13: 9.8708333 | BB13: 9.8708333 | BC13: 9.8708333 | BD13: 9.8708333 | BE13: 9.8708333 | BF13: 9.8708333 | BG13: 9.8708333 | BH13: 9.8708333 | BI13: 9.8708333 | BJ13: 10.166958 | BK13: 10.166958 | BL13: 10.166958 | BM13: 10.166958 | BN13: 10.166958 | BO13: 10.166958 | BP13: 10.166958 | BQ13: 10.166958 | BR13: 10.166958 | BS13: 10.166958 | BT13: 10.166958 | BU13: 10.166958 | BV13: 10.471967 | BW13: 10.471967 | BX13: 10.471967 | BY13: 10.471967 | BZ13: 10.471967 | CA13: 10.471967 | CB13: 10.471967 | CC13: 10.471967 | CD13: 10.471967 | CE13: 10.471967 | CF13: 10.471967 | CG13: 10.471967 | CH13: 10.786126 | CI13: 10.786126 | CJ13: 10.786126 | CK13: 10.786126 | CL13: 10.786126 | CM13: 10.786126 | CN13: 10.786126 | CO13: 10.786126 | CP13: 10.786126 | CQ13: 10.786126 | CR13: 10.786126 | CS13: 10.786126 | CT13: 0 | CU13: 0 | CV13: 0 | CW13: 0 | CX13: 0 | CY13: 0 | CZ13: 0 | DA13: 0 | DB13: 0 | DC13: 0 | DD13: 0 | DE13: 0 | DF13: 0 | DG13: 0 | DH13: 0 | DI13: 0 | DJ13: 0 | DK13: 0 | DL13: 0 | DM13: 0 | DN13: 0 | DO13: 0 | DP13: 0 | DQ13: 0 | DR13: 0 | DT13: =+F13-E13 -> 13.416 | DU13: =+G13-F13 -> 100.52 | DV13: =+H13-G13 -> 4.810125 | DW13: =+I13-H13 -> 3.5623837
B14: AACR | C14: Lower Middle Market | E14: =+SUMIFS($O14:$DR14,$O$7:$DR$7,E$7) -> 0 | F14: =+SUMIFS($O14:$DR14,$O$7:$DR$7,F$7) -> 0 | G14: =+SUMIFS($O14:$DR14,$O$7:$DR$7,G$7) -> 0 | H14: =+SUMIFS($O14:$DR14,$O$7:$DR$7,H$7) -> 20.415 | I14: =+SUMIFS($O14:$DR14,$O$7:$DR$7,I$7) -> 175.72917 | J14: =+SUMIFS($O14:$DR14,$O$7:$DR$7,J$7) -> 184.5155 | K14: =+SUMIFS($O14:$DR14,$O$7:$DR$7,K$7) -> 193.74 | L14: =+SUMIFS($O14:$DR14,$O$7:$DR$7,L$7) -> 203.4281 | M14: =+SUMIFS($O14:$DR14,$O$7:$DR$7,M$7) -> 194.9871 | O14: 0 | P14: 0 | Q14: 0 | R14: 0 | S14: 0 | T14: 0 | U14: 0 | V14: 0 | W14: 0 | X14: 0 | Y14: 0 | Z14: 0 | AA14: 0 | AB14: 0 | AC14: 0 | AD14: 0 | AE14: 0 | AF14: 0 | AG14: 0 | AH14: 0 | AI14: 0 | AJ14: 0 | AK14: 0 | AL14: 0 | AM14: 0 | AN14: 0 | AO14: 0 | AP14: 0 | AQ14: 0 | AR14: 0 | AS14: 0 | AT14: 0 | AU14: 0 | AV14: 0 | AW14: 0 | AX14: 0 | AY14: 0 | AZ14: 0 | BA14: 0 | BB14: 0 | BC14: 0 | BD14: 0 | BE14: 0 | BF14: 0 | BG14: 0 | BH14: 2.916 | BI14: 2.916 | BJ14: 14.583 | BK14: 14.583333 | BL14: 14.583333 | BM14: 14.583333 | BN14: 14.583333 | BO14: 14.583333 | BP14: 14.583333 | BQ14: 14.583333 | BR14: 14.583333 | BS14: 14.583333 | BT14: 14.583333 | BU14: 14.583333 | BV14: 15.3125 | BW14: 15.3125 | BX14: 15.3125 | BY14: 15.3125 | BZ14: 15.3125 | CA14: 15.3125 | CB14: 15.3125 | CC14: 15.3125 | CD14: 15.3125 | CE14: 15.3125 | CF14: 15.3125 | CG14: 15.3125 | CH14: 16.078 | CI14: 16.078 | CJ14: 16.078 | CK14: 16.078 | CL14: 16.078 | CM14: 16.078 | CN14: 16.078 | CO14: 16.078 | CP14: 16.078 | CQ14: 16.078 | CR14: 16.078 | CS14: 16.078 | CT14: 16.882 | CU14: 16.882 | CV14: 16.882 | CW14: 16.882 | CX14: 16.882 | CY14: 16.882 | CZ14: 16.882 | DA14: 16.882 | DB14: 16.882 | DC14: 16.882 | DD14: 16.882 | DE14: 16.882 | DF14: 17.7261 | DG14: 17.7261 | DH14: 17.7261 | DI14: 17.7261 | DJ14: 17.7261 | DK14: 17.7261 | DL14: 17.7261 | DM14: 17.7261 | DN14: 17.7261 | DO14: 17.7261 | DP14: 17.7261 | DQ14: 17.7261 | DR14: 0 | DT14: =+F14-E14 -> 0 | DU14: =+G14-F14 -> 0 | DV14: =+H14-G14 -> 20.415 | DW14: =+I14-H14 -> 155.31417
B15: AAI | C15: Lower Middle Market | E15: =+SUMIFS($O15:$DR15,$O$7:$DR$7,E$7) -> 0 | F15: =+SUMIFS($O15:$DR15,$O$7:$DR$7,F$7) -> 0 | G15: =+SUMIFS($O15:$DR15,$O$7:$DR$7,G$7) -> 0 | H15: =+SUMIFS($O15:$DR15,$O$7:$DR$7,H$7) -> 0 | I15: =+SUMIFS($O15:$DR15,$O$7:$DR$7,I$7) -> 40.916667 | J15: =+SUMIFS($O15:$DR15,$O$7:$DR$7,J$7) -> 150.2475 | K15: =+SUMIFS($O15:$DR15,$O$7:$DR$7,K$7) -> 154.75492 | L15: =+SUMIFS($O15:$DR15,$O$7:$DR$7,L$7) -> 159.39757 | M15: =+SUMIFS($O15:$DR15,$O$7:$DR$7,M$7) -> 164.1795 | O15: 0 | P15: 0 | Q15: 0 | R15: 0 | S15: 0 | T15: 0 | U15: 0 | V15: 0 | W15: 0 | X15: 0 | Y15: 0 | Z15: 0 | AA15: 0 | AB15: 0 | AC15: 0 | AD15: 0 | AE15: 0 | AF15: 0 | AG15: 0 | AH15: 0 | AI15: 0 | AJ15: 0 | AK15: 0 | AL15: 0 | AM15: 0 | AN15: 0 | AO15: 0 | AP15: 0 | AQ15: 0 | AR15: 0 | AS15: 0 | AT15: 0 | AU15: 0 | AV15: 0 | AW15: 0 | AX15: 0 | AY15: 0 | AZ15: 0 | BA15: 0 | BB15: 0 | BC15: 0 | BD15: 0 | BE15: 0 | BF15: 0 | BG15: 0 | BH15: 0 | BI15: 0 | BJ15: 0 | BK15: 0 | BL15: 0 | BM15: 2 | BN15: 2 | BO15: 2 | BP15: 2 | BQ15: 2 | BR15: 2 | BS15: 2 | BT15: 2 | BU15: 12.458333 | BV15: 12.458333 | BW15: 12.458333 | BX15: 12.458333 | BY15: 12.458333 | BZ15: 12.458333 | CA15: 12.458333 | CB15: 12.458333 | CC15: 12.458333 | CD15: 12.458333 | CE15: 12.458333 | CF15: 12.458333 | CG15: 12.832083 | CH15: 12.832083 | CI15: 12.832083 | CJ15: 12.832083 | CK15: 12.832083 | CL15: 12.832083 | CM15: 12.832083 | CN15: 12.832083 | CO15: 12.832083 | CP15: 12.832083 | CQ15: 12.832083 | CR15: 12.832083 | CS15: 13.217046 | CT15: 13.217046 | CU15: 13.217046 | CV15: 13.217046 | CW15: 13.217046 | CX15: 13.217046 | CY15: 13.217046 | CZ15: 13.217046 | DA15: 13.217046 | DB15: 13.217046 | DC15: 13.217046 | DD15: 13.217046 | DE15: 13.613557 | DF15: 13.613557 | DG15: 13.613557 | DH15: 13.613557 | DI15: 13.613557 | DJ15: 13.613557 | DK15: 13.613557 | DL15: 13.613557 | DM15: 13.613557 | DN15: 13.613557 | DO15: 13.613557 | DP15: 13.613557 | DQ15: 14.021964 | DR15: 14.021964 | DT15: =+F15-E15 -> 0 | DU15: =+G15-F15 -> 0 | DV15: =+H15-G15 -> 0 | DW15: =+I15-H15 -> 40.916667
B16: AAOS | C16: Upper Middle Market | E16: =+SUMIFS($O16:$DR16,$O$7:$DR$7,E$7) -> 0 | F16: =+SUMIFS($O16:$DR16,$O$7:$DR$7,F$7) -> 0 | G16: =+SUMIFS($O16:$DR16,$O$7:$DR$7,G$7) -> 17.5 | H16: =+SUMIFS($O16:$DR16,$O$7:$DR$7,H$7) -> 106.3051 | I16: =+SUMIFS($O16:$DR16,$O$7:$DR$7,I$7) -> 133.38265 | J16: =+SUMIFS($O16:$DR16,$O$7:$DR$7,J$7) -> 140.05179 | K16: =+SUMIFS($O16:$DR16,$O$7:$DR$7,K$7) -> 147.05438 | L16: =+SUMIFS($O16:$DR16,$O$7:$DR$7,L$7) -> 140.95254 | M16: =+SUMIFS($O16:$DR16,$O$7:$DR$7,M$7) -> 0 | O16: 0 | P16: 0 | Q16: 0 | R16: 0 | S16: 0 | T16: 0 | U16: 0 | V16: 0 | W16: 0 | X16: 0 | Y16: 0 | Z16: 0 | AA16: 0 | AB16: 0 | AC16: 0 | AD16: 0 | AE16: 0 | AF16: 0 | AG16: 0 | AH16: 0 | AI16: 0 | AJ16: 0 | AK16: 0 | AL16: 0 | AM16: 0 | AN16: 0 | AO16: 0 | AP16: 0 | AQ16: 0 | AR16: 2.5 | AS16: 2.5 | AT16: 2.5 | AU16: 2.5 | AV16: 2.5 | AW16: 2.5 | AX16: 2.5 | AY16: 2.5 | AZ16: 2.5 | BA16: 5.9 | BB16: 10.542 | BC16: 10.542 | BD16: 10.542 | BE16: 10.542 | BF16: 10.542 | BG16: 10.542 | BH16: 10.542 | BI16: 10.542 | BJ16: 11.0691 | BK16: 11.0691 | BL16: 11.0691 | BM16: 11.0691 | BN16: 11.0691 | BO16: 11.0691 | BP16: 11.0691 | BQ16: 11.0691 | BR16: 11.0691 | BS16: 11.0691 | BT16: 11.0691 | BU16: 11.0691 | BV16: 11.622555 | BW16: 11.622555 | BX16: 11.622555 | BY16: 11.622555 | BZ16: 11.622555 | CA16: 11.622555 | CB16: 11.622555 | CC16: 11.622555 | CD16: 11.622555 | CE16: 11.622555 | CF16: 11.622555 | CG16: 11.622555 | CH16: 12.203683 | CI16: 12.203683 | CJ16: 12.203683 | CK16: 12.203683 | CL16: 12.203683 | CM16: 12.203683 | CN16: 12.203683 | CO16: 12.203683 | CP16: 12.203683 | CQ16: 12.203683 | CR16: 12.203683 | CS16: 12.203683 | CT16: 12.813867 | CU16: 12.813867 | CV16: 12.813867 | CW16: 12.813867 | CX16: 12.813867 | CY16: 12.813867 | CZ16: 12.813867 | DA16: 12.813867 | DB16: 12.813867 | DC16: 12.813867 | DD16: 12.813867 | DE16: 12.813867 | DF16: 0 | DG16: 0 | DH16: 0 | DI16: 0 | DJ16: 0 | DK16: 0 | DL16: 0 | DM16: 0 | DN16: 0 | DO16: 0 | DP16: 0 | DQ16: 0 | DR16: 0 | DT16: =+F16-E16 -> 0 | DU16: =+G16-F16 -> 17.5 | DV16: =+H16-G16 -> 88.8051 | DW16: =+I16-H16 -> 27.077555
B17: AAP | C17: Major | E17: =+SUMIFS($O17:$DR17,$O$7:$DR$7,E$7) -> 225.499 | F17: =+SUMIFS($O17:$DR17,$O$7:$DR$7,F$7) -> 264.41 | G17: =+SUMIFS($O17:$DR17,$O$7:$DR$7,G$7) -> 276.41 | H17: =+SUMIFS($O17:$DR17,$O$7:$DR$7,H$7) -> 285.156 | I17: =+SUMIFS($O17:$DR17,$O$7:$DR$7,I$7) -> 399 | J17: =+SUMIFS($O17:$DR17,$O$7:$DR$7,J$7) -> 410.97 | K17: =+SUMIFS($O17:$DR17,$O$7:$DR$7,K$7) -> 423.2991 | L17: =+SUMIFS($O17:$DR17,$O$7:$DR$7,L$7) -> 435.99807 | M17: =+SUMIFS($O17:$DR17,$O$7:$DR$7,M$7) -> 449.07802 | O17: 18.212 | P17: 18.212 | Q17: 18.212 | R17: 18.212 | S17: 18.212 | T17: 18.212 | U17: 18.212 | V17: 18.212 | W17: 18.212 | X17: 18.917 | Y17: 21.337 | Z17: 21.337 | AA17: 21.883 | AB17: 21.883 | AC17: 21.883 | AD17: 21.883 | AE17: 21.883 | AF17: 21.883 | AG17: 21.883 | AH17: 21.883 | AI17: 21.883 | AJ17: 21.883 | AK17: 23.072 | AL17: 22.508 | AM17: 23.071 | AN17: 23.071 | AO17: 23.071 | AP17: 23.071 | AQ17: 23.071 | AR17: 23.071 | AS17: 23.071 | AT17: 22.629 | AU17: 23.071 | AV17: 23.071 | AW17: 23.071 | AX17: 23.071 | AY17: 23.763 | AZ17: 23.763 | BA17: 23.763 | BB17: 23.763 | BC17: 23.763 | BD17: 23.763 | BE17: 23.763 | BF17: 23.763 | BG17: 23.763 | BH17: 23.763 | BI17: 23.763 | BJ17: 23.763 | BK17: 33.25 | BL17: 33.25 | BM17: 33.25 | BN17: 33.25 | BO17: 33.25 | BP17: 33.25 | BQ17: 33.25 | BR17: 33.25 | BS17: 33.25 | BT17: 33.25 | BU17: 33.25 | BV17: 33.25 | BW17: 34.2475 | BX17: 34.2475 | BY17: 34.2475 | BZ17: 34.2475 | CA17: 34.2475 | CB17: 34.2475 | CC17: 34.2475 | CD17: 34.2475 | CE17: 34.2475 | CF17: 34.2475 | CG17: 34.2475 | CH17: 34.2475 | CI17: 35.274925 | CJ17: 35.274925 | CK17: 35.274925 | CL17: 35.274925 | CM17: 35.274925 | CN17: 35.274925 | CO17: 35.274925 | CP17: 35.274925 | CQ17: 35.274925 | CR17: 35.274925 | CS17: 35.274925 | CT17: 35.274925 | CU17: 36.333173 | CV17: 36.333173 | CW17: 36.333173 | CX17: 36.333173 | CY17: 36.333173 | CZ17: 36.333173 | DA17: 36.333173 | DB17: 36.333173 | DC17: 36.333173 | DD17: 36.333173 | DE17: 36.333173 | DF17: 36.333173 | DG17: 37.423168 | DH17: 37.423168 | DI17: 37.423168 | DJ17: 37.423168 | DK17: 37.423168 | DL17: 37.423168 | DM17: 37.423168 | DN17: 37.423168 | DO17: 37.423168 | DP17: 37.423168 | DQ17: 37.423168 | DR17: 37.423168 | DT17: =+F17-E17 -> 38.911 | DU17: =+G17-F17 -> 12 | DV17: =+H17-G17 -> 8.746 | DW17: =+I17-H17 -> 113.844
B18: ADA | C18: Lower Middle Market | E18: =+SUMIFS($O18:$DR18,$O$7:$DR$7,E$7) -> 0 | F18: =+SUMIFS($O18:$DR18,$O$7:$DR$7,F$7) -> 0 | G18: =+SUMIFS($O18:$DR18,$O$7:$DR$7,G$7) -> 0 | H18: =+SUMIFS($O18:$DR18,$O$7:$DR$7,H$7) -> 38.44 | I18: =+SUMIFS($O18:$DR18,$O$7:$DR$7,I$7) -> 178.5 | J18: =+SUMIFS($O18:$DR18,$O$7:$DR$7,J$7) -> 183.855 | K18: =+SUMIFS($O18:$DR18,$O$7:$DR$7,K$7) -> 189.37065 | L18: =+SUMIFS($O18:$DR18,$O$7:$DR$7,L$7) -> 195.05177 | M18: =+SUMIFS($O18:$DR18,$O$7:$DR$7,M$7) -> 200.90332 | O18: 0 | P18: 0 | Q18: 0 | R18: 0 | S18: 0 | T18: 0 | U18: 0 | V18: 0 | W18: 0 | X18: 0 | Y18: 0 | Z18: 0 | AA18: 0 | AB18: 0 | AC18: 0 | AD18: 0 | AE18: 0 | AF18: 0 | AG18: 0 | AH18: 0 | AI18: 0 | AJ18: 0 | AK18: 0 | AL18: 0 | AM18: 0 | AN18: 0 | AO18: 0 | AP18: 0 | AQ18: 0 | AR18: 0 | AS18: 0 | AT18: 0 | AU18: 0 | AV18: 0 | AW18: 0 | AX18: 0 | AY18: 0 | AZ18: 0 | BA18: 0 | BB18: 0 | BC18: 4.805 | BD18: 4.805 | BE18: 4.805 | BF18: 4.805 | BG18: 4.805 | BH18: 4.805 | BI18: 4.805 | BJ18: 4.805 | BK18: 14.875 | BL18: 14.875 | BM18: 14.875 | BN18: 14.875 | BO18: 14.875 | BP18: 14.875 | BQ18: 14.875 | BR18: 14.875 | BS18: 14.875 | BT18: 14.875 | BU18: 14.875 | BV18: 14.875 | BW18: 15.32125 | BX18: 15.32125 | BY18: 15.32125 | BZ18: 15.32125 | CA18: 15.32125 | CB18: 15.32125 | CC18: 15.32125 | CD18: 15.32125 | CE18: 15.32125 | CF18: 15.32125 | CG18: 15.32125 | CH18: 15.32125 | CI18: 15.780888 | CJ18: 15.780888 | CK18: 15.780888 | CL18: 15.780888 | CM18: 15.780888 | CN18: 15.780888 | CO18: 15.780888 | CP18: 15.780888 | CQ18: 15.780888 | CR18: 15.780888 | CS18: 15.780888 | CT18: 15.780888 | CU18: 16.254314 | CV18: 16.254314 | CW18: 16.254314 | CX18: 16.254314 | CY18: 16.254314 | CZ18: 16.254314 | DA18: 16.254314 | DB18: 16.254314 | DC18: 16.254314 | DD18: 16.254314 | DE18: 16.254314 | DF18: 16.254314 | DG18: 16.741944 | DH18: 16.741944 | DI18: 16.741944 | DJ18: 16.741944 | DK18: 16.741944 | DL18: 16.741944 | DM18: 16.741944 | DN18: 16.741944 | DO18: 16.741944 | DP18: 16.741944 | DQ18: 16.741944 | DR18: 16.741944 | DT18: =+F18-E18 -> 0 | DU18: =+G18-F18 -> 0 | DV18: =+H18-G18 -> 38.44 | DW18: =+I18-H18 -> 140.06
B19: AHRQ | C19: Lower Middle Market | E19: =+SUMIFS($O19:$DR19,$O$7:$DR$7,E$7) -> 0 | F19: =+SUMIFS($O19:$DR19,$O$7:$DR$7,F$7) -> 0 | G19: =+SUMIFS($O19:$DR19,$O$7:$DR$7,G$7) -> 0 | H19: =+SUMIFS($O19:$DR19,$O$7:$DR$7,H$7) -> 0 | I19: =+SUMIFS($O19:$DR19,$O$7:$DR$7,I$7) -> 37.5 | J19: =+SUMIFS($O19:$DR19,$O$7:$DR$7,J$7) -> 50 | K19: =+SUMIFS($O19:$DR19,$O$7:$DR$7,K$7) -> 12.5 | L19: =+SUMIFS($O19:$DR19,$O$7:$DR$7,L$7) -> 0 | M19: =+SUMIFS($O19:$DR19,$O$7:$DR$7,M$7) -> 0 | O19: 0 | P19: 0 | Q19: 0 | R19: 0 | S19: 0 | T19: 0 | U19: 0 | V19: 0 | W19: 0 | X19: 0 | Y19: 0 | Z19: 0 | AA19: 0 | AB19: 0 | AC19: 0 | AD19: 0 | AE19: 0 | AF19: 0 | AG19: 0 | AH19: 0 | AI19: 0 | AJ19: 0 | AK19: 0 | AL19: 0 | AM19: 0 | AN19: 0 | AO19: 0 | AP19: 0 | AQ19: 0 | AR19: 0 | AS19: 0 | AT19: 0 | AU19: 0 | AV19: 0 | AW19: 0 | AX19: 0 | AY19: 0 | AZ19: 0 | BA19: 0 | BB19: 0 | BC19: 0 | BD19: 0 | BE19: 0 | BF19: 0 | BG19: 0 | BH19: 0 | BI19: 0 | BJ19: 0 | BK19: 0 | BL19: 0 | BM19: 0 | BN19: 4.1666667 | BO19: 4.1666667 | BP19: 4.1666667 | BQ19: 4.1666667 | BR19: 4.1666667 | BS19: 4.1666667 | BT19: 4.1666667 | BU19: 4.1666667 | BV19: 4.1666667 | BW19: 4.1666667 | BX19: 4.1666667 | BY19: 4.1666667 | BZ19: 4.1666667 | CA19: 4.1666667 | CB19: 4.1666667 | CC19: 4.1666667 | CD19: 4.1666667 | CE19: 4.1666667 | CF19: 4.1666667 | CG19: 4.1666667 | CH19: 4.1666667 | CI19: 4.1666667 | CJ19: 4.1666667 | CK19: 4.1666667 | CL19: 0 | CM19: 0 | CN19: 0 | CO19: 0 | CP19: 0 | CQ19: 0 | CR19: 0 | CS19: 0 | CT19: 0 | CU19: 0 | CV19: 0 | CW19: 0 | CX19: 0 | CY19: 0 | CZ19: 0 | DA19: 0 | DB19: 0 | DC19: 0 | DD19: 0 | DE19: 0 | DF19: 0 | DG19: 0 | DH19: 0 | DI19: 0 | DJ19: 0 | DK19: 0 | DL19: 0 | DM19: 0 | DN19: 0 | DO19: 0 | DP19: 0 | DQ19: 0 | DR19: 0 | DT19: =+F19-E19 -> 0 | DU19: =+G19-F19 -> 0 | DV19: =+H19-G19 -> 0 | DW19: =+I19-H19 -> 37.5
B20: AIPP | C20: Major | E20: =+SUMIFS($O20:$DR20,$O$7:$DR$7,E$7) -> 0 | F20: =+SUMIFS($O20:$DR20,$O$7:$DR$7,F$7) -> 0 | G20: =+SUMIFS($O20:$DR20,$O$7:$DR$7,G$7) -> 0 | H20: =+SUMIFS($O20:$DR20,$O$7:$DR$7,H$7) -> 0 | I20: =+SUMIFS($O20:$DR20,$O$7:$DR$7,I$7) -> 58.05 | J20: =+SUMIFS($O20:$DR20,$O$7:$DR$7,J$7) -> 491.36 | K20: =+SUMIFS($O20:$DR20,$O$7:$DR$7,K$7) -> 590.0925 | L20: =+SUMIFS($O20:$DR20,$O$7:$DR$7,L$7) -> 607.79527 | M20: =+SUMIFS($O20:$DR20,$O$7:$DR$7,M$7) -> 626.02913 | O20: 0 | P20: 0 | Q20: 0 | R20: 0 | S20: 0 | T20: 0 | U20: 0 | V20: 0 | W20: 0 | X20: 0 | Y20: 0 | Z20: 0 | AA20: 0 | AB20: 0 | AC20: 0 | AD20: 0 | AE20: 0 | AF20: 0 | AG20: 0 | AH20: 0 | AI20: 0 | AJ20: 0 | AK20: 0 | AL20: 0 | AM20: 0 | AN20: 0 | AO20: 0 | AP20: 0 | AQ20: 0 | AR20: 0 | AS20: 0 | AT20: 0 | AU20: 0 | AV20: 0 | AW20: 0 | AX20: 0 | AY20: 0 | AZ20: 0 | BA20: 0 | BB20: 0 | BC20: 0 | BD20: 0 | BE20: 0 | BF20: 0 | BG20: 0 | BH20: 0 | BI20: 0 | BJ20: 0 | BK20: 0 | BL20: 0 | BM20: 5.805 | BN20: 5.805 | BO20: 5.805 | BP20: 5.805 | BQ20: 5.805 | BR20: 5.805 | BS20: 5.805 | BT20: 5.805 | BU20: 5.805 | BV20: 5.805 | BW20: 5.805 | BX20: 5.805 | BY20: 47.975 | BZ20: 47.975 | CA20: 47.975 | CB20: 47.975 | CC20: 47.975 | CD20: 47.975 | CE20: 47.975 | CF20: 47.975 | CG20: 47.975 | CH20: 47.975 | CI20: 47.975 | CJ20: 47.975 | CK20: 49.41425 | CL20: 49.41425 | CM20: 49.41425 | CN20: 49.41425 | CO20: 49.41425 | CP20: 49.41425 | CQ20: 49.41425 | CR20: 49.41425 | CS20: 49.41425 | CT20: 49.41425 | CU20: 49.41425 | CV20: 49.41425 | CW20: 50.896677 | CX20: 50.896677 | CY20: 50.896677 | CZ20: 50.896677 | DA20: 50.896677 | DB20: 50.896677 | DC20: 50.896677 | DD20: 50.896677 | DE20: 50.896677 | DF20: 50.896677 | DG20: 50.896677 | DH20: 50.896677 | DI20: 52.423578 | DJ20: 52.423578 | DK20: 52.423578 | DL20: 52.423578 | DM20: 52.423578 | DN20: 52.423578 | DO20: 52.423578 | DP20: 52.423578 | DQ20: 52.423578 | DR20: 52.423578 | DT20: =+F20-E20 -> 0 | DU20: =+G20-F20 -> 0 | DV20: =+H20-G20 -> 0 | DW20: =+I20-H20 -> 58.05
B21: ALLEN | C21: Upper Middle Market | E21: =+SUMIFS($O21:$DR21,$O$7:$DR$7,E$7) -> 0 | F21: =+SUMIFS($O21:$DR21,$O$7:$DR$7,F$7) -> 0 | G21: =+SUMIFS($O21:$DR21,$O$7:$DR$7,G$7) -> 257.041 | H21: =+SUMIFS($O21:$DR21,$O$7:$DR$7,H$7) -> 257.30004 | I21: =+SUMIFS($O21:$DR21,$O$7:$DR$7,I$7) -> 259.02504 | J21: =+SUMIFS($O21:$DR21,$O$7:$DR$7,J$7) -> 260.79579 | K21: =+SUMIFS($O21:$DR21,$O$7:$DR$7,K$7) -> 262.61966 | L21: =+SUMIFS($O21:$DR21,$O$7:$DR$7,L$7) -> 264.49825 | M21: =+SUMIFS($O21:$DR21,$O$7:$DR$7,M$7) -> 266.4332 | O21: 0 | P21: 0 | Q21: 0 | R21: 0 | S21: 0 | T21: 0 | U21: 0 | V21: 0 | W21: 0 | X21: 0 | Y21: 0 | Z21: 0 | AA21: 0 | AB21: 0 | AC21: 0 | AD21: 0 | AE21: 0 | AF21: 0 | AG21: 0 | AH21: 0 | AI21: 0 | AJ21: 0 | AK21: 0 | AL21: 0 | AM21: 0 | AN21: 8.334 | AO21: 10.417 | AP21: 12.5 | AQ21: 14.584 | AR21: 16.666 | AS21: 16.666 | AT21: 16.666 | AU21: 13.963 | AV21: 16.667 | AW21: 16.666 | AX21: 113.912 | AY21: 16.66667 | AZ21: 16.66667 | BA21: 25.95967 | BB21: 16.66667 | BC21: 16.66667 | BD21: 33.82867 | BE21: 16.66667 | BF21: 16.66667 | BG21: 23.81767 | BH21: 16.66667 | BI21: 16.66667 | BJ21: 40.36067 | BK21: 16.66667 | BL21: 16.66667 | BM21: 30.69167 | BN21: 16.66667 | BO21: 16.66667 | BP21: 31.66667 | BQ21: 16.66667 | BR21: 16.66667 | BS21: 31.66667 | BT21: 16.66667 | BU21: 16.66667 | BV21: 31.66667 | BW21: 16.66667 | BX21: 16.66667 | BY21: 31.11242 | BZ21: 16.66667 | CA21: 16.66667 | CB21: 32.11667 | CC21: 16.66667 | CD21: 16.66667 | CE21: 32.11667 | CF21: 16.66667 | CG21: 16.66667 | CH21: 32.11667 | CI21: 16.66667 | CJ21: 16.66667 | CK21: 31.545792 | CL21: 16.66667 | CM21: 16.66667 | CN21: 32.58017 | CO21: 16.66667 | CP21: 16.66667 | CQ21: 32.58017 | CR21: 16.66667 | CS21: 16.66667 | CT21: 32.58017 | CU21: 16.66667 | CV21: 16.66667 | CW21: 31.992166 | CX21: 16.66667 | CY21: 16.66667 | CZ21: 33.057575 | DA21: 16.66667 | DB21: 16.66667 | DC21: 33.057575 | DD21: 16.66667 | DE21: 16.66667 | DF21: 33.057575 | DG21: 16.66667 | DH21: 16.66667 | DI21: 32.451931 | DJ21: 16.66667 | DK21: 16.66667 | DL21: 33.549302 | DM21: 16.66667 | DN21: 16.66667 | DO21: 33.549302 | DP21: 16.66667 | DQ21: 16.66667 | DR21: 33.549302 | DT21: =+F21-E21 -> 0 | DU21: =+G21-F21 -> 257.041 | DV21: =+H21-G21 -> 0.25904 | DW21: =+I21-H21 -> 1.725
B22: AMA | C22: Mega | E22: =+SUMIFS($O22:$DR22,$O$7:$DR$7,E$7) -> 1334.569 | F22: =+SUMIFS($O22:$DR22,$O$7:$DR$7,F$7) -> 1606.576 | G22: =+SUMIFS($O22:$DR22,$O$7:$DR$7,G$7) -> 1662.549 | H22: =+SUMIFS($O22:$DR22,$O$7:$DR$7,H$7) -> 1841.8175 | I22: =+SUMIFS($O22:$DR22,$O$7:$DR$7,I$7) -> 1882.7406 | J22: =+SUMIFS($O22:$DR22,$O$7:$DR$7,J$7) -> 1935.1132 | K22: =+SUMIFS($O22:$DR22,$O$7:$DR$7,K$7) -> 164.7286 | L22: =+SUMIFS($O22:$DR22,$O$7:$DR$7,L$7) -> 169.67045 | M22: =+SUMIFS($O22:$DR22,$O$7:$DR$7,M$7) -> 0 | O22: 104.247 | P22: 104.247 | Q22: 104.247 | R22: 104.247 | S22: 107.22 | T22: 110.647 | U22: 110.647 | V22: 100.647 | W22: 110.647 | X22: 110.646 | Y22: 110.647 | Z22: 156.48 | AA22: 137.27 | AB22: 137.27 | AC22: 133.104 | AD22: 133.103 | AE22: 133.104 | AF22: 133.103 | AG22: 133.103 | AH22: 133.103 | AI22: 133.104 | AJ22: 134.104 | AK22: 133.104 | AL22: 133.104 | AM22: 137.208 | AN22: 137.208 | AO22: 137.208 | AP22: 137.208 | AQ22: 137.208 | AR22: 137.208 | AS22: 138.208 | AT22: 131.394 | AU22: 138.208 | AV22: 138.208 | AW22: 143.575 | AX22: 149.708 | AY22: 154.25563 | AZ22: 154.25563 | BA22: 154.25563 | BB22: 154.25563 | BC22: 154.25563 | BD22: 154.25563 | BE22: 154.25563 | BF22: 154.25563 | BG22: 154.25563 | BH22: 150.92229 | BI22: 151.29729 | BJ22: 151.29729 | BK22: 156.83067 | BL22: 156.83067 | BM22: 156.83067 | BN22: 156.83067 | BO22: 156.83067 | BP22: 156.83067 | BQ22: 156.83067 | BR22: 156.83067 | BS22: 156.83067 | BT22: 156.83067 | BU22: 157.21692 | BV22: 157.21692 | BW22: 161.19313 | BX22: 161.19313 | BY22: 161.19313 | BZ22: 161.19313 | CA22: 161.19313 | CB22: 161.19313 | CC22: 161.19313 | CD22: 161.19313 | CE22: 161.19313 | CF22: 161.19313 | CG22: 161.59097 | CH22: 161.59097 | CI22: 13.659088 | CJ22: 13.659088 | CK22: 13.659088 | CL22: 13.659088 | CM22: 13.659088 | CN22: 13.659088 | CO22: 13.659088 | CP22: 13.659088 | CQ22: 13.659088 | CR22: 13.659088 | CS22: 14.06886 | CT22: 14.06886 | CU22: 14.06886 | CV22: 14.06886 | CW22: 14.06886 | CX22: 14.06886 | CY22: 14.06886 | CZ22: 14.06886 | DA22: 14.06886 | DB22: 14.06886 | DC22: 14.06886 | DD22: 14.06886 | DE22: 14.490926 | DF22: 14.490926 | DG22: 0 | DH22: 0 | DI22: 0 | DJ22: 0 | DK22: 0 | DL22: 0 | DM22: 0 | DN22: 0 | DO22: 0 | DP22: 0 | DQ22: 0 | DR22: 0 | DT22: =+F22-E22 -> 272.007 | DU22: =+G22-F22 -> 55.973 | DV22: =+H22-G22 -> 179.26851 | DW22: =+I22-H22 -> 40.92307
B23: AORN | C23: Lower Middle Market | E23: =+SUMIFS($O23:$DR23,$O$7:$DR$7,E$7) -> 93.752 | F23: =+SUMIFS($O23:$DR23,$O$7:$DR$7,F$7) -> 128.287 | G23: =+SUMIFS($O23:$DR23,$O$7:$DR$7,G$7) -> 132.489 | H23: =+SUMIFS($O23:$DR23,$O$7:$DR$7,H$7) -> 137.41808 | I23: =+SUMIFS($O23:$DR23,$O$7:$DR$7,I$7) -> 142.22771 | J23: =+SUMIFS($O23:$DR23,$O$7:$DR$7,J$7) -> 35.860094 | K23: =+SUMIFS($O23:$DR23,$O$7:$DR$7,K$7) -> 0 | L23: =+SUMIFS($O23:$DR23,$O$7:$DR$7,L$7) -> 0 | M23: =+SUMIFS($O23:$DR23,$O$7:$DR$7,M$7) -> 0 | O23: 0 | P23: 0 | Q23: 0 | R23: 10.417 | S23: 10.417 | T23: 10.417 | U23: 10.417 | V23: 10.417 | W23: 10.417 | X23: 10.417 | Y23: 10.417 | Z23: 10.416 | AA23: 10.417 | AB23: 10.417 | AC23: 10.417 | AD23: 10.782 | AE23: 10.781 | AF23: 10.782 | AG23: 10.782 | AH23: 10.782 | AI23: 10.782 | AJ23: 10.782 | AK23: 10.782 | AL23: 10.781 | AM23: 10.782 | AN23: 10.782 | AO23: 10.782 | AP23: 11.159 | AQ23: 11.158 | AR23: 11.159 | AS23: 11.159 | AT23: 10.874 | AU23: 11.159 | AV23: 11.158 | AW23: 11.159 | AX23: 11.158 | AY23: 11.158594 | AZ23: 11.158594 | BA23: 11.158594 | BB23: 11.549145 | BC23: 11.549145 | BD23: 11.549145 | BE23: 11.549145 | BF23: 11.549145 | BG23: 11.549145 | BH23: 11.549145 | BI23: 11.549145 | BJ23: 11.549145 | BK23: 11.549145 | BL23: 11.549145 | BM23: 11.549145 | BN23: 11.953365 | BO23: 11.953365 | BP23: 11.953365 | BQ23: 11.953365 | BR23: 11.953365 | BS23: 11.953365 | BT23: 11.953365 | BU23: 11.953365 | BV23: 11.953365 | BW23: 11.953365 | BX23: 11.953365 | BY23: 11.953365 | BZ23: 0 | CA23: 0 | CB23: 0 | CC23: 0 | CD23: 0 | CE23: 0 | CF23: 0 | CG23: 0 | CH23: 0 | CI23: 0 | CJ23: 0 | CK23: 0 | CL23: 0 | CM23: 0 | CN23: 0 | CO23: 0 | CP23: 0 | CQ23: 0 | CR23: 0 | CS23: 0 | CT23: 0 | CU23: 0 | CV23: 0 | CW23: 0 | CX23: 0 | CY23: 0 | CZ23: 0 | DA23: 0 | DB23: 0 | DC23: 0 | DD23: 0 | DE23: 0 | DF23: 0 | DG23: 0 | DH23: 0 | DI23: 0 | DJ23: 0 | DK23: 0 | DL23: 0 | DM23: 0 | DN23: 0 | DO23: 0 | DP23: 0 | DQ23: 0 | DR23: 0 | DT23: =+F23-E23 -> 34.535 | DU23: =+G23-F23 -> 4.202 | DV23: =+H23-G23 -> 4.929082 | DW23: =+I23-H23 -> 4.8096329
B24: AOTA | C24: Lower Middle Market | E24: =+SUMIFS($O24:$DR24,$O$7:$DR$7,E$7) -> 92.25 | F24: =+SUMIFS($O24:$DR24,$O$7:$DR$7,F$7) -> 95.13 | G24: =+SUMIFS($O24:$DR24,$O$7:$DR$7,G$7) -> 88.41 | H24: =+SUMIFS($O24:$DR24,$O$7:$DR$7,H$7) -> 48.907667 | I24: =+SUMIFS($O24:$DR24,$O$7:$DR$7,I$7) -> 54.928557 | J24: =+SUMIFS($O24:$DR24,$O$7:$DR$7,J$7) -> 56.576413 | K24: =+SUMIFS($O24:$DR24,$O$7:$DR$7,K$7) -> 58.273706 | L24: =+SUMIFS($O24:$DR24,$O$7:$DR$7,L$7) -> 60.021917 | M24: =+SUMIFS($O24:$DR24,$O$7:$DR$7,M$7) -> 30.951492 | O24: 7.5 | P24: 7.5 | Q24: 7.5 | R24: 7.5 | S24: 7.5 | T24: 7.5 | U24: 7.875 | V24: 7.875 | W24: 7.875 | X24: 7.875 | Y24: 7.875 | Z24: 7.875 | AA24: 7.875 | AB24: 7.875 | AC24: 7.875 | AD24: 7.875 | AE24: 7.875 | AF24: 7.875 | AG24: 7.98 | AH24: 7.98 | AI24: 7.98 | AJ24: 7.98 | AK24: 7.98 | AL24: 7.98 | AM24: 8.111 | AN24: 8.111 | AO24: 8.111 | AP24: 8.111 | AQ24: 8.111 | AR24: 8.22 | AS24: 8.22 | AT24: 7.549 | AU24: 8.22 | AV24: 8.22 | AW24: 3.713 | AX24: 3.713 | AY24: 3.713 | AZ24: 3.713 | BA24: 3.713 | BB24: 3.713 | BC24: 3.713 | BD24: 3.713 | BE24: 3.713 | BF24: 4.5833333 | BG24: 4.5833333 | BH24: 4.5833333 | BI24: 4.5833333 | BJ24: 4.5833333 | BK24: 4.5833333 | BL24: 4.5833333 | BM24: 4.5833333 | BN24: 4.5833333 | BO24: 4.5833333 | BP24: 4.5833333 | BQ24: 3.82439 | BR24: 4.7208333 | BS24: 4.7208333 | BT24: 4.7208333 | BU24: 4.7208333 | BV24: 4.7208333 | BW24: 4.7208333 | BX24: 4.7208333 | BY24: 4.7208333 | BZ24: 4.7208333 | CA24: 4.7208333 | CB24: 4.7208333 | CC24: 3.9391217 | CD24: 4.8624583 | CE24: 4.8624583 | CF24: 4.8624583 | CG24: 4.8624583 | CH24: 4.8624583 | CI24: 4.8624583 | CJ24: 4.8624583 | CK24: 4.8624583 | CL24: 4.8624583 | CM24: 4.8624583 | CN24: 4.8624583 | CO24: 4.0572954 | CP24: 5.0083321 | CQ24: 5.0083321 | CR24: 5.0083321 | CS24: 5.0083321 | CT24: 5.0083321 | CU24: 5.0083321 | CV24: 5.0083321 | CW24: 5.0083321 | CX24: 5.0083321 | CY24: 5.0083321 | CZ24: 5.0083321 | DA24: 4.1790142 | DB24: 5.158582 | DC24: 5.158582 | DD24: 5.158582 | DE24: 5.158582 | DF24: 5.158582 | DG24: 5.158582 | DH24: 5.158582 | DI24: 5.158582 | DJ24: 5.158582 | DK24: 5.158582 | DL24: 5.158582 | DM24: 0 | DN24: 0 | DO24: 0 | DP24: 0 | DQ24: 0 | DR24: 0 | DT24: =+F24-E24 -> 2.88 | DU24: =+G24-F24 -> -6.72 | DV24: =+H24-G24 -> -39.502333 | DW24: =+I24-H24 -> 6.02089
... B58: EL | C58: Lower Middle Market | E58: =+SUMIFS($O58:$DR58,$O$7:$DR$7,E$7) -> 0 | F58: =+SUMIFS($O58:$DR58,$O$7:$DR$7,F$7) -> 0 | G58: =+SUMIFS($O58:$DR58,$O$7:$DR$7,G$7) -> 0 | H58: =+SUMIFS($O58:$DR58,$O$7:$DR$7,H$7) -> 0 | I58: =+SUMIFS($O58:$DR58,$O$7:$DR$7,I$7) -> 0 | J58: =+SUMIFS($O58:$DR58,$O$7:$DR$7,J$7) -> 0 | K58: =+SUMIFS($O58:$DR58,$O$7:$DR$7,K$7) -> 0 | L58: =+SUMIFS($O58:$DR58,$O$7:$DR$7,L$7) -> 0 | M58: =+SUMIFS($O58:$DR58,$O$7:$DR$7,M$7) -> 0 | O58: 0 | P58: 0 | Q58: 0 | R58: 0 | S58: 0 | T58: 0 | U58: 0 | V58: 0 | W58: 0 | X58: 0 | Y58: 0 | Z58: 0 | AA58: 0 | AB58: 0 | AC58: 0 | AD58: 0 | AE58: 0 | AF58: 0 | AG58: 0 | AH58: 0 | AI58: 0 | AJ58: 0 | AK58: 0 | AL58: 0 | AM58: 0 | AN58: 0 | AO58: 0 | AP58: 0 | AQ58: 0 | AR58: 0 | AS58: 0 | AT58: 0 | AU58: 0 | AV58: 0 | AW58: 0 | AX58: 0 | AY58: 0 | AZ58: 0 | BA58: 0 | BB58: 0 | BC58: 0 | BD58: 0 | BE58: 0 | BF58: 0 | BG58: 0 | BH58: 0 | BI58: 0 | BJ58: 0 | BK58: 0 | BL58: 0 | BM58: 0 | BN58: 0 | BO58: 0 | BP58: 0 | BQ58: 0 | BR58: 0 | BS58: 0 | BT58: 0 | BU58: 0 | BV58: 0 | BW58: 0 | BX58: 0 | BY58: 0 | BZ58: 0 | CA58: 0 | CB58: 0 | CC58: 0 | CD58: 0 | CE58: 0 | CF58: 0 | CG58: 0 | CH58: 0 | CI58: 0 | CJ58: 0 | CK58: 0 | CL58: 0 | CM58: 0 | CN58: 0 | CO58: 0 | CP58: 0 | CQ58: 0 | CR58: 0 | CS58: 0 | CT58: 0 | CU58: 0 | CV58: 0 | CW58: 0 | CX58: 0 | CY58: 0 | CZ58: 0 | DA58: 0 | DB58: 0 | DC58: 0 | DD58: 0 | DE58: 0 | DF58: 0 | DG58: 0 | DH58: 0 | DI58: 0 | DJ58: 0 | DK58: 0 | DL58: 0 | DM58: 0 | DN58: 0 | DO58: 0 | DP58: 0 | DQ58: 0 | DR58: 0 | DT58: =+F58-E58 -> 0 | DU58: =+G58-F58 -> 0 | DV58: =+H58-G58 -> 0 | DW58: =+I58-H58 -> 0
B60: Total Revenue1 | E60: =+SUMIFS($O60:$DR60,$O$7:$DR$7,E$7) -> 11167.372 | F60: =+SUMIFS($O60:$DR60,$O$7:$DR$7,F$7) -> 11832.24 | G60: =+SUMIFS($O60:$DR60,$O$7:$DR$7,G$7) -> 12843.318 | H60: =+SUMIFS($O60:$DR60,$O$7:$DR$7,H$7) -> 14067.637 | I60: =+SUMIFS($O60:$DR60,$O$7:$DR$7,I$7) -> 15164.823 | J60: =+SUMIFS($O60:$DR60,$O$7:$DR$7,J$7) -> 15806.088 | K60: =+SUMIFS($O60:$DR60,$O$7:$DR$7,K$7) -> 10174.325 | L60: =+SUMIFS($O60:$DR60,$O$7:$DR$7,L$7) -> 9125.1379 | M60: =+SUMIFS($O60:$DR60,$O$7:$DR$7,M$7) -> 7341.599 | O60: =SUM(O13:O59) -> 919.323 | P60: =SUM(P13:P59) -> 921.315 | Q60: =SUM(Q13:Q59) -> 921.416 | R60: =SUM(R13:R59) -> 931.833 | S60: =SUM(S13:S59) -> 935.01 | T60: =SUM(T13:T59) -> 938.942 | U60: =SUM(U13:U59) -> 925.846 | V60: =SUM(V13:V59) -> 918.079 | ... DR60: =SUM(DR13:DR59) -> 607.01269
B61: Check | BK61: 0 | BL61: 0 | BM61: 0 | BN61: 0 | BO61: 0 | BP61: 0 | BQ61: 0 | BR61: 0 | BS61: 0 | BT61: 0 | BU61: 0 | BV61: 0
B63: Revenue, Beginning | F63: =+E69 -> 11167.372 | G63: =+F69 -> 11832.24 | H63: =+G69 -> 12843.318
B64: Churn | F64: =+SUMIF(DT$13:DT$58,"<0") -> -597.862 | G64: =+SUMIF(DU$13:DU$58,"<0") -> -580.329 | H64: =+SUMIF(DV$13:DV$58,"<0") -> -178.76669
B65: Gross Retention | F65: =SUM(F63:F64) -> 10569.51 | G65: =SUM(G63:G64) -> 11251.911 | H65: =SUM(H63:H64) -> 12664.551
B66: Upsell | F66: =+SUMIF(DT$13:DT$58,">0")-F68 -> 930.189 | G66: =+SUMIF(DU$13:DU$58,">0")-G68 -> 1210.534 | H66: =+SUMIF(DV$13:DV$58,">0")-H68 -> 1128.4267
B67: Net Retention | F67: =+SUM(F65:F66) -> 11499.699 | G67: =+SUM(G65:G66) -> 12462.445 | H67: =+SUM(H65:H66) -> 13792.978
B68: New | F68: =+SUMIFS(F$13:F$58,E$13:E$58,0) -> 332.541 | G68: =+SUMIFS(G$13:G$58,F$13:F$58,0) -> 380.873 | H68: =+SUMIFS(H$13:H$58,G$13:G$58,0) -> 274.65855
B69: Revenue, Ending | E69: =+E60 -> 11167.372 | F69: =+SUM(F67:F68) -> 11832.24 | G69: =+SUM(G67:G68) -> 12843.318 | H69: =+SUM(H67:H68) -> 14067.637
B71: Gross Retention | F71: =+F65/F63 -> 0.9464635 | G71: =+G65/G63 -> 0.95095358 | H71: =+H65/H63 -> 0.98608096
B72: Net Retention | F72: =+F67/F63 -> 1.0297587 | G72: =+G67/G63 -> 1.0532617 | H72: =+H67/H63 -> 1.073942
B74: Mega
B75: Revenue, Beginning | F75: =+E84 -> 7304.549 | G75: =+F84 -> 7916.045 | H75: =+G84 -> 8245.29 | I75: =+H84 -> 8781.0996 | J75: =+I84 -> 9075.5233 | K75: =+J84 -> 9607.4895 | L75: =+K84 -> 11031.683 | M75: =+L84 -> 12578.996
B76: Churn | F76: =+SUMIFS(DT$13:DT$58,DT$13:DT$58,"<0",$C$13:$C$58,$B$74) -> 0 | G76: =+SUMIFS(DU$13:DU$58,DU$13:DU$58,"<0",$C$13:$C$58,$B$74) -> 0 | H76: =+SUMIFS(DV$13:DV$58,DV$13:DV$58,"<0",$C$13:$C$58,$B$74) -> 0 | I76: =+SUMIFS(DW$13:DW$58,DW$13:DW$58,"<0",$C$13:$C$58,$B$74) -> 0 | J76: =+Revenue_Assumptions!J14*J$75 -> 0 | K76: =+Revenue_Assumptions!K14*K$75 -> 0 | L76: =+Revenue_Assumptions!L14*L$75 -> 0 | M76: =+Revenue_Assumptions!M14*M$75 -> 0
B77: Expansion | F77: =+SUMIFS(DT$13:DT$58,DT$13:DT$58,">0",$C$13:$C$58,$B$74)-F82 -> 611.496 | G77: =+SUMIFS(DU$13:DU$58,DU$13:DU$58,">0",$C$13:$C$58,$B$74)-G82 -> 329.245 | H77: =+SUMIFS(DV$13:DV$58,DV$13:DV$58,">0",$C$13:$C$58,$B$74)-H82 -> 535.80959 | I77: =+SUMIFS(DW$13:DW$58,DW$13:DW$58,">0",$C$13:$C$58,$B$74)-I82 -> 294.42368 | J77: =+Revenue_Assumptions!J15*J$75 -> 499.15378 | K77: =+Revenue_Assumptions!K15*K$75 -> 528.41193 | L77: =+Revenue_Assumptions!L15*L$75 -> 606.74255 | M77: =+Revenue_Assumptions!M15*M$75 -> 691.84476
B78: Net Retention | F78: =SUM(F75:F77) -> 7916.045 | G78: =SUM(G75:G77) -> 8245.29 | H78: =SUM(H75:H77) -> 8781.0996 | I78: =SUM(I75:I77) -> 9075.5233 | J78: =SUM(J75:J77) -> 9574.677 | K78: =SUM(K75:K77) -> 10135.901 | L78: =SUM(L75:L77) -> 11638.425 | M78: =SUM(M75:M77) -> 13270.84
B80: YTD New Clients | AA80: =+'Bookings to Revenue_Calcs'!AA26 | AB80: =+'Bookings to Revenue_Calcs'!AB26 | AC80: =+'Bookings to Revenue_Calcs'!AC26 | AD80: =+'Bookings to Revenue_Calcs'!AD26 | AE80: =+'Bookings to Revenue_Calcs'!AE26 | AF80: =+'Bookings to Revenue_Calcs'!AF26 | AG80: =+'Bookings to Revenue_Calcs'!AG26 | AH80: =+'Bookings to Revenue_Calcs'!AH26 | ... DR80: =+'Bookings to Revenue_Calcs'!DR26 -> 1
B81: Avg Revenue per New Client | AA81: =+SUMIFS(Revenue_Assumptions!$E18:$M18,Revenue_Assumptions!$E$7:$M$7,AA$7)/12 -> 0 | AB81: =+SUMIFS(Revenue_Assumptions!$E18:$M18,Revenue_Assumptions!$E$7:$M$7,AB$7)/12 -> 0 | AC81: =+SUMIFS(Revenue_Assumptions!$E18:$M18,Revenue_Assumptions!$E$7:$M$7,AC$7)/12 -> 0 | AD81: =+SUMIFS(Revenue_Assumptions!$E18:$M18,Revenue_Assumptions!$E$7:$M$7,AD$7)/12 -> 0 | AE81: =+SUMIFS(Revenue_Assumptions!$E18:$M18,Revenue_Assumptions!$E$7:$M$7,AE$7)/12 -> 0 | AF81: =+SUMIFS(Revenue_Assumptions!$E18:$M18,Revenue_Assumptions!$E$7:$M$7,AF$7)/12 -> 0 | AG81: =+SUMIFS(Revenue_Assumptions!$E18:$M18,Revenue_Assumptions!$E$7:$M$7,AG$7)/12 -> 0 | AH81: =+SUMIFS(Revenue_Assumptions!$E18:$M18,Revenue_Assumptions!$E$7:$M$7,AH$7)/12 -> 0 | ... DR81: =+SUMIFS(Revenue_Assumptions!$E18:$M18,Revenue_Assumptions!$E$7:$M$7,DR$7)/12 -> 151.93828
B82: New Revenue | E82: =+SUMIFS($AA82:$DR82,$AA$7:$DR$7,E$7) -> 0 | F82: =+SUMIFS($AA82:$DR82,$AA$7:$DR$7,F$7) -> 0 | G82: =+SUMIFS($AA82:$DR82,$AA$7:$DR$7,G$7) -> 0 | H82: =+SUMIFS($AA82:$DR82,$AA$7:$DR$7,H$7) -> 0 | I82: =+SUMIFS($AA82:$DR82,$AA$7:$DR$7,I$7) -> 0 | J82: =+SUMIFS($AA82:$DR82,$AA$7:$DR$7,J$7) -> 32.8125 | K82: =+SUMIFS($AA82:$DR82,$AA$7:$DR$7,K$7) -> 895.78125 | L82: =+SUMIFS($AA82:$DR82,$AA$7:$DR$7,L$7) -> 940.57031 | M82: =+SUMIFS($AA82:$DR82,$AA$7:$DR$7,M$7) -> 987.59883 | AA82: =+AA80*AA81 -> 0 | AB82: =+AB80*AB81 -> 0 | AC82: =+AC80*AC81 -> 0 | AD82: =+AD80*AD81 -> 0 | AE82: =+AE80*AE81 -> 0 | AF82: =+AF80*AF81 -> 0 | AG82: =+AG80*AG81 -> 0 | AH82: =+AH80*AH81 -> 0 | ... DR82: =+DR80*DR81 -> 151.93828
B84: Total Revenue | E84: =+SUMIFS(E$13:E$58,$C$13:$C$58,$B$74) -> 7304.549 | F84: =+SUM(F78,F82) -> 7916.045 | G84: =+SUM(G78,G82) -> 8245.29 | H84: =+SUM(H78,H82) -> 8781.0996 | I84: =+SUM(I78,I82) -> 9075.5233 | J84: =+SUM(J78,J82) -> 9607.4895 | K84: =+SUM(K78,K82) -> 11031.683 | L84: =+SUM(L78,L82) -> 12578.996 | M84: =+SUM(M78,M82) -> 14258.439
B86: Major
B87: Revenue, Beginning | F87: =+E96 -> 1750.371 | G87: =+F96 -> 1771.212 | H87: =+G96 -> 1842.559 | I87: =+H96 -> 1905.0657 | J87: =+I96 -> 2067.5604 | K87: =+J96 -> 2432.239 | L87: =+K96 -> 2936.4859 | M87: =+L96 -> 3488.9031
B88: Churn | F88: =+SUMIFS(DT$13:DT$58,DT$13:DT$58,"<0",$C$13:$C$58,$B$86) -> -49.611 | G88: =+SUMIFS(DU$13:DU$58,DU$13:DU$58,"<0",$C$13:$C$58,$B$86) -> 0 | H88: =+SUMIFS(DV$13:DV$58,DV$13:DV$58,"<0",$C$13:$C$58,$B$86) -> 0 | I88: =+SUMIFS(DW$13:DW$58,DW$13:DW$58,"<0",$C$13:$C$58,$B$86) -> -92.243 | J88: =+Revenue_Assumptions!J21*J$87 -> 0 | K88: =+Revenue_Assumptions!K21*K$87 -> 0 | L88: =+Revenue_Assumptions!L21*L$87 -> 0 | M88: =+Revenue_Assumptions!M21*M$87 -> 0
B89: Expansion | F89: =+SUMIFS(DT$13:DT$58,DT$13:DT$58,">0",$C$13:$C$58,$B$86)-F94 -> 70.452 | G89: =+SUMIFS(DU$13:DU$58,DU$13:DU$58,">0",$C$13:$C$58,$B$86)-G94 -> 71.347 | H89: =+SUMIFS(DV$13:DV$58,DV$13:DV$58,">0",$C$13:$C$58,$B$86)-H94 -> 62.5067 | I89: =+SUMIFS(DW$13:DW$58,DW$13:DW$58,">0",$C$13:$C$58,$B$86)-I94 -> 254.73769 | J89: =+Revenue_Assumptions!J22*J$87 -> 124.05362 | K89: =+Revenue_Assumptions!K22*K$87 -> 145.93434 | L89: =+Revenue_Assumptions!L22*L$87 -> 176.18915 | M89: =+Revenue_Assumptions!M22*M$87 -> 209.33419
B90: Net Retention | F90: =SUM(F87:F89) -> 1771.212 | G90: =SUM(G87:G89) -> 1842.559 | H90: =SUM(H87:H89) -> 1905.0657 | I90: =SUM(I87:I89) -> 2067.5604 | J90: =SUM(J87:J89) -> 2191.614 | K90: =SUM(K87:K89) -> 2578.1734 | L90: =SUM(L87:L89) -> 3112.675 | M90: =SUM(M87:M89) -> 3698.2373
B92: YTD New Clients | AA92: =+'Bookings to Revenue_Calcs'!AA33 | AB92: =+'Bookings to Revenue_Calcs'!AB33 | AC92: =+'Bookings to Revenue_Calcs'!AC33 | AD92: =+'Bookings to Revenue_Calcs'!AD33 | AE92: =+'Bookings to Revenue_Calcs'!AE33 | AF92: =+'Bookings to Revenue_Calcs'!AF33 | AG92: =+'Bookings to Revenue_Calcs'!AG33 | AH92: =+'Bookings to Revenue_Calcs'!AH33 | ... DR92: =+'Bookings to Revenue_Calcs'!DR33 -> 1
B93: Avg Revenue per New Client | AA93: =+SUMIFS(Revenue_Assumptions!$E25:$M25,Revenue_Assumptions!$E$7:$M$7,AA$7)/12 -> 0 | AB93: =+SUMIFS(Revenue_Assumptions!$E25:$M25,Revenue_Assumptions!$E$7:$M$7,AB$7)/12 -> 0 | AC93: =+SUMIFS(Revenue_Assumptions!$E25:$M25,Revenue_Assumptions!$E$7:$M$7,AC$7)/12 -> 0 | AD93: =+SUMIFS(Revenue_Assumptions!$E25:$M25,Revenue_Assumptions!$E$7:$M$7,AD$7)/12 -> 0 | AE93: =+SUMIFS(Revenue_Assumptions!$E25:$M25,Revenue_Assumptions!$E$7:$M$7,AE$7)/12 -> 0 | AF93: =+SUMIFS(Revenue_Assumptions!$E25:$M25,Revenue_Assumptions!$E$7:$M$7,AF$7)/12 -> 0 | AG93: =+SUMIFS(Revenue_Assumptions!$E25:$M25,Revenue_Assumptions!$E$7:$M$7,AG$7)/12 -> 0 | AH93: =+SUMIFS(Revenue_Assumptions!$E25:$M25,Revenue_Assumptions!$E$7:$M$7,AH$7)/12 -> 0 | ... DR93: =+SUMIFS(Revenue_Assumptions!$E25:$M25,Revenue_Assumptions!$E$7:$M$7,DR$7)/12 -> 60.775312
B94: New Revenue | E94: =+SUMIFS($AA94:$DR94,$AA$7:$DR$7,E$7) -> 0 | F94: =+SUMIFS($AA94:$DR94,$AA$7:$DR$7,F$7) -> 0 | G94: =+SUMIFS($AA94:$DR94,$AA$7:$DR$7,G$7) -> 0 | H94: =+SUMIFS($AA94:$DR94,$AA$7:$DR$7,H$7) -> 0 | I94: =+SUMIFS($AA94:$DR94,$AA$7:$DR$7,I$7) -> 0 | J94: =+SUMIFS($AA94:$DR94,$AA$7:$DR$7,J$7) -> 240.625 | K94: =+SUMIFS($AA94:$DR94,$AA$7:$DR$7,K$7) -> 358.3125 | L94: =+SUMIFS($AA94:$DR94,$AA$7:$DR$7,L$7) -> 376.22812 | M94: =+SUMIFS($AA94:$DR94,$AA$7:$DR$7,M$7) -> 395.03953 | AA94: =+AA92*AA93 -> 0 | AB94: =+AB92*AB93 -> 0 | AC94: =+AC92*AC93 -> 0 | AD94: =+AD92*AD93 -> 0 | AE94: =+AE92*AE93 -> 0 | AF94: =+AF92*AF93 -> 0 | AG94: =+AG92*AG93 -> 0 | AH94: =+AH92*AH93 -> 0 | ... DR94: =+DR92*DR93 -> 60.775312
B96: Total Revenue | E96: =+SUMIFS(E$13:E$58,$C$13:$C$58,$B$86) -> 1750.371 | F96: =+SUM(F90,F94) -> 1771.212 | G96: =+SUM(G90,G94) -> 1842.559 | H96: =+SUM(H90,H94) -> 1905.0657 | I96: =+SUM(I90,I94) -> 2067.5604 | J96: =+SUM(J90,J94) -> 2432.239 | K96: =+SUM(K90,K94) -> 2936.4859 | L96: =+SUM(L90,L94) -> 3488.9031 | M96: =+SUM(M90,M94) -> 4093.2769
B98: Upper Middle Market
B99: Revenue, Beginning | F99: =+E108 -> 788.562 | G99: =+F108 -> 1021.766 | H99: =+G108 -> 1442.292 | I99: =+H108 -> 2048.7125 | J99: =+I108 -> 2199.9747 | K99: =+J108 -> 2835.7219 | L99: =+K108 -> 3625.4013 | M99: =+L108 -> 4699.4767
B100: Churn | F100: =+SUMIFS(DT$13:DT$58,DT$13:DT$58,"<0",$C$13:$C$58,$B$98) -> -57.492 | G100: =+SUMIFS(DU$13:DU$58,DU$13:DU$58,"<0",$C$13:$C$58,$B$98) -> -241.438 | H100: =+SUMIFS(DV$13:DV$58,DV$13:DV$58,"<0",$C$13:$C$58,$B$98) -> 0 | I100: =+SUMIFS(DW$13:DW$58,DW$13:DW$58,"<0",$C$13:$C$58,$B$98) -> 0 | J100: =+Revenue_Assumptions!J28*J$99 -> -21.999747 | K100: =+Revenue_Assumptions!K28*K$99 -> -28.357219 | L100: =+Revenue_Assumptions!L28*L$99 -> -36.254013 | M100: =+Revenue_Assumptions!M28*M$99 -> -46.994767
B101: Expansion | F101: =+SUMIFS(DT$13:DT$58,DT$13:DT$58,">0",$C$13:$C$58,$B$98)-F106 -> 290.696 | G101: =+SUMIFS(DU$13:DU$58,DU$13:DU$58,">0",$C$13:$C$58,$B$98)-G106 -> 661.964 | H101: =+SUMIFS(DV$13:DV$58,DV$13:DV$58,">0",$C$13:$C$58,$B$98)-H106 -> 606.42052 | I101: =+SUMIFS(DW$13:DW$58,DW$13:DW$58,">0",$C$13:$C$58,$B$98)-I106 -> 138.76217 | J101: =+Revenue_Assumptions!J29*J$99 -> 263.99696 | K101: =+Revenue_Assumptions!K29*K$99 -> 340.28663 | L101: =+Revenue_Assumptions!L29*L$99 -> 435.04816 | M101: =+Revenue_Assumptions!M29*M$99 -> 563.93721
B102: Net Retention | F102: =SUM(F99:F101) -> 1021.766 | G102: =SUM(G99:G101) -> 1442.292 | H102: =SUM(H99:H101) -> 2048.7125 | I102: =SUM(I99:I101) -> 2187.4747 | J102: =SUM(J99:J101) -> 2441.9719 | K102: =SUM(K99:K101) -> 3147.6513 | L102: =SUM(L99:L101) -> 4024.1955 | M102: =SUM(M99:M101) -> 5216.4192
B104: YTD New Clients | AA104: =+'Bookings to Revenue_Calcs'!AA47 | AB104: =+'Bookings to Revenue_Calcs'!AB47 | AC104: =+'Bookings to Revenue_Calcs'!AC47 | AD104: =+'Bookings to Revenue_Calcs'!AD47 | AE104: =+'Bookings to Revenue_Calcs'!AE47 | AF104: =+'Bookings to Revenue_Calcs'!AF47 | AG104: =+'Bookings to Revenue_Calcs'!AG47 | AH104: =+'Bookings to Revenue_Calcs'!AH47 | ... DR104: =+'Bookings to Revenue_Calcs'!DR47 -> 8.3333333
B105: Avg Revenue per New Client | AA105: =+SUMIFS(Revenue_Assumptions!$E32:$M32,Revenue_Assumptions!$E$7:$M$7,AA$7)/12 -> 0 | AB105: =+SUMIFS(Revenue_Assumptions!$E32:$M32,Revenue_Assumptions!$E$7:$M$7,AB$7)/12 -> 0 | AC105: =+SUMIFS(Revenue_Assumptions!$E32:$M32,Revenue_Assumptions!$E$7:$M$7,AC$7)/12 -> 0 | AD105: =+SUMIFS(Revenue_Assumptions!$E32:$M32,Revenue_Assumptions!$E$7:$M$7,AD$7)/12 -> 0 | AE105: =+SUMIFS(Revenue_Assumptions!$E32:$M32,Revenue_Assumptions!$E$7:$M$7,AE$7)/12 -> 0 | AF105: =+SUMIFS(Revenue_Assumptions!$E32:$M32,Revenue_Assumptions!$E$7:$M$7,AF$7)/12 -> 0 | AG105: =+SUMIFS(Revenue_Assumptions!$E32:$M32,Revenue_Assumptions!$E$7:$M$7,AG$7)/12 -> 0 | AH105: =+SUMIFS(Revenue_Assumptions!$E32:$M32,Revenue_Assumptions!$E$7:$M$7,AH$7)/12 -> 0 | ... DR105: =+SUMIFS(Revenue_Assumptions!$E32:$M32,Revenue_Assumptions!$E$7:$M$7,DR$7)/12 -> 20.258437
B106: New Revenue | E106: =+SUMIFS($AA106:$DR106,$AA$7:$DR$7,E$7) -> 0 | F106: =+SUMIFS($AA106:$DR106,$AA$7:$DR$7,F$7) -> 0 | G106: =+SUMIFS($AA106:$DR106,$AA$7:$DR$7,G$7) -> 0 | H106: =+SUMIFS($AA106:$DR106,$AA$7:$DR$7,H$7) -> 0 | I106: =+SUMIFS($AA106:$DR106,$AA$7:$DR$7,I$7) -> 12.5 | J106: =+SUMIFS($AA106:$DR106,$AA$7:$DR$7,J$7) -> 393.75 | K106: =+SUMIFS($AA106:$DR106,$AA$7:$DR$7,K$7) -> 477.75 | L106: =+SUMIFS($AA106:$DR106,$AA$7:$DR$7,L$7) -> 675.28125 | M106: =+SUMIFS($AA106:$DR106,$AA$7:$DR$7,M$7) -> 1043.3095 | AA106: =+AA104*AA105 -> 0 | AB106: =+AB104*AB105 -> 0 | AC106: =+AC104*AC105 -> 0 | AD106: =+AD104*AD105 -> 0 | AE106: =+AE104*AE105 -> 0 | AF106: =+AF104*AF105 -> 0 | AG106: =+AG104*AG105 -> 0 | AH106: =+AH104*AH105 -> 0 | ... DR106: =+DR104*DR105 -> 168.82031
B108: Total Revenue | E108: =+SUMIFS(E$13:E$58,$C$13:$C$58,$B$98) -> 788.562 | F108: =+SUM(F102,F106) -> 1021.766 | G108: =+SUM(G102,G106) -> 1442.292 | H108: =+SUM(H102,H106) -> 2048.7125 | I108: =+SUM(I102,I106) -> 2199.9747 | J108: =+SUM(J102,J106) -> 2835.7219 | K108: =+SUM(K102,K106) -> 3625.4013 | L108: =+SUM(L102,L106) -> 4699.4767 | M108: =+SUM(M102,M106) -> 6259.7287
B110: Lower Middle Market
B111: Revenue, Beginning | F111: =+E120 -> 1323.89 | G111: =+F120 -> 1123.217 | H111: =+G120 -> 1313.177 | I111: =+H120 -> 1332.7588 | J111: =+I120 -> 1821.7645 | K111: =+J120 -> 2286.47 | L111: =+K120 -> 2859.4402 | M111: =+L120 -> 3653.2182
B112: Churn | F112: =+SUMIFS(DT$13:DT$58,DT$13:DT$58,"<0",$C$13:$C$58,$B$110) -> -490.759 | G112: =+SUMIFS(DU$13:DU$58,DU$13:DU$58,"<0",$C$13:$C$58,$B$110) -> -338.891 | H112: =+SUMIFS(DV$13:DV$58,DV$13:DV$58,"<0",$C$13:$C$58,$B$110) -> -178.76669 | I112: =+SUMIFS(DW$13:DW$58,DW$13:DW$58,"<0",$C$13:$C$58,$B$110) -> -55.59764 | J112: =Revenue_Assumptions!J35*J$111 -> -54.652935 | K112: =Revenue_Assumptions!K35*K$111 -> -68.5941 | L112: =Revenue_Assumptions!L35*L$111 -> -85.783205 | M112: =Revenue_Assumptions!M35*M$111 -> -109.59654
B113: Expansion | F113: =+SUMIFS(DT$13:DT$58,DT$13:DT$58,">0",$C$13:$C$58,$B$110)-F118 -> 290.086 | G113: =+SUMIFS(DU$13:DU$58,DU$13:DU$58,">0",$C$13:$C$58,$B$110)-G118 -> 528.851 | H113: =+SUMIFS(DV$13:DV$58,DV$13:DV$58,">0",$C$13:$C$58,$B$110)-H118 -> 198.34846 | I113: =+SUMIFS(DW$13:DW$58,DW$13:DW$58,">0",$C$13:$C$58,$B$110)-I118 -> 536.79089 | J113: =Revenue_Assumptions!J36*J$111 -> 273.26468 | K113: =Revenue_Assumptions!K36*K$111 -> 342.9705 | L113: =Revenue_Assumptions!L36*L$111 -> 457.51042 | M113: =Revenue_Assumptions!M36*M$111 -> 602.781
B114: Net Retention | F114: =SUM(F111:F113) -> 1123.217 | G114: =SUM(G111:G113) -> 1313.177 | H114: =SUM(H111:H113) -> 1332.7588 | I114: =SUM(I111:I113) -> 1813.952 | J114: =SUM(J111:J113) -> 2040.3763 | K114: =SUM(K111:K113) -> 2560.8464 | L114: =SUM(L111:L113) -> 3231.1674 | M114: =SUM(M111:M113) -> 4146.4026
B116: YTD New Clients | AA116: =+'Bookings to Revenue_Calcs'!AA47 | AB116: =+'Bookings to Revenue_Calcs'!AB47 | AC116: =+'Bookings to Revenue_Calcs'!AC47 | AD116: =+'Bookings to Revenue_Calcs'!AD47 | AE116: =+'Bookings to Revenue_Calcs'!AE47 | AF116: =+'Bookings to Revenue_Calcs'!AF47 | AG116: =+'Bookings to Revenue_Calcs'!AG47 | AH116: =+'Bookings to Revenue_Calcs'!AH47 | ... DR116: =+'Bookings to Revenue_Calcs'!DR47 -> 8.3333333
B117: Avg Revenue per New Client | AA117: =+SUMIFS(Revenue_Assumptions!$E39:$M39,Revenue_Assumptions!$E$7:$M$7,AA$7)/12 -> 0 | AB117: =+SUMIFS(Revenue_Assumptions!$E39:$M39,Revenue_Assumptions!$E$7:$M$7,AB$7)/12 -> 0 | AC117: =+SUMIFS(Revenue_Assumptions!$E39:$M39,Revenue_Assumptions!$E$7:$M$7,AC$7)/12 -> 0 | AD117: =+SUMIFS(Revenue_Assumptions!$E39:$M39,Revenue_Assumptions!$E$7:$M$7,AD$7)/12 -> 0 | AE117: =+SUMIFS(Revenue_Assumptions!$E39:$M39,Revenue_Assumptions!$E$7:$M$7,AE$7)/12 -> 0 | AF117: =+SUMIFS(Revenue_Assumptions!$E39:$M39,Revenue_Assumptions!$E$7:$M$7,AF$7)/12 -> 0 | AG117: =+SUMIFS(Revenue_Assumptions!$E39:$M39,Revenue_Assumptions!$E$7:$M$7,AG$7)/12 -> 0 | AH117: =+SUMIFS(Revenue_Assumptions!$E39:$M39,Revenue_Assumptions!$E$7:$M$7,AH$7)/12 -> 0 | ... DR117: =+SUMIFS(Revenue_Assumptions!$E39:$M39,Revenue_Assumptions!$E$7:$M$7,DR$7)/12 -> 12.661523
B118: New Revenue | E118: =+SUMIFS($AA118:$DR118,$AA$7:$DR$7,E$7) -> 0 | F118: =+SUMIFS($AA118:$DR118,$AA$7:$DR$7,F$7) -> 0 | G118: =+SUMIFS($AA118:$DR118,$AA$7:$DR$7,G$7) -> 0 | H118: =+SUMIFS($AA118:$DR118,$AA$7:$DR$7,H$7) -> 0 | I118: =+SUMIFS($AA118:$DR118,$AA$7:$DR$7,I$7) -> 7.8125 | J118: =+SUMIFS($AA118:$DR118,$AA$7:$DR$7,J$7) -> 246.09375 | K118: =+SUMIFS($AA118:$DR118,$AA$7:$DR$7,K$7) -> 298.59375 | L118: =+SUMIFS($AA118:$DR118,$AA$7:$DR$7,L$7) -> 422.05078 | M118: =+SUMIFS($AA118:$DR118,$AA$7:$DR$7,M$7) -> 652.06846 | AA118: =+AA116*AA117 -> 0 | AB118: =+AB116*AB117 -> 0 | AC118: =+AC116*AC117 -> 0 | AD118: =+AD116*AD117 -> 0 | AE118: =+AE116*AE117 -> 0 | AF118: =+AF116*AF117 -> 0 | AG118: =+AG116*AG117 -> 0 | AH118: =+AH116*AH117 -> 0 | ... DR118: =+DR116*DR117 -> 105.5127
B120: Total Revenue | E120: =+SUMIFS(E$13:E$58,$C$13:$C$58,$B$110) -> 1323.89 | F120: =+SUM(F114,F118) -> 1123.217 | G120: =+SUM(G114,G118) -> 1313.177 | H120: =+SUM(H114,H118) -> 1332.7588 | I120: =+SUM(I114,I118) -> 1821.7645 | J120: =+SUM(J114,J118) -> 2286.47 | K120: =+SUM(K114,K118) -> 2859.4402 | L120: =+SUM(L114,L118) -> 3653.2182 | M120: =+SUM(M114,M118) -> 4798.4711
B122: Total Licensing Revenue | E122: =+SUMIFS($O122:$DR122,$O$7:$DR$7,E$7) -> 11167.372 | F122: =+SUMIFS($O122:$DR122,$O$7:$DR$7,F$7) -> 11832.24 | G122: =+SUMIFS($O122:$DR122,$O$7:$DR$7,G$7) -> 12843.318 | H122: =+SUMIFS($O122:$DR122,$O$7:$DR$7,H$7) -> 14067.637 | I122: =+SUMIFS($O122:$DR122,$O$7:$DR$7,I$7) -> 15185.135 | J122: =+SUM(J84,J96,J108,J120) -> 17161.92 | K122: =+SUM(K84,K96,K108,K120) -> 20453.01 | L122: =+SUM(L84,L96,L108,L120) -> 24420.594 | M122: =+SUM(M84,M96,M108,M120) -> 29409.916 | O122: =+SUM(O60,O82,O94,O106,O118) -> 919.323 | P122: =+SUM(P60,P82,P94,P106,P118) -> 921.315 | Q122: =+SUM(Q60,Q82,Q94,Q106,Q118) -> 921.416 | R122: =+SUM(R60,R82,R94,R106,R118) -> 931.833 | S122: =+SUM(S60,S82,S94,S106,S118) -> 935.01 | T122: =+SUM(T60,T82,T94,T106,T118) -> 938.942 | U122: =+SUM(U60,U82,U94,U106,U118) -> 925.846 | V122: =+SUM(V60,V82,V94,V106,V118) -> 918.079 | ... BV122: =+SUM(BV60,BV82,BV94,BV106,BV118) -> 1309.8714 | BW122: =+SUMIFS($E122:$M122,$E$7:$M$7,BW$7)*BW123 -> 1411.1156 | BX122: =+SUMIFS($E122:$M122,$E$7:$M$7,BX$7)*BX123 -> 1413.8382 | BY122: =+SUMIFS($E122:$M122,$E$7:$M$7,BY$7)*BY123 -> 1420.2154 | BZ122: =+SUMIFS($E122:$M122,$E$7:$M$7,BZ$7)*BZ123 -> 1422.3392 | CA122: =+SUMIFS($E122:$M122,$E$7:$M$7,CA$7)*CA123 -> 1422.318 | CB122: =+SUMIFS($E122:$M122,$E$7:$M$7,CB$7)*CB123 -> 1420.9363 | CC122: =+SUMIFS($E122:$M122,$E$7:$M$7,CC$7)*CC123 -> 1415.4816 | CD122: =+SUMIFS($E122:$M122,$E$7:$M$7,CD$7)*CD123 -> 1437.8293 | ... DR122: =+SUMIFS($E122:$M122,$E$7:$M$7,DR$7)*DR123 -> 2583.2225
B123: % Seasonality | E123: =+E122/SUMIFS($O122:$DR122,$O$7:$DR$7,E$7) -> 1 | F123: =+F122/SUMIFS($O122:$DR122,$O$7:$DR$7,F$7) -> 1 | G123: =+G122/SUMIFS($O122:$DR122,$O$7:$DR$7,G$7) -> 1 | H123: =+H122/SUMIFS($O122:$DR122,$O$7:$DR$7,H$7) -> 1 | I123: =+I122/SUMIFS($O122:$DR122,$O$7:$DR$7,I$7) -> 1 | J123: =+J122/SUMIFS($O122:$DR122,$O$7:$DR$7,J$7) -> 1 | K123: =+K122/SUMIFS($O122:$DR122,$O$7:$DR$7,K$7) -> 1 | L123: =+L122/SUMIFS($O122:$DR122,$O$7:$DR$7,L$7) -> 1 | M123: =+M122/SUMIFS($O122:$DR122,$O$7:$DR$7,M$7) -> 1 | O123: =+O122/SUMIFS($O122:$DR122,$O$7:$DR$7,O$7) -> 0.082322233 | P123: =+P122/SUMIFS($O122:$DR122,$O$7:$DR$7,P$7) -> 0.08250061 | Q123: =+Q122/SUMIFS($O122:$DR122,$O$7:$DR$7,Q$7) -> 0.082509654 | R123: =+R122/SUMIFS($O122:$DR122,$O$7:$DR$7,R$7) -> 0.083442461 | S123: =+S122/SUMIFS($O122:$DR122,$O$7:$DR$7,S$7) -> 0.08372695 | T123: =+T122/SUMIFS($O122:$DR122,$O$7:$DR$7,T$7) -> 0.084079047 | U123: =+U122/SUMIFS($O122:$DR122,$O$7:$DR$7,U$7) -> 0.082906345 | V123: =+V122/SUMIFS($O122:$DR122,$O$7:$DR$7,V$7) -> 0.082210837 | ... BV123: =+BV122/SUMIFS($O122:$DR122,$O$7:$DR$7,BV$7) -> 0.086260109 | BW123: =+AVERAGE(O123,AA123,AM123,BK123) -> 0.082223642 | BX123: =+AVERAGE(P123,AB123,AN123,BL123) -> 0.082382284 | BY123: =+AVERAGE(Q123,AC123,AO123,BM123) -> 0.082753875 | BZ123: =+AVERAGE(R123,AD123,AP123,BN123) -> 0.082877623 | CA123: =+AVERAGE(S123,AE123,AQ123,BO123) -> 0.082876389 | CB123: =+AVERAGE(T123,AF123,AR123,BP123) -> 0.082795879 | CC123: =+AVERAGE(U123,AG123,AS123,BQ123) -> 0.082478043 | CD123: =+AVERAGE(V123,AH123,AT123,BR123) -> 0.083780212 | ... DR123: =+AVERAGE(BJ123,BV123,CH123,DF123) -> 0.087835087
B124: % Contracted | E124: =+E60/E122 -> 1 | F124: =+F60/F122 -> 1 | G124: =+G60/G122 -> 1 | H124: =+H60/H122 -> 1 | I124: 0.99543394 | J124: =+J60/J122 -> 0.92099762 | K124: =+K60/K122 -> 0.49744878 | L124: =+L60/L122 -> 0.37366569 | M124: =+M60/M122 -> 0.24963006
B126: Managed Services
B128: AACN | C128: Lower Middle Market | E128: =+SUMIFS($O128:$DR128,$O$7:$DR$7,E$7) -> 0 | F128: =+SUMIFS($O128:$DR128,$O$7:$DR$7,F$7) -> 0 | G128: =+SUMIFS($O128:$DR128,$O$7:$DR$7,G$7) -> 5.5 | H128: =+SUMIFS($O128:$DR128,$O$7:$DR$7,H$7) -> 8.8 | I128: =+SUMIFS($O128:$DR128,$O$7:$DR$7,I$7) -> 5 | J128: =+SUMIFS($O128:$DR128,$O$7:$DR$7,J$7) -> 0 | K128: =+SUMIFS($O128:$DR128,$O$7:$DR$7,K$7) -> 0 | L128: =+SUMIFS($O128:$DR128,$O$7:$DR$7,L$7) -> 0 | M128: =+SUMIFS($O128:$DR128,$O$7:$DR$7,M$7) -> 0 | O128: 0 | P128: 0 | Q128: 0 | R128: 0 | S128: 0 | T128: 0 | U128: 0 | V128: 0 | W128: 0 | X128: 0 | Y128: 0 | Z128: 0 | AA128: 0 | AB128: 0 | AC128: 0 | AD128: 0 | AE128: 0 | AF128: 0 | AG128: 0 | AH128: 0 | AI128: 0 | AJ128: 0 | AK128: 0 | AL128: 0 | AM128: 0 | AN128: 0 | AO128: 0 | AP128: 0 | AQ128: 0 | AR128: 0 | AS128: 0 | AT128: 0 | AU128: 0 | AV128: 4.4 | AW128: 1.1 | AX128: 0 | AY128: 0 | AZ128: 0 | BA128: 0 | BB128: 0 | BC128: 0 | BD128: 0 | BE128: 7.48 | BF128: 1.32 | BG128: 0 | BH128: 0 | BI128: 0 | BJ128: 0 | BK128: 0 | BL128: 0 | BM128: 0 | BN128: 0.55555556 | BO128: 0.55555556 | BP128: 0.55555556 | BQ128: 0.55555556 | BR128: 0.55555556 | BS128: 0.55555556 | BT128: 0.55555556 | BU128: 0.55555556 | BV128: 0.55555556 | DT128: =+F128-E128 -> 0 | DU128: =+G128-F128 -> 5.5 | DV128: =+H128-G128 -> 3.3 | DW128: =+I128-H128 -> -3.8
B129: AACR | C129: Lower Middle Market | E129: =+SUMIFS($O129:$DR129,$O$7:$DR$7,E$7) -> 0 | F129: =+SUMIFS($O129:$DR129,$O$7:$DR$7,F$7) -> 0 | G129: =+SUMIFS($O129:$DR129,$O$7:$DR$7,G$7) -> 0 | H129: =+SUMIFS($O129:$DR129,$O$7:$DR$7,H$7) -> 75.85 | I129: =+SUMIFS($O129:$DR129,$O$7:$DR$7,I$7) -> 40 | J129: =+SUMIFS($O129:$DR129,$O$7:$DR$7,J$7) -> 0 | K129: =+SUMIFS($O129:$DR129,$O$7:$DR$7,K$7) -> 0 | L129: =+SUMIFS($O129:$DR129,$O$7:$DR$7,L$7) -> 0 | M129: =+SUMIFS($O129:$DR129,$O$7:$DR$7,M$7) -> 0 | O129: 0 | P129: 0 | Q129: 0 | R129: 0 | S129: 0 | T129: 0 | U129: 0 | V129: 0 | W129: 0 | X129: 0 | Y129: 0 | Z129: 0 | AA129: 0 | AB129: 0 | AC129: 0 | AD129: 0 | AE129: 0 | AF129: 0 | AG129: 0 | AH129: 0 | AI129: 0 | AJ129: 0 | AK129: 0 | AL129: 0 | AM129: 0 | AN129: 0 | AO129: 0 | AP129: 0 | AQ129: 0 | AR129: 0 | AS129: 0 | AT129: 0 | AU129: 0 | AV129: 0 | AW129: 0 | AX129: 0 | AY129: 0 | AZ129: 0 | BA129: 0 | BB129: 0 | BC129: 0 | BD129: 9.345 | BE129: 8.593 | BF129: 4.742 | BG129: 0 | BH129: 7.65 | BI129: 30.33 | BJ129: 15.19 | BK129: 19.09 | BL129: 0 | BM129: 7.11 | BN129: 1.5333333 | BO129: 1.5333333 | BP129: 1.5333333 | BQ129: 1.5333333 | BR129: 1.5333333 | BS129: 1.5333333 | BT129: 1.5333333 | BU129: 1.5333333 | BV129: 1.5333333 | DT129: =+F129-E129 -> 0 | DU129: =+G129-F129 -> 0 | DV129: =+H129-G129 -> 75.85 | DW129: =+I129-H129 -> -35.85
B130: AAI | C130: Lower Middle Market | E130: =+SUMIFS($O130:$DR130,$O$7:$DR$7,E$7) -> 0 | F130: =+SUMIFS($O130:$DR130,$O$7:$DR$7,F$7) -> 0 | G130: =+SUMIFS($O130:$DR130,$O$7:$DR$7,G$7) -> 0 | H130: =+SUMIFS($O130:$DR130,$O$7:$DR$7,H$7) -> 0 | I130: =+SUMIFS($O130:$DR130,$O$7:$DR$7,I$7) -> 40 | J130: =+SUMIFS($O130:$DR130,$O$7:$DR$7,J$7) -> 0 | K130: =+SUMIFS($O130:$DR130,$O$7:$DR$7,K$7) -> 0 | L130: =+SUMIFS($O130:$DR130,$O$7:$DR$7,L$7) -> 0 | M130: =+SUMIFS($O130:$DR130,$O$7:$DR$7,M$7) -> 0 | O130: 0 | P130: 0 | Q130: 0 | R130: 0 | S130: 0 | T130: 0 | U130: 0 | V130: 0 | W130: 0 | X130: 0 | Y130: 0 | Z130: 0 | AA130: 0 | AB130: 0 | AC130: 0 | AD130: 0 | AE130: 0 | AF130: 0 | AG130: 0 | AH130: 0 | AI130: 0 | AJ130: 0 | AK130: 0 | AL130: 0 | AM130: 0 | AN130: 0 | AO130: 0 | AP130: 0 | AQ130: 0 | AR130: 0 | AS130: 0 | AT130: 0 | AU130: 0 | AV130: 0 | AW130: 0 | AX130: 0 | AY130: 0 | AZ130: 0 | BA130: 0 | BB130: 0 | BC130: 0 | BD130: 0 | BE130: 0 | BF130: 0 | BG130: 0 | BH130: 0 | BI130: 0 | BJ130: 0 | BK130: 0 | BL130: 0 | BM130: 0 | BN130: 0 | BO130: 0 | BP130: 5.7142857 | BQ130: 5.7142857 | BR130: 5.7142857 | BS130: 5.7142857 | BT130: 5.7142857 | BU130: 5.7142857 | BV130: 5.7142857 | DT130: =+F130-E130 -> 0 | DU130: =+G130-F130 -> 0 | DV130: =+H130-G130 -> 0 | DW130: =+I130-H130 -> 40
B131: AAOS | C131: Upper Middle Market | E131: =+SUMIFS($O131:$DR131,$O$7:$DR$7,E$7) -> 0 | F131: =+SUMIFS($O131:$DR131,$O$7:$DR$7,F$7) -> 0 | G131: =+SUMIFS($O131:$DR131,$O$7:$DR$7,G$7) -> 39.039 | H131: =+SUMIFS($O131:$DR131,$O$7:$DR$7,H$7) -> 374.909 | I131: =+SUMIFS($O131:$DR131,$O$7:$DR$7,I$7) -> 219.70588 | J131: =+SUMIFS($O131:$DR131,$O$7:$DR$7,J$7) -> 0 | K131: =+SUMIFS($O131:$DR131,$O$7:$DR$7,K$7) -> 0 | L131: =+SUMIFS($O131:$DR131,$O$7:$DR$7,L$7) -> 0 | M131: =+SUMIFS($O131:$DR131,$O$7:$DR$7,M$7) -> 0 | O131: 0 | P131: 0 | Q131: 0 | R131: 0 | S131: 0 | T131: 0 | U131: 0 | V131: 0 | W131: 0 | X131: 0 | Y131: 0 | Z131: 0 | AA131: 0 | AB131: 0 | AC131: 0 | AD131: 0 | AE131: 0 | AF131: 0 | AG131: 0 | AH131: 0 | AI131: 0 | AJ131: 0 | AK131: 0 | AL131: 0 | AM131: 0 | AN131: 0 | AO131: 0 | AP131: 0 | AQ131: 0 | AR131: 0 | AS131: 0 | AT131: 0 | AU131: 4.83 | AV131: 1.915 | AW131: 4.776 | AX131: 27.518 | AY131: 3.238 | AZ131: 11.533 | BA131: 102.165 | BB131: 94.728 | BC131: 47.135 | BD131: 43.222 | BE131: 20.09 | BF131: 6.495 | BG131: 6.515 | BH131: 26.261 | BI131: 7.082 | BJ131: 6.445 | BK131: 6.648 | BL131: 7.694 | BM131: 14.08 | BN131: 18.128388 | BO131: 21.150687 | BP131: 24.972218 | BQ131: 24.347913 | BR131: 23.617476 | BS131: 22.73182 | BT131: 21.595229 | BU131: 17.370076 | BV131: 17.370076 | DT131: =+F131-E131 -> 0 | DU131: =+G131-F131 -> 39.039 | DV131: =+H131-G131 -> 335.87 | DW131: =+I131-H131 -> -155.20312
B132: AAP | C132: Major | E132: =+SUMIFS($O132:$DR132,$O$7:$DR$7,E$7) -> 176.502 | F132: =+SUMIFS($O132:$DR132,$O$7:$DR$7,F$7) -> 222.383 | G132: =+SUMIFS($O132:$DR132,$O$7:$DR$7,G$7) -> 123.762 | H132: =+SUMIFS($O132:$DR132,$O$7:$DR$7,H$7) -> 461.05 | I132: =+SUMIFS($O132:$DR132,$O$7:$DR$7,I$7) -> 175 | J132: =+SUMIFS($O132:$DR132,$O$7:$DR$7,J$7) -> 0 | K132: =+SUMIFS($O132:$DR132,$O$7:$DR$7,K$7) -> 0 | L132: =+SUMIFS($O132:$DR132,$O$7:$DR$7,L$7) -> 0 | M132: =+SUMIFS($O132:$DR132,$O$7:$DR$7,M$7) -> 0 | O132: 0.338 | P132: 4.918 | Q132: 2.624 | R132: 6.823 | S132: 1.096 | T132: 2.762 | U132: 20.101 | V132: 62.041 | W132: 28.793 | X132: 25.682 | Y132: 17.133 | Z132: 4.191 | AA132: 0 | AB132: 0 | AC132: 0 | AD132: 13.6 | AE132: 1.702 | AF132: 18.801 | AG132: 109.431 | AH132: 27.09 | AI132: 31.572 | AJ132: 11.418 | AK132: 2.45 | AL132: 6.319 | AM132: 10.028 | AN132: 3.997 | AO132: 17.425 | AP132: 26.763 | AQ132: 49.497 | AR132: 4.315 | AS132: 7.3 | AT132: 2.04 | AU132: 1.125 | AV132: 1.272 | AW132: 0 | AX132: 0 | AY132: 0 | AZ132: 0 | BA132: 11.15 | BB132: 21.839 | BC132: 19.734 | BD132: 26.358 | BE132: 80.795 | BF132: 89.325 | BG132: 84.318 | BH132: 71.031 | BI132: 47.879 | BJ132: 8.621 | BK132: 0.787 | BL132: 27.032 | BM132: 14.856 | BN132: 17.643333 | BO132: 17.91901 | BP132: 16.587884 | BQ132: 16.034954 | BR132: 14.752158 | BS132: 14.198952 | BT132: 13.489005 | BU132: 11.934837 | BV132: 9.7648664 | DT132: =+F132-E132 -> 45.881 | DU132: =+G132-F132 -> -98.621 | DV132: =+H132-G132 -> 337.288 | DW132: =+I132-H132 -> -286.05
B133: ADA | C133: Lower Middle Market | E133: =+SUMIFS($O133:$DR133,$O$7:$DR$7,E$7) -> 0 | F133: =+SUMIFS($O133:$DR133,$O$7:$DR$7,F$7) -> 0 | G133: =+SUMIFS($O133:$DR133,$O$7:$DR$7,G$7) -> 0 | H133: =+SUMIFS($O133:$DR133,$O$7:$DR$7,H$7) -> 24.6 | I133: =+SUMIFS($O133:$DR133,$O$7:$DR$7,I$7) -> 65 | J133: =+SUMIFS($O133:$DR133,$O$7:$DR$7,J$7) -> 0 | K133: =+SUMIFS($O133:$DR133,$O$7:$DR$7,K$7) -> 0 | L133: =+SUMIFS($O133:$DR133,$O$7:$DR$7,L$7) -> 0 | M133: =+SUMIFS($O133:$DR133,$O$7:$DR$7,M$7) -> 0 | O133: 0 | P133: 0 | Q133: 0 | R133: 0 | S133: 0 | T133: 0 | U133: 0 | V133: 0 | W133: 0 | X133: 0 | Y133: 0 | Z133: 0 | AA133: 0 | AB133: 0 | AC133: 0 | AD133: 0 | AE133: 0 | AF133: 0 | AG133: 0 | AH133: 0 | AI133: 0 | AJ133: 0 | AK133: 0 | AL133: 0 | AM133: 0 | AN133: 0 | AO133: 0 | AP133: 0 | AQ133: 0 | AR133: 0 | AS133: 0 | AT133: 0 | AU133: 0 | AV133: 0 | AW133: 0 | AX133: 0 | AY133: 0 | AZ133: 0 | BA133: 0 | BB133: 0 | BC133: 0 | BD133: 0 | BE133: 0 | BF133: 0.85 | BG133: 14.45 | BH133: 7.6 | BI133: 1.7 | BJ133: 0 | BK133: 8.46 | BL133: 1.23 | BM133: 20.81 | BN133: 3.8333333 | BO133: 3.8333333 | BP133: 3.8333333 | BQ133: 3.8333333 | BR133: 3.8333333 | BS133: 3.8333333 | BT133: 3.8333333 | BU133: 3.8333333 | BV133: 3.8333333 | DT133: =+F133-E133 -> 0 | DU133: =+G133-F133 -> 0 | DV133: =+H133-G133 -> 24.6 | DW133: =+I133-H133 -> 40.4
B134: AHRQ | C134: Lower Middle Market | E134: =+SUMIFS($O134:$DR134,$O$7:$DR$7,E$7) -> 0 | F134: =+SUMIFS($O134:$DR134,$O$7:$DR$7,F$7) -> 0 | G134: =+SUMIFS($O134:$DR134,$O$7:$DR$7,G$7) -> 0 | H134: =+SUMIFS($O134:$DR134,$O$7:$DR$7,H$7) -> 0 | I134: =+SUMIFS($O134:$DR134,$O$7:$DR$7,I$7) -> 0 | J134: =+SUMIFS($O134:$DR134,$O$7:$DR$7,J$7) -> 0 | K134: =+SUMIFS($O134:$DR134,$O$7:$DR$7,K$7) -> 0 | L134: =+SUMIFS($O134:$DR134,$O$7:$DR$7,L$7) -> 0 | M134: =+SUMIFS($O134:$DR134,$O$7:$DR$7,M$7) -> 0 | O134: 0 | P134: 0 | Q134: 0 | R134: 0 | S134: 0 | T134: 0 | U134: 0 | V134: 0 | W134: 0 | X134: 0 | Y134: 0 | Z134: 0 | AA134: 0 | AB134: 0 | AC134: 0 | AD134: 0 | AE134: 0 | AF134: 0 | AG134: 0 | AH134: 0 | AI134: 0 | AJ134: 0 | AK134: 0 | AL134: 0 | AM134: 0 | AN134: 0 | AO134: 0 | AP134: 0 | AQ134: 0 | AR134: 0 | AS134: 0 | AT134: 0 | AU134: 0 | AV134: 0 | AW134: 0 | AX134: 0 | AY134: 0 | AZ134: 0 | BA134: 0 | BB134: 0 | BC134: 0 | BD134: 0 | BE134: 0 | BF134: 0 | BG134: 0 | BH134: 0 | BI134: 0 | BJ134: 0 | BK134: 0 | BL134: 0 | BM134: 0 | BN134: 0 | BO134: 0 | BP134: 0 | BQ134: 0 | BR134: 0 | BS134: 0 | BT134: 0 | BU134: 0 | BV134: 0 | DT134: =+F134-E134 -> 0 | DU134: =+G134-F134 -> 0 | DV134: =+H134-G134 -> 0 | DW134: =+I134-H134 -> 0
B135: AIPP | C135: Major | E135: =+SUMIFS($O135:$DR135,$O$7:$DR$7,E$7) -> 0 | F135: =+SUMIFS($O135:$DR135,$O$7:$DR$7,F$7) -> 0 | G135: =+SUMIFS($O135:$DR135,$O$7:$DR$7,G$7) -> 0 | H135: =+SUMIFS($O135:$DR135,$O$7:$DR$7,H$7) -> 0 | I135: =+SUMIFS($O135:$DR135,$O$7:$DR$7,I$7) -> 100 | J135: =+SUMIFS($O135:$DR135,$O$7:$DR$7,J$7) -> 0 | K135: =+SUMIFS($O135:$DR135,$O$7:$DR$7,K$7) -> 0 | L135: =+SUMIFS($O135:$DR135,$O$7:$DR$7,L$7) -> 0 | M135: =+SUMIFS($O135:$DR135,$O$7:$DR$7,M$7) -> 0 | O135: 0 | P135: 0 | Q135: 0 | R135: 0 | S135: 0 | T135: 0 | U135: 0 | V135: 0 | W135: 0 | X135: 0 | Y135: 0 | Z135: 0 | AA135: 0 | AB135: 0 | AC135: 0 | AD135: 0 | AE135: 0 | AF135: 0 | AG135: 0 | AH135: 0 | AI135: 0 | AJ135: 0 | AK135: 0 | AL135: 0 | AM135: 0 | AN135: 0 | AO135: 0 | AP135: 0 | AQ135: 0 | AR135: 0 | AS135: 0 | AT135: 0 | AU135: 0 | AV135: 0 | AW135: 0 | AX135: 0 | AY135: 0 | AZ135: 0 | BA135: 0 | BB135: 0 | BC135: 0 | BD135: 0 | BE135: 0 | BF135: 0 | BG135: 0 | BH135: 0 | BI135: 0 | BJ135: 0 | BK135: 0 | BL135: 0 | BM135: 0 | BN135: 0 | BO135: 0 | BP135: 0 | BQ135: 8.3333333 | BR135: 18.333333 | BS135: 18.333333 | BT135: 20.166667 | BU135: 17.416667 | BV135: 17.416667 | DT135: =+F135-E135 -> 0 | DU135: =+G135-F135 -> 0 | DV135: =+H135-G135 -> 0 | DW135: =+I135-H135 -> 100
B136: ALLEN | C136: Upper Middle Market | E136: =+SUMIFS($O136:$DR136,$O$7:$DR$7,E$7) -> 0 | F136: =+SUMIFS($O136:$DR136,$O$7:$DR$7,F$7) -> 0 | G136: =+SUMIFS($O136:$DR136,$O$7:$DR$7,G$7) -> 5.7 | H136: =+SUMIFS($O136:$DR136,$O$7:$DR$7,H$7) -> 73.44 | I136: =+SUMIFS($O136:$DR136,$O$7:$DR$7,I$7) -> 75 | J136: =+SUMIFS($O136:$DR136,$O$7:$DR$7,J$7) -> 0 | K136: =+SUMIFS($O136:$DR136,$O$7:$DR$7,K$7) -> 0 | L136: =+SUMIFS($O136:$DR136,$O$7:$DR$7,L$7) -> 0 | M136: =+SUMIFS($O136:$DR136,$O$7:$DR$7,M$7) -> 0 | O136: 0 | P136: 0 | Q136: 0 | R136: 0 | S136: 0 | T136: 0 | U136: 0 | V136: 0 | W136: 0 | X136: 0 | Y136: 0 | Z136: 0 | AA136: 0 | AB136: 0 | AC136: 0 | AD136: 0 | AE136: 0 | AF136: 0 | AG136: 0 | AH136: 0 | AI136: 0 | AJ136: 0 | AK136: 0 | AL136: 0 | AM136: 0 | AN136: 0 | AO136: 0 | AP136: 0 | AQ136: 0 | AR136: 0 | AS136: 0 | AT136: 0 | AU136: 0 | AV136: 1.9 | AW136: 0.95 | AX136: 2.85 | AY136: 0 | AZ136: 10.675 | BA136: 16.615 | BB136: 3.52 | BC136: 6.38 | BD136: 13.23 | BE136: 10.045 | BF136: 1.34 | BG136: 0 | BH136: 8.95 | BI136: 2.685 | BJ136: 0 | BK136: 0 | BL136: 3.3 | BM136: 0.4 | BN136: 7.9222222 | BO136: 7.9222222 | BP136: 7.9222222 | BQ136: 7.9222222 | BR136: 7.9222222 | BS136: 7.9222222 | BT136: 7.9222222 | BU136: 7.9222222 | BV136: 7.9222222 | DT136: =+F136-E136 -> 0 | DU136: =+G136-F136 -> 5.7 | DV136: =+H136-G136 -> 67.74 | DW136: =+I136-H136 -> 1.56
B137: AMA | C137: Mega | E137: =+SUMIFS($O137:$DR137,$O$7:$DR$7,E$7) -> 1985.327 | F137: =+SUMIFS($O137:$DR137,$O$7:$DR$7,F$7) -> 1997.576 | G137: =+SUMIFS($O137:$DR137,$O$7:$DR$7,G$7) -> 1745.82 | H137: =+SUMIFS($O137:$DR137,$O$7:$DR$7,H$7) -> 1811.915 | I137: =+SUMIFS($O137:$DR137,$O$7:$DR$7,I$7) -> 1844 | J137: =+SUMIFS($O137:$DR137,$O$7:$DR$7,J$7) -> 0 | K137: =+SUMIFS($O137:$DR137,$O$7:$DR$7,K$7) -> 0 | L137: =+SUMIFS($O137:$DR137,$O$7:$DR$7,L$7) -> 0 | M137: =+SUMIFS($O137:$DR137,$O$7:$DR$7,M$7) -> 0 | O137: 113.894 | P137: 133.412 | Q137: 121.507 | R137: 140.542 | S137: 185.268 | T137: 193.304 | U137: 197.47 | V137: 196.875 | W137: 181.672 | X137: 170.909 | Y137: 182.677 | Z137: 167.797 | AA137: 172.142 | AB137: 131.78 | AC137: 194.192 | AD137: 136.503 | AE137: 152.135 | AF137: 155.664 | AG137: 151.005 | AH137: 197.002 | AI137: 208.296 | AJ137: 215.74 | AK137: 154.136 | AL137: 128.981 | AM137: 174.44 | AN137: 96.04 | AO137: 144.48 | AP137: 107.94 | AQ137: 105.7 | AR137: 140.98 | AS137: 172.2 | AT137: 177.52 | AU137: 182.98 | AV137: 162.54 | AW137: 122.92 | AX137: 158.08 | AY137: 150.815 | AZ137: 141.205 | BA137: 184.76 | BB137: 195.415 | BC137: 153.995 | BD137: 188.041 | BE137: 151.255 | BF137: 150.76 | BG137: 148.179 | BH137: 141.795 | BI137: 92.845 | BJ137: 112.85 | BK137: 121.96 | BL137: 128.9 | BM137: 156.06 | BN137: 152.85289 | BO137: 160.72631 | BP137: 160.79275 | BQ137: 176.59158 | BR137: 173.03788 | BS137: 176.2601 | BT137: 167.44709 | BU137: 147.99822 | BV137: 121.37319 | DT137: =+F137-E137 -> 12.249 | DU137: =+G137-F137 -> -251.756 | DV137: =+H137-G137 -> 66.095 | DW137: =+I137-H137 -> 32.085
B138: AORN | C138: Lower Middle Market | E138: =+SUMIFS($O138:$DR138,$O$7:$DR$7,E$7) -> 46.98 | F138: =+SUMIFS($O138:$DR138,$O$7:$DR$7,F$7) -> 61.355 | G138: =+SUMIFS($O138:$DR138,$O$7:$DR$7,G$7) -> 69.825 | H138: =+SUMIFS($O138:$DR138,$O$7:$DR$7,H$7) -> 119.455 | I138: =+SUMIFS($O138:$DR138,$O$7:$DR$7,I$7) -> 135 | J138: =+SUMIFS($O138:$DR138,$O$7:$DR$7,J$7) -> 0 | K138: =+SUMIFS($O138:$DR138,$O$7:$DR$7,K$7) -> 0 | L138: =+SUMIFS($O138:$DR138,$O$7:$DR$7,L$7) -> 0 | M138: =+SUMIFS($O138:$DR138,$O$7:$DR$7,M$7) -> 0 | O138: 0 | P138: 18.67 | Q138: 0.34 | R138: 1.221 | S138: 4.57 | T138: 1.819 | U138: 7.038 | V138: 0.969 | W138: 8.473 | X138: 2.425 | Y138: 1.455 | Z138: 0 | AA138: 23.513 | AB138: 4.437 | AC138: 0.8 | AD138: 0 | AE138: 0.738 | AF138: 2.042 | AG138: 0.695 | AH138: 0 | AI138: 0 | AJ138: 0 | AK138: 27.019 | AL138: 2.111 | AM138: 0 | AN138: 10.399 | AO138: 14.696 | AP138: 12.373 | AQ138: 11.823 | AR138: 9.647 | AS138: 0.342 | AT138: 0 | AU138: 0 | AV138: 0 | AW138: 4.38 | AX138: 6.165 | AY138: 5.415 | AZ138: 6.453 | BA138: 27.265 | BB138: 36.112 | BC138: 11.06 | BD138: 0 | BE138: 8.03 | BF138: 0 | BG138: 10.8 | BH138: 0.88 | BI138: 2.85 | BJ138: 10.59 | BK138: 20.82 | BL138: 19 | BM138: 0 | BN138: 10.575556 | BO138: 10.575556 | BP138: 10.575556 | BQ138: 10.575556 | BR138: 10.575556 | BS138: 10.575556 | BT138: 10.575556 | BU138: 10.575556 | BV138: 10.575556 | DT138: =+F138-E138 -> 14.375 | DU138: =+G138-F138 -> 8.47 | DV138: =+H138-G138 -> 49.63 | DW138: =+I138-H138 -> 15.545
B139: AOTA | C139: Lower Middle Market | E139: =+SUMIFS($O139:$DR139,$O$7:$DR$7,E$7) -> 0 | F139: =+SUMIFS($O139:$DR139,$O$7:$DR$7,F$7) -> 42.618 | G139: =+SUMIFS($O139:$DR139,$O$7:$DR$7,G$7) -> 3.581 | H139: =+SUMIFS($O139:$DR139,$O$7:$DR$7,H$7) -> 2.46 | I139: =+SUMIFS($O139:$DR139,$O$7:$DR$7,I$7) -> 2.5 | J139: =+SUMIFS($O139:$DR139,$O$7:$DR$7,J$7) -> 0 | K139: =+SUMIFS($O139:$DR139,$O$7:$DR$7,K$7) -> 0 | L139: =+SUMIFS($O139:$DR139,$O$7:$DR$7,L$7) -> 0 | M139: =+SUMIFS($O139:$DR139,$O$7:$DR$7,M$7) -> 0 | O139: 0 | P139: 0 | Q139: 0 | R139: 0 | S139: 0 | T139: 0 | U139: 0 | V139: 0 | W139: 0 | X139: 0 | Y139: 0 | Z139: 0 | AA139: 0 | AB139: 0 | AC139: 0 | AD139: 0 | AE139: 0 | AF139: 0 | AG139: 0 | AH139: 0 | AI139: 3.85 | AJ139: 29.259 | AK139: 7.545 | AL139: 1.964 | AM139: 3.581 | AN139: 0 | AO139: 0 | AP139: 0 | AQ139: 0 | AR139: 0 | AS139: 0 | AT139: 0 | AU139: 0 | AV139: 0 | AW139: 0 | AX139: 0 | AY139: 0 | AZ139: 0 | BA139: 0 | BB139: 0 | BC139: 1.968 | BD139: 0.492 | BE139: 0 | BF139: 0 | BG139: 0 | BH139: 0 | BI139: 0 | BJ139: 0 | BK139: 0 | BL139: 0 | BM139: 0 | BN139: 0.27777778 | BO139: 0.27777778 | BP139: 0.27777778 | BQ139: 0.27777778 | BR139: 0.27777778 | BS139: 0.27777778 | BT139: 0.27777778 | BU139: 0.27777778 | BV139: 0.27777778 | DT139: =+F139-E139 -> 42.618 | DU139: =+G139-F139 -> -39.037 | DV139: =+H139-G139 -> -1.121 | DW139: =+I139-H139 -> 0.04
... B170: UCSF | C170: Upper Middle Market | E170: =+SUMIFS($O170:$DR170,$O$7:$DR$7,E$7) -> 82.236 | F170: =+SUMIFS($O170:$DR170,$O$7:$DR$7,F$7) -> 48.862 | G170: =+SUMIFS($O170:$DR170,$O$7:$DR$7,G$7) -> 0 | H170: =+SUMIFS($O170:$DR170,$O$7:$DR$7,H$7) -> 0 | I170: =+SUMIFS($O170:$DR170,$O$7:$DR$7,I$7) -> 0 | J170: =+SUMIFS($O170:$DR170,$O$7:$DR$7,J$7) -> 0 | K170: =+SUMIFS($O170:$DR170,$O$7:$DR$7,K$7) -> 0 | L170: =+SUMIFS($O170:$DR170,$O$7:$DR$7,L$7) -> 0 | M170: =+SUMIFS($O170:$DR170,$O$7:$DR$7,M$7) -> 0 | O170: 7.323 | P170: 5.821 | Q170: 5.965 | R170: 8.682 | S170: 7.886 | T170: 5.609 | U170: 8.146 | V170: 6.149 | W170: 5.929 | X170: 7.436 | Y170: 6.46 | Z170: 6.83 | AA170: 4.09 | AB170: 3.959 | AC170: 6.298 | AD170: 6.553 | AE170: 4.683 | AF170: 4.528 | AG170: 6.343 | AH170: 6.348 | AI170: 6.06 | AJ170: 0 | AK170: 0 | AL170: 0 | AM170: 0 | AN170: 0 | AO170: 0 | AP170: 0 | AQ170: 0 | AR170: 0 | AS170: 0 | AT170: 0 | AU170: 0 | AV170: 0 | AW170: 0 | AX170: 0 | AY170: 0 | AZ170: 0 | BA170: 0 | BB170: 0 | BC170: 0 | BD170: 0 | BE170: 0 | BF170: 0 | BG170: 0 | BH170: 0 | BI170: 0 | BJ170: 0 | BK170: 0 | BL170: 0 | BM170: 0 | BN170: 0 | BO170: 0 | BP170: 0 | BQ170: 0 | BR170: 0 | BS170: 0 | BT170: 0 | BU170: 0 | BV170: 0 | DT170: =+F170-E170 -> -33.374 | DU170: =+G170-F170 -> -48.862 | DV170: =+H170-G170 -> 0 | DW170: =+I170-H170 -> 0
B171: OTHER | E171: =+SUMIFS($O171:$DR171,$O$7:$DR$7,E$7) -> 0 | F171: =+SUMIFS($O171:$DR171,$O$7:$DR$7,F$7) -> 0 | G171: =+SUMIFS($O171:$DR171,$O$7:$DR$7,G$7) -> 0 | H171: =+SUMIFS($O171:$DR171,$O$7:$DR$7,H$7) -> 0 | I171: =+SUMIFS($O171:$DR171,$O$7:$DR$7,I$7) -> 425 | J171: =+SUMIFS($O171:$DR171,$O$7:$DR$7,J$7) -> 0 | K171: =+SUMIFS($O171:$DR171,$O$7:$DR$7,K$7) -> 0 | L171: =+SUMIFS($O171:$DR171,$O$7:$DR$7,L$7) -> 0 | M171: =+SUMIFS($O171:$DR171,$O$7:$DR$7,M$7) -> 0 | O171: 0 | P171: 0 | Q171: 0 | R171: 0 | S171: 0 | T171: 0 | U171: 0 | V171: 0 | W171: 0 | X171: 0 | Y171: 0 | Z171: 0 | AA171: 0 | AB171: 0 | AC171: 0 | AD171: 0 | AE171: 0 | AF171: 0 | AG171: 0 | AH171: 0 | AI171: 0 | AJ171: 0 | AK171: 0 | AL171: 0 | AM171: 0 | AN171: 0 | AO171: 0 | AP171: 0 | AQ171: 0 | AR171: 0 | AS171: 0 | AT171: 0 | AU171: 0 | AV171: 0 | AW171: 0 | AX171: 0 | AY171: 0 | AZ171: 0 | BA171: 0 | BB171: 0 | BC171: 0 | BD171: 0 | BE171: 0 | BF171: 0 | BG171: 0 | BH171: 0 | BI171: 0 | BJ171: 0 | BK171: 0 | BL171: 0 | BM171: 0 | BN171: 0 | BO171: 0 | BP171: 0 | BQ171: 33.333333 | BR171: 69 | BS171: 91.441667 | BT171: 91.69 | BU171: 76.69425 | BV171: 62.84075 | DT171: =+F171-E171 -> 0 | DU171: =+G171-F171 -> 0 | DV171: =+H171-G171 -> 0 | DW171: =+I171-H171 -> 425
B172: AAAS | C172: Lower Middle Market | E172: =+SUMIFS($O172:$DR172,$O$7:$DR$7,E$7) -> 0 | F172: =+SUMIFS($O172:$DR172,$O$7:$DR$7,F$7) -> 0 | G172: =+SUMIFS($O172:$DR172,$O$7:$DR$7,G$7) -> 0 | H172: =+SUMIFS($O172:$DR172,$O$7:$DR$7,H$7) -> 0 | I172: =+SUMIFS($O172:$DR172,$O$7:$DR$7,I$7) -> 0 | J172: =+SUMIFS($O172:$DR172,$O$7:$DR$7,J$7) -> 0 | K172: =+SUMIFS($O172:$DR172,$O$7:$DR$7,K$7) -> 0 | L172: =+SUMIFS($O172:$DR172,$O$7:$DR$7,L$7) -> 0 | M172: =+SUMIFS($O172:$DR172,$O$7:$DR$7,M$7) -> 0 | O172: 0 | P172: 0 | Q172: 0 | R172: 0 | S172: 0 | T172: 0 | U172: 0 | V172: 0 | W172: 0 | X172: 0 | Y172: 0 | Z172: 0 | AA172: 0 | AB172: 0 | AC172: 0 | AD172: 0 | AE172: 0 | AF172: 0 | AG172: 0 | AH172: 0 | AI172: 0 | AJ172: 0 | AK172: 0 | AL172: 0 | AM172: 0 | AN172: 0 | AO172: 0 | AP172: 0 | AQ172: 0 | AR172: 0 | AS172: 0 | AT172: 0 | AU172: 0 | AV172: 0 | AW172: 0 | AX172: 0 | AY172: 0 | AZ172: 0 | BA172: 0 | BB172: 0 | BC172: 0 | BD172: 0 | BE172: 0 | BF172: 0 | BG172: 0 | BH172: 0 | BI172: 0 | BJ172: 0 | BK172: 0 | BL172: 0 | BM172: 0 | BN172: 0 | BO172: 0 | BP172: 0 | BQ172: 0 | BR172: 0 | BS172: 0 | BT172: 0 | BU172: 0 | BV172: 0 | DT172: =+F172-E172 -> 0 | DU172: =+G172-F172 -> 0 | DV172: =+H172-G172 -> 0 | DW172: =+I172-H172 -> 0
B173: EL | C173: Lower Middle Market | E173: =+SUMIFS($O173:$DR173,$O$7:$DR$7,E$7) -> 0 | F173: =+SUMIFS($O173:$DR173,$O$7:$DR$7,F$7) -> 0 | G173: =+SUMIFS($O173:$DR173,$O$7:$DR$7,G$7) -> 0 | H173: =+SUMIFS($O173:$DR173,$O$7:$DR$7,H$7) -> 0 | I173: =+SUMIFS($O173:$DR173,$O$7:$DR$7,I$7) -> 0 | J173: =+SUMIFS($O173:$DR173,$O$7:$DR$7,J$7) -> 0 | K173: =+SUMIFS($O173:$DR173,$O$7:$DR$7,K$7) -> 0 | L173: =+SUMIFS($O173:$DR173,$O$7:$DR$7,L$7) -> 0 | M173: =+SUMIFS($O173:$DR173,$O$7:$DR$7,M$7) -> 0 | O173: 0 | P173: 0 | Q173: 0 | R173: 0 | S173: 0 | T173: 0 | U173: 0 | V173: 0 | W173: 0 | X173: 0 | Y173: 0 | Z173: 0 | AA173: 0 | AB173: 0 | AC173: 0 | AD173: 0 | AE173: 0 | AF173: 0 | AG173: 0 | AH173: 0 | AI173: 0 | AJ173: 0 | AK173: 0 | AL173: 0 | AM173: 0 | AN173: 0 | AO173: 0 | AP173: 0 | AQ173: 0 | AR173: 0 | AS173: 0 | AT173: 0 | AU173: 0 | AV173: 0 | AW173: 0 | AX173: 0 | AY173: 0 | AZ173: 0 | BA173: 0 | BB173: 0 | BC173: 0 | BD173: 0 | BE173: 0 | BF173: 0 | BG173: 0 | BH173: 0 | BI173: 0 | BJ173: 0 | BK173: 0 | BL173: 0 | BM173: 0 | BN173: 0 | BO173: 0 | BP173: 0 | BQ173: 0 | BR173: 0 | BS173: 0 | BT173: 0 | BU173: 0 | BV173: 0 | DT173: =+F173-E173 -> 0 | DU173: =+G173-F173 -> 0 | DV173: =+H173-G173 -> 0 | DW173: =+I173-H173 -> 0
B175: Forecast Revenue | E175: =+SUMIFS($O175:$DR175,$O$7:$DR$7,E$7) -> 6500.695 | F175: =+SUMIFS($O175:$DR175,$O$7:$DR$7,F$7) -> 6734.763 | G175: =+SUMIFS($O175:$DR175,$O$7:$DR$7,G$7) -> 6116.35 | H175: =+SUMIFS($O175:$DR175,$O$7:$DR$7,H$7) -> 7915.71 | I175: =+SUMIFS($O175:$DR175,$O$7:$DR$7,I$7) -> 9081.8099 | J175: =+SUMIFS($O175:$DR175,$O$7:$DR$7,J$7) -> 0 | K175: =+SUMIFS($O175:$DR175,$O$7:$DR$7,K$7) -> 0 | L175: =+SUMIFS($O175:$DR175,$O$7:$DR$7,L$7) -> 0 | M175: =+SUMIFS($O175:$DR175,$O$7:$DR$7,M$7) -> 0 | O175: =SUM(O128:O174) -> 352.018 | P175: =SUM(P128:P174) -> 445.985 | Q175: =SUM(Q128:Q174) -> 408.965 | R175: =SUM(R128:R174) -> 517.386 | S175: =SUM(S128:S174) -> 483.324 | T175: =SUM(T128:T174) -> 635.413 | U175: =SUM(U128:U174) -> 627.623 | V175: =SUM(V128:V174) -> 612.374 | ... DR175: =SUM(DR128:DR174) -> 0
B176: Check | BK176: 0 | BL176: 0 | BM176: 0 | BN176: 0 | BO176: 0 | BP176: 0 | BQ176: 0 | BR176: 0 | BS176: 0 | BT176: 0 | BU176: 0 | BV176: 0
B178: Revenue, Beginning | F178: =+E184 -> 6500.695 | G178: =+F184 -> 6734.763 | H178: =+G184 -> 6116.35
B179: Churn | F179: =+SUMIF(DT$128:DT$173,"<0") -> -237.046 | G179: =+SUMIF(DU$128:DU$173,"<0") -> -1658.865 | H179: =+SUMIF(DV$128:DV$173,"<0") -> -333.791
B180: Gross Retention | F180: =SUM(F178:F179) -> 6263.649 | G180: =SUM(G178:G179) -> 5075.898 | H180: =SUM(H178:H179) -> 5782.559
B181: Upsell | F181: =+SUMIF(DT$128:DT$173,">0")-F183 -> 352.089 | G181: =+SUMIF(DU$128:DU$173,">0")-G183 -> 890.634 | H181: =+SUMIF(DV$128:DV$173,">0")-H183 -> 1968.546
B182: Net Retention | F182: =+SUM(F180:F181) -> 6615.738 | G182: =+SUM(G180:G181) -> 5966.532 | H182: =+SUM(H180:H181) -> 7751.105
B183: New | F183: =+SUMIFS(F$128:F$173,E$128:E$173,0) -> 119.025 | G183: =+SUMIFS(G$128:G$173,F$128:F$173,0) -> 149.818 | H183: =+SUMIFS(H$128:H$173,G$128:G$173,0) -> 164.605
B184: Revenue, Ending | E184: =+E175 -> 6500.695 | F184: =+SUM(F182:F183) -> 6734.763 | G184: =+SUM(G182:G183) -> 6116.35 | H184: =+SUM(H182:H183) -> 7915.71
B186: Gross Retention | F186: =+F180/F178 -> 0.96353528 | G186: =+G180/G178 -> 0.75368621 | H186: =+H180/H178 -> 0.94542644
B187: Net Retention | F187: =+F182/F178 -> 1.017697 | G187: =+G182/G178 -> 0.88593051 | H187: =+H182/H178 -> 1.2672762
B189: Mega
...

Sheet COGS_Calcs
B2: Project Shasta
B3: {=MID(CELL("filename",A1),FIND("]",CELL("filename",A1))+1,255)} -> #VALUE!
B4: Spring 2022
B5: CONFIDENTIAL
F7: 2019 | G7: =+F7+1 -> 2020 | H7: =+G7+1 -> 2021 | I7: =+H7+1 -> 2022 | J7: =+I7+1 -> 2023 | K7: =+J7+1 -> 2024 | L7: =+K7+1 -> 2025 | M7: =+L7+1 -> 2026 | AA7: =+YEAR(AA8) -> 2019 | AB7: =+YEAR(AB8) -> 2019 | AC7: =+YEAR(AC8) -> 2019 | AD7: =+YEAR(AD8) -> 2019 | AE7: =+YEAR(AE8) -> 2019 | AF7: =+YEAR(AF8) -> 2019 | AG7: =+YEAR(AG8) -> 2019 | AH7: =+YEAR(AH8) -> 2019 | ... DR7: =+YEAR(DR8) -> 2026
F8: =+DATE(F7,12,31) -> 43830 | G8: =+DATE(G7,12,31) -> 44196 | H8: =+DATE(H7,12,31) -> 44561 | I8: =+DATE(I7,12,31) -> 44926 | J8: =+DATE(J7,12,31) -> 45291 | K8: =+DATE(K7,12,31) -> 45657 | L8: =+DATE(L7,12,31) -> 46022 | M8: =+DATE(M7,12,31) -> 46387 | AA8: 43496 | AB8: =+EOMONTH(AA8,1) -> 43524 | AC8: =+EOMONTH(AB8,1) -> 43555 | AD8: =+EOMONTH(AC8,1) -> 43585 | AE8: =+EOMONTH(AD8,1) -> 43616 | AF8: =+EOMONTH(AE8,1) -> 43646 | AG8: =+EOMONTH(AF8,1) -> 43677 | AH8: =+EOMONTH(AG8,1) -> 43708 | AI8: =+EOMONTH(AH8,1) -> 43738 | ... DR8: =+EOMONTH(DQ8,1) -> 46387
B9: $ in thousands | F9: Actual | G9: Actual | H9: Actual | I9: Budget | J9: Projection | K9: Projection | L9: Projection | M9: Projection | AA9: Actual | AB9: Actual | AC9: Actual | AD9: Actual | AE9: Actual | AF9: Actual | AG9: Actual | AH9: Actual | AI9: Actual | AJ9: Actual | AK9: Actual | AL9: Actual | AM9: Actual | AN9: Actual | AO9: Actual | AP9: Actual | AQ9: Actual | AR9: Actual | AS9: Actual | AT9: Actual | AU9: Actual | AV9: Actual | AW9: Actual | AX9: Actual | AY9: Actual | AZ9: Actual | BA9: Actual | BB9: Actual | BC9: Actual | BD9: Actual | BE9: Actual | BF9: Actual | BG9: Actual | BH9: Actual | BI9: Actual | BJ9: Actual | BK9: Actual | BL9: Actual | BM9: Actual | BN9: Budget | BO9: Budget | BP9: Budget | BQ9: Budget | BR9: Budget | BS9: Budget | BT9: Budget | BU9: Budget | BV9: Budget | BW9: Projection | BX9: Projection | BY9: Projection | BZ9: Projection | CA9: Projection | CB9: Projection | CC9: Projection | CD9: Projection | CE9: Projection | CF9: Projection | CG9: Projection | CH9: Projection | CI9: Projection | CJ9: Projection | CK9: Projection | CL9: Projection | CM9: Projection | CN9: Projection | CO9: Projection | CP9: Projection | CQ9: Projection | CR9: Projection | CS9: Projection | CT9: Projection | CU9: Projection | CV9: Projection | CW9: Projection | CX9: Projection | CY9: Projection | CZ9: Projection | DA9: Projection | DB9: Projection | DC9: Projection | DD9: Projection | DE9: Projection | DF9: Projection | DG9: Projection | DH9: Projection | DI9: Projection | DJ9: Projection | DK9: Projection | DL9: Projection | DM9: Projection | DN9: Projection | DO9: Projection | DP9: Projection | DQ9: Projection | DR9: Projection
B11: Licensing
B13: AACN | C13: Lower Middle Market | F13: =+SUMIFS($AA13:$DR13,$AA$7:$DR$7,F$7) -> 2.473661 | G13: =+SUMIFS($AA13:$DR13,$AA$7:$DR$7,G$7) -> 13.603427 | H13: =+SUMIFS($AA13:$DR13,$AA$7:$DR$7,H$7) -> 5.2553438 | I13: =+SUMIFS($AA13:$DR13,$AA$7:$DR$7,I$7) -> 0 | J13: =+SUMIFS($AA13:$DR13,$AA$7:$DR$7,J$7) -> 0 | K13: =+SUMIFS($AA13:$DR13,$AA$7:$DR$7,K$7) -> 0 | L13: =+SUMIFS($AA13:$DR13,$AA$7:$DR$7,L$7) -> 0 | M13: =+SUMIFS($AA13:$DR13,$AA$7:$DR$7,M$7) -> 0 | AA13: 0 | AB13: 0 | AC13: 0 | AD13: 0 | AE13: 0 | AF13: 0 | AG13: 0.013812677 | AH13: 0 | AI13: 0.0043150032 | AJ13: 0.1975421 | AK13: 1.0030476 | AL13: 1.2549436 | AM13: 0.9292265 | AN13: 3.478431 | AO13: 1.7152249 | AP13: 2.3633506 | AQ13: 0.74093747 | AR13: 0.41773475 | AS13: 1.4611706 | AT13: 0.60891347 | AU13: 0.61079065 | AV13: 0.4765874 | AW13: 0.19945129 | AX13: 0.60160824 | AY13: 1.7303651 | AZ13: 0.19463814 | BA13: 0.092654293 | BB13: 0.11529826 | BC13: 0.31412815 | BD13: 0.18835335 | BE13: 0.53349225 | BF13: 0.23165989 | BG13: 0.89204201 | BH13: 0.23044284 | BI13: 0.48405136 | BJ13: 0.24821816
B14: AACR | C14: Lower Middle Market | F14: =+SUMIFS($AA14:$DR14,$AA$7:$DR$7,F$7) -> 0 | G14: =+SUMIFS($AA14:$DR14,$AA$7:$DR$7,G$7) -> 0 | H14: =+SUMIFS($AA14:$DR14,$AA$7:$DR$7,H$7) -> 2.0581105 | I14: =+SUMIFS($AA14:$DR14,$AA$7:$DR$7,I$7) -> 0 | J14: =+SUMIFS($AA14:$DR14,$AA$7:$DR$7,J$7) -> 0 | K14: =+SUMIFS($AA14:$DR14,$AA$7:$DR$7,K$7) -> 0 | L14: =+SUMIFS($AA14:$DR14,$AA$7:$DR$7,L$7) -> 0 | M14: =+SUMIFS($AA14:$DR14,$AA$7:$DR$7,M$7) -> 0 | AA14: 0 | AB14: 0 | AC14: 0 | AD14: 0 | AE14: 0 | AF14: 0 | AG14: 0 | AH14: 0 | AI14: 0 | AJ14: 0 | AK14: 0 | AL14: 0 | AM14: 0 | AN14: 0 | AO14: 0 | AP14: 0 | AQ14: 0 | AR14: 0 | AS14: 0 | AT14: 0 | AU14: 0 | AV14: 0 | AW14: 0 | AX14: 0 | AY14: 0 | AZ14: 0 | BA14: 0 | BB14: 0.0037956411 | BC14: 0.0085845416 | BD14: 0.10543871 | BE14: 0.14893678 | BF14: 0.087297308 | BG14: 0.13812463 | BH14: 0.47229775 | BI14: 0.6011921 | BJ14: 0.49244301
B15: AAI | C15: Lower Middle Market | F15: =+SUMIFS($AA15:$DR15,$AA$7:$DR$7,F$7) -> 0 | G15: =+SUMIFS($AA15:$DR15,$AA$7:$DR$7,G$7) -> 0 | H15: =+SUMIFS($AA15:$DR15,$AA$7:$DR$7,H$7) -> 0 | I15: =+SUMIFS($AA15:$DR15,$AA$7:$DR$7,I$7) -> 0 | J15: =+SUMIFS($AA15:$DR15,$AA$7:$DR$7,J$7) -> 0 | K15: =+SUMIFS($AA15:$DR15,$AA$7:$DR$7,K$7) -> 0 | L15: =+SUMIFS($AA15:$DR15,$AA$7:$DR$7,L$7) -> 0 | M15: =+SUMIFS($AA15:$DR15,$AA$7:$DR$7,M$7) -> 0 | AA15: 0 | AB15: 0 | AC15: 0 | AD15: 0 | AE15: 0 | AF15: 0 | AG15: 0 | AH15: 0 | AI15: 0 | AJ15: 0 | AK15: 0 | AL15: 0 | AM15: 0 | AN15: 0 | AO15: 0 | AP15: 0 | AQ15: 0 | AR15: 0 | AS15: 0 | AT15: 0 | AU15: 0 | AV15: 0 | AW15: 0 | AX15: 0 | AY15: 0 | AZ15: 0 | BA15: 0 | BB15: 0 | BC15: 0 | BD15: 0 | BE15: 0 | BF15: 0 | BG15: 0 | BH15: 0 | BI15: 0 | BJ15: 0
B16: AAOS | C16: Upper Middle Market | F16: =+SUMIFS($AA16:$DR16,$AA$7:$DR$7,F$7) -> 0 | G16: =+SUMIFS($AA16:$DR16,$AA$7:$DR$7,G$7) -> 0 | H16: =+SUMIFS($AA16:$DR16,$AA$7:$DR$7,H$7) -> 24.473857 | I16: =+SUMIFS($AA16:$DR16,$AA$7:$DR$7,I$7) -> 0 | J16: =+SUMIFS($AA16:$DR16,$AA$7:$DR$7,J$7) -> 0 | K16: =+SUMIFS($AA16:$DR16,$AA$7:$DR$7,K$7) -> 0 | L16: =+SUMIFS($AA16:$DR16,$AA$7:$DR$7,L$7) -> 0 | M16: =+SUMIFS($AA16:$DR16,$AA$7:$DR$7,M$7) -> 0 | AA16: 0 | AB16: 0 | AC16: 0 | AD16: 0 | AE16: 0 | AF16: 0 | AG16: 0 | AH16: 0 | AI16: 0 | AJ16: 0 | AK16: 0 | AL16: 0 | AM16: 0 | AN16: 0 | AO16: 0 | AP16: 0 | AQ16: 0 | AR16: 0 | AS16: 0 | AT16: 0 | AU16: 0 | AV16: 0 | AW16: 0 | AX16: 0 | AY16: 0 | AZ16: 0.01980245 | BA16: 0.0068485652 | BB16: 0 | BC16: 0.33832217 | BD16: 0.34834676 | BE16: 0.91670979 | BF16: 3.4851088 | BG16: 3.090564 | BH16: 6.2581993 | BI16: 4.8818074 | BJ16: 5.1281479
B17: AAP | C17: Major | F17: =+SUMIFS($AA17:$DR17,$AA$7:$DR$7,F$7) -> 47.019762 | G17: =+SUMIFS($AA17:$DR17,$AA$7:$DR$7,G$7) -> 24.701726 | H17: =+SUMIFS($AA17:$DR17,$AA$7:$DR$7,H$7) -> 16.944509 | I17: =+SUMIFS($AA17:$DR17,$AA$7:$DR$7,I$7) -> 0 | J17: =+SUMIFS($AA17:$DR17,$AA$7:$DR$7,J$7) -> 0 | K17: =+SUMIFS($AA17:$DR17,$AA$7:$DR$7,K$7) -> 0 | L17: =+SUMIFS($AA17:$DR17,$AA$7:$DR$7,L$7) -> 0 | M17: =+SUMIFS($AA17:$DR17,$AA$7:$DR$7,M$7) -> 0 | AA17: 3.3629843 | AB17: 1.1368268 | AC17: 8.209188 | AD17: 3.223379 | AE17: 3.1298497 | AF17: 4.1842419 | AG17: 5.6674764 | AH17: 6.0234296 | AI17: 2.8700845 | AJ17: 5.0786975 | AK17: 2.0987348 | AL17: 2.0348698 | AM17: 1.4829749 | AN17: 0.93823992 | AO17: 2.4291153 | AP17: 1.7853337 | AQ17: 1.2271394 | AR17: 1.1766318 | AS17: 1.7744851 | AT17: 2.9930649 | AU17: 1.8871839 | AV17: 3.5760756 | AW17: 3.658232 | AX17: 1.7732493 | AY17: 2.3495539 | AZ17: 2.1539916 | BA17: 1.3322629 | BB17: 0.53347452 | BC17: 0.99883581 | BD17: 0.39215628 | BE17: 2.7289429 | BF17: 0.47376552 | BG17: 1.4062687 | BH17: 0.49121131 | BI17: 1.7457504 | BJ17: 2.3382948
B18: ADA | C18: Lower Middle Market | F18: =+SUMIFS($AA18:$DR18,$AA$7:$DR$7,F$7) -> 0 | G18: =+SUMIFS($AA18:$DR18,$AA$7:$DR$7,G$7) -> 0 | H18: =+SUMIFS($AA18:$DR18,$AA$7:$DR$7,H$7) -> 0.93796194 | I18: =+SUMIFS($AA18:$DR18,$AA$7:$DR$7,I$7) -> 0 | J18: =+SUMIFS($AA18:$DR18,$AA$7:$DR$7,J$7) -> 0 | K18: =+SUMIFS($AA18:$DR18,$AA$7:$DR$7,K$7) -> 0 | L18: =+SUMIFS($AA18:$DR18,$AA$7:$DR$7,L$7) -> 0 | M18: =+SUMIFS($AA18:$DR18,$AA$7:$DR$7,M$7) -> 0 | AA18: 0 | AB18: 0 | AC18: 0 | AD18: 0 | AE18: 0 | AF18: 0 | AG18: 0 | AH18: 0 | AI18: 0 | AJ18: 0 | AK18: 0 | AL18: 0 | AM18: 0 | AN18: 0 | AO18: 0 | AP18: 0 | AQ18: 0 | AR18: 0 | AS18: 0 | AT18: 0 | AU18: 0 | AV18: 0 | AW18: 0 | AX18: 0 | AY18: 0 | AZ18: 0 | BA18: 0 | BB18: 0 | BC18: 0 | BD18: 0.036517133 | BE18: 0.0039547863 | BF18: 0.0038595745 | BG18: 0 | BH18: 0.082851005 | BI18: 0.29803071 | BJ18: 0.51274873
B19: AHRQ | C19: Lower Middle Market | F19: =+SUMIFS($AA19:$DR19,$AA$7:$DR$7,F$7) -> 0 | G19: =+SUMIFS($AA19:$DR19,$AA$7:$DR$7,G$7) -> 0 | H19: =+SUMIFS($AA19:$DR19,$AA$7:$DR$7,H$7) -> 0 | I19: =+SUMIFS($AA19:$DR19,$AA$7:$DR$7,I$7) -> 0 | J19: =+SUMIFS($AA19:$DR19,$AA$7:$DR$7,J$7) -> 0 | K19: =+SUMIFS($AA19:$DR19,$AA$7:$DR$7,K$7) -> 0 | L19: =+SUMIFS($AA19:$DR19,$AA$7:$DR$7,L$7) -> 0 | M19: =+SUMIFS($AA19:$DR19,$AA$7:$DR$7,M$7) -> 0 | AA19: 0 | AB19: 0 | AC19: 0 | AD19: 0 | AE19: 0 | AF19: 0 | AG19: 0 | AH19: 0 | AI19: 0 | AJ19: 0 | AK19: 0 | AL19: 0 | AM19: 0 | AN19: 0 | AO19: 0 | AP19: 0 | AQ19: 0 | AR19: 0 | AS19: 0 | AT19: 0 | AU19: 0 | AV19: 0 | AW19: 0 | AX19: 0 | AY19: 0 | AZ19: 0 | BA19: 0 | BB19: 0 | BC19: 0 | BD19: 0 | BE19: 0 | BF19: 0 | BG19: 0 | BH19: 0 | BI19: 0 | BJ19: 0
B20: AIPP | C20: Major | F20: =+SUMIFS($AA20:$DR20,$AA$7:$DR$7,F$7) -> 0 | G20: =+SUMIFS($AA20:$DR20,$AA$7:$DR$7,G$7) -> 0 | H20: =+SUMIFS($AA20:$DR20,$AA$7:$DR$7,H$7) -> 0 | I20: =+SUMIFS($AA20:$DR20,$AA$7:$DR$7,I$7) -> 0 | J20: =+SUMIFS($AA20:$DR20,$AA$7:$DR$7,J$7) -> 0 | K20: =+SUMIFS($AA20:$DR20,$AA$7:$DR$7,K$7) -> 0 | L20: =+SUMIFS($AA20:$DR20,$AA$7:$DR$7,L$7) -> 0 | M20: =+SUMIFS($AA20:$DR20,$AA$7:$DR$7,M$7) -> 0 | AA20: 0 | AB20: 0 | AC20: 0 | AD20: 0 | AE20: 0 | AF20: 0 | AG20: 0 | AH20: 0 | AI20: 0 | AJ20: 0 | AK20: 0 | AL20: 0 | AM20: 0 | AN20: 0 | AO20: 0 | AP20: 0 | AQ20: 0 | AR20: 0 | AS20: 0 | AT20: 0 | AU20: 0 | AV20: 0 | AW20: 0 | AX20: 0 | AY20: 0 | AZ20: 0 | BA20: 0 | BB20: 0 | BC20: 0 | BD20: 0 | BE20: 0 | BF20: 0 | BG20: 0 | BH20: 0 | BI20: 0 | BJ20: 0
B21: ALLEN | C21: Upper Middle Market | F21: =+SUMIFS($AA21:$DR21,$AA$7:$DR$7,F$7) -> 0.45556075 | G21: =+SUMIFS($AA21:$DR21,$AA$7:$DR$7,G$7) -> 35.35503 | H21: =+SUMIFS($AA21:$DR21,$AA$7:$DR$7,H$7) -> 43.708185 | I21: =+SUMIFS($AA21:$DR21,$AA$7:$DR$7,I$7) -> 0 | J21: =+SUMIFS($AA21:$DR21,$AA$7:$DR$7,J$7) -> 0 | K21: =+SUMIFS($AA21:$DR21,$AA$7:$DR$7,K$7) -> 0 | L21: =+SUMIFS($AA21:$DR21,$AA$7:$DR$7,L$7) -> 0 | M21: =+SUMIFS($AA21:$DR21,$AA$7:$DR$7,M$7) -> 0 | AA21: 0 | AB21: 0 | AC21: 0.075913136 | AD21: 0 | AE21: 0 | AF21: 0.0081275186 | AG21: 0 | AH21: 0.018045105 | AI21: 0 | AJ21: 0.18331029 | AK21: 0.025261544 | AL21: 0.14490316 | AM21: 0.11215024 | AN21: 1.7140474 | AO21: 1.2186278 | AP21: 1.3591446 | AQ21: 1.4596021 | AR21: 4.7302452 | AS21: 4.1455135 | AT21: 4.6366293 | AU21: 2.964056 | AV21: 3.5676551 | AW21: 4.7714323 | AX21: 4.675927 | AY21: 3.8963324 | AZ21: 4.1499295 | BA21: 3.9963912 | BB21: 3.7621576 | BC21: 5.4598672 | BD21: 3.9648356 | BE21: 2.804399 | BF21: 4.3127886 | BG21: 3.3024298 | BH21: 2.0957186 | BI21: 4.6312241 | BJ21: 1.3321116
B22: AMA | C22: Mega | F22: =+SUMIFS($AA22:$DR22,$AA$7:$DR$7,F$7) -> 326.2527 | G22: =+SUMIFS($AA22:$DR22,$AA$7:$DR$7,G$7) -> 158.60949 | H22: =+SUMIFS($AA22:$DR22,$AA$7:$DR$7,H$7) -> 192.58217 | I22: =+SUMIFS($AA22:$DR22,$AA$7:$DR$7,I$7) -> 0 | J22: =+SUMIFS($AA22:$DR22,$AA$7:$DR$7,J$7) -> 0 | K22: =+SUMIFS($AA22:$DR22,$AA$7:$DR$7,K$7) -> 0 | L22: =+SUMIFS($AA22:$DR22,$AA$7:$DR$7,L$7) -> 0 | M22: =+SUMIFS($AA22:$DR22,$AA$7:$DR$7,M$7) -> 0 | AA22: 19.603729 | AB22: 32.856753 | AC22: 33.267641 | AD22: 43.751815 | AE22: 44.320755 | AF22: 29.45154 | AG22: 24.16103 | AH22: 23.892125 | AI22: 19.874672 | AJ22: 23.855028 | AK22: 16.446241 | AL22: 14.771366 | AM22: 15.251374 | AN22: 23.223621 | AO22: 17.432501 | AP22: 15.500902 | AQ22: 12.103186 | AR22: 13.448291 | AS22: 16.485301 | AT22: 9.6413695 | AU22: 8.7718837 | AV22: 12.922258 | AW22: 7.6589432 | AX22: 6.1698606 | AY22: 14.708746 | AZ22: 14.754205 | BA22: 15.604159 | BB22: 7.8179854 | BC22: 13.554693 | BD22: 11.810563 | BE22: 14.513418 | BF22: 22.262411 | BG22: 13.983032 | BH22: 22.831333 | BI22: 22.935812 | BJ22: 17.805809
B23: AORN | C23: Lower Middle Market | F23: =+SUMIFS($AA23:$DR23,$AA$7:$DR$7,F$7) -> 15.025989 | G23: =+SUMIFS($AA23:$DR23,$AA$7:$DR$7,G$7) -> 8.7882128 | H23: =+SUMIFS($AA23:$DR23,$AA$7:$DR$7,H$7) -> 15.101439 | I23: =+SUMIFS($AA23:$DR23,$AA$7:$DR$7,I$7) -> 0 | J23: =+SUMIFS($AA23:$DR23,$AA$7:$DR$7,J$7) -> 0 | K23: =+SUMIFS($AA23:$DR23,$AA$7:$DR$7,K$7) -> 0 | L23: =+SUMIFS($AA23:$DR23,$AA$7:$DR$7,L$7) -> 0 | M23: =+SUMIFS($AA23:$DR23,$AA$7:$DR$7,M$7) -> 0 | AA23: 0.25410076 | AB23: 1.1676479 | AC23: 0.42854922 | AD23: 0.37604447 | AE23: 1.2968035 | AF23: 1.9979773 | AG23: 1.4795579 | AH23: 2.675975 | AI23: 2.6422212 | AJ23: 2.0457121 | AK23: 0.30386441 | AL23: 0.357535 | AM23: 1.7224298 | AN23: 0.25582884 | AO23: 2.1378906 | AP23: 0.12028488 | AQ23: 0.30666768 | AR23: 0.2414936 | AS23: 0.60353814 | AT23: 0.90471689 | AU23: 0.85373749 | AV23: 0.14434922 | AW23: 0.94047544 | AX23: 0.55680024 | AY23: 2.3530467 | AZ23: 1.4153498 | BA23: 0.63903564 | BB23: 0.30773774 | BC23: 0.65826906 | BD23: 2.4019413 | BE23: 2.9493892 | BF23: 0.53659957 | BG23: 0.93714791 | BH23: 2.1480429 | BI23: 0.14381543 | BJ23: 0.61106418
B24: AOTA | C24: Lower Middle Market | F24: =+SUMIFS($AA24:$DR24,$AA$7:$DR$7,F$7) -> 12.092873 | G24: =+SUMIFS($AA24:$DR24,$AA$7:$DR$7,G$7) -> 3.6539287 | H24: =+SUMIFS($AA24:$DR24,$AA$7:$DR$7,H$7) -> 5.6338862 | I24: =+SUMIFS($AA24:$DR24,$AA$7:$DR$7,I$7) -> 0 | J24: =+SUMIFS($AA24:$DR24,$AA$7:$DR$7,J$7) -> 0 | K24: =+SUMIFS($AA24:$DR24,$AA$7:$DR$7,K$7) -> 0 | L24: =+SUMIFS($AA24:$DR24,$AA$7:$DR$7,L$7) -> 0 | M24: =+SUMIFS($AA24:$DR24,$AA$7:$DR$7,M$7) -> 0 | AA24: 1.3495978 | AB24: 0.4007777 | AC24: 0.76726246 | AD24: 0.69307634 | AE24: 3.2118626 | AF24: 1.7887281 | AG24: 0.27879355 | AH24: 1.1003811 | AI24: 0.087498458 | AJ24: 0.16298269 | AK24: 1.0167134 | AL24: 1.2351992 | AM24: 1.1653699 | AN24: 0.53680937 | AO24: 0.18981007 | AP24: 1.0490112 | AQ24: 0.23130573 | AR24: 0.0082188723 | AS24: 0.13259701 | AT24: 0.086405672 | AU24: 0.017171906 | AV24: 0.10092093 | AW24: 0.040628275 | AX24: 0.09567984 | AY24: 0.3913812 | AZ24: 0.47929634 | BA24: 0.28045939 | BB24: 0.84224942 | BC24: 0.18105606 | BD24: 0.22003255 | BE24: 0.44894256 | BF24: 0.35756853 | BG24: 0.84052494 | BH24: 0.42061198 | BI24: 0.86302832 | BJ24: 0.30873486
... B58: EL | C58: Lower Middle Market | F58: =+SUMIFS($AA58:$DR58,$AA$7:$DR$7,F$7) -> 14.856469 | G58: =+SUMIFS($AA58:$DR58,$AA$7:$DR$7,G$7) -> 3.4620316 | H58: =+SUMIFS($AA58:$DR58,$AA$7:$DR$7,H$7) -> 0.35832793 | I58: =+SUMIFS($AA58:$DR58,$AA$7:$DR$7,I$7) -> 0 | J58: =+SUMIFS($AA58:$DR58,$AA$7:$DR$7,J$7) -> 0 | K58: =+SUMIFS($AA58:$DR58,$AA$7:$DR$7,K$7) -> 0 | L58: =+SUMIFS($AA58:$DR58,$AA$7:$DR$7,L$7) -> 0 | M58: =+SUMIFS($AA58:$DR58,$AA$7:$DR$7,M$7) -> 0 | AA58: 2.4831102 | AB58: 5.2025387 | AC58: 1.9420829 | AD58: 1.9803777 | AE58: 2.7168995 | AF58: 0.53145975 | AG58: 0 | AH58: 0 | AI58: 0 | AJ58: 0 | AK58: 0 | AL58: 0 | AM58: 0.5854165 | AN58: 0 | AO58: 0.31649546 | AP58: 1.1194254 | AQ58: 0.88241545 | AR58: 0 | AS58: 0.068453317 | AT58: 0.15589522 | AU58: 0.25377458 | AV58: 0 | AW58: 0 | AX58: 0.080155638 | AY58: 0.35832793 | AZ58: 0 | BA58: 0 | BB58: 0 | BC58: 0 | BD58: 0 | BE58: 0 | BF58: 0 | BG58: 0 | BH58: 0 | BI58: 0 | BJ58: 0
B60: Total | F60: =+SUMIFS($AA60:$DR60,$AA$7:$DR$7,F$7) -> 1503.9461 | G60: =+SUMIFS($AA60:$DR60,$AA$7:$DR$7,G$7) -> 1196.8802 | H60: =+SUMIFS($AA60:$DR60,$AA$7:$DR$7,H$7) -> 1032.6039 | I60: =+SUMIFS($AA60:$DR60,$AA$7:$DR$7,I$7) -> 0 | J60: =+SUMIFS($AA60:$DR60,$AA$7:$DR$7,J$7) -> 0 | K60: =+SUMIFS($AA60:$DR60,$AA$7:$DR$7,K$7) -> 0 | L60: =+SUMIFS($AA60:$DR60,$AA$7:$DR$7,L$7) -> 0 | M60: =+SUMIFS($AA60:$DR60,$AA$7:$DR$7,M$7) -> 0 | AA60: =SUM(AA13:AA59) -> 120.813 | AB60: =SUM(AB13:AB59) -> 120.5299 | AC60: =SUM(AC13:AC59) -> 123.2864 | AD60: =SUM(AD13:AD59) -> 143.02661 | AE60: =SUM(AE13:AE59) -> 140.62187 | AF60: =SUM(AF13:AF59) -> 135.30032 | AG60: =SUM(AG13:AG59) -> 135.13648 | AH60: =SUM(AH13:AH59) -> 137.14661 | ... BJ60: =SUM(BJ13:BJ59) -> 80.162965
B62: Revenue
B63: Mega | F63: =+Revenue_Calcs!F84 -> 7916.045 | G63: =+Revenue_Calcs!G84 -> 8245.29 | H63: =+Revenue_Calcs!H84 -> 8781.0996 | I63: =+Revenue_Calcs!I84 -> 9075.5233 | J63: =+Revenue_Calcs!J84 -> 9607.4895 | K63: =+Revenue_Calcs!K84 -> 11031.683 | L63: =+Revenue_Calcs!L84 -> 12578.996 | M63: =+Revenue_Calcs!M84 -> 14258.439
B64: Major | F64: =+Revenue_Calcs!F96 -> 1771.212 | G64: =+Revenue_Calcs!G96 -> 1842.559 | H64: =+Revenue_Calcs!H96 -> 1905.0657 | I64: =+Revenue_Calcs!I96 -> 2067.5604 | J64: =+Revenue_Calcs!J96 -> 2432.239 | K64: =+Revenue_Calcs!K96 -> 2936.4859 | L64: =+Revenue_Calcs!L96 -> 3488.9031 | M64: =+Revenue_Calcs!M96 -> 4093.2769
B65: Upper Middle Market | F65: =+Revenue_Calcs!F108 -> 1021.766 | G65: =+Revenue_Calcs!G108 -> 1442.292 | H65: =+Revenue_Calcs!H108 -> 2048.7125 | I65: =+Revenue_Calcs!I108 -> 2199.9747 | J65: =+Revenue_Calcs!J108 -> 2835.7219 | K65: =+Revenue_Calcs!K108 -> 3625.4013 | L65: =+Revenue_Calcs!L108 -> 4699.4767 | M65: =+Revenue_Calcs!M108 -> 6259.7287
B66: Lower Middle Market | F66: =+Revenue_Calcs!F120 -> 1123.217 | G66: =+Revenue_Calcs!G120 -> 1313.177 | H66: =+Revenue_Calcs!H120 -> 1332.7588 | I66: =+Revenue_Calcs!I120 -> 1821.7645 | J66: =+Revenue_Calcs!J120 -> 2286.47 | K66: =+Revenue_Calcs!K120 -> 2859.4402 | L66: =+Revenue_Calcs!L120 -> 3653.2182 | M66: =+Revenue_Calcs!M120 -> 4798.4711
B67: Total | F67: =SUM(F63:F66) -> 11832.24 | G67: =SUM(G63:G66) -> 12843.318 | H67: =SUM(H63:H66) -> 14067.637 | I67: =SUM(I63:I66) -> 15164.823 | J67: =SUM(J63:J66) -> 17161.92 | K67: =SUM(K63:K66) -> 20453.01 | L67: =SUM(L63:L66) -> 24420.594 | M67: =SUM(M63:M66) -> 29409.916
B69: Cost of Sales
B70: Mega | F70: =+SUMIFS($AA70:$DR70,$AA$7:$DR$7,F$7) -> 902.11757 | G70: =+SUMIFS($AA70:$DR70,$AA$7:$DR$7,G$7) -> 713.19791 | H70: =+SUMIFS($AA70:$DR70,$AA$7:$DR$7,H$7) -> 542.40104 | I70: =+I63*(1-COGS_Assumptions!I13) -> 726.04186 | J70: =+J63*(1-COGS_Assumptions!J13) -> 768.59916 | K70: =+K63*(1-COGS_Assumptions!K13) -> 860.47125 | L70: =+L63*(1-COGS_Assumptions!L13) -> 956.00366 | M70: =+M63*(1-COGS_Assumptions!M13) -> 1055.1245 | AA70: =+SUMIFS(AA$13:AA$58,$C$13:$C$58,$B70) -> 68.054948 | AB70: =+SUMIFS(AB$13:AB$58,$C$13:$C$58,$B70) -> 74.235249 | AC70: =+SUMIFS(AC$13:AC$58,$C$13:$C$58,$B70) -> 70.740238 | AD70: =+SUMIFS(AD$13:AD$58,$C$13:$C$58,$B70) -> 93.129748 | AE70: =+SUMIFS(AE$13:AE$58,$C$13:$C$58,$B70) -> 91.881697 | AF70: =+SUMIFS(AF$13:AF$58,$C$13:$C$58,$B70) -> 82.011965 | AG70: =+SUMIFS(AG$13:AG$58,$C$13:$C$58,$B70) -> 86.230839 | AH70: =+SUMIFS(AH$13:AH$58,$C$13:$C$58,$B70) -> 85.382009 | ... BJ70: =+SUMIFS(BJ$13:BJ$58,$C$13:$C$58,$B70) -> 42.508776 | BK70: =+SUMIFS($F70:$M70,$F$7:$M$7,BK$7)*BK$75 -> 62.784997 | BL70: =+SUMIFS($F70:$M70,$F$7:$M$7,BL$7)*BL$75 -> 63.818748 | BM70: =+SUMIFS($F70:$M70,$F$7:$M$7,BM$7)*BM$75 -> 62.966376 | BN70: =+SUMIFS($F70:$M70,$F$7:$M$7,BN$7)*BN$75 -> 67.734476 | BO70: =+SUMIFS($F70:$M70,$F$7:$M$7,BO$7)*BO$75 -> 59.576116 | BP70: =+SUMIFS($F70:$M70,$F$7:$M$7,BP$7)*BP$75 -> 58.884635 | BQ70: =+SUMIFS($F70:$M70,$F$7:$M$7,BQ$7)*BQ$75 -> 59.755491 | BR70: =+SUMIFS($F70:$M70,$F$7:$M$7,BR$7)*BR$75 -> 63.790202 | ... DR70: =+SUMIFS($F70:$M70,$F$7:$M$7,DR$7)*DR$75 -> 72.605983
B71: Major | F71: =+SUMIFS($AA71:$DR71,$AA$7:$DR$7,F$7) -> 273.4258 | G71: =+SUMIFS($AA71:$DR71,$AA$7:$DR$7,G$7) -> 219.61596 | H71: =+SUMIFS($AA71:$DR71,$AA$7:$DR$7,H$7) -> 170.75762 | I71: =+I64*(1-COGS_Assumptions!I14) -> 214.58955 | J71: =+J64*(1-COGS_Assumptions!J14) -> 252.43909 | K71: =+K64*(1-COGS_Assumptions!K14) -> 298.90128 | L71: =+L64*(1-COGS_Assumptions!L14) -> 348.15335 | M71: =+M64*(1-COGS_Assumptions!M14) -> 400.2765 | AA71: =+SUMIFS(AA$13:AA$58,$C$13:$C$58,$B71) -> 21.990762 | AB71: =+SUMIFS(AB$13:AB$58,$C$13:$C$58,$B71) -> 20.040356 | AC71: =+SUMIFS(AC$13:AC$58,$C$13:$C$58,$B71) -> 26.635063 | AD71: =+SUMIFS(AD$13:AD$58,$C$13:$C$58,$B71) -> 18.880376 | AE71: =+SUMIFS(AE$13:AE$58,$C$13:$C$58,$B71) -> 17.184828 | AF71: =+SUMIFS(AF$13:AF$58,$C$13:$C$58,$B71) -> 21.489903 | AG71: =+SUMIFS(AG$13:AG$58,$C$13:$C$58,$B71) -> 20.594572 | AH71: =+SUMIFS(AH$13:AH$58,$C$13:$C$58,$B71) -> 21.100755 | ... BJ71: =+SUMIFS(BJ$13:BJ$58,$C$13:$C$58,$B71) -> 11.337856 | BK71: =+SUMIFS($F71:$M71,$F$7:$M$7,BK$7)*BK$75 -> 18.556787 | BL71: =+SUMIFS($F71:$M71,$F$7:$M$7,BL$7)*BL$75 -> 18.862323 | BM71: =+SUMIFS($F71:$M71,$F$7:$M$7,BM$7)*BM$75 -> 18.610395 | BN71: =+SUMIFS($F71:$M71,$F$7:$M$7,BN$7)*BN$75 -> 20.019659 | BO71: =+SUMIFS($F71:$M71,$F$7:$M$7,BO$7)*BO$75 -> 17.608367 | BP71: =+SUMIFS($F71:$M71,$F$7:$M$7,BP$7)*BP$75 -> 17.403993 | BQ71: =+SUMIFS($F71:$M71,$F$7:$M$7,BQ$7)*BQ$75 -> 17.661383 | BR71: =+SUMIFS($F71:$M71,$F$7:$M$7,BR$7)*BR$75 -> 18.853886 | ... DR71: =+SUMIFS($F71:$M71,$F$7:$M$7,DR$7)*DR$75 -> 27.544113
B72: Upper Middle Market | F72: =+SUMIFS($AA72:$DR72,$AA$7:$DR$7,F$7) -> 169.91649 | G72: =+SUMIFS($AA72:$DR72,$AA$7:$DR$7,G$7) -> 138.62616 | H72: =+SUMIFS($AA72:$DR72,$AA$7:$DR$7,H$7) -> 212.63335 | I72: =+I65*(1-COGS_Assumptions!I15) -> 176.31356 | J72: =+J65*(1-COGS_Assumptions!J15) -> 227.26454 | K72: =+K65*(1-COGS_Assumptions!K15) -> 283.30137 | L72: =+L65*(1-COGS_Assumptions!L15) -> 357.83437 | M72: =+M65*(1-COGS_Assumptions!M15) -> 464.11788 | AA72: =+SUMIFS(AA$13:AA$58,$C$13:$C$58,$B72) -> 16.753382 | AB72: =+SUMIFS(AB$13:AB$58,$C$13:$C$58,$B72) -> 10.733904 | AC72: =+SUMIFS(AC$13:AC$58,$C$13:$C$58,$B72) -> 14.234974 | AD72: =+SUMIFS(AD$13:AD$58,$C$13:$C$58,$B72) -> 16.035981 | AE72: =+SUMIFS(AE$13:AE$58,$C$13:$C$58,$B72) -> 12.357457 | AF72: =+SUMIFS(AF$13:AF$58,$C$13:$C$58,$B72) -> 19.416413 | AG72: =+SUMIFS(AG$13:AG$58,$C$13:$C$58,$B72) -> 13.581551 | AH72: =+SUMIFS(AH$13:AH$58,$C$13:$C$58,$B72) -> 14.029985 | ... BJ72: =+SUMIFS(BJ$13:BJ$58,$C$13:$C$58,$B72) -> 19.762112 | BK72: =+SUMIFS($F72:$M72,$F$7:$M$7,BK$7)*BK$75 -> 15.246843 | BL72: =+SUMIFS($F72:$M72,$F$7:$M$7,BL$7)*BL$75 -> 15.497882 | BM72: =+SUMIFS($F72:$M72,$F$7:$M$7,BM$7)*BM$75 -> 15.29089 | BN72: =+SUMIFS($F72:$M72,$F$7:$M$7,BN$7)*BN$75 -> 16.448785 | BO72: =+SUMIFS($F72:$M72,$F$7:$M$7,BO$7)*BO$75 -> 14.467592 | BP72: =+SUMIFS($F72:$M72,$F$7:$M$7,BP$7)*BP$75 -> 14.299671 | BQ72: =+SUMIFS($F72:$M72,$F$7:$M$7,BQ$7)*BQ$75 -> 14.511151 | BR72: =+SUMIFS($F72:$M72,$F$7:$M$7,BR$7)*BR$75 -> 15.490949 | ... DR72: =+SUMIFS($F72:$M72,$F$7:$M$7,DR$7)*DR$75 -> 31.937212
B73: Lower Middle Market | F73: =+SUMIFS($AA73:$DR73,$AA$7:$DR$7,F$7) -> 158.4862 | G73: =+SUMIFS($AA73:$DR73,$AA$7:$DR$7,G$7) -> 125.44012 | H73: =+SUMIFS($AA73:$DR73,$AA$7:$DR$7,H$7) -> 106.81189 | I73: =+I66*(1-COGS_Assumptions!I16) -> 133.72261 | J73: =+J66*(1-COGS_Assumptions!J16) -> 167.8333 | K73: =+K66*(1-COGS_Assumptions!K16) -> 204.17203 | L73: =+L66*(1-COGS_Assumptions!L16) -> 253.54356 | M73: =+M66*(1-COGS_Assumptions!M16) -> 323.43038 | AA73: =+SUMIFS(AA$13:AA$58,$C$13:$C$58,$B73) -> 14.013907 | AB73: =+SUMIFS(AB$13:AB$58,$C$13:$C$58,$B73) -> 15.520389 | AC73: =+SUMIFS(AC$13:AC$58,$C$13:$C$58,$B73) -> 11.676122 | AD73: =+SUMIFS(AD$13:AD$58,$C$13:$C$58,$B73) -> 14.980509 | AE73: =+SUMIFS(AE$13:AE$58,$C$13:$C$58,$B73) -> 19.197887 | AF73: =+SUMIFS(AF$13:AF$58,$C$13:$C$58,$B73) -> 12.382038 | AG73: =+SUMIFS(AG$13:AG$58,$C$13:$C$58,$B73) -> 14.729515 | AH73: =+SUMIFS(AH$13:AH$58,$C$13:$C$58,$B73) -> 16.633859 | ... BJ73: =+SUMIFS(BJ$13:BJ$58,$C$13:$C$58,$B73) -> 6.5542208 | BK73: =+SUMIFS($F73:$M73,$F$7:$M$7,BK$7)*BK$75 -> 11.56376 | BL73: =+SUMIFS($F73:$M73,$F$7:$M$7,BL$7)*BL$75 -> 11.754157 | BM73: =+SUMIFS($F73:$M73,$F$7:$M$7,BM$7)*BM$75 -> 11.597167 | BN73: =+SUMIFS($F73:$M73,$F$7:$M$7,BN$7)*BN$75 -> 12.475357 | BO73: =+SUMIFS($F73:$M73,$F$7:$M$7,BO$7)*BO$75 -> 10.972748 | BP73: =+SUMIFS($F73:$M73,$F$7:$M$7,BP$7)*BP$75 -> 10.84539 | BQ73: =+SUMIFS($F73:$M73,$F$7:$M$7,BQ$7)*BQ$75 -> 11.005785 | BR73: =+SUMIFS($F73:$M73,$F$7:$M$7,BR$7)*BR$75 -> 11.748899 | ... DR73: =+SUMIFS($F73:$M73,$F$7:$M$7,DR$7)*DR$75 -> 22.256123
B74: Total | F74: =+SUMIFS($AA74:$DR74,$AA$7:$DR$7,F$7) -> 1503.9461 | G74: =+SUMIFS($AA74:$DR74,$AA$7:$DR$7,G$7) -> 1196.8802 | H74: =+SUMIFS($AA74:$DR74,$AA$7:$DR$7,H$7) -> 1032.6039 | I74: =+SUMIFS($AA74:$DR74,$AA$7:$DR$7,I$7) -> 1250.6676 | J74: =+SUMIFS($AA74:$DR74,$AA$7:$DR$7,J$7) -> 1416.1361 | K74: =+SUMIFS($AA74:$DR74,$AA$7:$DR$7,K$7) -> 1646.8459 | L74: =+SUMIFS($AA74:$DR74,$AA$7:$DR$7,L$7) -> 1915.5349 | M74: =+SUMIFS($AA74:$DR74,$AA$7:$DR$7,M$7) -> 2242.9493 | AA74: =SUM(AA70:AA73) -> 120.813 | AB74: =SUM(AB70:AB73) -> 120.5299 | AC74: =SUM(AC70:AC73) -> 123.2864 | AD74: =SUM(AD70:AD73) -> 143.02661 | AE74: =SUM(AE70:AE73) -> 140.62187 | AF74: =SUM(AF70:AF73) -> 135.30032 | AG74: =SUM(AG70:AG73) -> 135.13648 | AH74: =SUM(AH70:AH73) -> 137.14661 | ... DR74: =SUM(DR70:DR73) -> 154.34343
B75: % Seasonality | F75: =+F74/SUMIFS($AA74:$DR74,$AA$7:$DR$7,F$7) -> 1 | G75: =+G74/SUMIFS($AA74:$DR74,$AA$7:$DR$7,G$7) -> 1 | H75: =+H74/SUMIFS($AA74:$DR74,$AA$7:$DR$7,H$7) -> 1 | I75: =+I74/SUMIFS($AA74:$DR74,$AA$7:$DR$7,I$7) -> 1 | J75: =+J74/SUMIFS($AA74:$DR74,$AA$7:$DR$7,J$7) -> 1 | K75: =+K74/SUMIFS($AA74:$DR74,$AA$7:$DR$7,K$7) -> 1 | L75: =+L74/SUMIFS($AA74:$DR74,$AA$7:$DR$7,L$7) -> 1 | M75: =+M74/SUMIFS($AA74:$DR74,$AA$7:$DR$7,M$7) -> 1 | AA75: =+AA74/SUMIFS($AA74:$DR74,$AA$7:$DR$7,AA$7) -> 0.080330673 | AB75: =+AB74/SUMIFS($AA74:$DR74,$AA$7:$DR$7,AB$7) -> 0.080142435 | AC75: =+AC74/SUMIFS($AA74:$DR74,$AA$7:$DR$7,AC$7) -> 0.081975278 | AD75: =+AD74/SUMIFS($AA74:$DR74,$AA$7:$DR$7,AD$7) -> 0.095100894 | AE75: =+AE74/SUMIFS($AA74:$DR74,$AA$7:$DR$7,AE$7) -> 0.093501937 | AF75: =+AF74/SUMIFS($AA74:$DR74,$AA$7:$DR$7,AF$7) -> 0.089963545 | AG75: =+AG74/SUMIFS($AA74:$DR74,$AA$7:$DR$7,AG$7) -> 0.089854603 | AH75: =+AH74/SUMIFS($AA74:$DR74,$AA$7:$DR$7,AH$7) -> 0.091191175 | ... BJ75: =+BJ74/SUMIFS($AA74:$DR74,$AA$7:$DR$7,BJ$7) -> 0.077631864 | BK75: =+AVERAGE(AA75,AM75,AY75) -> 0.086475726 | BL75: =+AVERAGE(AB75,AN75,AZ75) -> 0.087899543 | BM75: =+AVERAGE(AC75,AO75,BA75) -> 0.086725545 | BN75: =+AVERAGE(AD75,AP75,BB75) -> 0.093292797 | BO75: =+AVERAGE(AE75,AQ75,BC75) -> 0.082056035 | BP75: =+AVERAGE(AF75,AR75,BD75) -> 0.081103637 | BQ75: =+AVERAGE(AG75,AS75,BE75) -> 0.082303093 | BR75: =+AVERAGE(AH75,AT75,BF75) -> 0.087860227 | ... DR75: =+AVERAGE(CH75,CT75,DF75) -> 0.068812717
B77: Gross Profit
B78: Mega | F78: =+F63-F70 -> 7013.9274 | G78: =+G63-G70 -> 7532.0921 | H78: =+H63-H70 -> 8238.6986 | I78: =+I63-I70 -> 8349.4814 | J78: =+J63-J70 -> 8838.8904 | K78: =+K63-K70 -> 10171.211 | L78: =+L63-L70 -> 11622.992 | M78: =+M63-M70 -> 13203.315
B79: Major | F79: =+F64-F71 -> 1497.7862 | G79: =+G64-G71 -> 1622.943 | H79: =+H64-H71 -> 1734.3081 | I79: =+I64-I71 -> 1852.9708 | J79: =+J64-J71 -> 2179.7999 | K79: =+K64-K71 -> 2637.5846 | L79: =+L64-L71 -> 3140.7498 | M79: =+M64-M71 -> 3693.0004
B80: Upper Middle Market | F80: =+F65-F72 -> 851.84951 | G80: =+G65-G72 -> 1303.6658 | H80: =+H65-H72 -> 1836.0792 | I80: =+I65-I72 -> 2023.6611 | J80: =+J65-J72 -> 2608.4574 | K80: =+K65-K72 -> 3342.1 | L80: =+L65-L72 -> 4341.6423 | M80: =+M65-M72 -> 5795.6108
B81: Lower Middle Market | F81: =+F66-F73 -> 964.7308 | G81: =+G66-G73 -> 1187.7369 | H81: =+H66-H73 -> 1225.9469 | I81: =+I66-I73 -> 1688.0419 | J81: =+J66-J73 -> 2118.6367 | K81: =+K66-K73 -> 2655.2681 | L81: =+L66-L73 -> 3399.6746 | M81: =+M66-M73 -> 4475.0407
B82: Total | F82: =SUM(F78:F81) -> 10328.294 | G82: =SUM(G78:G81) -> 11646.438 | H82: =SUM(H78:H81) -> 13035.033 | I82: =SUM(I78:I81) -> 13914.155 | J82: =SUM(J78:J81) -> 15745.784 | K82: =SUM(K78:K81) -> 18806.164 | L82: =SUM(L78:L81) -> 22505.059 | M82: =SUM(M78:M81) -> 27166.967
B84: Gross Margin
B85: Mega | F85: =+F78/F63 -> 0.88603936 | G85: =+G78/G63 -> 0.91350239 | H85: =+H78/H63 -> 0.93823085 | I85: =+I78/I63 -> 0.92 | J85: =+J78/J63 -> 0.92 | K85: =+K78/K63 -> 0.922 | L85: =+L78/L63 -> 0.924 | M85: =+M78/M63 -> 0.926
B86: Major | F86: =+F79/F64 -> 0.84562785 | G86: =+G79/G64 -> 0.88080926 | H86: =+H79/H64 -> 0.91036654 | I86: =+I79/I64 -> 0.89621123 | J86: =+J79/J64 -> 0.89621123 | K86: =+K79/K64 -> 0.89821123 | L86: =+L79/L64 -> 0.90021123 | M86: =+M79/M64 -> 0.90221123
B87: Upper Middle Market | F87: =+F80/F65 -> 0.83370312 | G87: =+G80/G65 -> 0.90388482 | H87: =+H80/H65 -> 0.89621123 | I87: =+I80/I65 -> 0.91985655 | J87: =+J80/J65 -> 0.91985655 | K87: =+K80/K65 -> 0.92185655 | L87: =+L80/L65 -> 0.92385655 | M87: =+M80/M65 -> 0.92585655
B88: Lower Middle Market | F88: =+F81/F66 -> 0.85889975 | G88: =+G81/G66 -> 0.90447585 | H88: =+H81/H66 -> 0.91985655 | I88: =+I81/I66 -> 0.9265972 | J88: =+J81/J66 -> 0.9265972 | K88: =+K81/K66 -> 0.9285972 | L88: =+L81/L66 -> 0.9305972 | M88: =+M81/M66 -> 0.9325972
B89: Total | F89: =+F82/F67 -> 0.87289422 | G89: =+G82/G67 -> 0.90680912 | H89: =+H82/H67 -> 0.9265972 | I89: =+I82/I67 -> 0.91752838 | J89: =+J82/J67 -> 0.91748382 | K89: =+K82/K67 -> 0.91948149 | L89: =+L82/L67 -> 0.92156067 | M89: =+M82/M67 -> 0.92373493
B91: Hosting
B92: Revenue | F92: =+SUMIFS($AA92:$DR92,$AA$7:$DR$7,F$7) -> 11832.24 | G92: =+SUMIFS($AA92:$DR92,$AA$7:$DR$7,G$7) -> 12843.318 | H92: =+SUMIFS($AA92:$DR92,$AA$7:$DR$7,H$7) -> 14067.637 | I92: =+SUMIFS($AA92:$DR92,$AA$7:$DR$7,I$7) -> 15185.135 | J92: =+SUMIFS($AA92:$DR92,$AA$7:$DR$7,J$7) -> 17161.92 | K92: =+SUMIFS($AA92:$DR92,$AA$7:$DR$7,K$7) -> 20453.01 | L92: =+SUMIFS($AA92:$DR92,$AA$7:$DR$7,L$7) -> 24420.594 | M92: =+SUMIFS($AA92:$DR92,$AA$7:$DR$7,M$7) -> 29409.916 | AA92: =+Revenue_Calcs!AA122 -> 981.129 | AB92: =+Revenue_Calcs!AB122 -> 981.129 | AC92: =+Revenue_Calcs!AC122 -> 976.962 | AD92: =+Revenue_Calcs!AD122 -> 977.327 | AE92: =+Revenue_Calcs!AE122 -> 975.227 | AF92: =+Revenue_Calcs!AF122 -> 962.73 | AG92: =+Revenue_Calcs!AG122 -> 972.843 | AH92: =+Revenue_Calcs!AH122 -> 1101.548 | ... DR92: =+Revenue_Calcs!DR122 -> 2583.2225
B93: % of Revenue | F93: =+F94/F92 -> 0.093645213 | G93: =+G94/G92 -> 0.10485094 | H93: =+H94/H92 -> 0.11751273 | I93: =+I94/I92 -> 0.10457439 | J93: =+J94/J92 -> 0.10113178 | K93: =+COGS_Assumptions!K18 -> 0.10013178 | L93: =+COGS_Assumptions!L18 -> 0.099131775 | M93: =+COGS_Assumptions!M18 -> 0.098131775 | AA93: =+AA94/AA92 -> 0.090416163 | AB93: =+AB94/AB92 -> 0.089411423 | AC93: =+AC94/AC92 -> 0.092201191 | AD93: =+AD94/AD92 -> 0.091020876 | AE93: =+AE94/AE92 -> 0.11740532 | AF93: =+AF94/AF92 -> 0.1155127 | AG93: =+AG94/AG92 -> 0.1047718 | AH93: =+AH94/AH92 -> 0.069074185 | ... CH93: =+CH94/CH92 -> 0.095158313 | CI93: =+SUMIFS($F93:$M93,$F$7:$M$7,CI$7) -> 0.10013178 | CJ93: =+SUMIFS($F93:$M93,$F$7:$M$7,CJ$7) -> 0.10013178 | CK93: =+SUMIFS($F93:$M93,$F$7:$M$7,CK$7) -> 0.10013178 | CL93: =+SUMIFS($F93:$M93,$F$7:$M$7,CL$7) -> 0.10013178 | CM93: =+SUMIFS($F93:$M93,$F$7:$M$7,CM$7) -> 0.10013178 | CN93: =+SUMIFS($F93:$M93,$F$7:$M$7,CN$7) -> 0.10013178 | CO93: =+SUMIFS($F93:$M93,$F$7:$M$7,CO$7) -> 0.10013178 | CP93: =+SUMIFS($F93:$M93,$F$7:$M$7,CP$7) -> 0.10013178 | ... DR93: =+SUMIFS($F93:$M93,$F$7:$M$7,DR$7) -> 0.098131775
B94: Total | F94: =+SUMIFS($AA94:$DR94,$AA$7:$DR$7,F$7) -> 1108.0326 | G94: =+SUMIFS($AA94:$DR94,$AA$7:$DR$7,G$7) -> 1346.634 | H94: =+SUMIFS($AA94:$DR94,$AA$7:$DR$7,H$7) -> 1653.1264 | I94: =+SUMIFS($AA94:$DR94,$AA$7:$DR$7,I$7) -> 1587.9762 | J94: =+SUMIFS($AA94:$DR94,$AA$7:$DR$7,J$7) -> 1735.6155 | K94: =+K92*K93 -> 2047.9962 | L94: =+L92*L93 -> 2420.8568 | M94: =+M92*M93 -> 2886.0472 | AA94: 88.70992 | AB94: 87.72414 | AC94: 90.07706 | AD94: 88.95716 | AE94: 114.49684 | AF94: 111.20754 | AG94: 101.92651 | AH94: 76.08853 | AI94: 84.88898 | AJ94: 97.77277 | AK94: 90.02633 | AL94: 76.15685 | AM94: 91.7527 | AN94: 90.39665 | AO94: 97.35521 | AP94: 103.91077 | AQ94: 112.22462 | AR94: 123.16744 | AS94: 109.41586 | AT94: 109.96173 | AU94: 121.57349 | AV94: 128.09661 | AW94: 129.77107 | AX94: 129.00786 | AY94: 144.33116 | AZ94: 141.57008 | BA94: 170.55899 | BB94: 146.48361 | BC94: 125.10361 | BD94: 136.09896 | BE94: 135.17979 | BF94: 129.8899 | BG94: 132.2477 | BH94: 132.68108 | BI94: 127.71285 | BJ94: 131.26869 | BK94: 121.502 | BL94: 136.446 | BM94: 128.90282 | BN94: 129.50282 | BO94: 129.60282 | BP94: 130.20282 | BQ94: 134.30282 | BR94: 134.90282 | BS94: 135.00282 | BT94: 135.60282 | BU94: 135.70282 | BV94: 136.30282 | BW94: 144.63462 | BX94: 144.63462 | BY94: 144.63462 | BZ94: 144.63462 | CA94: 144.63462 | CB94: 144.63462 | CC94: 144.63462 | CD94: 144.63462 | CE94: 144.63462 | CF94: 144.63462 | CG94: 144.63462 | CH94: 144.63462 | CI94: =+CI92*CI93 -> 167.01799 | CJ94: =+CJ92*CJ93 -> 168.11718 | CK94: =+CK92*CK93 -> 168.59619 | CL94: =+CL92*CL93 -> 169.83214 | CM94: =+CM92*CM93 -> 169.5332 | CN94: =+CN92*CN93 -> 169.26569 | CO94: =+CO92*CO93 -> 169.02859 | CP94: =+CP92*CP93 -> 172.7196 | ... DR94: =+DR92*DR93 -> 253.49621
B96: Service Costs
B97: Revenue | F97: =+SUMIFS($AA97:$DR97,$AA$7:$DR$7,F$7) -> 11832.24 | G97: =+SUMIFS($AA97:$DR97,$AA$7:$DR$7,G$7) -> 12843.318 | H97: =+SUMIFS($AA97:$DR97,$AA$7:$DR$7,H$7) -> 14067.637 | I97: =+SUMIFS($AA97:$DR97,$AA$7:$DR$7,I$7) -> 15185.135 | J97: =+SUMIFS($AA97:$DR97,$AA$7:$DR$7,J$7) -> 17161.92 | K97: =+SUMIFS($AA97:$DR97,$AA$7:$DR$7,K$7) -> 20453.01 | L97: =+SUMIFS($AA97:$DR97,$AA$7:$DR$7,L$7) -> 24420.594 | M97: =+SUMIFS($AA97:$DR97,$AA$7:$DR$7,M$7) -> 29409.916 | AA97: =+Revenue_Calcs!AA122 -> 981.129 | AB97: =+Revenue_Calcs!AB122 -> 981.129 | AC97: =+Revenue_Calcs!AC122 -> 976.962 | AD97: =+Revenue_Calcs!AD122 -> 977.327 | AE97: =+Revenue_Calcs!AE122 -> 975.227 | AF97: =+Revenue_Calcs!AF122 -> 962.73 | AG97: =+Revenue_Calcs!AG122 -> 972.843 | AH97: =+Revenue_Calcs!AH122 -> 1101.548 | ... DR97: =+Revenue_Calcs!DR122 -> 2583.2225
B98: % of Revenue | F98: =+F99/F97 -> 0.024851011 | G98: =+G99/G97 -> 0.026495934 | H98: =+H99/H97 -> 0.022370363 | I98: =+I99/I97 -> 0.023326448 | J98: =+J99/J97 -> 0.022375118 | K98: =+COGS_Assumptions!K19 -> 0.021375118 | L98: =+COGS_Assumptions!L19 -> 0.020375118 | M98: =+COGS_Assumptions!M19 -> 0.019375118 | AA98: =+AA99/AA97 -> 0.024398025 | AB98: =+AB99/AB97 -> 0.02505642 | AC98: =+AC99/AC97 -> 0.022443278 | AD98: =+AD99/AD97 -> 0.023733755 | AE98: =+AE99/AE97 -> 0.024217664 | AF98: =+AF99/AF97 -> 0.024621244 | AG98: =+AG99/AG97 -> 0.02550023 | AH98: =+AH99/AH97 -> 0.02344714 | ... CH98: =+CH99/CH97 -> 0.021053507 | CI98: =+SUMIFS($F98:$M98,$F$7:$M$7,CI$7) -> 0.021375118 | CJ98: =+SUMIFS($F98:$M98,$F$7:$M$7,CJ$7) -> 0.021375118 | CK98: =+SUMIFS($F98:$M98,$F$7:$M$7,CK$7) -> 0.021375118 | CL98: =+SUMIFS($F98:$M98,$F$7:$M$7,CL$7) -> 0.021375118 | CM98: =+SUMIFS($F98:$M98,$F$7:$M$7,CM$7) -> 0.021375118 | CN98: =+SUMIFS($F98:$M98,$F$7:$M$7,CN$7) -> 0.021375118 | CO98: =+SUMIFS($F98:$M98,$F$7:$M$7,CO$7) -> 0.021375118 | CP98: =+SUMIFS($F98:$M98,$F$7:$M$7,CP$7) -> 0.021375118 | ... DR98: =+SUMIFS($F98:$M98,$F$7:$M$7,DR$7) -> 0.019375118
B99: Total | F99: =+SUMIFS($AA99:$DR99,$AA$7:$DR$7,F$7) -> 294.04313 | G99: =+SUMIFS($AA99:$DR99,$AA$7:$DR$7,G$7) -> 340.29571 | H99: =+SUMIFS($AA99:$DR99,$AA$7:$DR$7,H$7) -> 314.69813 | I99: =+SUMIFS($AA99:$DR99,$AA$7:$DR$7,I$7) -> 354.21527 | J99: =+SUMIFS($AA99:$DR99,$AA$7:$DR$7,J$7) -> 384 | K99: =+K97*K98 -> 437.18551 | L99: =+L97*L98 -> 497.57248 | M99: =+M97*M98 -> 569.8206 | AA99: 23.93761 | AB99: 24.58358 | AC99: 21.92623 | AD99: 23.19564 | AE99: 23.61772 | AF99: 23.70361 | AG99: 24.80772 | AH99: 25.82815 | AI99: 23.9233 | AJ99: 25.97929 | AK99: 24.67334 | AL99: 27.86694 | AM99: 25.68089 | AN99: 20.18636 | AO99: 24.32559 | AP99: 22.75321 | AQ99: 45.13158 | AR99: 28.1452 | AS99: 28.88154 | AT99: 30.13597 | AU99: 27.38623 | AV99: 27.86027 | AW99: 30.01027 | AX99: 29.7986 | AY99: 31.60522 | AZ99: 28.26161 | BA99: 25.51025 | BB99: 27.86866 | BC99: 29.06649 | BD99: 28.86649 | BE99: 24.19523 | BF99: 23.18666 | BG99: 23.22283 | BH99: 23.11997 | BI99: 24.46994 | BJ99: 25.32478 | BK99: 25.944 | BL99: 25.482 | BM99: 26.405593 | BN99: 26.605593 | BO99: 30.97226 | BP99: 31.17226 | BQ99: 31.17226 | BR99: 31.17226 | BS99: 31.17226 | BT99: 31.37226 | BU99: 31.37226 | BV99: 31.37226 | BW99: 32 | BX99: 32 | BY99: 32 | BZ99: 32 | CA99: 32 | CB99: 32 | CC99: 32 | CD99: 32 | CE99: 32 | CF99: 32 | CG99: 32 | CH99: 32 | CI99: =+CI97*CI98 -> 35.653311 | CJ99: =+CJ97*CJ98 -> 35.887955 | CK99: =+CK97*CK98 -> 35.990209 | CL99: =+CL97*CL98 -> 36.254048 | CM99: =+CM97*CM98 -> 36.190232 | CN99: =+CN97*CN98 -> 36.133126 | CO99: =+CO97*CO98 -> 36.082514 | CP99: =+CP97*CP98 -> 36.870433 | ... DR99: =+DR97*DR98 -> 50.050242
B101: Contractors
B102: Revenue | F102: =+SUMIFS($AA102:$DR102,$AA$7:$DR$7,F$7) -> 11832.24 | G102: =+SUMIFS($AA102:$DR102,$AA$7:$DR$7,G$7) -> 12843.318 | H102: =+SUMIFS($AA102:$DR102,$AA$7:$DR$7,H$7) -> 14067.637 | I102: =+SUMIFS($AA102:$DR102,$AA$7:$DR$7,I$7) -> 15185.135 | J102: =+SUMIFS($AA102:$DR102,$AA$7:$DR$7,J$7) -> 17161.92 | K102: =+SUMIFS($AA102:$DR102,$AA$7:$DR$7,K$7) -> 20453.01 | L102: =+SUMIFS($AA102:$DR102,$AA$7:$DR$7,L$7) -> 24420.594 | M102: =+SUMIFS($AA102:$DR102,$AA$7:$DR$7,M$7) -> 29409.916 | AA102: =+Revenue_Calcs!AA122 -> 981.129 | AB102: =+Revenue_Calcs!AB122 -> 981.129 | AC102: =+Revenue_Calcs!AC122 -> 976.962 | AD102: =+Revenue_Calcs!AD122 -> 977.327 | AE102: =+Revenue_Calcs!AE122 -> 975.227 | AF102: =+Revenue_Calcs!AF122 -> 962.73 | AG102: =+Revenue_Calcs!AG122 -> 972.843 | AH102: =+Revenue_Calcs!AH122 -> 1101.548 | ... DR102: =+Revenue_Calcs!DR122 -> 2583.2225
B103: % of Revenue | F103: =+F104/F102 -> 0.0043102574 | G103: =+G104/G102 -> 0.0052242902 | H103: =+H104/H102 -> 0 | I103: =+I104/I102 -> 0 | J103: =+J104/J102 -> 0 | K103: =+COGS_Assumptions!K20 -> 0 | L103: =+COGS_Assumptions!L20 -> 0 | M103: =+COGS_Assumptions!M20 -> 0 | AA103: =+AA104/AA102 -> 0 | AB103: =+AB104/AB102 -> 0 | AC103: =+AC104/AC102 -> 0 | AD103: =+AD104/AD102 -> 0 | AE103: =+AE104/AE102 -> 0.007177816 | AF103: =+AF104/AF102 -> 0.0072709898 | AG103: =+AG104/AG102 -> 0.014390811 | AH103: =+AH104/AH102 -> 0.0063546936 | ... BV103: =+BV104/BV102 -> 0 | BW103: =+SUMIFS($F103:$M103,$F$7:$M$7,BW$7) -> 0 | BX103: =+SUMIFS($F103:$M103,$F$7:$M$7,BX$7) -> 0 | BY103: =+SUMIFS($F103:$M103,$F$7:$M$7,BY$7) -> 0 | BZ103: =+SUMIFS($F103:$M103,$F$7:$M$7,BZ$7) -> 0 | CA103: =+SUMIFS($F103:$M103,$F$7:$M$7,CA$7) -> 0 | CB103: =+SUMIFS($F103:$M103,$F$7:$M$7,CB$7) -> 0 | CC103: =+SUMIFS($F103:$M103,$F$7:$M$7,CC$7) -> 0 | CD103: =+SUMIFS($F103:$M103,$F$7:$M$7,CD$7) -> 0 | ... DR103: =+SUMIFS($F103:$M103,$F$7:$M$7,DR$7) -> 0
B104: Total | F104: =+SUMIFS($AA104:$DR104,$AA$7:$DR$7,F$7) -> 51 | G104: =+SUMIFS($AA104:$DR104,$AA$7:$DR$7,G$7) -> 67.09722 | H104: =+SUMIFS($AA104:$DR104,$AA$7:$DR$7,H$7) -> 0 | I104: =+SUMIFS($AA104:$DR104,$AA$7:$DR$7,I$7) -> 0 | J104: =+SUMIFS($AA104:$DR104,$AA$7:$DR$7,J$7) -> 0 | K104: =+SUMIFS($AA104:$DR104,$AA$7:$DR$7,K$7) -> 0 | L104: =+SUMIFS($AA104:$DR104,$AA$7:$DR$7,L$7) -> 0 | M104: =+SUMIFS($AA104:$DR104,$AA$7:$DR$7,M$7) -> 0 | AA104: 0 | AB104: 0 | AC104: 0 | AD104: 0 | AE104: 7 | AF104: 7 | AG104: 14 | AH104: 7 | AI104: -14 | AJ104: 10 | AK104: 10 | AL104: 10 | AM104: 10 | AN104: 10 | AO104: 10 | AP104: 10 | AQ104: 10 | AR104: 10 | AS104: 7.09722 | AT104: 0 | AU104: 0 | AV104: 0 | AW104: 0 | AX104: 0 | AY104: 0 | AZ104: 0 | BA104: 0 | BB104: 0 | BC104: 0 | BD104: 0 | BE104: 0 | BF104: 0 | BG104: 0 | BH104: 0 | BI104: 0 | BJ104: 0 | BK104: 0 | BL104: 0 | BM104: 0 | BN104: 0 | BO104: 0 | BP104: 0 | BQ104: 0 | BR104: 0 | BS104: 0 | BT104: 0 | BU104: 0 | BV104: 0 | BW104: 0 | BX104: 0 | BY104: 0 | BZ104: 0 | CA104: 0 | CB104: 0 | CC104: 0 | CD104: 0 | CE104: 0 | CF104: 0 | CG104: 0 | CH104: 0 | CI104: =+CI102*CI103 -> 0 | CJ104: =+CJ102*CJ103 -> 0 | CK104: =+CK102*CK103 -> 0 | CL104: =+CL102*CL103 -> 0 | CM104: =+CM102*CM103 -> 0 | CN104: =+CN102*CN103 -> 0 | CO104: =+CO102*CO103 -> 0 | CP104: =+CP102*CP103 -> 0 | ... DR104: =+DR102*DR103 -> 0
B107: Total Licensing | F107: =+SUMIFS($AA107:$DR107,$AA$7:$DR$7,F$7) -> 2957.0218 | G107: =+SUMIFS($AA107:$DR107,$AA$7:$DR$7,G$7) -> 2950.9071 | H107: =+SUMIFS($AA107:$DR107,$AA$7:$DR$7,H$7) -> 3000.4284 | I107: =+SUMIFS($AA107:$DR107,$AA$7:$DR$7,I$7) -> 3192.8591 | J107: =+SUMIFS($AA107:$DR107,$AA$7:$DR$7,J$7) -> 3535.7516 | K107: =+SUMIFS($AA107:$DR107,$AA$7:$DR$7,K$7) -> 4132.0276 | L107: =+SUMIFS($AA107:$DR107,$AA$7:$DR$7,L$7) -> 4833.9642 | M107: =+SUMIFS($AA107:$DR107,$AA$7:$DR$7,M$7) -> 5698.8171 | AA107: =+SUM(AA74,AA94,AA99,AA104) -> 233.46053 | AB107: =+SUM(AB74,AB94,AB99,AB104) -> 232.83762 | AC107: =+SUM(AC74,AC94,AC99,AC104) -> 235.28969 | AD107: =+SUM(AD74,AD94,AD99,AD104) -> 255.17941 | AE107: =+SUM(AE74,AE94,AE99,AE104) -> 285.73643 | AF107: =+SUM(AF74,AF94,AF99,AF104) -> 277.21147 | AG107: =+SUM(AG74,AG94,AG99,AG104) -> 275.87071 | AH107: =+SUM(AH74,AH94,AH99,AH104) -> 246.06329 | ... DR107: =+SUM(DR74,DR94,DR99,DR104) -> 457.88989
B108: % Margin | F108: =+(1-F107/F67) -> 0.75008774 | G108: =+(1-G107/G67) -> 0.77023795 | H108: =+(1-H107/H67) -> 0.78671411 | I108: =+(1-I107/I67) -> 0.78945623 | J108: =+(1-J107/J67) -> 0.79397693 | K108: =+(1-K107/K67) -> 0.79797459 | L108: =+(1-L107/L67) -> 0.80205378 | M108: =+(1-M107/M67) -> 0.80622804
B110: Managed Services
B112: AACN | C112: Lower Middle Market | F112: =+SUMIFS($AA112:$DR112,$AA$7:$DR$7,F$7) -> 0 | G112: =+SUMIFS($AA112:$DR112,$AA$7:$DR$7,G$7) -> 3.7902264 | H112: =+SUMIFS($AA112:$DR112,$AA$7:$DR$7,H$7) -> 3.46764 | I112: =+SUMIFS($AA112:$DR112,$AA$7:$DR$7,I$7) -> 0 | J112: =+SUMIFS($AA112:$DR112,$AA$7:$DR$7,J$7) -> 0 | K112: =+SUMIFS($AA112:$DR112,$AA$7:$DR$7,K$7) -> 0 | L112: =+SUMIFS($AA112:$DR112,$AA$7:$DR$7,L$7) -> 0 | M112: =+SUMIFS($AA112:$DR112,$AA$7:$DR$7,M$7) -> 0 | AA112: 0 | AB112: 0 | AC112: 0 | AD112: 0 | AE112: 0 | AF112: 0 | AG112: 0 | AH112: 0 | AI112: 0 | AJ112: 0 | AK112: 0 | AL112: 0 | AM112: 0.012729062 | AN112: 0.095424124 | AO112: 0.1476754 | AP112: 0.018087962 | AQ112: 0.1458276 | AR112: 0.22633237 | AS112: 0.22877023 | AT112: 0.25712868 | AU112: 0.61317959 | AV112: 1.4581957 | AW112: 0.36993187 | AX112: 0.21694388 | AY112: 0.80696372 | AZ112: 0.34862536 | BA112: 0.22033331 | BB112: 0.31619262 | BC112: 0.21102277 | BD112: 0 | BE112: 0.7226352 | BF112: 0.54698455 | BG112: 0.18359029 | BH112: 0.085979898 | BI112: 0 | BJ112: 0.025312296
B113: AACR | C113: Lower Middle Market | F113: =+SUMIFS($AA113:$DR113,$AA$7:$DR$7,F$7) -> 0 | G113: =+SUMIFS($AA113:$DR113,$AA$7:$DR$7,G$7) -> 0 | H113: =+SUMIFS($AA113:$DR113,$AA$7:$DR$7,H$7) -> 14.664097 | I113: =+SUMIFS($AA113:$DR113,$AA$7:$DR$7,I$7) -> 0 | J113: =+SUMIFS($AA113:$DR113,$AA$7:$DR$7,J$7) -> 0 | K113: =+SUMIFS($AA113:$DR113,$AA$7:$DR$7,K$7) -> 0 | L113: =+SUMIFS($AA113:$DR113,$AA$7:$DR$7,L$7) -> 0 | M113: =+SUMIFS($AA113:$DR113,$AA$7:$DR$7,M$7) -> 0 | AA113: 0 | AB113: 0 | AC113: 0 | AD113: 0 | AE113: 0 | AF113: 0 | AG113: 0 | AH113: 0 | AI113: 0 | AJ113: 0 | AK113: 0 | AL113: 0 | AM113: 0 | AN113: 0 | AO113: 0 | AP113: 0 | AQ113: 0 | AR113: 0 | AS113: 0 | AT113: 0 | AU113: 0 | AV113: 0 | AW113: 0 | AX113: 0 | AY113: 0 | AZ113: 0 | BA113: 0 | BB113: 0 | BC113: 0.21435827 | BD113: 2.7435031 | BE113: 1.319769 | BF113: 0.4274196 | BG113: 1.0284312 | BH113: 4.9506385 | BI113: 2.4571836 | BJ113: 1.522794
B114: AAI | C114: Lower Middle Market | F114: =+SUMIFS($AA114:$DR114,$AA$7:$DR$7,F$7) -> 0 | G114: =+SUMIFS($AA114:$DR114,$AA$7:$DR$7,G$7) -> 0 | H114: =+SUMIFS($AA114:$DR114,$AA$7:$DR$7,H$7) -> 0 | I114: =+SUMIFS($AA114:$DR114,$AA$7:$DR$7,I$7) -> 0 | J114: =+SUMIFS($AA114:$DR114,$AA$7:$DR$7,J$7) -> 0 | K114: =+SUMIFS($AA114:$DR114,$AA$7:$DR$7,K$7) -> 0 | L114: =+SUMIFS($AA114:$DR114,$AA$7:$DR$7,L$7) -> 0 | M114: =+SUMIFS($AA114:$DR114,$AA$7:$DR$7,M$7) -> 0 | AA114: 0 | AB114: 0 | AC114: 0 | AD114: 0 | AE114: 0 | AF114: 0 | AG114: 0 | AH114: 0 | AI114: 0 | AJ114: 0 | AK114: 0 | AL114: 0 | AM114: 0 | AN114: 0 | AO114: 0 | AP114: 0 | AQ114: 0 | AR114: 0 | AS114: 0 | AT114: 0 | AU114: 0 | AV114: 0 | AW114: 0 | AX114: 0 | AY114: 0 | AZ114: 0 | BA114: 0 | BB114: 0 | BC114: 0 | BD114: 0 | BE114: 0 | BF114: 0 | BG114: 0 | BH114: 0 | BI114: 0 | BJ114: 0
B115: AAOS | C115: Upper Middle Market | F115: =+SUMIFS($AA115:$DR115,$AA$7:$DR$7,F$7) -> 0 | G115: =+SUMIFS($AA115:$DR115,$AA$7:$DR$7,G$7) -> 16.759343 | H115: =+SUMIFS($AA115:$DR115,$AA$7:$DR$7,H$7) -> 98.557195 | I115: =+SUMIFS($AA115:$DR115,$AA$7:$DR$7,I$7) -> 0 | J115: =+SUMIFS($AA115:$DR115,$AA$7:$DR$7,J$7) -> 0 | K115: =+SUMIFS($AA115:$DR115,$AA$7:$DR$7,K$7) -> 0 | L115: =+SUMIFS($AA115:$DR115,$AA$7:$DR$7,L$7) -> 0 | M115: =+SUMIFS($AA115:$DR115,$AA$7:$DR$7,M$7) -> 0 | AA115: 0 | AB115: 0 | AC115: 0 | AD115: 0 | AE115: 0 | AF115: 0 | AG115: 0 | AH115: 0 | AI115: 0 | AJ115: 0 | AK115: 0 | AL115: 0 | AM115: 0 | AN115: 0 | AO115: 0 | AP115: 0 | AQ115: 0 | AR115: 1.7020765 | AS115: 2.2836896 | AT115: 0.20820407 | AU115: 2.8449667 | AV115: 2.3278208 | AW115: 4.1185862 | AX115: 3.2739992 | AY115: 4.7828582 | AZ115: 8.6895405 | BA115: 17.990669 | BB115: 21.826223 | BC115: 19.295887 | BD115: 5.0936977 | BE115: 5.2568358 | BF115: 2.7182292 | BG115: 4.1056527 | BH115: 6.5089055 | BI115: 1.5068321 | BJ115: 0.78186344
B116: AAP | C116: Major | F116: =+SUMIFS($AA116:$DR116,$AA$7:$DR$7,F$7) -> 67.777487 | G116: =+SUMIFS($AA116:$DR116,$AA$7:$DR$7,G$7) -> 33.443125 | H116: =+SUMIFS($AA116:$DR116,$AA$7:$DR$7,H$7) -> 132.04805 | I116: =+SUMIFS($AA116:$DR116,$AA$7:$DR$7,I$7) -> 0 | J116: =+SUMIFS($AA116:$DR116,$AA$7:$DR$7,J$7) -> 0 | K116: =+SUMIFS($AA116:$DR116,$AA$7:$DR$7,K$7) -> 0 | L116: =+SUMIFS($AA116:$DR116,$AA$7:$DR$7,L$7) -> 0 | M116: =+SUMIFS($AA116:$DR116,$AA$7:$DR$7,M$7) -> 0 | AA116: 1.1918211 | AB116: 0.83510719 | AC116: 1.8023812 | AD116: 2.7463138 | AE116: 2.3189027 | AF116: 8.9771312 | AG116: 16.15963 | AH116: 16.317084 | AI116: 7.4706613 | AJ116: 4.3434424 | AK116: 2.5155419 | AL116: 3.0994706 | AM116: 4.3071865 | AN116: 5.2836062 | AO116: 4.9287659 | AP116: 4.7642042 | AQ116: 5.0457579 | AR116: 2.014378 | AS116: 2.5076862 | AT116: 1.1682456 | AU116: 1.164192 | AV116: 1.9975453 | AW116: 0.24925302 | AX116: 0.012303971 | AY116: 0 | AZ116: 1.686913 | BA116: 2.0995871 | BB116: 6.1174083 | BC116: 8.4891212 | BD116: 9.6825424 | BE116: 27.816174 | BF116: 18.496495 | BG116: 27.004726 | BH116: 19.876831 | BI116: 8.8438454 | BJ116: 1.9344083
B117: ADA | C117: Lower Middle Market | F117: =+SUMIFS($AA117:$DR117,$AA$7:$DR$7,F$7) -> 0 | G117: =+SUMIFS($AA117:$DR117,$AA$7:$DR$7,G$7) -> 0 | H117: =+SUMIFS($AA117:$DR117,$AA$7:$DR$7,H$7) -> 8.9192226 | I117: =+SUMIFS($AA117:$DR117,$AA$7:$DR$7,I$7) -> 0 | J117: =+SUMIFS($AA117:$DR117,$AA$7:$DR$7,J$7) -> 0 | K117: =+SUMIFS($AA117:$DR117,$AA$7:$DR$7,K$7) -> 0 | L117: =+SUMIFS($AA117:$DR117,$AA$7:$DR$7,L$7) -> 0 | M117: =+SUMIFS($AA117:$DR117,$AA$7:$DR$7,M$7) -> 0 | AA117: 0 | AB117: 0 | AC117: 0 | AD117: 0 | AE117: 0 | AF117: 0 | AG117: 0 | AH117: 0 | AI117: 0 | AJ117: 0 | AK117: 0 | AL117: 0 | AM117: 0 | AN117: 0 | AO117: 0 | AP117: 0 | AQ117: 0 | AR117: 0 | AS117: 0 | AT117: 0 | AU117: 0 | AV117: 0 | AW117: 0 | AX117: 0 | AY117: 0 | AZ117: 0 | BA117: 0 | BB117: 0 | BC117: 0 | BD117: 0 | BE117: 0.12747527 | BF117: 1.789368 | BG117: 3.2221716 | BH117: 1.5673334 | BI117: 1.9148897 | BJ117: 0.29798457
B118: AHRQ | C118: Lower Middle Market | F118: =+SUMIFS($AA118:$DR118,$AA$7:$DR$7,F$7) -> 0 | G118: =+SUMIFS($AA118:$DR118,$AA$7:$DR$7,G$7) -> 0 | H118: =+SUMIFS($AA118:$DR118,$AA$7:$DR$7,H$7) -> 0 | I118: =+SUMIFS($AA118:$DR118,$AA$7:$DR$7,I$7) -> 0 | J118: =+SUMIFS($AA118:$DR118,$AA$7:$DR$7,J$7) -> 0 | K118: =+SUMIFS($AA118:$DR118,$AA$7:$DR$7,K$7) -> 0 | L118: =+SUMIFS($AA118:$DR118,$AA$7:$DR$7,L$7) -> 0 | M118: =+SUMIFS($AA118:$DR118,$AA$7:$DR$7,M$7) -> 0 | AA118: 0 | AB118: 0 | AC118: 0 | AD118: 0 | AE118: 0 | AF118: 0 | AG118: 0 | AH118: 0 | AI118: 0 | AJ118: 0 | AK118: 0 | AL118: 0 | AM118: 0 | AN118: 0 | AO118: 0 | AP118: 0 | AQ118: 0 | AR118: 0 | AS118: 0 | AT118: 0 | AU118: 0 | AV118: 0 | AW118: 0 | AX118: 0 | AY118: 0 | AZ118: 0 | BA118: 0 | BB118: 0 | BC118: 0 | BD118: 0 | BE118: 0 | BF118: 0 | BG118: 0 | BH118: 0 | BI118: 0 | BJ118: 0
B119: AIPP | C119: Major | F119: =+SUMIFS($AA119:$DR119,$AA$7:$DR$7,F$7) -> 0 | G119: =+SUMIFS($AA119:$DR119,$AA$7:$DR$7,G$7) -> 0 | H119: =+SUMIFS($AA119:$DR119,$AA$7:$DR$7,H$7) -> 0 | I119: =+SUMIFS($AA119:$DR119,$AA$7:$DR$7,I$7) -> 0 | J119: =+SUMIFS($AA119:$DR119,$AA$7:$DR$7,J$7) -> 0 | K119: =+SUMIFS($AA119:$DR119,$AA$7:$DR$7,K$7) -> 0 | L119: =+SUMIFS($AA119:$DR119,$AA$7:$DR$7,L$7) -> 0 | M119: =+SUMIFS($AA119:$DR119,$AA$7:$DR$7,M$7) -> 0 | AA119: 0 | AB119: 0 | AC119: 0 | AD119: 0 | AE119: 0 | AF119: 0 | AG119: 0 | AH119: 0 | AI119: 0 | AJ119: 0 | AK119: 0 | AL119: 0 | AM119: 0 | AN119: 0 | AO119: 0 | AP119: 0 | AQ119: 0 | AR119: 0 | AS119: 0 | AT119: 0 | AU119: 0 | AV119: 0 | AW119: 0 | AX119: 0 | AY119: 0 | AZ119: 0 | BA119: 0 | BB119: 0 | BC119: 0 | BD119: 0 | BE119: 0 | BF119: 0 | BG119: 0 | BH119: 0 | BI119: 0 | BJ119: 0
B120: ALLEN | C120: Upper Middle Market | F120: =+SUMIFS($AA120:$DR120,$AA$7:$DR$7,F$7) -> 0 | G120: =+SUMIFS($AA120:$DR120,$AA$7:$DR$7,G$7) -> 11.310523 | H120: =+SUMIFS($AA120:$DR120,$AA$7:$DR$7,H$7) -> 23.277895 | I120: =+SUMIFS($AA120:$DR120,$AA$7:$DR$7,I$7) -> 0 | J120: =+SUMIFS($AA120:$DR120,$AA$7:$DR$7,J$7) -> 0 | K120: =+SUMIFS($AA120:$DR120,$AA$7:$DR$7,K$7) -> 0 | L120: =+SUMIFS($AA120:$DR120,$AA$7:$DR$7,L$7) -> 0 | M120: =+SUMIFS($AA120:$DR120,$AA$7:$DR$7,M$7) -> 0 | AA120: 0 | AB120: 0 | AC120: 0 | AD120: 0 | AE120: 0 | AF120: 0 | AG120: 0 | AH120: 0 | AI120: 0 | AJ120: 0 | AK120: 0 | AL120: 0 | AM120: 0 | AN120: 0 | AO120: 0 | AP120: 0 | AQ120: 0.071556116 | AR120: 1.2392102 | AS120: 2.1017242 | AT120: 5.2720974 | AU120: 1.0006851 | AV120: 1.0229593 | AW120: 0.21907054 | AX120: 0.38322045 | AY120: 0.3067692 | AZ120: 3.7381287 | BA120: 3.42294 | BB120: 1.4068406 | BC120: 0.68920293 | BD120: 3.6546109 | BE120: 3.0856868 | BF120: 1.4939537 | BG120: 2.5653028 | BH120: 1.2392553 | BI120: 1.4867843 | BJ120: 0.1884191
B121: AMA | C121: Mega | F121: =+SUMIFS($AA121:$DR121,$AA$7:$DR$7,F$7) -> 648.74574 | G121: =+SUMIFS($AA121:$DR121,$AA$7:$DR$7,G$7) -> 572.76527 | H121: =+SUMIFS($AA121:$DR121,$AA$7:$DR$7,H$7) -> 518.32853 | I121: =+SUMIFS($AA121:$DR121,$AA$7:$DR$7,I$7) -> 0 | J121: =+SUMIFS($AA121:$DR121,$AA$7:$DR$7,J$7) -> 0 | K121: =+SUMIFS($AA121:$DR121,$AA$7:$DR$7,K$7) -> 0 | L121: =+SUMIFS($AA121:$DR121,$AA$7:$DR$7,L$7) -> 0 | M121: =+SUMIFS($AA121:$DR121,$AA$7:$DR$7,M$7) -> 0 | AA121: 50.413887 | AB121: 47.177468 | AC121: 62.374997 | AD121: 41.45573 | AE121: 43.898594 | AF121: 55.959199 | AG121: 43.845768 | AH121: 65.349334 | AI121: 72.341042 | AJ121: 66.717865 | AK121: 56.129503 | AL121: 43.08235 | AM121: 54.042708 | AN121: 34.884647 | AO121: 45.706344 | AP121: 34.153453 | AQ121: 34.963656 | AR121: 44.6746 | AS121: 56.129025 | AT121: 60.112826 | AU121: 64.622768 | AV121: 53.547327 | AW121: 40.429141 | AX121: 49.498776 | AY121: 43.646784 | AZ121: 44.090911 | BA121: 48.780135 | BB121: 54.620231 | BC121: 43.158431 | BD121: 50.78702 | BE121: 45.224269 | BF121: 43.653205 | BG121: 41.779949 | BH121: 41.074099 | BI121: 30.811059 | BJ121: 30.702432
B122: AORN | C122: Lower Middle Market | F122: =+SUMIFS($AA122:$DR122,$AA$7:$DR$7,F$7) -> 16.91346 | G122: =+SUMIFS($AA122:$DR122,$AA$7:$DR$7,G$7) -> 31.819694 | H122: =+SUMIFS($AA122:$DR122,$AA$7:$DR$7,H$7) -> 30.395849 | I122: =+SUMIFS($AA122:$DR122,$AA$7:$DR$7,I$7) -> 0 | J122: =+SUMIFS($AA122:$DR122,$AA$7:$DR$7,J$7) -> 0 | K122: =+SUMIFS($AA122:$DR122,$AA$7:$DR$7,K$7) -> 0 | L122: =+SUMIFS($AA122:$DR122,$AA$7:$DR$7,L$7) -> 0 | M122: =+SUMIFS($AA122:$DR122,$AA$7:$DR$7,M$7) -> 0 | AA122: 2.4210339 | AB122: 1.4392522 | AC122: 0.60997633 | AD122: 0.11071072 | AE122: 0.16808072 | AF122: 0.52745568 | AG122: 0.28261958 | AH122: 0.17026398 | AI122: 1.8193048 | AJ122: 2.6339544 | AK122: 6.1033894 | AL122: 0.62741847 | AM122: 1.3404918 | AN122: 4.330792 | AO122: 5.4941127 | AP122: 6.2403484 | AQ122: 5.5780854 | AR122: 5.0201914 | AS122: 0.24327434 | AT122: 0.21374167 | AU122: 0.13796338 | AV122: 0.79970261 | AW122: 1.3497291 | AX122: 1.0712614 | AY122: 1.4282088 | AZ122: 2.2554134 | BA122: 4.9828545 | BB122: 7.6199812 | BC122: 3.1591084 | BD122: 2.154971 | BE122: 1.7072004 | BF122: 1.4455836 | BG122: 1.5084768 | BH122: 0.77033903 | BI122: 1.407736 | BJ122: 1.9559754
B123: AOTA | C123: Lower Middle Market | F123: =+SUMIFS($AA123:$DR123,$AA$7:$DR$7,F$7) -> 13.896273 | G123: =+SUMIFS($AA123:$DR123,$AA$7:$DR$7,G$7) -> 4.0654565 | H123: =+SUMIFS($AA123:$DR123,$AA$7:$DR$7,H$7) -> 0.61009668 | I123: =+SUMIFS($AA123:$DR123,$AA$7:$DR$7,I$7) -> 0 | J123: =+SUMIFS($AA123:$DR123,$AA$7:$DR$7,J$7) -> 0 | K123: =+SUMIFS($AA123:$DR123,$AA$7:$DR$7,K$7) -> 0 | L123: =+SUMIFS($AA123:$DR123,$AA$7:$DR$7,L$7) -> 0 | M123: =+SUMIFS($AA123:$DR123,$AA$7:$DR$7,M$7) -> 0 | AA123: 0 | AB123: 0 | AC123: 0 | AD123: 0.18696047 | AE123: 0.1772888 | AF123: 0.070552713 | AG123: 0.46448089 | AH123: 1.2376262 | AI123: 2.4234727 | AJ123: 6.5008102 | AK123: 1.8925028 | AL123: 0.94257788 | AM123: 0.1375255 | AN123: 1.2815212 | AO123: 2.4718678 | AP123: 0.029888199 | AQ123: 0 | AR123: 0 | AS123: 0 | AT123: 0.14465385 | AU123: 0 | AV123: 0 | AW123: 0 | AX123: 0 | AY123: 0 | AZ123: 0.12464796 | BA123: 0.061779385 | BB123: 0.18887373 | BC123: 0.22245724 | BD123: 0 | BE123: 0 | BF123: 0 | BG123: 0.012338365 | BH123: 0 | BI123: 0 | BJ123: 0
... B157: EL | C157: Lower Middle Market | F157: =+SUMIFS($AA157:$DR157,$AA$7:$DR$7,F$7) -> 0 | G157: =+SUMIFS($AA157:$DR157,$AA$7:$DR$7,G$7) -> 0 | H157: =+SUMIFS($AA157:$DR157,$AA$7:$DR$7,H$7) -> 0 | I157: =+SUMIFS($AA157:$DR157,$AA$7:$DR$7,I$7) -> 0 | J157: =+SUMIFS($AA157:$DR157,$AA$7:$DR$7,J$7) -> 0 | K157: =+SUMIFS($AA157:$DR157,$AA$7:$DR$7,K$7) -> 0 | L157: =+SUMIFS($AA157:$DR157,$AA$7:$DR$7,L$7) -> 0 | M157: =+SUMIFS($AA157:$DR157,$AA$7:$DR$7,M$7) -> 0 | AA157: 0 | AB157: 0 | AC157: 0 | AD157: 0 | AE157: 0 | AF157: 0 | AG157: 0 | AH157: 0 | AI157: 0 | AJ157: 0 | AK157: 0 | AL157: 0 | AM157: 0 | AN157: 0 | AO157: 0 | AP157: 0 | AQ157: 0 | AR157: 0 | AS157: 0 | AT157: 0 | AU157: 0 | AV157: 0 | AW157: 0 | AX157: 0 | AY157: 0 | AZ157: 0 | BA157: 0 | BB157: 0 | BC157: 0 | BD157: 0 | BE157: 0 | BF157: 0 | BG157: 0 | BH157: 0 | BI157: 0 | BJ157: 0
B159: Total | F159: =+SUMIFS($AA159:$DR159,$AA$7:$DR$7,F$7) -> 1948.5264 | G159: =+SUMIFS($AA159:$DR159,$AA$7:$DR$7,G$7) -> 1950.8452 | H159: =+SUMIFS($AA159:$DR159,$AA$7:$DR$7,H$7) -> 2291.4315 | I159: =+SUMIFS($AA159:$DR159,$AA$7:$DR$7,I$7) -> 0 | J159: =+SUMIFS($AA159:$DR159,$AA$7:$DR$7,J$7) -> 0 | K159: =+SUMIFS($AA159:$DR159,$AA$7:$DR$7,K$7) -> 0 | L159: =+SUMIFS($AA159:$DR159,$AA$7:$DR$7,L$7) -> 0 | M159: =+SUMIFS($AA159:$DR159,$AA$7:$DR$7,M$7) -> 0 | AA159: =SUM(AA112:AA158) -> 156.13697 | AB159: =SUM(AB112:AB158) -> 155.95094 | AC159: =SUM(AC112:AC158) -> 157.27138 | AD159: =SUM(AD112:AD158) -> 116.09428 | AE159: =SUM(AE112:AE158) -> 145.76297 | AF159: =SUM(AF112:AF158) -> 181.74769 | AG159: =SUM(AG112:AG158) -> 150.73666 | AH159: =SUM(AH112:AH158) -> 196.19922 | ... DR159: =SUM(DR112:DR158) -> 0
B161: Revenue
B162: Mega | F162: =+Revenue_Calcs!F192 -> 5771.188 | G162: =+Revenue_Calcs!G192 -> 4972.649 | H162: =+Revenue_Calcs!H192 -> 5881.46 | I162: =+Revenue_Calcs!I192 -> 6810.12 | J162: =+Revenue_Calcs!J192 -> 7205.6172 | K162: =+Revenue_Calcs!K192 -> 8273.762 | L162: =+Revenue_Calcs!L192 -> 9434.2467 | M162: =+Revenue_Calcs!M192 -> 10693.829
B163: Major | F163: =+Revenue_Calcs!F197 -> 613.39 | G163: =+Revenue_Calcs!G197 -> 511.382 | H163: =+Revenue_Calcs!H197 -> 754.264 | I163: =+Revenue_Calcs!I197 -> 625.984 | J163: =+Revenue_Calcs!J197 -> 1118.8299 | K163: =+Revenue_Calcs!K197 -> 1321.4186 | L163: =+Revenue_Calcs!L197 -> 1535.1174 | M163: =+Revenue_Calcs!M197 -> 1760.109
B164: Upper Middle Market | F164: =+Revenue_Calcs!F202 -> 140.926 | G164: =+Revenue_Calcs!G202 -> 440.998 | H164: =+Revenue_Calcs!H202 -> 945.901 | I164: =+Revenue_Calcs!I202 -> 804.70588 | J164: =+Revenue_Calcs!J202 -> 1162.646 | K164: =+Revenue_Calcs!K202 -> 1450.1605 | L164: =+Revenue_Calcs!L202 -> 1832.7959 | M164: =+Revenue_Calcs!M202 -> 2378.6969
B165: Lower Middle Market | F165: =+Revenue_Calcs!F207 -> 209.259 | G165: =+Revenue_Calcs!G207 -> 191.321 | H165: =+Revenue_Calcs!H207 -> 334.085 | I165: =+Revenue_Calcs!I207 -> 416 | J165: =+Revenue_Calcs!J207 -> 708.8057 | K165: =+Revenue_Calcs!K207 -> 857.83205 | L165: =+Revenue_Calcs!L207 -> 1059.4333 | M165: =+Revenue_Calcs!M207 -> 1343.5719
B166: Total | F166: =SUM(F162:F165) -> 6734.763 | G166: =SUM(G162:G165) -> 6116.35 | H166: =SUM(H162:H165) -> 7915.71 | I166: =SUM(I162:I165) -> 8656.8099 | J166: =SUM(J162:J165) -> 10195.899 | K166: =SUM(K162:K165) -> 11903.173 | L166: =SUM(L162:L165) -> 13861.593 | M166: =SUM(M162:M165) -> 16176.207
B168: Cost of Sales
B169: Mega | F169: =+SUMIFS($AA169:$DR169,$AA$7:$DR$7,F$7) -> 1586.5397 | G169: =+SUMIFS($AA169:$DR169,$AA$7:$DR$7,G$7) -> 1493.7647 | H169: =+SUMIFS($AA169:$DR169,$AA$7:$DR$7,H$7) -> 1631.7376 | I169: =+I162*(1-COGS_Assumptions!I24) -> 2111.1372 | J169: =+J162*(1-COGS_Assumptions!J24) -> 2233.7413 | K169: =+K162*(1-COGS_Assumptions!K24) -> 2540.0449 | L169: =+L162*(1-COGS_Assumptions!L24) -> 2868.011 | M169: =+M162*(1-COGS_Assumptions!M24) -> 3218.8426 | AA169: =+SUMIFS(AA$112:AA$157,$C$13:$C$58,$B169) -> 140.84078 | AB169: =+SUMIFS(AB$112:AB$157,$C$13:$C$58,$B169) -> 135.81265 | AC169: =+SUMIFS(AC$112:AC$157,$C$13:$C$58,$B169) -> 132.01117 | AD169: =+SUMIFS(AD$112:AD$157,$C$13:$C$58,$B169) -> 93.763044 | AE169: =+SUMIFS(AE$112:AE$157,$C$13:$C$58,$B169) -> 125.92427 | AF169: =+SUMIFS(AF$112:AF$157,$C$13:$C$58,$B169) -> 149.72957 | AG169: =+SUMIFS(AG$112:AG$157,$C$13:$C$58,$B169) -> 105.79507 | AH169: =+SUMIFS(AH$112:AH$157,$C$13:$C$58,$B169) -> 154.03749 | ... BJ169: =+SUMIFS(BJ$112:BJ$157,$C$13:$C$58,$B169) -> 89.748845 | BK169: =+SUMIFS($F169:$M169,$F$7:$M$7,BK$7)*BK$175 -> 159.76615 | BL169: =+SUMIFS($F169:$M169,$F$7:$M$7,BL$7)*BL$175 -> 175.96542 | BM169: =+SUMIFS($F169:$M169,$F$7:$M$7,BM$7)*BM$175 -> 184.84988 | BN169: =+SUMIFS($F169:$M169,$F$7:$M$7,BN$7)*BN$175 -> 161.5141 | BO169: =+SUMIFS($F169:$M169,$F$7:$M$7,BO$7)*BO$175 -> 167.01883 | BP169: =+SUMIFS($F169:$M169,$F$7:$M$7,BP$7)*BP$175 -> 192.78971 | BQ169: =+SUMIFS($F169:$M169,$F$7:$M$7,BQ$7)*BQ$175 -> 193.96182 | BR169: =+SUMIFS($F169:$M169,$F$7:$M$7,BR$7)*BR$175 -> 204.9991 | ... DR169: =+SUMIFS($F169:$M169,$F$7:$M$7,DR$7)*DR$175 -> 184.93586
B170: Major | F170: =+SUMIFS($AA170:$DR170,$AA$7:$DR$7,F$7) -> 195.37124 | G170: =+SUMIFS($AA170:$DR170,$AA$7:$DR$7,G$7) -> 129.0751 | H170: =+SUMIFS($AA170:$DR170,$AA$7:$DR$7,H$7) -> 234.52192 | I170: =+I163*(1-COGS_Assumptions!I25) -> 194.05504 | J170: =+J163*(1-COGS_Assumptions!J25) -> 346.83728 | K170: =+K163*(1-COGS_Assumptions!K25) -> 405.67552 | L170: =+L163*(1-COGS_Assumptions!L25) -> 466.67568 | M170: =+M163*(1-COGS_Assumptions!M25) -> 529.79282 | AA170: =+SUMIFS(AA$112:AA$157,$C$13:$C$58,$B170) -> 3.9546351 | AB170: =+SUMIFS(AB$112:AB$157,$C$13:$C$58,$B170) -> 3.2050102 | AC170: =+SUMIFS(AC$112:AC$157,$C$13:$C$58,$B170) -> 11.96636 | AD170: =+SUMIFS(AD$112:AD$157,$C$13:$C$58,$B170) -> 11.020652 | AE170: =+SUMIFS(AE$112:AE$157,$C$13:$C$58,$B170) -> 7.7299989 | AF170: =+SUMIFS(AF$112:AF$157,$C$13:$C$58,$B170) -> 17.783864 | AG170: =+SUMIFS(AG$112:AG$157,$C$13:$C$58,$B170) -> 31.623634 | AH170: =+SUMIFS(AH$112:AH$157,$C$13:$C$58,$B170) -> 30.061465 | ... BJ170: =+SUMIFS(BJ$112:BJ$157,$C$13:$C$58,$B170) -> 6.0721571 | BK170: =+SUMIFS($F170:$M170,$F$7:$M$7,BK$7)*BK$175 -> 14.685652 | BL170: =+SUMIFS($F170:$M170,$F$7:$M$7,BL$7)*BL$175 -> 16.174684 | BM170: =+SUMIFS($F170:$M170,$F$7:$M$7,BM$7)*BM$175 -> 16.991341 | BN170: =+SUMIFS($F170:$M170,$F$7:$M$7,BN$7)*BN$175 -> 14.846323 | BO170: =+SUMIFS($F170:$M170,$F$7:$M$7,BO$7)*BO$175 -> 15.352316 | BP170: =+SUMIFS($F170:$M170,$F$7:$M$7,BP$7)*BP$175 -> 17.721167 | BQ170: =+SUMIFS($F170:$M170,$F$7:$M$7,BQ$7)*BQ$175 -> 17.828907 | BR170: =+SUMIFS($F170:$M170,$F$7:$M$7,BR$7)*BR$175 -> 18.84345 | ... DR170: =+SUMIFS($F170:$M170,$F$7:$M$7,DR$7)*DR$175 -> 30.438795
B171: Upper Middle Market | F171: =+SUMIFS($AA171:$DR171,$AA$7:$DR$7,F$7) -> 104.46324 | G171: =+SUMIFS($AA171:$DR171,$AA$7:$DR$7,G$7) -> 223.99287 | H171: =+SUMIFS($AA171:$DR171,$AA$7:$DR$7,H$7) -> 337.85995 | I171: =+I164*(1-COGS_Assumptions!I26) -> 281.64706 | J171: =+J164*(1-COGS_Assumptions!J26) -> 406.92609 | K171: =+K164*(1-COGS_Assumptions!K26) -> 503.2057 | L171: =+L164*(1-COGS_Assumptions!L26) -> 630.4818 | M171: =+M164*(1-COGS_Assumptions!M26) -> 811.13564 | AA171: =+SUMIFS(AA$112:AA$157,$C$13:$C$58,$B171) -> 2.7684286 | AB171: =+SUMIFS(AB$112:AB$157,$C$13:$C$58,$B171) -> 10.044384 | AC171: =+SUMIFS(AC$112:AC$157,$C$13:$C$58,$B171) -> 10.524109 | AD171: =+SUMIFS(AD$112:AD$157,$C$13:$C$58,$B171) -> 8.3537877 | AE171: =+SUMIFS(AE$112:AE$157,$C$13:$C$58,$B171) -> 9.553273 | AF171: =+SUMIFS(AF$112:AF$157,$C$13:$C$58,$B171) -> 11.435148 | AG171: =+SUMIFS(AG$112:AG$157,$C$13:$C$58,$B171) -> 9.6499469 | AH171: =+SUMIFS(AH$112:AH$157,$C$13:$C$58,$B171) -> 8.2725311 | ... BJ171: =+SUMIFS(BJ$112:BJ$157,$C$13:$C$58,$B171) -> 12.871549 | BK171: =+SUMIFS($F171:$M171,$F$7:$M$7,BK$7)*BK$75 -> 24.355634 | BL171: =+SUMIFS($F171:$M171,$F$7:$M$7,BL$7)*BL$75 -> 24.756648 | BM171: =+SUMIFS($F171:$M171,$F$7:$M$7,BM$7)*BM$75 -> 24.425995 | BN171: =+SUMIFS($F171:$M171,$F$7:$M$7,BN$7)*BN$75 -> 26.275642 | BO171: =+SUMIFS($F171:$M171,$F$7:$M$7,BO$7)*BO$75 -> 23.110841 | BP171: =+SUMIFS($F171:$M171,$F$7:$M$7,BP$7)*BP$75 -> 22.842601 | BQ171: =+SUMIFS($F171:$M171,$F$7:$M$7,BQ$7)*BQ$75 -> 23.180424 | BR171: =+SUMIFS($F171:$M171,$F$7:$M$7,BR$7)*BR$75 -> 24.745574 | ... DR171: =+SUMIFS($F171:$M171,$F$7:$M$7,DR$7)*DR$75 -> 55.816447
B172: Lower Middle Market | F172: =+SUMIFS($AA172:$DR172,$AA$7:$DR$7,F$7) -> 62.152265 | G172: =+SUMIFS($AA172:$DR172,$AA$7:$DR$7,G$7) -> 104.01256 | H172: =+SUMIFS($AA172:$DR172,$AA$7:$DR$7,H$7) -> 87.312056 | I172: =+I165*(1-COGS_Assumptions!I27) -> 104 | J172: =+J165*(1-COGS_Assumptions!J27) -> 177.20143 | K172: =+K165*(1-COGS_Assumptions!K27) -> 211.88452 | L172: =+L165*(1-COGS_Assumptions!L27) -> 258.50172 | M172: =+M165*(1-COGS_Assumptions!M27) -> 323.80083 | AA172: =+SUMIFS(AA$112:AA$157,$C$13:$C$58,$B172) -> 8.5731276 | AB172: =+SUMIFS(AB$112:AB$157,$C$13:$C$58,$B172) -> 6.8888931 | AC172: =+SUMIFS(AC$112:AC$157,$C$13:$C$58,$B172) -> 2.7697383 | AD172: =+SUMIFS(AD$112:AD$157,$C$13:$C$58,$B172) -> 2.956795 | AE172: =+SUMIFS(AE$112:AE$157,$C$13:$C$58,$B172) -> 2.5554247 | AF172: =+SUMIFS(AF$112:AF$157,$C$13:$C$58,$B172) -> 2.7991119 | AG172: =+SUMIFS(AG$112:AG$157,$C$13:$C$58,$B172) -> 3.6680008 | AH172: =+SUMIFS(AH$112:AH$157,$C$13:$C$58,$B172) -> 3.8277338 | ... BJ172: =+SUMIFS(BJ$112:BJ$157,$C$13:$C$58,$B172) -> 5.2782601 | BK172: =+SUMIFS($F172:$M172,$F$7:$M$7,BK$7)*BK$75 -> 8.9934755 | BL172: =+SUMIFS($F172:$M172,$F$7:$M$7,BL$7)*BL$75 -> 9.1415525 | BM172: =+SUMIFS($F172:$M172,$F$7:$M$7,BM$7)*BM$75 -> 9.0194567 | BN172: =+SUMIFS($F172:$M172,$F$7:$M$7,BN$7)*BN$75 -> 9.7024509 | BO172: =+SUMIFS($F172:$M172,$F$7:$M$7,BO$7)*BO$75 -> 8.5338276 | BP172: =+SUMIFS($F172:$M172,$F$7:$M$7,BP$7)*BP$75 -> 8.4347782 | BQ172: =+SUMIFS($F172:$M172,$F$7:$M$7,BQ$7)*BQ$75 -> 8.5595216 | BR172: =+SUMIFS($F172:$M172,$F$7:$M$7,BR$7)*BR$75 -> 9.1374636 | ... DR172: =+SUMIFS($F172:$M172,$F$7:$M$7,DR$7)*DR$75 -> 22.281615
B173: Total | F173: =+SUMIFS($AA173:$DR173,$AA$7:$DR$7,F$7) -> 1948.5264 | G173: =+SUMIFS($AA173:$DR173,$AA$7:$DR$7,G$7) -> 1950.8452 | H173: =+SUMIFS($AA173:$DR173,$AA$7:$DR$7,H$7) -> 2291.4315 | I173: =+SUMIFS($AA173:$DR173,$AA$7:$DR$7,I$7) -> 2690.8393 | J173: =+SUMIFS($AA173:$DR173,$AA$7:$DR$7,J$7) -> 3164.7061 | K173: =+SUMIFS($AA173:$DR173,$AA$7:$DR$7,K$7) -> 3660.8107 | L173: =+SUMIFS($AA173:$DR173,$AA$7:$DR$7,L$7) -> 4223.6702 | M173: =+SUMIFS($AA173:$DR173,$AA$7:$DR$7,M$7) -> 4883.5719 | AA173: =SUM(AA169:AA172) -> 156.13697 | AB173: =SUM(AB169:AB172) -> 155.95094 | AC173: =SUM(AC169:AC172) -> 157.27138 | AD173: =SUM(AD169:AD172) -> 116.09428 | AE173: =SUM(AE169:AE172) -> 145.76297 | AF173: =SUM(AF169:AF172) -> 181.74769 | AG173: =SUM(AG169:AG172) -> 150.73666 | AH173: =SUM(AH169:AH172) -> 196.19922 | ... DR173: =SUM(DR169:DR172) -> 293.47272
B175: % Seasonality | F175: =+F173/SUMIFS($AA173:$DR173,$AA$7:$DR$7,F$7) -> 1 | G175: =+G173/SUMIFS($AA173:$DR173,$AA$7:$DR$7,G$7) -> 1 | H175: =+H173/SUMIFS($AA173:$DR173,$AA$7:$DR$7,H$7) -> 1 | I175: =+I173/SUMIFS($AA173:$DR173,$AA$7:$DR$7,I$7) -> 1 | J175: =+J173/SUMIFS($AA173:$DR173,$AA$7:$DR$7,J$7) -> 1 | K175: =+K173/SUMIFS($AA173:$DR173,$AA$7:$DR$7,K$7) -> 1 | L175: =+L173/SUMIFS($AA173:$DR173,$AA$7:$DR$7,L$7) -> 1 | M175: =+M173/SUMIFS($AA173:$DR173,$AA$7:$DR$7,M$7) -> 1 | AA175: =+AA173/SUMIFS($AA173:$DR173,$AA$7:$DR$7,AA$7) -> 0.080130797 | AB175: =+AB173/SUMIFS($AA173:$DR173,$AA$7:$DR$7,AB$7) -> 0.080035323 | AC175: =+AC173/SUMIFS($AA173:$DR173,$AA$7:$DR$7,AC$7) -> 0.080712985 | AD175: =+AD173/SUMIFS($AA173:$DR173,$AA$7:$DR$7,AD$7) -> 0.059580552 | AE175: =+AE173/SUMIFS($AA173:$DR173,$AA$7:$DR$7,AE$7) -> 0.07480677 | AF175: =+AF173/SUMIFS($AA173:$DR173,$AA$7:$DR$7,AF$7) -> 0.093274433 | AG175: =+AG173/SUMIFS($AA173:$DR173,$AA$7:$DR$7,AG$7) -> 0.077359309 | AH175: =+AH173/SUMIFS($AA173:$DR173,$AA$7:$DR$7,AH$7) -> 0.10069107 | ... BJ175: =+BJ173/SUMIFS($AA173:$DR173,$AA$7:$DR$7,BJ$7) -> 0.049737822 | BK175: =+AVERAGE(AA175,AM175,AY175) -> 0.075677766 | BL175: =+AVERAGE(AB175,AN175,AZ175) -> 0.08335101 | BM175: =+AVERAGE(AC175,AO175,BA175) -> 0.087559388 | BN175: =+AVERAGE(AD175,AP175,BB175) -> 0.076505732 | BO175: =+AVERAGE(AE175,AQ175,BC175) -> 0.079113205 | BP175: =+AVERAGE(AF175,AR175,BD175) -> 0.091320313 | BQ175: =+AVERAGE(AG175,AS175,BE175) -> 0.091875514 | BR175: =+AVERAGE(AH175,AT175,BF175) -> 0.097103636 | ... DR175: =+AVERAGE(CH175,CT175,DF175) -> 0.057454148
B177: Gross Profit
B178: Mega | F178: =+F162-F169 -> 4184.6483 | G178: =+G162-G169 -> 3478.8843 | H178: =+H162-H169 -> 4249.7224 | I178: =+I162-I169 -> 4698.9828 | J178: =+J162-J169 -> 4971.8758 | K178: =+K162-K169 -> 5733.7171 | L178: =+L162-L169 -> 6566.2357 | M178: =+M162-M169 -> 7474.9867
B179: Major | F179: =+F163-F170 -> 418.01876 | G179: =+G163-G170 -> 382.3069 | H179: =+H163-H170 -> 519.74208 | I179: =+I163-I170 -> 431.92896 | J179: =+J163-J170 -> 771.99266 | K179: =+K163-K170 -> 915.74311 | L179: =+L163-L170 -> 1068.4417 | M179: =+M163-M170 -> 1230.3162
B180: Upper Middle Market | F180: =+F164-F171 -> 36.462765 | G180: =+G164-G171 -> 217.00513 | H180: =+H164-H171 -> 608.04105 | I180: =+I164-I171 -> 523.05882 | J180: =+J164-J171 -> 755.71989 | K180: =+K164-K171 -> 946.95483 | L180: =+L164-L171 -> 1202.3141 | M180: =+M164-M171 -> 1567.5613
B181: Lower Middle Market | F181: =+F165-F172 -> 147.10674 | G181: =+G165-G172 -> 87.308441 | H181: =+H165-H172 -> 246.77294 | I181: =+I165-I172 -> 312 | J181: =+J165-J172 -> 531.60428 | K181: =+K165-K172 -> 645.94753 | L181: =+L165-L172 -> 800.93155 | M181: =+M165-M172 -> 1019.7711
B182: Total | F182: =SUM(F178:F181) -> 4786.2366 | G182: =SUM(G178:G181) -> 4165.5048 | H182: =SUM(H178:H181) -> 5624.2785 | I182: =SUM(I178:I181) -> 5965.9706 | J182: =SUM(J178:J181) -> 7031.1927 | K182: =SUM(K178:K181) -> 8242.3626 | L182: =SUM(L178:L181) -> 9637.9231 | M182: =SUM(M178:M181) -> 11292.635
B184: Gross Margin
B185: Mega | F185: =+F178/F162 -> 0.72509306 | G185: =+G178/G162 -> 0.69960383 | H185: =+H178/H162 -> 0.7225625 | I185: =+I178/I162 -> 0.69 | J185: =+J178/J162 -> 0.69 | K185: =+K178/K162 -> 0.693 | L185: =+L178/L162 -> 0.696 | M185: =+M178/M162 -> 0.699
B186: Major | F186: =+F179/F163 -> 0.68148937 | G186: =+G179/G163 -> 0.74759554 | H186: =+H179/H163 -> 0.68907184 | I186: =+I179/I163 -> 0.69 | J186: =+J179/J163 -> 0.69 | K186: =+K179/K163 -> 0.693 | L186: =+L179/L163 -> 0.696 | M186: =+M179/M163 -> 0.699
B187: Upper Middle Market | F187: =+F180/F164 -> 0.25873696 | G187: =+G180/G164 -> 0.49207736 | H187: =+H180/H164 -> 0.6428168 | I187: =+I180/I164 -> 0.65 | J187: =+J180/J164 -> 0.65 | K187: =+K180/K164 -> 0.653 | L187: =+L180/L164 -> 0.656 | M187: =+M180/M164 -> 0.659
B188: Lower Middle Market | F188: =+F181/F165 -> 0.70298881 | G188: =+G181/G165 -> 0.45634531 | H188: =+H181/H165 -> 0.73865317 | I188: =+I181/I165 -> 0.75 | J188: =+J181/J165 -> 0.75 | K188: =+K181/K165 -> 0.753 | L188: =+L181/L165 -> 0.756 | M188: =+M181/M165 -> 0.759
...

Sheet Opex_Calcs
B2: Project Shasta
B3: {=MID(CELL("filename",A1),FIND("]",CELL("filename",A1))+1,255)} -> #VALUE!
B4: Spring 2022
B5: CONFIDENTIAL
F7: 2019 | G7: =+F7+1 -> 2020 | H7: =+G7+1 -> 2021 | I7: =+H7+1 -> 2022 | J7: =+I7+1 -> 2023 | K7: =+J7+1 -> 2024 | L7: =+K7+1 -> 2025 | M7: =+L7+1 -> 2026 | AA7: =+YEAR(AA8) -> 2019 | AB7: =+YEAR(AB8) -> 2019 | AC7: =+YEAR(AC8) -> 2019 | AD7: =+YEAR(AD8) -> 2019 | AE7: =+YEAR(AE8) -> 2019 | AF7: =+YEAR(AF8) -> 2019 | AG7: =+YEAR(AG8) -> 2019 | AH7: =+YEAR(AH8) -> 2019 | ... DR7: =+YEAR(DR8) -> 2026
F8: =+DATE(F7,12,31) -> 43830 | G8: =+DATE(G7,12,31) -> 44196 | H8: =+DATE(H7,12,31) -> 44561 | I8: =+DATE(I7,12,31) -> 44926 | J8: =+DATE(J7,12,31) -> 45291 | K8: =+DATE(K7,12,31) -> 45657 | L8: =+DATE(L7,12,31) -> 46022 | M8: =+DATE(M7,12,31) -> 46387 | AA8: 43496 | AB8: =+EOMONTH(AA8,1) -> 43524 | AC8: =+EOMONTH(AB8,1) -> 43555 | AD8: =+EOMONTH(AC8,1) -> 43585 | AE8: =+EOMONTH(AD8,1) -> 43616 | AF8: =+EOMONTH(AE8,1) -> 43646 | AG8: =+EOMONTH(AF8,1) -> 43677 | AH8: =+EOMONTH(AG8,1) -> 43708 | AI8: =+EOMONTH(AH8,1) -> 43738 | ... DR8: =+EOMONTH(DQ8,1) -> 46387
B9: $ in thousands | F9: Actual | G9: Actual | H9: Actual | I9: Budget | J9: Projection | K9: Projection | L9: Projection | M9: Projection | AA9: Actual | AB9: Actual | AC9: Actual | AD9: Actual | AE9: Actual | AF9: Actual | AG9: Actual | AH9: Actual | AI9: Actual | AJ9: Actual | AK9: Actual | AL9: Actual | AM9: Actual | AN9: Actual | AO9: Actual | AP9: Actual | AQ9: Actual | AR9: Actual | AS9: Actual | AT9: Actual | AU9: Actual | AV9: Actual | AW9: Actual | AX9: Actual | AY9: Actual | AZ9: Actual | BA9: Actual | BB9: Actual | BC9: Actual | BD9: Actual | BE9: Actual | BF9: Actual | BG9: Actual | BH9: Actual | BI9: Actual | BJ9: Actual | BK9: Actual | BL9: Actual | BM9: Actual | BN9: Budget | BO9: Budget | BP9: Budget | BQ9: Budget | BR9: Budget | BS9: Budget | BT9: Budget | BU9: Budget | BV9: Budget | BW9: Projection | BX9: Projection | BY9: Projection | BZ9: Projection | CA9: Projection | CB9: Projection | CC9: Projection | CD9: Projection | CE9: Projection | CF9: Projection | CG9: Projection | CH9: Projection | CI9: Projection | CJ9: Projection | CK9: Projection | CL9: Projection | CM9: Projection | CN9: Projection | CO9: Projection | CP9: Projection | CQ9: Projection | CR9: Projection | CS9: Projection | CT9: Projection | CU9: Projection | CV9: Projection | CW9: Projection | CX9: Projection | CY9: Projection | CZ9: Projection | DA9: Projection | DB9: Projection | DC9: Projection | DD9: Projection | DE9: Projection | DF9: Projection | DG9: Projection | DH9: Projection | DI9: Projection | DJ9: Projection | DK9: Projection | DL9: Projection | DM9: Projection | DN9: Projection | DO9: Projection | DP9: Projection | DQ9: Projection | DR9: Projection
B11: Headcount(1)
B12: Delivery | F12: =+F28/F22 -> 120.30285 | G12: =+G28/G22 -> 117.83842 | H12: =+H28/H22 -> 92.771815 | I12: =+I28/I22 -> 98.545257 | J12: =+J28/J22 -> 113.42356 | K12: =+K28/K22 -> 129.14242 | L12: =+L28/L22 -> 147.10405 | M12: =+M28/M22 -> 167.06569 | AA12: 106 | AB12: 108 | AC12: 111 | AD12: 113 | AE12: 114 | AF12: 122 | AG12: 124 | AH12: 125 | AI12: 126 | AJ12: 133 | AK12: 132 | AL12: 129 | AM12: 127 | AN12: 128 | AO12: 123 | AP12: 122 | AQ12: 122 | AR12: 122 | AS12: 118 | AT12: 116 | AU12: 115 | AV12: 112 | AW12: 109 | AX12: 98 | AY12: 97 | AZ12: 96 | BA12: 97 | BB12: 95 | BC12: 94 | BD12: 94 | BE12: 96 | BF12: 95 | BG12: 88 | BH12: 86 | BI12: 89 | BJ12: 88 | BK12: 92 | BL12: 93 | BM12: 95 | BN12: 97 | BO12: 97 | BP12: 98 | BQ12: 101 | BR12: 102 | BS12: 102 | BT12: 102 | BU12: 102 | BV12: 102 | BW12: 106 | BX12: 107 | BY12: 108 | BZ12: 111 | CA12: 112 | CB12: 113 | CC12: 114 | CD12: 116 | CE12: 117 | CF12: 118 | CG12: 119 | CH12: 120 | CI12: =+SUMIFS(Opex_Assumptions!$F12:$M12,Opex_Assumptions!$F$7:$M$7,CI$7)/12+CH12 -> 121.40653 | CJ12: =+SUMIFS(Opex_Assumptions!$F12:$M12,Opex_Assumptions!$F$7:$M$7,CJ$7)/12+CI12 -> 122.81305 | CK12: =+SUMIFS(Opex_Assumptions!$F12:$M12,Opex_Assumptions!$F$7:$M$7,CK$7)/12+CJ12 -> 124.21958 | CL12: =+SUMIFS(Opex_Assumptions!$F12:$M12,Opex_Assumptions!$F$7:$M$7,CL$7)/12+CK12 -> 125.6261 | CM12: =+SUMIFS(Opex_Assumptions!$F12:$M12,Opex_Assumptions!$F$7:$M$7,CM$7)/12+CL12 -> 127.03263 | CN12: =+SUMIFS(Opex_Assumptions!$F12:$M12,Opex_Assumptions!$F$7:$M$7,CN$7)/12+CM12 -> 128.43915 | CO12: =+SUMIFS(Opex_Assumptions!$F12:$M12,Opex_Assumptions!$F$7:$M$7,CO$7)/12+CN12 -> 129.84568 | CP12: =+SUMIFS(Opex_Assumptions!$F12:$M12,Opex_Assumptions!$F$7:$M$7,CP$7)/12+CO12 -> 131.2522 | ... DR12: =+SUMIFS(Opex_Assumptions!$F12:$M12,Opex_Assumptions!$F$7:$M$7,DR$7)/12+DQ12 -> 176.63491
B13: Sales & CS | F13: =+F29/F23 -> 9.4004113 | G13: =+G29/G23 -> 8.8314191 | H13: =+H29/H23 -> 7.7286007 | I13: =+I29/I23 -> 8.4959295 | J13: =+J29/J23 -> 9.8181818 | K13: =+K29/K23 -> 11.083333 | L13: =+L29/L23 -> 13.083333 | M13: =+M29/M23 -> 15.083333 | AA13: 9 | AB13: 9 | AC13: 9 | AD13: 10 | AE13: 9 | AF13: 8 | AG13: 10 | AH13: 10 | AI13: 10 | AJ13: 11 | AK13: 10 | AL13: 8 | AM13: 9 | AN13: 9 | AO13: 9 | AP13: 9 | AQ13: 9 | AR13: 9 | AS13: 9 | AT13: 9 | AU13: 9 | AV13: 8 | AW13: 9 | AX13: 8 | AY13: 8 | AZ13: 7 | BA13: 7 | BB13: 7 | BC13: 7 | BD13: 7 | BE13: 7 | BF13: 7 | BG13: 7 | BH13: 9 | BI13: 10 | BJ13: 10 | BK13: 10 | BL13: 10 | BM13: 10 | BN13: 8 | BO13: 8 | BP13: 8 | BQ13: 8 | BR13: 8 | BS13: 8 | BT13: 8 | BU13: 8 | BV13: 8 | BW13: 9 | BX13: 9 | BY13: 10 | BZ13: 10 | CA13: 10 | CB13: 10 | CC13: 10 | CD13: 10 | CE13: 10 | CF13: 10 | CG13: 10 | CH13: 10 | CI13: =+SUMIFS(Opex_Assumptions!$F13:$M13,Opex_Assumptions!$F$7:$M$7,CI$7)/12+CH13 -> 10.166667 | CJ13: =+SUMIFS(Opex_Assumptions!$F13:$M13,Opex_Assumptions!$F$7:$M$7,CJ$7)/12+CI13 -> 10.333333 | CK13: =+SUMIFS(Opex_Assumptions!$F13:$M13,Opex_Assumptions!$F$7:$M$7,CK$7)/12+CJ13 -> 10.5 | CL13: =+SUMIFS(Opex_Assumptions!$F13:$M13,Opex_Assumptions!$F$7:$M$7,CL$7)/12+CK13 -> 10.666667 | CM13: =+SUMIFS(Opex_Assumptions!$F13:$M13,Opex_Assumptions!$F$7:$M$7,CM$7)/12+CL13 -> 10.833333 | CN13: =+SUMIFS(Opex_Assumptions!$F13:$M13,Opex_Assumptions!$F$7:$M$7,CN$7)/12+CM13 -> 11 | CO13: =+SUMIFS(Opex_Assumptions!$F13:$M13,Opex_Assumptions!$F$7:$M$7,CO$7)/12+CN13 -> 11.166667 | CP13: =+SUMIFS(Opex_Assumptions!$F13:$M13,Opex_Assumptions!$F$7:$M$7,CP$7)/12+CO13 -> 11.333333 | ... DR13: =+SUMIFS(Opex_Assumptions!$F13:$M13,Opex_Assumptions!$F$7:$M$7,DR$7)/12+DQ13 -> 16
B14: Executive | F14: =+F30/F24 -> 8.1532711 | G14: =+G30/G24 -> 8 | H14: =+H30/H24 -> 7.151029 | I14: =+I30/I24 -> 7 | J14: =+J30/J24 -> 7 | K14: =+K30/K24 -> 7 | L14: =+L30/L24 -> 7 | M14: =+M30/M24 -> 7 | AA14: 8 | AB14: 9 | AC14: 9 | AD14: 8 | AE14: 8 | AF14: 8 | AG14: 8 | AH14: 8 | AI14: 8 | AJ14: 8 | AK14: 8 | AL14: 8 | AM14: 8 | AN14: 8 | AO14: 8 | AP14: 8 | AQ14: 8 | AR14: 8 | AS14: 8 | AT14: 8 | AU14: 8 | AV14: 8 | AW14: 8 | AX14: 8 | AY14: 8 | AZ14: 8 | BA14: 7 | BB14: 7 | BC14: 7 | BD14: 7 | BE14: 7 | BF14: 7 | BG14: 7 | BH14: 7 | BI14: 7 | BJ14: 7 | BK14: 7 | BL14: 7 | BM14: 7 | BN14: 7 | BO14: 7 | BP14: 7 | BQ14: 7 | BR14: 7 | BS14: 7 | BT14: 7 | BU14: 7 | BV14: 7 | BW14: 7 | BX14: 7 | BY14: 7 | BZ14: 7 | CA14: 7 | CB14: 7 | CC14: 7 | CD14: 7 | CE14: 7 | CF14: 7 | CG14: 7 | CH14: 7 | CI14: =+SUMIFS(Opex_Assumptions!$F14:$M14,Opex_Assumptions!$F$7:$M$7,CI$7)/12+CH14 -> 7 | CJ14: =+SUMIFS(Opex_Assumptions!$F14:$M14,Opex_Assumptions!$F$7:$M$7,CJ$7)/12+CI14 -> 7 | CK14: =+SUMIFS(Opex_Assumptions!$F14:$M14,Opex_Assumptions!$F$7:$M$7,CK$7)/12+CJ14 -> 7 | CL14: =+SUMIFS(Opex_Assumptions!$F14:$M14,Opex_Assumptions!$F$7:$M$7,CL$7)/12+CK14 -> 7 | CM14: =+SUMIFS(Opex_Assumptions!$F14:$M14,Opex_Assumptions!$F$7:$M$7,CM$7)/12+CL14 -> 7 | CN14: =+SUMIFS(Opex_Assumptions!$F14:$M14,Opex_Assumptions!$F$7:$M$7,CN$7)/12+CM14 -> 7 | CO14: =+SUMIFS(Opex_Assumptions!$F14:$M14,Opex_Assumptions!$F$7:$M$7,CO$7)/12+CN14 -> 7 | CP14: =+SUMIFS(Opex_Assumptions!$F14:$M14,Opex_Assumptions!$F$7:$M$7,CP$7)/12+CO14 -> 7 | ... DR14: =+SUMIFS(Opex_Assumptions!$F14:$M14,Opex_Assumptions!$F$7:$M$7,DR$7)/12+DQ14 -> 7
B15: Admin | F15: =+F31/F25 -> 12.028654 | G15: =+G31/G25 -> 13.566974 | H15: =+H31/H25 -> 11.912906 | I15: =+I31/I25 -> 11.498869 | J15: =+J31/J25 -> 11 | K15: =+K31/K25 -> 12.083333 | L15: =+L31/L25 -> 14.625 | M15: =+M31/M25 -> 18.166667 | AA15: 11 | AB15: 11 | AC15: 11 | AD15: 12 | AE15: 10 | AF15: 10 | AG15: 12 | AH15: 13 | AI15: 12 | AJ15: 14 | AK15: 14 | AL15: 14 | AM15: 15 | AN15: 14 | AO15: 14 | AP15: 13 | AQ15: 13 | AR15: 13 | AS15: 13 | AT15: 13 | AU15: 13 | AV15: 14 | AW15: 14 | AX15: 14 | AY15: 12 | AZ15: 12 | BA15: 12 | BB15: 12 | BC15: 12 | BD15: 12 | BE15: 12 | BF15: 12 | BG15: 12 | BH15: 11 | BI15: 12 | BJ15: 12 | BK15: 12 | BL15: 13 | BM15: 13 | BN15: 12 | BO15: 11 | BP15: 11 | BQ15: 11 | BR15: 11 | BS15: 11 | BT15: 11 | BU15: 11 | BV15: 11 | BW15: 11 | BX15: 11 | BY15: 11 | BZ15: 11 | CA15: 11 | CB15: 11 | CC15: 11 | CD15: 11 | CE15: 11 | CF15: 11 | CG15: 11 | CH15: 11 | CI15: =+SUMIFS(Opex_Assumptions!$F15:$M15,Opex_Assumptions!$F$7:$M$7,CI$7)/12+CH15 -> 11.166667 | CJ15: =+SUMIFS(Opex_Assumptions!$F15:$M15,Opex_Assumptions!$F$7:$M$7,CJ$7)/12+CI15 -> 11.333333 | CK15: =+SUMIFS(Opex_Assumptions!$F15:$M15,Opex_Assumptions!$F$7:$M$7,CK$7)/12+CJ15 -> 11.5 | CL15: =+SUMIFS(Opex_Assumptions!$F15:$M15,Opex_Assumptions!$F$7:$M$7,CL$7)/12+CK15 -> 11.666667 | CM15: =+SUMIFS(Opex_Assumptions!$F15:$M15,Opex_Assumptions!$F$7:$M$7,CM$7)/12+CL15 -> 11.833333 | CN15: =+SUMIFS(Opex_Assumptions!$F15:$M15,Opex_Assumptions!$F$7:$M$7,CN$7)/12+CM15 -> 12 | CO15: =+SUMIFS(Opex_Assumptions!$F15:$M15,Opex_Assumptions!$F$7:$M$7,CO$7)/12+CN15 -> 12.166667 | CP15: =+SUMIFS(Opex_Assumptions!$F15:$M15,Opex_Assumptions!$F$7:$M$7,CP$7)/12+CO15 -> 12.333333 | ... DR15: =+SUMIFS(Opex_Assumptions!$F15:$M15,Opex_Assumptions!$F$7:$M$7,DR$7)/12+DQ15 -> 20
B16: Total | F16: =SUM(F12:F15) -> 149.88518 | G16: =SUM(G12:G15) -> 148.23681 | H16: =SUM(H12:H15) -> 119.56435 | I16: =SUM(I12:I15) -> 125.54006 | J16: =SUM(J12:J15) -> 141.24174 | K16: =SUM(K12:K15) -> 159.30908 | L16: =SUM(L12:L15) -> 181.81239 | M16: =SUM(M12:M15) -> 207.31569 | AA16: =SUM(AA12:AA15) -> 134 | AB16: =SUM(AB12:AB15) -> 137 | AC16: =SUM(AC12:AC15) -> 140 | AD16: =SUM(AD12:AD15) -> 143 | AE16: =SUM(AE12:AE15) -> 141 | AF16: =SUM(AF12:AF15) -> 148 | AG16: =SUM(AG12:AG15) -> 154 | AH16: =SUM(AH12:AH15) -> 156 | ... DR16: =SUM(DR12:DR15) -> 219.63491
B18: Memo: Revenue / Delivery Headcount | F18: =+'Income Statement'!F$16/F12 -> 0 | G18: =+'Income Statement'!G$16/G12 -> 0 | H18: =+'Income Statement'!H$16/H12 -> 0 | I18: =+'Income Statement'!I$16/I12 -> 0 | J18: =+'Income Statement'!J$16/J12 -> 0 | K18: =+'Income Statement'!K$16/K12 -> 0 | L18: =+'Income Statement'!L$16/L12 -> 0 | M18: =+'Income Statement'!M$16/M12 -> 0 | AA18: =+'Income Statement'!Q$16/AA12 -> 0 | AB18: =+'Income Statement'!R$16/AB12 -> 0 | AC18: =+'Income Statement'!S$16/AC12 -> 0 | AD18: =+'Income Statement'!T$16/AD12 -> 0 | AE18: =+'Income Statement'!U$16/AE12 -> 0 | AF18: =+'Income Statement'!V$16/AF12 -> 0 | AG18: =+'Income Statement'!W$16/AG12 -> 0 | AH18: =+'Income Statement'!X$16/AH12 -> 0 | ... DR18: =+'Income Statement'!DH$16/DR12 -> 0
B19: Memo: Revenue / Sales & CS Headcount | F19: =+'Income Statement'!F$16/F13 -> 0 | G19: =+'Income Statement'!G$16/G13 -> 0 | H19: =+'Income Statement'!H$16/H13 -> 0 | I19: =+'Income Statement'!I$16/I13 -> 0 | J19: =+'Income Statement'!J$16/J13 -> 0 | K19: =+'Income Statement'!K$16/K13 -> 0 | L19: =+'Income Statement'!L$16/L13 -> 0 | M19: =+'Income Statement'!M$16/M13 -> 0 | AA19: =+'Income Statement'!Q$16/AA13 -> 0 | AB19: =+'Income Statement'!R$16/AB13 -> 0 | AC19: =+'Income Statement'!S$16/AC13 -> 0 | AD19: =+'Income Statement'!T$16/AD13 -> 0 | AE19: =+'Income Statement'!U$16/AE13 -> 0 | AF19: =+'Income Statement'!V$16/AF13 -> 0 | AG19: =+'Income Statement'!W$16/AG13 -> 0 | AH19: =+'Income Statement'!X$16/AH13 -> 0 | ... DR19: =+'Income Statement'!DH$16/DR13 -> 0
B21: Average Salary(1)
B22: Delivery | F22: =+SUMIFS($AA22:$DR22,$AA$7:$DR$7,F$7) -> 86.426861 | G22: =+SUMIFS($AA22:$DR22,$AA$7:$DR$7,G$7) -> 79.670345 | H22: =+SUMIFS($AA22:$DR22,$AA$7:$DR$7,H$7) -> 88.859187 | I22: =+SUMIFS($AA22:$DR22,$AA$7:$DR$7,I$7) -> 95.356819 | J22: =+SUMIFS($AA22:$DR22,$AA$7:$DR$7,J$7) -> 96.854271 | K22: =+SUMIFS($AA22:$DR22,$AA$7:$DR$7,K$7) -> 99.759899 | L22: =+SUMIFS($AA22:$DR22,$AA$7:$DR$7,L$7) -> 102.7527 | M22: =+SUMIFS($AA22:$DR22,$AA$7:$DR$7,M$7) -> 105.83528 | AA22: =+AA28/AA12 -> 7.0007802 | AB22: =+AB28/AB12 -> 7.3847803 | AC22: =+AC28/AC12 -> 6.8400899 | AD22: =+AD28/AD12 -> 6.9209573 | AE22: =+AE28/AE12 -> 7.2262605 | AF22: =+AF28/AF12 -> 7.5617012 | AG22: =+AG28/AG12 -> 7.5598441 | AH22: =+AH28/AH12 -> 7.6195933 | ... CH22: =+CH28/CH12 -> 8.0767955 | CI22: =+SUMIFS(Opex_Assumptions!$F18:$M18,Opex_Assumptions!$F$7:$M$7,CI$7)/12 -> 8.3133249 | CJ22: =+SUMIFS(Opex_Assumptions!$F18:$M18,Opex_Assumptions!$F$7:$M$7,CJ$7)/12 -> 8.3133249 | CK22: =+SUMIFS(Opex_Assumptions!$F18:$M18,Opex_Assumptions!$F$7:$M$7,CK$7)/12 -> 8.3133249 | CL22: =+SUMIFS(Opex_Assumptions!$F18:$M18,Opex_Assumptions!$F$7:$M$7,CL$7)/12 -> 8.3133249 | CM22: =+SUMIFS(Opex_Assumptions!$F18:$M18,Opex_Assumptions!$F$7:$M$7,CM$7)/12 -> 8.3133249 | CN22: =+SUMIFS(Opex_Assumptions!$F18:$M18,Opex_Assumptions!$F$7:$M$7,CN$7)/12 -> 8.3133249 | CO22: =+SUMIFS(Opex_Assumptions!$F18:$M18,Opex_Assumptions!$F$7:$M$7,CO$7)/12 -> 8.3133249 | CP22: =+SUMIFS(Opex_Assumptions!$F18:$M18,Opex_Assumptions!$F$7:$M$7,CP$7)/12 -> 8.3133249 | ... DR22: =+SUMIFS(Opex_Assumptions!$F18:$M18,Opex_Assumptions!$F$7:$M$7,DR$7)/12 -> 8.8196064
B23: Sales & CS | F23: =+SUMIFS($AA23:$DR23,$AA$7:$DR$7,F$7) -> 81.770314 | G23: =+SUMIFS($AA23:$DR23,$AA$7:$DR$7,G$7) -> 77.524213 | H23: =+SUMIFS($AA23:$DR23,$AA$7:$DR$7,H$7) -> 70.581749 | I23: =+SUMIFS($AA23:$DR23,$AA$7:$DR$7,I$7) -> 59.741506 | J23: =+SUMIFS($AA23:$DR23,$AA$7:$DR$7,J$7) -> 58.142727 | K23: =+SUMIFS($AA23:$DR23,$AA$7:$DR$7,K$7) -> 59.887009 | L23: =+SUMIFS($AA23:$DR23,$AA$7:$DR$7,L$7) -> 61.68362 | M23: =+SUMIFS($AA23:$DR23,$AA$7:$DR$7,M$7) -> 63.534128 | AA23: =+AA29/AA13 -> 7.2059183 | AB23: =+AB29/AB13 -> 6.8856789 | AC23: =+AC29/AC13 -> 7.0580736 | AD23: =+AD29/AD13 -> 6.4887592 | AE23: =+AE29/AE13 -> 7.1752869 | AF23: =+AF29/AF13 -> 7.6779421 | AG23: =+AG29/AG13 -> 6.8008674 | AH23: =+AH29/AH13 -> 6.8008674 | ... CH23: =+CH29/CH13 -> 4.7571322 | CI23: =+SUMIFS(Opex_Assumptions!$F19:$M19,Opex_Assumptions!$F$7:$M$7,CI$7)/12 -> 4.9905841 | CJ23: =+SUMIFS(Opex_Assumptions!$F19:$M19,Opex_Assumptions!$F$7:$M$7,CJ$7)/12 -> 4.9905841 | CK23: =+SUMIFS(Opex_Assumptions!$F19:$M19,Opex_Assumptions!$F$7:$M$7,CK$7)/12 -> 4.9905841 | CL23: =+SUMIFS(Opex_Assumptions!$F19:$M19,Opex_Assumptions!$F$7:$M$7,CL$7)/12 -> 4.9905841 | CM23: =+SUMIFS(Opex_Assumptions!$F19:$M19,Opex_Assumptions!$F$7:$M$7,CM$7)/12 -> 4.9905841 | CN23: =+SUMIFS(Opex_Assumptions!$F19:$M19,Opex_Assumptions!$F$7:$M$7,CN$7)/12 -> 4.9905841 | CO23: =+SUMIFS(Opex_Assumptions!$F19:$M19,Opex_Assumptions!$F$7:$M$7,CO$7)/12 -> 4.9905841 | CP23: =+SUMIFS(Opex_Assumptions!$F19:$M19,Opex_Assumptions!$F$7:$M$7,CP$7)/12 -> 4.9905841 | ... DR23: =+SUMIFS(Opex_Assumptions!$F19:$M19,Opex_Assumptions!$F$7:$M$7,DR$7)/12 -> 5.2945107
B24: Executive | F24: =+SUMIFS($AA24:$DR24,$AA$7:$DR$7,F$7) -> 198.68775 | G24: =+SUMIFS($AA24:$DR24,$AA$7:$DR$7,G$7) -> 214.18385 | H24: =+SUMIFS($AA24:$DR24,$AA$7:$DR$7,H$7) -> 232.84317 | I24: =+SUMIFS($AA24:$DR24,$AA$7:$DR$7,I$7) -> 262.01745 | J24: =+SUMIFS($AA24:$DR24,$AA$7:$DR$7,J$7) -> 268.22225 | K24: =+SUMIFS($AA24:$DR24,$AA$7:$DR$7,K$7) -> 276.26892 | L24: =+SUMIFS($AA24:$DR24,$AA$7:$DR$7,L$7) -> 284.55699 | M24: =+SUMIFS($AA24:$DR24,$AA$7:$DR$7,M$7) -> 293.0937 | AA24: =+AA30/AA14 -> 17.391383 | AB24: =+AB30/AB14 -> 15.204802 | AC24: =+AC30/AC14 -> 15.248286 | AD24: =+AD30/AD14 -> 16.758015 | AE24: =+AE30/AE14 -> 16.758015 | AF24: =+AF30/AF14 -> 16.758015 | AG24: =+AG30/AG14 -> 16.758015 | AH24: =+AH30/AH14 -> 16.758015 | ... CH24: =+CH30/CH14 -> 22.351854 | CI24: =+SUMIFS(Opex_Assumptions!$F20:$M20,Opex_Assumptions!$F$7:$M$7,CI$7)/12 -> 23.02241 | CJ24: =+SUMIFS(Opex_Assumptions!$F20:$M20,Opex_Assumptions!$F$7:$M$7,CJ$7)/12 -> 23.02241 | CK24: =+SUMIFS(Opex_Assumptions!$F20:$M20,Opex_Assumptions!$F$7:$M$7,CK$7)/12 -> 23.02241 | CL24: =+SUMIFS(Opex_Assumptions!$F20:$M20,Opex_Assumptions!$F$7:$M$7,CL$7)/12 -> 23.02241 | CM24: =+SUMIFS(Opex_Assumptions!$F20:$M20,Opex_Assumptions!$F$7:$M$7,CM$7)/12 -> 23.02241 | CN24: =+SUMIFS(Opex_Assumptions!$F20:$M20,Opex_Assumptions!$F$7:$M$7,CN$7)/12 -> 23.02241 | CO24: =+SUMIFS(Opex_Assumptions!$F20:$M20,Opex_Assumptions!$F$7:$M$7,CO$7)/12 -> 23.02241 | CP24: =+SUMIFS(Opex_Assumptions!$F20:$M20,Opex_Assumptions!$F$7:$M$7,CP$7)/12 -> 23.02241 | ... DR24: =+SUMIFS(Opex_Assumptions!$F20:$M20,Opex_Assumptions!$F$7:$M$7,DR$7)/12 -> 24.424475
B25: Admin | F25: =+SUMIFS($AA25:$DR25,$AA$7:$DR$7,F$7) -> 84.867562 | G25: =+SUMIFS($AA25:$DR25,$AA$7:$DR$7,G$7) -> 95.651783 | H25: =+SUMIFS($AA25:$DR25,$AA$7:$DR$7,H$7) -> 101.72271 | I25: =+SUMIFS($AA25:$DR25,$AA$7:$DR$7,I$7) -> 110.68847 | J25: =+SUMIFS($AA25:$DR25,$AA$7:$DR$7,J$7) -> 113.53512 | K25: =+SUMIFS($AA25:$DR25,$AA$7:$DR$7,K$7) -> 116.94117 | L25: =+SUMIFS($AA25:$DR25,$AA$7:$DR$7,L$7) -> 120.44941 | M25: =+SUMIFS($AA25:$DR25,$AA$7:$DR$7,M$7) -> 124.06289 | AA25: =+AA31/AA15 -> 6.5588993 | AB25: =+AB31/AB15 -> 6.2868947 | AC25: =+AC31/AC15 -> 6.3234841 | AD25: =+AD31/AD15 -> 6.2249663 | AE25: =+AE31/AE15 -> 7.7090668 | AF25: =+AF31/AF15 -> 7.7090668 | AG25: =+AG31/AG15 -> 6.9807534 | AH25: =+AH31/AH15 -> 6.9224126 | ... CH25: =+CH31/CH15 -> 9.4612601 | CI25: =+SUMIFS(Opex_Assumptions!$F21:$M21,Opex_Assumptions!$F$7:$M$7,CI$7)/12 -> 9.7450979 | CJ25: =+SUMIFS(Opex_Assumptions!$F21:$M21,Opex_Assumptions!$F$7:$M$7,CJ$7)/12 -> 9.7450979 | CK25: =+SUMIFS(Opex_Assumptions!$F21:$M21,Opex_Assumptions!$F$7:$M$7,CK$7)/12 -> 9.7450979 | CL25: =+SUMIFS(Opex_Assumptions!$F21:$M21,Opex_Assumptions!$F$7:$M$7,CL$7)/12 -> 9.7450979 | CM25: =+SUMIFS(Opex_Assumptions!$F21:$M21,Opex_Assumptions!$F$7:$M$7,CM$7)/12 -> 9.7450979 | CN25: =+SUMIFS(Opex_Assumptions!$F21:$M21,Opex_Assumptions!$F$7:$M$7,CN$7)/12 -> 9.7450979 | CO25: =+SUMIFS(Opex_Assumptions!$F21:$M21,Opex_Assumptions!$F$7:$M$7,CO$7)/12 -> 9.7450979 | CP25: =+SUMIFS(Opex_Assumptions!$F21:$M21,Opex_Assumptions!$F$7:$M$7,CP$7)/12 -> 9.7450979 | ... DR25: =+SUMIFS(Opex_Assumptions!$F21:$M21,Opex_Assumptions!$F$7:$M$7,DR$7)/12 -> 10.338574
B27: Total Salary(1)
B28: Delivery | F28: =+SUMIFS($AA28:$DR28,$AA$7:$DR$7,F$7) -> 10397.397 | G28: =+SUMIFS($AA28:$DR28,$AA$7:$DR$7,G$7) -> 9388.2273 | H28: =+SUMIFS($AA28:$DR28,$AA$7:$DR$7,H$7) -> 8243.6281 | I28: =+SUMIFS($AA28:$DR28,$AA$7:$DR$7,I$7) -> 9396.9622 | J28: =+SUMIFS($AA28:$DR28,$AA$7:$DR$7,J$7) -> 10985.556 | K28: =+SUMIFS($AA28:$DR28,$AA$7:$DR$7,K$7) -> 12883.234 | L28: =+SUMIFS($AA28:$DR28,$AA$7:$DR$7,L$7) -> 15115.338 | M28: =+SUMIFS($AA28:$DR28,$AA$7:$DR$7,M$7) -> 17681.444 | AA28: 742.0827 | AB28: 797.55628 | AC28: 759.24998 | AD28: 782.06817 | AE28: 823.7937 | AF28: 922.52755 | AG28: 937.42067 | AH28: 952.44916 | AI28: 884.94462 | AJ28: 940.85336 | AK28: 909.25027 | AL28: 945.20088 | AM28: 935.70558 | AN28: 910.84501 | AO28: 865.51169 | AP28: 780.67667 | AQ28: 773.44951 | AR28: 787.70807 | AS28: 777.0328 | AT28: 774.30916 | AU28: 754.68672 | AV28: 710.48763 | AW28: 639.71293 | AX28: 678.10155 | AY28: 667.18875 | AZ28: 646.46605 | BA28: 676.94196 | BB28: 699.79271 | BC28: 697.96158 | BD28: 709.07004 | BE28: 723.4926 | BF28: 707.61818 | BG28: 667.77865 | BH28: 690.50111 | BI28: 684.13281 | BJ28: 672.68364 | BK28: 738.58844 | BL28: 738.09021 | BM28: 757.98741 | BN28: 782.71108 | BO28: 793.51108 | BP28: 800.91 | BQ28: 801.27733 | BR28: 796.77733 | BS28: 796.77733 | BT28: 796.77733 | BU28: 796.77733 | BV28: 796.77733 | BW28: 852.48629 | BX28: 860.21129 | BY28: 870.93629 | BZ28: 896.68629 | CA28: 904.41129 | CB28: 912.13629 | CC28: 919.86129 | CD28: 938.31546 | CE28: 946.04046 | CF28: 953.76546 | CG28: 961.49046 | CH28: 969.21546 | CI28: =+CI12*CI22 -> 1009.2919 | CJ28: =+CJ12*CJ22 -> 1020.9848 | CK28: =+CK12*CK22 -> 1032.6777 | CL28: =+CL12*CL22 -> 1044.3706 | CM28: =+CM12*CM22 -> 1056.0635 | CN28: =+CN12*CN22 -> 1067.7564 | CO28: =+CO12*CO22 -> 1079.4493 | CP28: =+CP12*CP22 -> 1091.1422 | ... DR28: =+DR12*DR22 -> 1557.8504
B29: Sales & CS | F29: =+SUMIFS($AA29:$DR29,$AA$7:$DR$7,F$7) -> 768.67458 | G29: =+SUMIFS($AA29:$DR29,$AA$7:$DR$7,G$7) -> 684.64881 | H29: =+SUMIFS($AA29:$DR29,$AA$7:$DR$7,H$7) -> 545.49816 | I29: =+SUMIFS($AA29:$DR29,$AA$7:$DR$7,I$7) -> 507.55962 | J29: =+SUMIFS($AA29:$DR29,$AA$7:$DR$7,J$7) -> 570.85587 | K29: =+SUMIFS($AA29:$DR29,$AA$7:$DR$7,K$7) -> 663.74769 | L29: =+SUMIFS($AA29:$DR29,$AA$7:$DR$7,L$7) -> 807.02736 | M29: =+SUMIFS($AA29:$DR29,$AA$7:$DR$7,M$7) -> 958.30643 | AA29: 64.853264 | AB29: 61.97111 | AC29: 63.522662 | AD29: 64.887592 | AE29: 64.577582 | AF29: 61.423537 | AG29: 68.008674 | AH29: 68.008674 | AI29: 68.008674 | AJ29: 74.772982 | AK29: 60.058786 | AL29: 48.581044 | AM29: 55.986406 | AN29: 59.734817 | AO29: 59.184083 | AP29: 59.184083 | AQ29: 59.184083 | AR29: 59.184083 | AS29: 59.184083 | AT29: 59.184083 | AU29: 55.09127 | AV29: 50.761458 | AW29: 54.17904 | AX29: 53.791326 | AY29: 50.580621 | AZ29: 42.458241 | BA29: 42.176011 | BB29: 42.176011 | BC29: 42.176011 | BD29: 42.176011 | BE29: 42.176011 | BF29: 43.029699 | BG29: 35.152135 | BH29: 50.347084 | BI29: 55.527404 | BJ29: 57.522916 | BK29: 48.89866 | BL29: 48.89866 | BM29: 50.34055 | BN29: 39.93575 | BO29: 39.93575 | BP29: 39.93575 | BQ29: 39.93575 | BR29: 39.93575 | BS29: 39.93575 | BT29: 39.93575 | BU29: 39.93575 | BV29: 39.93575 | BW29: 47.571322 | BX29: 47.571322 | BY29: 47.571322 | BZ29: 47.571322 | CA29: 47.571322 | CB29: 47.571322 | CC29: 47.571322 | CD29: 47.571322 | CE29: 47.571322 | CF29: 47.571322 | CG29: 47.571322 | CH29: 47.571322 | CI29: =+CI13*CI23 -> 50.737605 | CJ29: =+CJ13*CJ23 -> 51.569369 | CK29: =+CK13*CK23 -> 52.401133 | CL29: =+CL13*CL23 -> 53.232897 | CM29: =+CM13*CM23 -> 54.064661 | CN29: =+CN13*CN23 -> 54.896425 | CO29: =+CO13*CO23 -> 55.728189 | CP29: =+CP13*CP23 -> 56.559953 | ... DR29: =+DR13*DR23 -> 84.712171
